Workbook
Name __123Graph_A: #REF!
Name __123Graph_X: #REF!
Name _AtRisk_SimSetting_AutomaticallyGenerateReports: 0
Name _AtRisk_SimSetting_AutomaticResultsDisplayMode: 0
Name _AtRisk_SimSetting_ConvergenceConfidenceLevel: 0.95
Name _AtRisk_SimSetting_ConvergencePercentileToTest: 0.9
Name _AtRisk_SimSetting_ConvergencePerformMeanTest: 1
Name _AtRisk_SimSetting_ConvergencePerformPercentileTest: 0
Name _AtRisk_SimSetting_ConvergencePerformStdDeviationTest: 0
Name _AtRisk_SimSetting_ConvergenceTestAllOutputs: 1
Name _AtRisk_SimSetting_ConvergenceTestingPeriod: 100
Name _AtRisk_SimSetting_ConvergenceTolerance: 0.03
Name _AtRisk_SimSetting_LiveUpdate: 1
Name _AtRisk_SimSetting_LiveUpdatePeriod: -1
Name _AtRisk_SimSetting_RandomNumberGenerator: 0
Name _AtRisk_SimSetting_ReportsList: 0
Name _AtRisk_SimSetting_SimNameCount: 0
Name _AtRisk_SimSetting_StdRecalcBehavior: 0
Name _AtRisk_SimSetting_StdRecalcWithoutRiskStatic: 0
Name _AtRisk_SimSetting_StdRecalcWithoutRiskStaticPercentile: 0.5
Name _Order1: 255
Name _Order2: 0
Name _Regression_Int: 1
Name dddd: #REF!
Name OPERATIVO: #REF!
Name RiskAfterRecalcMacro: ""
Name RiskAfterSimMacro: ""
Name RiskBeforeRecalcMacro: ""
Name RiskBeforeSimMacro: ""
Name RiskCollectDistributionSamples: 2
Name RiskFixedSeed: 1
Name RiskHasSettings: 5
Name RiskMinimizeOnStart: 0
Name RiskMonitorConvergence: 1
Name RiskNumIterations: 1000
Name RiskNumSimulations: 1
Name RiskPauseOnError: 0
Name RiskRunAfterRecalcMacro: 0
Name RiskRunAfterSimMacro: 0
Name RiskRunBeforeRecalcMacro: 0
Name RiskRunBeforeSimMacro: 0
Name RiskSamplingType: 2
Name RiskStandardRecalc: 1
Name RiskUpdateDisplay: 0
Name RiskUseDifferentSeedForEachSim: 0
Name RiskUseFixedSeed: 0
Name RiskUseMultipleCPUs: 0

Sheet EMP FISCALIZABLE
A3: 1 | E3: TAREO DE EMPLEADOS - MES DE JUNIO DEL 2021 | J3: 12 | K3: 13 | L3: 14 | M3: 15 | O3: 16 | P3: 17 | Q3: 18 | R3: 19 | S3: 20 | T3: 21 | U3: 22 | V3: 23 | X3: 24 | Y3: 25 | Z3: 26 | AA3: 27 | AB3: 28 | AC3: 29 | AD3: 30 | AE3: 31 | AG3: 32 | AH3: 33 | AI3: 34 | AJ3: 35 | AK3: 36 | AL3: 37 | AM3: 38 | AN3: 39 | AP3: 40 | AQ3: 41 | AR3: 42 | AS3: 43 | AT3: 44 | AU3: 45 | AV3: 46 | AW3: 47 | AY3: 48 | AZ3: 49 | BA3: 50 | BB3: 51 | BC3: 52 | BD3: 53 | BE3: 54 | BF3: 55 | BH3: 56 | BI3: 57 | BJ3: 58 | BK3: 59 | BL3: 60 | BM3: 61 | BN3: 62 | BO3: 63 | BQ3: 64 | BR3: 65 | BS3: 66 | BT3: 67 | BU3: 68 | BV3: 69 | BW3: 70 | BX3: 71 | BZ3: 72 | CA3: 73 | CB3: 74 | CC3: 75 | CD3: 76 | CE3: 77 | CF3: 78 | CG3: 79 | CI3: 80 | CJ3: 81 | CK3: 82 | CL3: 83 | CM3: 84 | CN3: 85 | CO3: 86 | CP3: 87 | CR3: 88 | CS3: 89 | CT3: 90 | CU3: 91 | CV3: 92 | CW3: 93 | CX3: 94 | CY3: 95 | DA3: 96 | DB3: 97 | DC3: 98 | DD3: 99 | DE3: 100 | DF3: 101 | DG3: 102 | DH3: 103 | DJ3: 104 | DK3: 105 | DL3: 106 | DM3: 107 | DN3: 108 | DO3: 109 | DP3: 110 | DQ3: 111 | DS3: 112 | DT3: 113 | DU3: 114 | DV3: 115 | DW3: 116 | DX3: 117 | DY3: 118 | DZ3: 119 | EB3: 120 | EC3: 121 | ED3: 122 | EE3: 123 | EF3: 124 | EG3: 125 | EH3: 126 | EI3: 127 | EK3: 128 | EL3: 129 | EM3: 130 | EN3: 131 | EO3: 132 | EP3: 133 | EQ3: 134 | ER3: 135 | ET3: 136 | EU3: 137 | EV3: 138 | EW3: 139 | EX3: 1 | EY3: 141 | EZ3: 142 | FA3: 143 | FC3: 144 | FD3: 145 | FE3: 146 | FF3: 147 | FG3: 148 | FH3: 149 | FI3: 150 | FJ3: 151 | FL3: 152 | FM3: 153 | FN3: 154 | FO3: 155 | FP3: 156 | FQ3: 157 | FR3: 158 | FS3: 159 | FU3: 160 | FV3: 161 | FW3: 162 | FX3: 163 | FY3: 164 | FZ3: 165 | GA3: 166 | GB3: 167 | GD3: 168 | GE3: 169 | GF3: 170 | GG3: 171 | GH3: 172 | GI3: 173 | GJ3: 174 | GK3: 175 | GM3: 176 | GN3: 177 | GO3: 178 | GP3: 179 | GQ3: 180 | GR3: 181 | GS3: 182 | GT3: 183 | GV3: 184 | GW3: 185 | GX3: 186 | GY3: 187 | GZ3: 188 | HA3: 189 | HB3: 190 | HC3: 191 | HE3: 192 | HF3: 193 | HG3: 194 | HH3: 195 | HI3: 196 | HJ3: 197 | HK3: 198 | HL3: 199 | HN3: 200 | HO3: 201 | HP3: 202 | HQ3: 203 | HR3: 204 | HS3: 205 | HT3: 206 | HU3: 207 | HW3: 208 | HX3: 209 | HY3: 210 | HZ3: 211 | IA3: 212 | IB3: 213 | IC3: 214 | ID3: 215 | IF3: 216 | IG3: 217 | IH3: 218 | II3: 219 | IJ3: 220 | IK3: 221 | IL3: 222 | IM3: 223 | IO3: 224 | IP3: 225 | IQ3: 226 | IR3: 227 | IS3: 228 | IT3: 229 | IU3: 230 | IV3: 231 | IX3: 232 | IY3: 233 | IZ3: 234 | JA3: 235 | JB3: 236 | JC3: 237 | JD3: 238 | JE3: 239 | JG3: 240 | JH3: 241 | JI3: 242 | JJ3: 243 | JK3: 244 | JL3: 245 | JM3: 246 | JN3: 247 | JP3: 248 | JQ3: 249 | JR3: 250 | JS3: 251 | JT3: 252 | JU3: 253 | JV3: 254 | JW3: 255 | JY3: 256
B4: Ciclo de Pago 01 al 30 de Junio - Haber basico
B5: Ciclo de HE: 15 de mayo al 14 de junio del 2021
A7: N° | B7: DNI | C7: COD. SAP | D7: UBICACIÓN | E7: APELLIDOS Y NOMBRES | F7: PUESTO | G7: FECHA INGRESO | H7: Fecha de ingreso Site | I7: FECHA DE CESE | J7: 44331 | S7: =J7+1 -> 44332 | AB7: =S7+1 -> 44333 | AK7: =AB7+1 -> 44334 | AT7: =AK7+1 -> 44335 | BC7: =AT7+1 -> 44336 | BL7: =BC7+1 -> 44337 | BU7: =BL7+1 -> 44338 | CD7: =BU7+1 -> 44339 | CM7: =CD7+1 -> 44340 | CV7: =CM7+1 -> 44341 | DE7: =CV7+1 -> 44342 | DN7: =DE7+1 -> 44343 | DW7: =DN7+1 -> 44344 | EF7: =DW7+1 -> 44345 | EO7: =EF7+1 -> 44346 | EX7: =EO7+1 -> 44347 | FG7: =EX7+1 -> 44348 | FP7: =FG7+1 -> 44349 | FY7: =FP7+1 -> 44350 | GH7: =FY7+1 -> 44351 | GQ7: =GH7+1 -> 44352 | GZ7: =GQ7+1 -> 44353 | HI7: =GZ7+1 -> 44354 | HR7: =HI7+1 -> 44355 | IA7: =HR7+1 -> 44356 | IJ7: =IA7+1 -> 44357 | IS7: =IJ7+1 -> 44358 | JB7: =IS7+1 -> 44359 | JK7: =JB7+1 -> 44360 | JT7: =JK7+1 -> 44361 | KC7: =JT7+1 -> 44362 | KL7: =KC7+1 -> 44363 | KU7: =KL7+1 -> 44364 | LD7: =KU7+1 -> 44365 | LM7: =LD7+1 -> 44366 | LV7: =LM7+1 -> 44367 | ME7: =LV7+1 -> 44368 | MN7: =ME7+1 -> 44369 | MW7: =MN7+1 -> 44370 | NF7: =MW7+1 -> 44371 | NO7: =NF7+1 -> 44372 | NX7: =NO7+1 -> 44373 | OG7: =NX7+1 -> 44374 | OP7: =OG7+1 -> 44375 | OY7: =OP7+1 -> 44376 | PH7: =OY7+1 -> 44377 | PR7: DIAS TRABAJADOS | PS7: DESCANSO SEMANAL | PT7: FERIANO NO LABORADO | PU7: TOTAL DIAS TRABAJADOS | PV7: DIAS DESCANSO MEDICO | PY7: DIAS SUBSIDIO | QB7: DIAS VACACIONES | QE7: DIAS LICENCIA SIN GOCE | QH7: DIAS LICENCIA CON GOCE | QK7: DIAS FALTA 1 | QN7: DIAS FALTA MES ANTERIOR | QQ7: TOTAL DIAS | QR7: DIAS REINTEGRO DE ESTRUCTURA SALARIAL | QS7: HORAS EXTRAS DEL MES | QV7: REINTEGRO DE HORAS EXTRAS | QY7: DETALLE REINTEGRO HHEE | QZ7: DEL MES | RA7: REINTEGRO
J8: Entrada | K8: Salida | L8: Día | M8: Total Horas | N8: Horas Efectivas | O8: Normal | P8: 0.25 | Q8: 0.35 | R8: 1 | S8: Entrada | T8: Salida | U8: Día | V8: Total Horas | W8: Horas Efectivas | X8: Normal | Y8: 0.25 | Z8: 0.35 | AA8: 1 | AB8: Entrada | AC8: Salida | AD8: Día | AE8: Total Horas | AF8: Horas Efectivas | AG8: Normal | AH8: 0.25 | AI8: 0.35 | AJ8: 1 | AK8: Entrada | AL8: Salida | AM8: Día | AN8: Total Horas | AO8: Horas Efectivas | AP8: Normal | AQ8: 0.25 | AR8: 0.35 | AS8: 1 | AT8: Entrada | AU8: Salida | AV8: Día | AW8: Total Horas | AX8: Horas Efectivas | AY8: Normal | AZ8: 0.25 | BA8: 0.35 | BB8: 1 | BC8: Entrada | BD8: Salida | BE8: Día | BF8: Total Horas | BG8: Horas Efectivas | BH8: Normal | BI8: 0.25 | BJ8: 0.35 | BK8: 1 | BL8: Entrada | BM8: Salida | BN8: Día | BO8: Total Horas | BP8: Horas Efectivas | BQ8: Normal | BR8: 0.25 | BS8: 0.35 | BT8: 1 | BU8: Entrada | BV8: Salida | BW8: Día | BX8: Total Horas | BY8: Horas Efectivas | BZ8: Normal | CA8: 0.25 | CB8: 0.35 | CC8: 1 | CD8: Entrada | CE8: Salida | CF8: Día | CG8: Total Horas | CH8: Horas Efectivas | CI8: Normal | CJ8: 0.25 | CK8: 0.35 | CL8: 1 | CM8: Entrada | CN8: Salida | CO8: Día | CP8: Total Horas | CQ8: Horas Efectivas | CR8: Normal | CS8: 0.25 | CT8: 0.35 | CU8: 1 | CV8: Entrada | CW8: Salida | CX8: Día | CY8: Total Horas | CZ8: Horas Efectivas | DA8: Normal | DB8: 0.25 | DC8: 0.35 | DD8: 1 | DE8: Entrada | DF8: Salida | DG8: Día | DH8: Total Horas | DI8: Horas Efectivas | DJ8: Normal | DK8: 0.25 | DL8: 0.35 | DM8: 1 | DN8: Entrada | DO8: Salida | DP8: Día | DQ8: Total Horas | DR8: Horas Efectivas | DS8: Normal | DT8: 0.25 | DU8: 0.35 | DV8: 1 | DW8: Entrada | DX8: Salida | DY8: Día | DZ8: Total Horas | EA8: Horas Efectivas | EB8: Normal | EC8: 0.25 | ED8: 0.35 | EE8: 1 | EF8: Entrada | EG8: Salida | EH8: Día | EI8: Total Horas | EJ8: Horas Efectivas | EK8: Normal | EL8: 0.25 | EM8: 0.35 | EN8: 1 | EO8: Entrada | EP8: Salida | EQ8: Día | ER8: Total Horas | ES8: Horas Efectivas | ET8: Normal | EU8: 0.25 | EV8: 0.35 | EW8: 1 | EX8: Entrada | EY8: Salida | EZ8: Día | FA8: Total Horas | FB8: Horas Efectivas | FC8: Normal | FD8: 0.25 | FE8: 0.35 | FF8: 1 | FG8: Entrada | FH8: Salida | FI8: Día | FJ8: Total Horas | FK8: Horas Efectivas | FL8: Normal | FM8: 0.25 | FN8: 0.35 | FO8: 1 | FP8: Entrada | FQ8: Salida | FR8: Día | FS8: Total Horas | FT8: Horas Efectivas | FU8: Normal | FV8: 0.25 | FW8: 0.35 | FX8: 1 | FY8: Entrada | FZ8: Salida | GA8: Día | GB8: Total Horas | GC8: Horas Efectivas | GD8: Normal | GE8: 0.25 | GF8: 0.35 | GG8: 1 | GH8: Entrada | GI8: Salida | GJ8: Día | GK8: Total Horas | GL8: Horas Efectivas | GM8: Normal | GN8: 0.25 | GO8: 0.35 | GP8: 1 | GQ8: Entrada | GR8: Salida | GS8: Día | GT8: Total Horas | GU8: Horas Efectivas | GV8: Normal | GW8: 0.25 | GX8: 0.35 | GY8: 1 | GZ8: Entrada | HA8: Salida | HB8: Día | HC8: Total Horas | HD8: Horas Efectivas | HE8: Normal | HF8: 0.25 | HG8: 0.35 | HH8: 1 | HI8: Entrada | HJ8: Salida | HK8: Día | HL8: Total Horas | HM8: Horas Efectivas | HN8: Normal | HO8: 0.25 | HP8: 0.35 | HQ8: 1 | HR8: Entrada | HS8: Salida | HT8: Día | HU8: Total Horas | HV8: Horas Efectivas | HW8: Normal | HX8: 0.25 | HY8: 0.35 | HZ8: 1 | IA8: Entrada | IB8: Salida | IC8: Día | ID8: Total Horas | IE8: Horas Efectivas | IF8: Normal | IG8: 0.25 | IH8: 0.35 | II8: 1 | IJ8: Entrada | IK8: Salida | IL8: Día | IM8: Total Horas | IN8: Horas Efectivas | IO8: Normal | IP8: 0.25 | IQ8: 0.35 | IR8: 1 | IS8: Entrada | IT8: Salida | IU8: Día | IV8: Total Horas | IW8: Horas Efectivas | IX8: Normal | IY8: 0.25 | IZ8: 0.35 | JA8: 1 | JB8: Entrada | JC8: Salida | JD8: Día | JE8: Total Horas | JF8: Horas Efectivas | JG8: Normal | JH8: 0.25 | JI8: 0.35 | JJ8: 1 | JK8: Entrada | JL8: Salida | JM8: Día | JN8: Total Horas | JO8: Horas Efectivas | JP8: Normal | JQ8: 0.25 | JR8: 0.35 | JS8: 1 | JT8: Entrada | JU8: Salida | JV8: Día | JW8: Total Horas | JX8: Horas Efectivas | JY8: Normal | JZ8: 0.25 | KA8: 0.35 | KB8: 1 | KC8: Entrada | KD8: Salida | KE8: Día | KF8: Total Horas | KG8: Horas Efectivas | KH8: Normal | KI8: 0.25 | KJ8: 0.35 | KK8: 1 | KL8: Entrada | KM8: Salida | KN8: Día | KO8: Total Horas | KP8: Horas Efectivas | KQ8: Normal | KR8: 0.25 | KS8: 0.35 | KT8: 1 | KU8: Entrada | KV8: Salida | KW8: Día | KX8: Total Horas | KY8: Horas Efectivas | KZ8: Normal | LA8: 0.25 | LB8: 0.35 | LC8: 1 | LD8: Entrada | LE8: Salida | LF8: Día | LG8: Total Horas | LH8: Horas Efectivas | LI8: Normal | LJ8: 0.25 | LK8: 0.35 | LL8: 1 | LM8: Entrada | LN8: Salida | LO8: Día | LP8: Total Horas | LQ8: Horas Efectivas | LR8: Normal | LS8: 0.25 | LT8: 0.35 | LU8: 1 | LV8: Entrada | LW8: Salida | LX8: Día | LY8: Total Horas | LZ8: Horas Efectivas | MA8: Normal | MB8: 0.25 | MC8: 0.35 | MD8: 1 | ME8: Entrada | MF8: Salida | MG8: Día | MH8: Total Horas | MI8: Horas Efectivas | MJ8: Normal | MK8: 0.25 | ML8: 0.35 | MM8: 1 | MN8: Entrada | MO8: Salida | MP8: Día | MQ8: Total Horas | MR8: Horas Efectivas | MS8: Normal | MT8: 0.25 | MU8: 0.35 | MV8: 1 | MW8: Entrada | MX8: Salida | MY8: Día | MZ8: Total Horas | NA8: Horas Efectivas | NB8: Normal | NC8: 0.25 | ND8: 0.35 | NE8: 1 | NF8: Entrada | NG8: Salida | NH8: Día | NI8: Total Horas | NJ8: Horas Efectivas | NK8: Normal | NL8: 0.25 | NM8: 0.35 | NN8: 1 | NO8: Entrada | NP8: Salida | NQ8: Día | NR8: Total Horas | NS8: Horas Efectivas | NT8: Normal | NU8: 0.25 | NV8: 0.35 | NW8: 1 | NX8: Entrada | NY8: Salida | NZ8: Día | OA8: Total Horas | OB8: Horas Efectivas | OC8: Normal | OD8: 0.25 | OE8: 0.35 | OF8: 1 | OG8: Entrada | OH8: Salida | OI8: Día | OJ8: Total Horas | OK8: Horas Efectivas | OL8: Normal | OM8: 0.25 | ON8: 0.35 | OO8: 1 | OP8: Entrada | OQ8: Salida | OR8: Día | OS8: Total Horas | OT8: Horas Efectivas | OU8: Normal | OV8: 0.25 | OW8: 0.35 | OX8: 1 | OY8: Entrada | OZ8: Salida | PA8: Día | PB8: Total Horas | PC8: Horas Efectivas | PD8: Normal | PE8: 0.25 | PF8: 0.35 | PG8: 1 | PH8: Entrada | PI8: Salida | PJ8: Día | PK8: Total Horas | PL8: Horas Efectivas | PM8: Normal | PN8: 0.25 | PO8: 0.35 | PP8: 1 | PV8: DESCANSO MEDICO | PW8: FECHA INICIO | PX8: FECHA TERMINO | PY8: SUBSIDIO | PZ8: FECHA INICIO | QA8: FECHA TERMINO | QB8: VACACIONES | QC8: FECHA INICIO | QD8: FECHA TERMINO | QE8: LSG | QF8: FECHA INICIO | QG8: FECHA TERMINO | QH8: LCG | QI8: FECHA INICIO | QJ8: FECHA TERMINO | QK8: FALTA1 | QL8: FECHA INICIO | QM8: FECHA TERMINO | QN8: FALTA1 | QO8: FECHA INICIO | QP8: FECHA TERMINO | QS8: 0.25 | QT8: 0.35 | QU8: DSO O FERIADO | QV8: 0.25 | QW8: 0.35 | QX8: DSO O FERIADO | QZ8: ASIGNACION POR TRANSPORTE | RA8: ASIGNACION POR TRANSPORTE | RB8: OTROS INGRESOS | RC8: NUEVO HABER BASICO (INCREMENTO O REDUCCION DE SUELDO) | RD8: FECHA DE FIN? | RE8: CONCEPTO 1 | RF8: CONCEPTO 2 | RG8: Bono Nocturno
JZ9: =IF(JV9="NOR",IF(JW9>10,2,IF(JW9>8,(JW9-JY9),0)),0) -> 0 | KA9: =IF(JV9="NOR",IF(JW9<10,0,IF(JW9>10,(JW9-(JY9+JZ9)),0)),0) -> 0 | KB9: =IF(JV9="DOM",JW9,0) -> 0
A10: 1 | B10: 80124762 | D10: PROYECTO | E10: ALLEMAN LLASACA KARIN GUISELA | F10: VIGÍA | G10: 44348 | H10: 44348 | J10: 0 | K10: 0 | L10: NA | M10: =SUM(K10-J10) -> 0 | N10: =IF(M10>1,M10-1,0) -> 0 | O10: =IF(D10="STAFF",IF(L10="NOR",IF(N10>8.5,8.5,N10),0),IF(L10="NOR",IF(N10>8,8,N10),IF(D10="CAMPO",IF(L10="NOR",IF(N10>8,8,N10),0),IF(L10="NOR",IF(N10>8,8,N10),0)))) -> 0 | P10: =IF(L10="NOR",IF(N10>10,2,IF(N10>8,(N10-O10),0)),0) -> 0 | Q10: =IF(L10="NOR",IF(N10<10,0,IF(N10>10,(N10-(O10+P10)),0)),0) -> 0 | R10: =IF(L10="DOM",N10,0) -> 0 | S10: 0 | T10: 0 | U10: NA | V10: =SUM(T10-S10) -> 0 | W10: =IF(V10>1,V10-1,0) -> 0 | X10: =IF(D10="STAFF",IF(U10="NOR",IF(W10>8.5,8.5,W10),0),IF(U10="NOR",IF(W10>8,8,W10),IF(M10="CAMPO",IF(U10="NOR",IF(W10>8,8,W10),0),IF(U10="NOR",IF(W10>8,8,W10),0)))) -> 0 | Y10: =IF(U10="NOR",IF(W10>10,2,IF(W10>8,(W10-X10),0)),0) -> 0 | Z10: =IF(U10="NOR",IF(W10<10,0,IF(W10>10,(W10-(X10+Y10)),0)),0) -> 0 | AA10: =IF(U10="DOM",W10,0) -> 0 | AB10: 0 | AC10: 0 | AD10: NA | AE10: =SUM(AC10-AB10) -> 0 | AF10: =IF(AE10>1,AE10-1,0) -> 0 | AG10: =IF(D10="STAFF",IF(AD10="NOR",IF(AF10>8.5,8.5,AF10),0),IF(AD10="NOR",IF(AF10>8,8,AF10),IF(AE10="CAMPO",IF(AD10="NOR",IF(AF10>8,8,AF10),0),IF(AD10="NOR",IF(AF10>8,8,AF10),0)))) -> 0 | AH10: =IF(AD10="NOR",IF(AF10>10,2,IF(AF10>8,(AF10-AG10),0)),0) -> 0 | AI10: =IF(AD10="NOR",IF(AF10<10,0,IF(AF10>10,(AF10-(AG10+AH10)),0)),0) -> 0 | AJ10: =IF(AD10="DOM",AF10,0) -> 0 | AK10: 0 | AL10: 0 | AM10: NA | AN10: =SUM(AL10-AK10) -> 0 | AO10: =IF(AN10>1,AN10-1,0) -> 0 | AP10: =IF(D10="PROYECTO",IF(AM10="NOR",IF(AO10>8,8,AO10),0),IF(AM10="NOR",IF(AO10>8,8,AO10),0)) -> 0 | AQ10: =IF(AM10="NOR",IF(AO10>10,2,IF(AO10>8,(AO10-AP10),0)),0) -> 0 | AR10: =IF(AM10="NOR",IF(AO10<10,0,IF(AO10>10,(AO10-(AP10+AQ10)),0)),0) -> 0 | AS10: =IF(AM10="DOM",AO10,0) -> 0 | AT10: 0 | AU10: 0 | AV10: NA | AW10: =SUM(AU10-AT10) -> 0 | AX10: =IF(AW10>1,AW10-1,0) -> 0 | AY10: =IF(AO10="PROYECTO",IF(AV10="NOR",IF(AX10>8,8,AX10),0),IF(AV10="NOR",IF(AX10>8,8,AX10),0)) -> 0 | AZ10: =IF(AV10="NOR",IF(AX10>10,2,IF(AX10>8,(AX10-AY10),0)),0) -> 0 | BA10: =IF(AV10="NOR",IF(AX10<10,0,IF(AX10>10,(AX10-(AY10+AZ10)),0)),0) -> 0 | BB10: =IF(AV10="DOM",AX10,0) -> 0 | BC10: 0 | BD10: 0 | BE10: NA | BF10: =SUM(BD10-BC10) -> 0 | BG10: =IF(BF10>1,BF10-1,0) -> 0 | BH10: =IF(D10="STAFF",IF(BE10="NOR",IF(BG10>8.5,8.5,BG10),0),IF(BE10="NOR",IF(BG10>8,8,BG10),IF(BF10="CAMPO",IF(BE10="NOR",IF(BG10>8,8,BG10),0),IF(BE10="NOR",IF(BG10>8,8,BG10),0)))) -> 0 | BI10: =IF(BE10="NOR",IF(BG10>10,2,IF(BG10>8,(BG10-BH10),0)),0) -> 0 | BJ10: =IF(BE10="NOR",IF(BG10<10,0,IF(BG10>10,(BG10-(BH10+BI10)),0)),0) -> 0 | BK10: =IF(BE10="DOM",BG10,0) -> 0 | BL10: 0 | BM10: 0 | BN10: NA | BO10: =SUM(BM10-BL10) -> 0 | BP10: =IF(BO10>1,BO10-1,0) -> 0 | BQ10: =IF(D10="STAFF",IF(BN10="NOR",IF(BP10>8.5,8.5,BP10),0),IF(BN10="NOR",IF(BP10>8,8,BP10),IF(BO10="CAMPO",IF(BN10="NOR",IF(BP10>8,8,BP10),0),IF(BN10="NOR",IF(BP10>8,8,BP10),0)))) -> 0 | BR10: =IF(BN10="NOR",IF(BP10>10,2,IF(BP10>8,(BP10-BQ10),0)),0) -> 0 | BS10: =IF(BN10="NOR",IF(BP10<10,0,IF(BP10>10,(BP10-(BQ10+BR10)),0)),0) -> 0 | BT10: =IF(BN10="DOM",BP10,0) -> 0 | BU10: 0 | BV10: 0 | BW10: NA | BX10: =SUM(BV10-BU10) -> 0 | BY10: =IF(BX10>1,BX10-1,0) -> 0 | BZ10: =IF(D10="STAFF",IF(BW10="NOR",IF(BY10>8.5,8.5,BY10),0),IF(BW10="NOR",IF(BY10>8,8,BY10),IF(BX10="CAMPO",IF(BW10="NOR",IF(BY10>8,8,BY10),0),IF(BW10="NOR",IF(BY10>8,8,BY10),0)))) -> 0 | CA10: =IF(BW10="NOR",IF(BY10>10,2,IF(BY10>8,(BY10-BZ10),0)),0) -> 0 | CB10: =IF(BW10="NOR",IF(BY10<10,0,IF(BY10>10,(BY10-(BZ10+CA10)),0)),0) -> 0 | CC10: =IF(BW10="DOM",BY10,0) -> 0 | CD10: 0 | CE10: 0 | CF10: NA | CG10: =SUM(CE10-CD10) -> 0 | CH10: =IF(CG10>1,CG10-1,0) -> 0 | CI10: =IF(D10="STAFF",IF(CF10="NOR",IF(CH10>8.5,8.5,CH10),0),IF(CF10="NOR",IF(CH10>8,8,CH10),IF(CG10="CAMPO",IF(CF10="NOR",IF(CH10>8,8,CH10),0),IF(CF10="NOR",IF(CH10>8,8,CH10),0)))) -> 0 | CJ10: =IF(CF10="NOR",IF(CH10>10,2,IF(CH10>8,(CH10-CI10),0)),0) -> 0 | CK10: =IF(CF10="NOR",IF(CH10<10,0,IF(CH10>10,(CH10-(CI10+CJ10)),0)),0) -> 0 | CL10: =IF(CF10="DOM",CH10,0) -> 0 | CM10: 0 | CN10: 0 | CO10: NA | CP10: =SUM(CN10-CM10) -> 0 | CQ10: =IF(CP10>1,CP10-1,0) -> 0 | CR10: =IF(D10="STAFF",IF(CO10="NOR",IF(CQ10>8.5,8.5,CQ10),0),IF(CO10="NOR",IF(CQ10>8,8,CQ10),IF(CP10="CAMPO",IF(CO10="NOR",IF(CQ10>8,8,CQ10),0),IF(CO10="NOR",IF(CQ10>8,8,CQ10),0)))) -> 0 | CS10: =IF(CO10="NOR",IF(CQ10>10,2,IF(CQ10>8,(CQ10-CR10),0)),0) -> 0 | CT10: =IF(CO10="NOR",IF(CQ10<10,0,IF(CQ10>10,(CQ10-(CR10+CS10)),0)),0) -> 0 | CU10: =IF(CO10="DOM",CQ10,0) -> 0 | CV10: 0 | CW10: 0 | CX10: NA | CY10: =SUM(CW10-CV10) -> 0 | CZ10: =IF(CY10>1,CY10-1,0) -> 0 | DA10: =IF(CQ10="PROYECTO",IF(CX10="NOR",IF(CZ10>8,8,CZ10),0),IF(CX10="NOR",IF(CZ10>8,8,CZ10),0)) -> 0 | DB10: =IF(CX10="NOR",IF(CZ10>10,2,IF(CZ10>8,(CZ10-DA10),0)),0) -> 0 | DC10: =IF(CX10="NOR",IF(CZ10<10,0,IF(CZ10>10,(CZ10-(DA10+DB10)),0)),0) -> 0 | DD10: =IF(CX10="DOM",CZ10,0) -> 0 | DE10: 0 | DF10: 0 | DG10: NA | DH10: =SUM(DF10-DE10) -> 0 | DI10: =IF(DH10>1,DH10-1,0) -> 0 | DJ10: =IF(CZ10="PROYECTO",IF(DG10="NOR",IF(DI10>8,8,DI10),0),IF(DG10="NOR",IF(DI10>8,8,DI10),0)) -> 0 | DK10: =IF(DG10="NOR",IF(DI10>10,2,IF(DI10>8,(DI10-DJ10),0)),0) -> 0 | DL10: =IF(DG10="NOR",IF(DI10<10,0,IF(DI10>10,(DI10-(DJ10+DK10)),0)),0) -> 0 | DM10: =IF(DG10="DOM",DI10,0) -> 0 | DN10: 0 | DO10: 0 | DP10: NA | DQ10: =SUM(DO10-DN10) -> 0 | DR10: =IF(DQ10>1,DQ10-1,0) -> 0 | DS10: =IF(D10="STAFF",IF(DP10="NOR",IF(DR10>8.5,8.5,DR10),0),IF(DP10="NOR",IF(DR10>8,8,DR10),IF(DQ10="CAMPO",IF(DP10="NOR",IF(DR10>8,8,DR10),0),IF(DP10="NOR",IF(DR10>8,8,DR10),0)))) -> 0 | DT10: =IF(DP10="NOR",IF(DR10>10,2,IF(DR10>8,(DR10-DS10),0)),0) -> 0 | DU10: =IF(DP10="NOR",IF(DR10<10,0,IF(DR10>10,(DR10-(DS10+DT10)),0)),0) -> 0 | DV10: =IF(DP10="DOM",DR10,0) -> 0 | DW10: 0 | DX10: 0 | DY10: NA | DZ10: =SUM(DX10-DW10) -> 0 | EA10: =IF(DZ10>1,DZ10-1,0) -> 0 | EB10: =IF(D10="STAFF",IF(DY10="NOR",IF(EA10>8.5,8.5,EA10),0),IF(DY10="NOR",IF(EA10>8,8,EA10),IF(DZ10="CAMPO",IF(DY10="NOR",IF(EA10>8,8,EA10),0),IF(DY10="NOR",IF(EA10>8,8,EA10),0)))) -> 0 | EC10: =IF(DY10="NOR",IF(EA10>10,2,IF(EA10>8,(EA10-EB10),0)),0) -> 0 | ED10: =IF(DY10="NOR",IF(EA10<10,0,IF(EA10>10,(EA10-(EB10+EC10)),0)),0) -> 0 | EE10: =IF(DY10="DOM",EA10,0) -> 0 | EF10: 0 | EG10: 0 | EH10: NA | EI10: =SUM(EG10-EF10) -> 0 | EJ10: =IF(EI10>1,EI10-1,0) -> 0 | EK10: =IF(D10="STAFF",IF(EH10="NOR",IF(EJ10>8.5,8.5,EJ10),0),IF(EH10="NOR",IF(EJ10>8,8,EJ10),IF(EI10="CAMPO",IF(EH10="NOR",IF(EJ10>8,8,EJ10),0),IF(EH10="NOR",IF(EJ10>8,8,EJ10),0)))) -> 0 | EL10: =IF(EH10="NOR",IF(EJ10>10,2,IF(EJ10>8,(EJ10-EK10),0)),0) -> 0 | EM10: =IF(EH10="NOR",IF(EJ10<10,0,IF(EJ10>10,(EJ10-(EK10+EL10)),0)),0) -> 0 | EN10: =IF(EH10="DOM",EJ10,0) -> 0 | EO10: 0 | EP10: 0 | EQ10: NA | ER10: =SUM(EP10-EO10) -> 0 | ES10: =IF(ER10>1,ER10-1,0) -> 0 | ET10: =IF(D10="STAFF",IF(EQ10="NOR",IF(ES10>8.5,8.5,ES10),0),IF(EQ10="NOR",IF(ES10>8,8,ES10),IF(ER10="CAMPO",IF(EQ10="NOR",IF(ES10>8,8,ES10),0),IF(EQ10="NOR",IF(ES10>8,8,ES10),0)))) -> 0 | EU10: =IF(EQ10="NOR",IF(ES10>10,2,IF(ES10>8,(ES10-ET10),0)),0) -> 0 | EV10: =IF(EQ10="NOR",IF(ES10<10,0,IF(ES10>10,(ES10-(ET10+EU10)),0)),0) -> 0 | EW10: =IF(EQ10="DOM",ES10,0) -> 0 | EX10: 0 | EY10: 0 | EZ10: NA | FA10: =SUM(EY10-EX10) -> 0 | FB10: =IF(FA10>1,FA10-1,0) -> 0 | FC10: =IF(D10="STAFF",IF(EZ10="NOR",IF(FB10>8.5,8.5,FB10),0),IF(EZ10="NOR",IF(FB10>8,8,FB10),IF(FA10="CAMPO",IF(EZ10="NOR",IF(FB10>8,8,FB10),0),IF(EZ10="NOR",IF(FB10>8,8,FB10),0)))) -> 0 | FD10: =IF(EZ10="NOR",IF(FB10>10,2,IF(FB10>8,(FB10-FC10),0)),0) -> 0 | FE10: =IF(EZ10="NOR",IF(FB10<10,0,IF(FB10>10,(FB10-(FC10+FD10)),0)),0) -> 0 | FF10: =IF(EZ10="DOM",FB10,0) -> 0 | FG10: 7 | FH10: 18 | FI10: NOR | FJ10: =SUM(FH10-FG10) -> 11 | FK10: =IF(FJ10>1,FJ10-1,0) -> 10 | FL10: =IF(D10="STAFF",IF(FI10="NOR",IF(FK10>8.5,8.5,FK10),0),IF(FI10="NOR",IF(FK10>8,8,FK10),IF(FJ10="CAMPO",IF(FI10="NOR",IF(FK10>8,8,FK10),0),IF(FI10="NOR",IF(FK10>8,8,FK10),0)))) -> 8 | FM10: =IF(FI10="NOR",IF(FK10>10,2,IF(FK10>8,(FK10-FL10),0)),0) -> 2 | FN10: =IF(FI10="NOR",IF(FK10<10,0,IF(FK10>10,(FK10-(FL10+FM10)),0)),0) -> 0 | FO10: =IF(FI10="DOM",FK10,0) -> 0 | FP10: 7 | FQ10: 18 | FR10: NOR | FS10: =SUM(FQ10-FP10) -> 11 | FT10: =IF(FS10>1,FS10-1,0) -> 10 | FU10: =IF(FK10="PROYECTO",IF(FR10="NOR",IF(FT10>8,8,FT10),0),IF(FR10="NOR",IF(FT10>8,8,FT10),0)) -> 8 | FV10: =IF(FR10="NOR",IF(FT10>10,2,IF(FT10>8,(FT10-FU10),0)),0) -> 2 | FW10: =IF(FR10="NOR",IF(FT10<10,0,IF(FT10>10,(FT10-(FU10+FV10)),0)),0) -> 0 | FX10: =IF(FR10="DOM",FT10,0) -> 0 | FY10: 7 | FZ10: 18 | GA10: NOR | GB10: =SUM(FZ10-FY10) -> 11 | GC10: =IF(GB10>1,GB10-1,0) -> 10 | GD10: =IF(D10="STAFF",IF(GA10="NOR",IF(GC10>8.5,8.5,GC10),0),IF(GA10="NOR",IF(GC10>8,8,GC10),IF(GB10="CAMPO",IF(GA10="NOR",IF(GC10>8,8,GC10),0),IF(GA10="NOR",IF(GC10>8,8,GC10),0)))) -> 8 | GE10: =IF(GA10="NOR",IF(GC10>10,2,IF(GC10>8,(GC10-GD10),0)),0) -> 2 | GF10: =IF(GA10="NOR",IF(GC10<10,0,IF(GC10>10,(GC10-(GD10+GE10)),0)),0) -> 0 | GG10: =IF(GA10="DOM",GC10,0) -> 0 | GH10: 7 | GI10: 18 | GJ10: NOR | GK10: =SUM(GI10-GH10) -> 11 | GL10: =IF(GK10>1,GK10-1,0) -> 10 | GM10: =IF(D10="STAFF",IF(GJ10="NOR",IF(GL10>8.5,8.5,GL10),0),IF(GJ10="NOR",IF(GL10>8,8,GL10),IF(GK10="CAMPO",IF(GJ10="NOR",IF(GL10>8,8,GL10),0),IF(GJ10="NOR",IF(GL10>8,8,GL10),0)))) -> 8 | GN10: =IF(GJ10="NOR",IF(GL10>10,2,IF(GL10>8,(GL10-GM10),0)),0) -> 2 | GO10: =IF(GJ10="NOR",IF(GL10<10,0,IF(GL10>10,(GL10-(GM10+GN10)),0)),0) -> 0 | GP10: =IF(GJ10="DOM",GL10,0) -> 0 | GQ10: 7 | GR10: 18 | GS10: NOR | GT10: =SUM(GR10-GQ10) -> 11 | GU10: =IF(GT10>1,GT10-1,0) -> 10 | GV10: =IF(D10="STAFF",IF(GS10="NOR",IF(GU10>8.5,8.5,GU10),0),IF(GS10="NOR",IF(GU10>8,8,GU10),IF(GT10="CAMPO",IF(GS10="NOR",IF(GU10>8,8,GU10),0),IF(GS10="NOR",IF(GU10>8,8,GU10),0)))) -> 8 | GW10: =IF(GS10="NOR",IF(GU10>10,2,IF(GU10>8,(GU10-GV10),0)),0) -> 2 | GX10: =IF(GS10="NOR",IF(GU10<10,0,IF(GU10>10,(GU10-(GV10+GW10)),0)),0) -> 0 | GY10: =IF(GS10="DOM",GU10,0) -> 0 | GZ10: 0 | HA10: 0 | HB10: DS | HC10: =SUM(HA10-GZ10) -> 0 | HD10: =IF(HC10>1,HC10-1,0) -> 0 | HE10: =IF(D10="STAFF",IF(HB10="NOR",IF(HD10>8.5,8.5,HD10),0),IF(HB10="NOR",IF(HD10>8,8,HD10),IF(HC10="CAMPO",IF(HB10="NOR",IF(HD10>8,8,HD10),0),IF(HB10="NOR",IF(HD10>8,8,HD10),0)))) -> 0 | HF10: =IF(HB10="NOR",IF(HD10>10,2,IF(HD10>8,(HD10-HE10),0)),0) -> 0 | HG10: =IF(HB10="NOR",IF(HD10<10,0,IF(HD10>10,(HD10-(HE10+HF10)),0)),0) -> 0 | HH10: =IF(HB10="DOM",HD10,0) -> 0 | HI10: 7 | HJ10: 18 | HK10: NOR | HL10: =SUM(HJ10-HI10) -> 11 | HM10: =IF(HL10>1,HL10-1,0) -> 10 | HN10: =IF(D10="STAFF",IF(HK10="NOR",IF(HM10>8.5,8.5,HM10),0),IF(HK10="NOR",IF(HM10>8,8,HM10),IF(HL10="CAMPO",IF(HK10="NOR",IF(HM10>8,8,HM10),0),IF(HK10="NOR",IF(HM10>8,8,HM10),0)))) -> 8 | HO10: =IF(HK10="NOR",IF(HM10>10,2,IF(HM10>8,(HM10-HN10),0)),0) -> 2 | HP10: =IF(HK10="NOR",IF(HM10<10,0,IF(HM10>10,(HM10-(HN10+HO10)),0)),0) -> 0 | HQ10: =IF(HK10="DOM",HM10,0) -> 0 | HR10: 7 | HS10: 18 | HT10: NOR | HU10: =SUM(HS10-HR10) -> 11 | HV10: =IF(HU10>1,HU10-1,0) -> 10 | HW10: =IF(D10="STAFF",IF(HT10="NOR",IF(HV10>8.5,8.5,HV10),0),IF(HT10="NOR",IF(HV10>8,8,HV10),IF(HU10="CAMPO",IF(HT10="NOR",IF(HV10>8,8,HV10),0),IF(HT10="NOR",IF(HV10>8,8,HV10),0)))) -> 8 | HX10: =IF(HT10="NOR",IF(HV10>10,2,IF(HV10>8,(HV10-HW10),0)),0) -> 2 | HY10: =IF(HT10="NOR",IF(HV10<10,0,IF(HV10>10,(HV10-(HW10+HX10)),0)),0) -> 0 | HZ10: =IF(HT10="DOM",HV10,0) -> 0 | IA10: 7 | IB10: 18 | IC10: NOR | ID10: =SUM(IB10-IA10) -> 11 | IE10: =IF(ID10>1,ID10-1,0) -> 10 | IF10: =IF(D10="STAFF",IF(IC10="NOR",IF(IE10>8.5,8.5,IE10),0),IF(IC10="NOR",IF(IE10>8,8,IE10),IF(ID10="CAMPO",IF(IC10="NOR",IF(IE10>8,8,IE10),0),IF(IC10="NOR",IF(IE10>8,8,IE10),0)))) -> 8 | IG10: =IF(IC10="NOR",IF(IE10>10,2,IF(IE10>8,(IE10-IF10),0)),0) -> 2 | IH10: =IF(IC10="NOR",IF(IE10<10,0,IF(IE10>10,(IE10-(IF10+IG10)),0)),0) -> 0 | II10: =IF(IC10="DOM",IE10,0) -> 0 | IJ10: 7 | IK10: 13 | IL10: NOR | IM10: =SUM(IK10-IJ10) -> 6 | IN10: =IF(IM10>1,IM10-1,0) -> 5 | IO10: =IF(D10="STAFF",IF(IL10="NOR",IF(IN10>8.5,8.5,IN10),0),IF(IL10="NOR",IF(IN10>8,8,IN10),IF(IM10="CAMPO",IF(IL10="NOR",IF(IN10>8,8,IN10),0),IF(IL10="NOR",IF(IN10>8,8,IN10),0)))) -> 5 | IP10: =IF(IL10="NOR",IF(IN10>10,2,IF(IN10>8,(IN10-IO10),0)),0) -> 0 | IQ10: =IF(IL10="NOR",IF(IN10<10,0,IF(IN10>10,(IN10-(IO10+IP10)),0)),0) -> 0 | IR10: =IF(IL10="DOM",IN10,0) -> 0 | IS10: 7 | IT10: 18 | IU10: NOR | IV10: =SUM(IT10-IS10) -> 11 | IW10: =IF(IV10>1,IV10-1,0) -> 10 | IX10: =IF(D10="STAFF",IF(IU10="NOR",IF(IW10>8.5,8.5,IW10),0),IF(IU10="NOR",IF(IW10>8,8,IW10),IF(IV10="CAMPO",IF(IU10="NOR",IF(IW10>8,8,IW10),0),IF(IU10="NOR",IF(IW10>8,8,IW10),0)))) -> 8 | IY10: =IF(IU10="NOR",IF(IW10>10,2,IF(IW10>8,(IW10-IX10),0)),0) -> 2 | IZ10: =IF(IU10="NOR",IF(IW10<10,0,IF(IW10>10,(IW10-(IX10+IY10)),0)),0) -> 0 | JA10: =IF(IU10="DOM",IW10,0) -> 0 | JB10: 7 | JC10: 18 | JD10: NOR | JE10: =SUM(JC10-JB10) -> 11 | JF10: =IF(JE10>1,JE10-1,0) -> 10 | JG10: =IF(D10="STAFF",IF(JD10="NOR",IF(JF10>8.5,8.5,JF10),0),IF(JD10="NOR",IF(JF10>8,8,JF10),IF(JE10="CAMPO",IF(JD10="NOR",IF(JF10>8,8,JF10),0),IF(JD10="NOR",IF(JF10>8,8,JF10),0)))) -> 8 | JH10: =IF(JD10="NOR",IF(JF10>10,2,IF(JF10>8,(JF10-JG10),0)),0) -> 2 | JI10: =IF(JD10="NOR",IF(JF10<10,0,IF(JF10>10,(JF10-(JG10+JH10)),0)),0) -> 0 | JJ10: =IF(JD10="DOM",JF10,0) -> 0 | JK10: 0 | JL10: 0 | JM10: DS | JN10: =SUM(JL10-JK10) -> 0 | JO10: =IF(JN10>1,JN10-1,0) -> 0 | JP10: =IF(D10="STAFF",IF(JM10="NOR",IF(JO10>8.5,8.5,JO10),0),IF(JM10="NOR",IF(JO10>8,8,JO10),IF(JN10="CAMPO",IF(JM10="NOR",IF(JO10>8,8,JO10),0),IF(JM10="NOR",IF(JO10>8,8,JO10),0)))) -> 0 | JQ10: =IF(JM10="NOR",IF(JO10>10,2,IF(JO10>8,(JO10-JP10),0)),0) -> 0 | JR10: =IF(JM10="NOR",IF(JO10<10,0,IF(JO10>10,(JO10-(JP10+JQ10)),0)),0) -> 0 | JS10: =IF(JM10="DOM",JO10,0) -> 0 | JT10: 7 | JU10: 18 | JV10: NOR | JW10: =SUM(JU10-JT10) -> 11 | JX10: =IF(JW10>1,JW10-1,0) -> 10 | JY10: =IF(D10="STAFF",IF(JV10="NOR",IF(JX10>8.5,8.5,JX10),0),IF(JV10="NOR",IF(JX10>8,8,JX10),IF(JW10="CAMPO",IF(JV10="NOR",IF(JX10>8,8,JX10),0),IF(JV10="NOR",IF(JX10>8,8,JX10),0)))) -> 8 | JZ10: =IF(JV10="NOR",IF(JX10>10,2,IF(JX10>8,(JX10-JY10),0)),0) -> 2 | KA10: =IF(JV10="NOR",IF(JX10<10,0,IF(JX10>10,(JX10-(JY10+JZ10)),0)),0) -> 0 | KB10: =IF(JV10="DOM",JX10,0) -> 0 | KC10: 7 | KD10: 16 | KE10: NOR | KF10: =SUM(KD10-KC10) -> 9 | KG10: =IF(KF10>1,KF10-1,0) -> 8 | KH10: =IF(D10="STAFF",IF(KE10="NOR",IF(KG10>8.5,8.5,KG10),0),IF(KE10="NOR",IF(KG10>8,8,KG10),IF(KF10="CAMPO",IF(KE10="NOR",IF(KG10>8,8,KG10),0),IF(KE10="NOR",IF(KG10>8,8,KG10),0)))) -> 8 | KI10: =IF(KE10="NOR",IF(KG10>10,2,IF(KG10>8,(KG10-KH10),0)),0) -> 0 | KJ10: =IF(KE10="NOR",IF(KG10<10,0,IF(KG10>10,(KG10-(KH10+KI10)),0)),0) -> 0 | KK10: =IF(KE10="DOM",KG10,0) -> 0 | KL10: 7 | KM10: 16 | KN10: NOR | KO10: =SUM(KM10-KL10) -> 9 | KP10: =IF(KO10>1,KO10-1,0) -> 8 | KQ10: =IF(D10="STAFF",IF(KN10="NOR",IF(KP10>8.5,8.5,KP10),0),IF(KN10="NOR",IF(KP10>8,8,KP10),IF(KO10="CAMPO",IF(KN10="NOR",IF(KP10>8,8,KP10),0),IF(KN10="NOR",IF(KP10>8,8,KP10),0)))) -> 8 | KR10: =IF(KN10="NOR",IF(KP10>10,2,IF(KP10>8,(KP10-KQ10),0)),0) -> 0 | KS10: =IF(KN10="NOR",IF(KP10<10,0,IF(KP10>10,(KP10-(KQ10+KR10)),0)),0) -> 0 | KT10: =IF(KN10="DOM",KP10,0) -> 0 | KU10: 7 | KV10: 16 | KW10: NOR | KX10: =SUM(KV10-KU10) -> 9 | KY10: =IF(KX10>1,KX10-1,0) -> 8 | KZ10: =IF(D10="STAFF",IF(KW10="NOR",IF(KY10>8.5,8.5,KY10),0),IF(KW10="NOR",IF(KY10>8,8,KY10),IF(KX10="CAMPO",IF(KW10="NOR",IF(KY10>8,8,KY10),0),IF(KW10="NOR",IF(KY10>8,8,KY10),0)))) -> 8 | LA10: =IF(KW10="NOR",IF(KY10>10,2,IF(KY10>8,(KY10-KZ10),0)),0) -> 0 | LB10: =IF(KW10="NOR",IF(KY10<10,0,IF(KY10>10,(KY10-(KZ10+LA10)),0)),0) -> 0 | LC10: =IF(KW10="DOM",KY10,0) -> 0 | LD10: 7 | LE10: 16 | LF10: NOR | LG10: =SUM(LE10-LD10) -> 9 | LH10: =IF(LG10>1,LG10-1,0) -> 8 | LI10: =IF(D10="STAFF",IF(LF10="NOR",IF(LH10>8.5,8.5,LH10),0),IF(LF10="NOR",IF(LH10>8,8,LH10),IF(LG10="CAMPO",IF(LF10="NOR",IF(LH10>8,8,LH10),0),IF(LF10="NOR",IF(LH10>8,8,LH10),0)))) -> 8 | LJ10: =IF(LF10="NOR",IF(LH10>10,2,IF(LH10>8,(LH10-LI10),0)),0) -> 0 | LK10: =IF(LF10="NOR",IF(LH10<10,0,IF(LH10>10,(LH10-(LI10+LJ10)),0)),0) -> 0 | LL10: =IF(LF10="DOM",LH10,0) -> 0 | LM10: 7 | LN10: 16 | LO10: NOR | LP10: =SUM(LN10-LM10) -> 9 | LQ10: =IF(LP10>1,LP10-1,0) -> 8 | LR10: =IF(D10="STAFF",IF(LO10="NOR",IF(LQ10>8.5,8.5,LQ10),0),IF(LO10="NOR",IF(LQ10>8,8,LQ10),IF(LP10="CAMPO",IF(LO10="NOR",IF(LQ10>8,8,LQ10),0),IF(LO10="NOR",IF(LQ10>8,8,LQ10),0)))) -> 8 | LS10: =IF(LO10="NOR",IF(LQ10>10,2,IF(LQ10>8,(LQ10-LR10),0)),0) -> 0 | LT10: =IF(LO10="NOR",IF(LQ10<10,0,IF(LQ10>10,(LQ10-(LR10+LS10)),0)),0) -> 0 | LU10: =IF(LO10="DOM",LQ10,0) -> 0 | LV10: 7 | LW10: 16 | LX10: NOR | LY10: =SUM(LW10-LV10) -> 9 | LZ10: =IF(LY10>1,LY10-1,0) -> 8 | MA10: =IF(D10="STAFF",IF(LX10="NOR",IF(LZ10>8.5,8.5,LZ10),0),IF(LX10="NOR",IF(LZ10>8,8,LZ10),IF(LY10="CAMPO",IF(LX10="NOR",IF(LZ10>8,8,LZ10),0),IF(LX10="NOR",IF(LZ10>8,8,LZ10),0)))) -> 8 | MB10: =IF(LX10="NOR",IF(LZ10>10,2,IF(LZ10>8,(LZ10-MA10),0)),0) -> 0 | MC10: =IF(LX10="NOR",IF(LZ10<10,0,IF(LZ10>10,(LZ10-(MA10+MB10)),0)),0) -> 0 | MD10: =IF(LX10="DOM",LZ10,0) -> 0 | ME10: 7 | MF10: 16 | MG10: NOR | MH10: =SUM(MF10-ME10) -> 9 | MI10: =IF(MH10>1,MH10-1,0) -> 8 | MJ10: =IF(D10="STAFF",IF(MG10="NOR",IF(MI10>8.5,8.5,MI10),0),IF(MG10="NOR",IF(MI10>8,8,MI10),IF(MH10="CAMPO",IF(MG10="NOR",IF(MI10>8,8,MI10),0),IF(MG10="NOR",IF(MI10>8,8,MI10),0)))) -> 8 | MK10: =IF(MG10="NOR",IF(MI10>10,2,IF(MI10>8,(MI10-MJ10),0)),0) -> 0 | ML10: =IF(MG10="NOR",IF(MI10<10,0,IF(MI10>10,(MI10-(MJ10+MK10)),0)),0) -> 0 | MM10: =IF(MG10="DOM",MI10,0) -> 0 | MN10: 7 | MO10: 16 | MP10: NOR | MQ10: =SUM(MO10-MN10) -> 9 | MR10: =IF(MQ10>1,MQ10-1,0) -> 8 | MS10: =IF(D10="STAFF",IF(MP10="NOR",IF(MR10>8.5,8.5,MR10),0),IF(MP10="NOR",IF(MR10>8,8,MR10),IF(MQ10="CAMPO",IF(MP10="NOR",IF(MR10>8,8,MR10),0),IF(MP10="NOR",IF(MR10>8,8,MR10),0)))) -> 8 | MT10: =IF(MP10="NOR",IF(MR10>10,2,IF(MR10>8,(MR10-MS10),0)),0) -> 0 | MU10: =IF(MP10="NOR",IF(MR10<10,0,IF(MR10>10,(MR10-(MS10+MT10)),0)),0) -> 0 | MV10: =IF(MP10="DOM",MR10,0) -> 0 | MW10: 7 | MX10: 16 | MY10: NOR | MZ10: =SUM(MX10-MW10) -> 9 | NA10: =IF(MZ10>1,MZ10-1,0) -> 8 | NB10: =IF(D10="STAFF",IF(MY10="NOR",IF(NA10>8.5,8.5,NA10),0),IF(MY10="NOR",IF(NA10>8,8,NA10),IF(MZ10="CAMPO",IF(MY10="NOR",IF(NA10>8,8,NA10),0),IF(MY10="NOR",IF(NA10>8,8,NA10),0)))) -> 8 | NC10: =IF(MY10="NOR",IF(NA10>10,2,IF(NA10>8,(NA10-NB10),0)),0) -> 0 | ND10: =IF(MY10="NOR",IF(NA10<10,0,IF(NA10>10,(NA10-(NB10+NC10)),0)),0) -> 0 | NE10: =IF(MY10="DOM",NA10,0) -> 0 | NF10: 7 | NG10: 16 | NH10: NOR | NI10: =SUM(NG10-NF10) -> 9 | NJ10: =IF(NI10>1,NI10-1,0) -> 8 | NK10: =IF(D10="STAFF",IF(NH10="NOR",IF(NJ10>8.5,8.5,NJ10),0),IF(NH10="NOR",IF(NJ10>8,8,NJ10),IF(NI10="CAMPO",IF(NH10="NOR",IF(NJ10>8,8,NJ10),0),IF(NH10="NOR",IF(NJ10>8,8,NJ10),0)))) -> 8 | NL10: =IF(NH10="NOR",IF(NJ10>10,2,IF(NJ10>8,(NJ10-NK10),0)),0) -> 0 | NM10: =IF(NH10="NOR",IF(NJ10<10,0,IF(NJ10>10,(NJ10-(NK10+NL10)),0)),0) -> 0 | NN10: =IF(NH10="DOM",NJ10,0) -> 0 | NO10: 7 | NP10: 16 | NQ10: NOR | NR10: =SUM(NP10-NO10) -> 9 | NS10: =IF(NR10>1,NR10-1,0) -> 8 | NT10: =IF(D10="STAFF",IF(NQ10="NOR",IF(NS10>8.5,8.5,NS10),0),IF(NQ10="NOR",IF(NS10>8,8,NS10),IF(NR10="CAMPO",IF(NQ10="NOR",IF(NS10>8,8,NS10),0),IF(NQ10="NOR",IF(NS10>8,8,NS10),0)))) -> 8 | NU10: =IF(NQ10="NOR",IF(NS10>10,2,IF(NS10>8,(NS10-NT10),0)),0) -> 0 | NV10: =IF(NQ10="NOR",IF(NS10<10,0,IF(NS10>10,(NS10-(NT10+NU10)),0)),0) -> 0 | NW10: =IF(NQ10="DOM",NS10,0) -> 0 | NX10: 7 | NY10: 16 | NZ10: NOR | OA10: =SUM(NY10-NX10) -> 9 | OB10: =IF(OA10>1,OA10-1,0) -> 8 | OC10: =IF(D10="STAFF",IF(NZ10="NOR",IF(OB10>8.5,8.5,OB10),0),IF(NZ10="NOR",IF(OB10>8,8,OB10),IF(OA10="CAMPO",IF(NZ10="NOR",IF(OB10>8,8,OB10),0),IF(NZ10="NOR",IF(OB10>8,8,OB10),0)))) -> 8 | OD10: =IF(NZ10="NOR",IF(OB10>10,2,IF(OB10>8,(OB10-OC10),0)),0) -> 0 | OE10: =IF(NZ10="NOR",IF(OB10<10,0,IF(OB10>10,(OB10-(OC10+OD10)),0)),0) -> 0 | OF10: =IF(NZ10="DOM",OB10,0) -> 0 | OG10: 0 | OH10: 0 | OI10: DS | OJ10: =SUM(OH10-OG10) -> 0 | OK10: =IF(OJ10>1,OJ10-1,0) -> 0 | OL10: =IF(D10="STAFF",IF(OI10="NOR",IF(OK10>8.5,8.5,OK10),0),IF(OI10="NOR",IF(OK10>8,8,OK10),IF(OJ10="CAMPO",IF(OI10="NOR",IF(OK10>8,8,OK10),0),IF(OI10="NOR",IF(OK10>8,8,OK10),0)))) -> 0 | OM10: =IF(OI10="NOR",IF(OK10>10,2,IF(OK10>8,(OK10-OL10),0)),0) -> 0 | ON10: =IF(OI10="NOR",IF(OK10<10,0,IF(OK10>10,(OK10-(OL10+OM10)),0)),0) -> 0 | OO10: =IF(OI10="DOM",OK10,0) -> 0 | OP10: 7 | OQ10: 16 | OR10: NOR | OS10: =SUM(OQ10-OP10) -> 9 | OT10: =IF(OS10>1,OS10-1,0) -> 8 | OU10: =IF(D10="STAFF",IF(OR10="NOR",IF(OT10>8.5,8.5,OT10),0),IF(OR10="NOR",IF(OT10>8,8,OT10),IF(OS10="CAMPO",IF(OR10="NOR",IF(OT10>8,8,OT10),0),IF(OR10="NOR",IF(OT10>8,8,OT10),0)))) -> 8 | OV10: =IF(OR10="NOR",IF(OT10>10,2,IF(OT10>8,(OT10-OU10),0)),0) -> 0 | OW10: =IF(OR10="NOR",IF(OT10<10,0,IF(OT10>10,(OT10-(OU10+OV10)),0)),0) -> 0 | OX10: =IF(OR10="DOM",OT10,0) -> 0 | OY10: 0 | OZ10: 0 | PA10: FE | PB10: =SUM(OZ10-OY10) -> 0 | PC10: =IF(PB10>1,PB10-1,0) -> 0 | PD10: =IF(D10="STAFF",IF(PA10="NOR",IF(PC10>8.5,8.5,PC10),0),IF(PA10="NOR",IF(PC10>8,8,PC10),IF(PB10="CAMPO",IF(PA10="NOR",IF(PC10>8,8,PC10),0),IF(PA10="NOR",IF(PC10>8,8,PC10),0)))) -> 0 | PE10: =IF(PA10="NOR",IF(PC10>10,2,IF(PC10>8,(PC10-PD10),0)),0) -> 0 | PF10: =IF(PA10="NOR",IF(PC10<10,0,IF(PC10>10,(PC10-(PD10+PE10)),0)),0) -> 0 | PG10: =IF(PA10="DOM",PC10,0) -> 0 | PH10: 7 | PI10: 16 | PJ10: NOR | PK10: =SUM(PI10-PH10) -> 9 | PL10: =IF(PK10>1,PK10-1,0) -> 8 | PM10: =IF(M10="STAFF",IF(PJ10="NOR",IF(PL10>8.5,8.5,PL10),0),IF(PJ10="NOR",IF(PL10>8,8,PL10),IF(PK10="CAMPO",IF(PJ10="NOR",IF(PL10>8,8,PL10),0),IF(PJ10="NOR",IF(PL10>8,8,PL10),0)))) -> 8 | PN10: =IF(PJ10="NOR",IF(PL10>10,2,IF(PL10>8,(PL10-PM10),0)),0) -> 0 | PO10: =IF(PJ10="NOR",IF(PL10<10,0,IF(PL10>10,(PL10-(PM10+PN10)),0)),0) -> 0 | PP10: =IF(PJ10="DOM",PL10,0) -> 0 | PR10: =COUNTIF(FG10:PP10,"NOR") -> 26 | PS10: =COUNTIF(FG10:PP10,"DS") -> 3 | PT10: =COUNTIF(FG10:PP10,"FE") -> 1 | PU10: =SUM(PR10:PT10) -> 30 | PV10: =COUNTIF(FG10:PP10,"DM") -> 0 | PY10: =COUNTIF(FG10:PP10,"SUB") -> 0 | QB10: =COUNTIF(FG10:PP10,"VA") -> 0 | QE10: =COUNTIF(FG10:PP10,"LSG") -> 0 | QH10: =COUNTIF(FG10:PP10,"LCG") -> 0 | QK10: =COUNTIF(FG10:PP10,"FA") -> 0 | QN10: =COUNTIF(J10:FF10,"FA") -> 0 | QQ10: =PU10+PV10+PY10+QB10+QE10+QH10+QK10+QN10 -> 30 | QS10: =P10+Y10++AH10+AQ10+AZ10+BI10+BR10+CA10+CJ10+CS10+DB10+DK10+DT10+EC10+EL10+EU10+FD10+FM10+FV10+GE10+GN10+GW10+HF10+HO10+HX10+IG10+IP10+IY10+JH10+JQ10+JZ10 -> 22 | QT10: =Q10+Z10++AI10+AR10+BA10+BJ10+BS10+CB10+CK10+CT10+DC10+DL10+DU10+ED10+EM10+EV10+FE10+FN10+FW10+GF10+GO10+GX10+HG10+HP10+HY10+IH10+IQ10+IZ10+JI10+JR10+KA10 -> 0 | RG10: 1
A11: =A10+1 -> 2 | B11: 48135459 | D11: PROYECTO | E11: AMADO LA ROSA PAMELA LUCERO | F11: VIGÍA | G11: 44291 | H11: 44295 | J11: 7 | K11: 18 | L11: NOR | M11: =SUM(K11-J11) -> 11 | N11: =IF(M11>1,M11-1,0) -> 10 | O11: =IF(D11="STAFF",IF(L11="NOR",IF(N11>8.5,8.5,N11),0),IF(L11="NOR",IF(N11>8,8,N11),IF(D11="CAMPO",IF(L11="NOR",IF(N11>8,8,N11),0),IF(L11="NOR",IF(N11>8,8,N11),0)))) -> 8 | P11: =IF(L11="NOR",IF(N11>10,2,IF(N11>8,(N11-O11),0)),0) -> 2 | Q11: =IF(L11="NOR",IF(N11<10,0,IF(N11>10,(N11-(O11+P11)),0)),0) -> 0 | R11: =IF(L11="DOM",N11,0) -> 0 | S11: 0 | T11: 0 | U11: DS | V11: =SUM(T11-S11) -> 0 | W11: =IF(V11>1,V11-1,0) -> 0 | X11: =IF(D11="STAFF",IF(U11="NOR",IF(W11>8.5,8.5,W11),0),IF(U11="NOR",IF(W11>8,8,W11),IF(M11="CAMPO",IF(U11="NOR",IF(W11>8,8,W11),0),IF(U11="NOR",IF(W11>8,8,W11),0)))) -> 0 | Y11: =IF(U11="NOR",IF(W11>10,2,IF(W11>8,(W11-X11),0)),0) -> 0 | Z11: =IF(U11="NOR",IF(W11<10,0,IF(W11>10,(W11-(X11+Y11)),0)),0) -> 0 | AA11: =IF(U11="DOM",W11,0) -> 0 | AB11: 7 | AC11: 18 | AD11: NOR | AE11: =SUM(AC11-AB11) -> 11 | AF11: =IF(AE11>1,AE11-1,0) -> 10 | AG11: =IF(D11="STAFF",IF(AD11="NOR",IF(AF11>8.5,8.5,AF11),0),IF(AD11="NOR",IF(AF11>8,8,AF11),IF(AE11="CAMPO",IF(AD11="NOR",IF(AF11>8,8,AF11),0),IF(AD11="NOR",IF(AF11>8,8,AF11),0)))) -> 8 | AH11: =IF(AD11="NOR",IF(AF11>10,2,IF(AF11>8,(AF11-AG11),0)),0) -> 2 | AI11: =IF(AD11="NOR",IF(AF11<10,0,IF(AF11>10,(AF11-(AG11+AH11)),0)),0) -> 0 | AJ11: =IF(AD11="DOM",AF11,0) -> 0 | AK11: 7 | AL11: 18 | AM11: NOR | AN11: =SUM(AL11-AK11) -> 11 | AO11: =IF(AN11>1,AN11-1,0) -> 10 | AP11: =IF(D11="PROYECTO",IF(AM11="NOR",IF(AO11>8,8,AO11),0),IF(AM11="NOR",IF(AO11>8,8,AO11),0)) -> 8 | AQ11: =IF(AM11="NOR",IF(AO11>10,2,IF(AO11>8,(AO11-AP11),0)),0) -> 2 | AR11: =IF(AM11="NOR",IF(AO11<10,0,IF(AO11>10,(AO11-(AP11+AQ11)),0)),0) -> 0 | AS11: =IF(AM11="DOM",AO11,0) -> 0 | AT11: 7 | AU11: 18 | AV11: NOR | AW11: =SUM(AU11-AT11) -> 11 | AX11: =IF(AW11>1,AW11-1,0) -> 10 | AY11: =IF(AO11="PROYECTO",IF(AV11="NOR",IF(AX11>8,8,AX11),0),IF(AV11="NOR",IF(AX11>8,8,AX11),0)) -> 8 | AZ11: =IF(AV11="NOR",IF(AX11>10,2,IF(AX11>8,(AX11-AY11),0)),0) -> 2 | BA11: =IF(AV11="NOR",IF(AX11<10,0,IF(AX11>10,(AX11-(AY11+AZ11)),0)),0) -> 0 | BB11: =IF(AV11="DOM",AX11,0) -> 0 | BC11: 7 | BD11: 18 | BE11: NOR | BF11: =SUM(BD11-BC11) -> 11 | BG11: =IF(BF11>1,BF11-1,0) -> 10 | BH11: =IF(D11="STAFF",IF(BE11="NOR",IF(BG11>8.5,8.5,BG11),0),IF(BE11="NOR",IF(BG11>8,8,BG11),IF(BF11="CAMPO",IF(BE11="NOR",IF(BG11>8,8,BG11),0),IF(BE11="NOR",IF(BG11>8,8,BG11),0)))) -> 8 | BI11: =IF(BE11="NOR",IF(BG11>10,2,IF(BG11>8,(BG11-BH11),0)),0) -> 2 | BJ11: =IF(BE11="NOR",IF(BG11<10,0,IF(BG11>10,(BG11-(BH11+BI11)),0)),0) -> 0 | BK11: =IF(BE11="DOM",BG11,0) -> 0 | BL11: 7 | BM11: 18 | BN11: NOR | BO11: =SUM(BM11-BL11) -> 11 | BP11: =IF(BO11>1,BO11-1,0) -> 10 | BQ11: =IF(D11="STAFF",IF(BN11="NOR",IF(BP11>8.5,8.5,BP11),0),IF(BN11="NOR",IF(BP11>8,8,BP11),IF(BO11="CAMPO",IF(BN11="NOR",IF(BP11>8,8,BP11),0),IF(BN11="NOR",IF(BP11>8,8,BP11),0)))) -> 8 | BR11: =IF(BN11="NOR",IF(BP11>10,2,IF(BP11>8,(BP11-BQ11),0)),0) -> 2 | BS11: =IF(BN11="NOR",IF(BP11<10,0,IF(BP11>10,(BP11-(BQ11+BR11)),0)),0) -> 0 | BT11: =IF(BN11="DOM",BP11,0) -> 0 | BU11: 7 | BV11: 18 | BW11: NOR | BX11: =SUM(BV11-BU11) -> 11 | BY11: =IF(BX11>1,BX11-1,0) -> 10 | BZ11: =IF(D11="STAFF",IF(BW11="NOR",IF(BY11>8.5,8.5,BY11),0),IF(BW11="NOR",IF(BY11>8,8,BY11),IF(BX11="CAMPO",IF(BW11="NOR",IF(BY11>8,8,BY11),0),IF(BW11="NOR",IF(BY11>8,8,BY11),0)))) -> 8 | CA11: =IF(BW11="NOR",IF(BY11>10,2,IF(BY11>8,(BY11-BZ11),0)),0) -> 2 | CB11: =IF(BW11="NOR",IF(BY11<10,0,IF(BY11>10,(BY11-(BZ11+CA11)),0)),0) -> 0 | CC11: =IF(BW11="DOM",BY11,0) -> 0 | CD11: 0 | CE11: 0 | CF11: DS | CG11: =SUM(CE11-CD11) -> 0 | CH11: =IF(CG11>1,CG11-1,0) -> 0 | CI11: =IF(D11="STAFF",IF(CF11="NOR",IF(CH11>8.5,8.5,CH11),0),IF(CF11="NOR",IF(CH11>8,8,CH11),IF(CG11="CAMPO",IF(CF11="NOR",IF(CH11>8,8,CH11),0),IF(CF11="NOR",IF(CH11>8,8,CH11),0)))) -> 0 | CJ11: =IF(CF11="NOR",IF(CH11>10,2,IF(CH11>8,(CH11-CI11),0)),0) -> 0 | CK11: =IF(CF11="NOR",IF(CH11<10,0,IF(CH11>10,(CH11-(CI11+CJ11)),0)),0) -> 0 | CL11: =IF(CF11="DOM",CH11,0) -> 0 | CM11: 7 | CN11: 18 | CO11: NOR | CP11: =SUM(CN11-CM11) -> 11 | CQ11: =IF(CP11>1,CP11-1,0) -> 10 | CR11: =IF(D11="STAFF",IF(CO11="NOR",IF(CQ11>8.5,8.5,CQ11),0),IF(CO11="NOR",IF(CQ11>8,8,CQ11),IF(CP11="CAMPO",IF(CO11="NOR",IF(CQ11>8,8,CQ11),0),IF(CO11="NOR",IF(CQ11>8,8,CQ11),0)))) -> 8 | CS11: =IF(CO11="NOR",IF(CQ11>10,2,IF(CQ11>8,(CQ11-CR11),0)),0) -> 2 | CT11: =IF(CO11="NOR",IF(CQ11<10,0,IF(CQ11>10,(CQ11-(CR11+CS11)),0)),0) -> 0 | CU11: =IF(CO11="DOM",CQ11,0) -> 0 | CV11: 7 | CW11: 18 | CX11: NOR | CY11: =SUM(CW11-CV11) -> 11 | CZ11: =IF(CY11>1,CY11-1,0) -> 10 | DA11: =IF(CQ11="PROYECTO",IF(CX11="NOR",IF(CZ11>8,8,CZ11),0),IF(CX11="NOR",IF(CZ11>8,8,CZ11),0)) -> 8 | DB11: =IF(CX11="NOR",IF(CZ11>10,2,IF(CZ11>8,(CZ11-DA11),0)),0) -> 2 | DC11: =IF(CX11="NOR",IF(CZ11<10,0,IF(CZ11>10,(CZ11-(DA11+DB11)),0)),0) -> 0 | DD11: =IF(CX11="DOM",CZ11,0) -> 0 | DE11: 7 | DF11: 18 | DG11: NOR | DH11: =SUM(DF11-DE11) -> 11 | DI11: =IF(DH11>1,DH11-1,0) -> 10 | DJ11: =IF(CZ11="PROYECTO",IF(DG11="NOR",IF(DI11>8,8,DI11),0),IF(DG11="NOR",IF(DI11>8,8,DI11),0)) -> 8 | DK11: =IF(DG11="NOR",IF(DI11>10,2,IF(DI11>8,(DI11-DJ11),0)),0) -> 2 | DL11: =IF(DG11="NOR",IF(DI11<10,0,IF(DI11>10,(DI11-(DJ11+DK11)),0)),0) -> 0 | DM11: =IF(DG11="DOM",DI11,0) -> 0 | DN11: 7 | DO11: 18 | DP11: NOR | DQ11: =SUM(DO11-DN11) -> 11 | DR11: =IF(DQ11>1,DQ11-1,0) -> 10 | DS11: =IF(D11="STAFF",IF(DP11="NOR",IF(DR11>8.5,8.5,DR11),0),IF(DP11="NOR",IF(DR11>8,8,DR11),IF(DQ11="CAMPO",IF(DP11="NOR",IF(DR11>8,8,DR11),0),IF(DP11="NOR",IF(DR11>8,8,DR11),0)))) -> 8 | DT11: =IF(DP11="NOR",IF(DR11>10,2,IF(DR11>8,(DR11-DS11),0)),0) -> 2 | DU11: =IF(DP11="NOR",IF(DR11<10,0,IF(DR11>10,(DR11-(DS11+DT11)),0)),0) -> 0 | DV11: =IF(DP11="DOM",DR11,0) -> 0 | DW11: 7 | DX11: 18 | DY11: NOR | DZ11: =SUM(DX11-DW11) -> 11 | EA11: =IF(DZ11>1,DZ11-1,0) -> 10 | EB11: =IF(D11="STAFF",IF(DY11="NOR",IF(EA11>8.5,8.5,EA11),0),IF(DY11="NOR",IF(EA11>8,8,EA11),IF(DZ11="CAMPO",IF(DY11="NOR",IF(EA11>8,8,EA11),0),IF(DY11="NOR",IF(EA11>8,8,EA11),0)))) -> 8 | EC11: =IF(DY11="NOR",IF(EA11>10,2,IF(EA11>8,(EA11-EB11),0)),0) -> 2 | ED11: =IF(DY11="NOR",IF(EA11<10,0,IF(EA11>10,(EA11-(EB11+EC11)),0)),0) -> 0 | EE11: =IF(DY11="DOM",EA11,0) -> 0 | EF11: 7 | EG11: 18 | EH11: NOR | EI11: =SUM(EG11-EF11) -> 11 | EJ11: =IF(EI11>1,EI11-1,0) -> 10 | EK11: =IF(D11="STAFF",IF(EH11="NOR",IF(EJ11>8.5,8.5,EJ11),0),IF(EH11="NOR",IF(EJ11>8,8,EJ11),IF(EI11="CAMPO",IF(EH11="NOR",IF(EJ11>8,8,EJ11),0),IF(EH11="NOR",IF(EJ11>8,8,EJ11),0)))) -> 8 | EL11: =IF(EH11="NOR",IF(EJ11>10,2,IF(EJ11>8,(EJ11-EK11),0)),0) -> 2 | EM11: =IF(EH11="NOR",IF(EJ11<10,0,IF(EJ11>10,(EJ11-(EK11+EL11)),0)),0) -> 0 | EN11: =IF(EH11="DOM",EJ11,0) -> 0 | EO11: 0 | EP11: 0 | EQ11: DS | ER11: =SUM(EP11-EO11) -> 0 | ES11: =IF(ER11>1,ER11-1,0) -> 0 | ET11: =IF(D11="STAFF",IF(EQ11="NOR",IF(ES11>8.5,8.5,ES11),0),IF(EQ11="NOR",IF(ES11>8,8,ES11),IF(ER11="CAMPO",IF(EQ11="NOR",IF(ES11>8,8,ES11),0),IF(EQ11="NOR",IF(ES11>8,8,ES11),0)))) -> 0 | EU11: =IF(EQ11="NOR",IF(ES11>10,2,IF(ES11>8,(ES11-ET11),0)),0) -> 0 | EV11: =IF(EQ11="NOR",IF(ES11<10,0,IF(ES11>10,(ES11-(ET11+EU11)),0)),0) -> 0 | EW11: =IF(EQ11="DOM",ES11,0) -> 0 | EX11: 7 | EY11: 18 | EZ11: NOR | FA11: =SUM(EY11-EX11) -> 11 | FB11: =IF(FA11>1,FA11-1,0) -> 10 | FC11: =IF(D11="STAFF",IF(EZ11="NOR",IF(FB11>8.5,8.5,FB11),0),IF(EZ11="NOR",IF(FB11>8,8,FB11),IF(FA11="CAMPO",IF(EZ11="NOR",IF(FB11>8,8,FB11),0),IF(EZ11="NOR",IF(FB11>8,8,FB11),0)))) -> 8 | FD11: =IF(EZ11="NOR",IF(FB11>10,2,IF(FB11>8,(FB11-FC11),0)),0) -> 2 | FE11: =IF(EZ11="NOR",IF(FB11<10,0,IF(FB11>10,(FB11-(FC11+FD11)),0)),0) -> 0 | FF11: =IF(EZ11="DOM",FB11,0) -> 0 | FG11: 7 | FH11: 18 | FI11: NOR | FJ11: =SUM(FH11-FG11) -> 11 | FK11: =IF(FJ11>1,FJ11-1,0) -> 10 | FL11: =IF(D11="STAFF",IF(FI11="NOR",IF(FK11>8.5,8.5,FK11),0),IF(FI11="NOR",IF(FK11>8,8,FK11),IF(FJ11="CAMPO",IF(FI11="NOR",IF(FK11>8,8,FK11),0),IF(FI11="NOR",IF(FK11>8,8,FK11),0)))) -> 8 | FM11: =IF(FI11="NOR",IF(FK11>10,2,IF(FK11>8,(FK11-FL11),0)),0) -> 2 | FN11: =IF(FI11="NOR",IF(FK11<10,0,IF(FK11>10,(FK11-(FL11+FM11)),0)),0) -> 0 | FO11: =IF(FI11="DOM",FK11,0) -> 0 | FP11: 7 | FQ11: 18 | FR11: NOR | FS11: =SUM(FQ11-FP11) -> 11 | FT11: =IF(FS11>1,FS11-1,0) -> 10 | FU11: =IF(FK11="PROYECTO",IF(FR11="NOR",IF(FT11>8,8,FT11),0),IF(FR11="NOR",IF(FT11>8,8,FT11),0)) -> 8 | FV11: =IF(FR11="NOR",IF(FT11>10,2,IF(FT11>8,(FT11-FU11),0)),0) -> 2 | FW11: =IF(FR11="NOR",IF(FT11<10,0,IF(FT11>10,(FT11-(FU11+FV11)),0)),0) -> 0 | FX11: =IF(FR11="DOM",FT11,0) -> 0 | FY11: 7 | FZ11: 18 | GA11: NOR | GB11: =SUM(FZ11-FY11) -> 11 | GC11: =IF(GB11>1,GB11-1,0) -> 10 | GD11: =IF(D11="STAFF",IF(GA11="NOR",IF(GC11>8.5,8.5,GC11),0),IF(GA11="NOR",IF(GC11>8,8,GC11),IF(GB11="CAMPO",IF(GA11="NOR",IF(GC11>8,8,GC11),0),IF(GA11="NOR",IF(GC11>8,8,GC11),0)))) -> 8 | GE11: =IF(GA11="NOR",IF(GC11>10,2,IF(GC11>8,(GC11-GD11),0)),0) -> 2 | GF11: =IF(GA11="NOR",IF(GC11<10,0,IF(GC11>10,(GC11-(GD11+GE11)),0)),0) -> 0 | GG11: =IF(GA11="DOM",GC11,0) -> 0 | GH11: 7 | GI11: 18 | GJ11: NOR | GK11: =SUM(GI11-GH11) -> 11 | GL11: =IF(GK11>1,GK11-1,0) -> 10 | GM11: =IF(D11="STAFF",IF(GJ11="NOR",IF(GL11>8.5,8.5,GL11),0),IF(GJ11="NOR",IF(GL11>8,8,GL11),IF(GK11="CAMPO",IF(GJ11="NOR",IF(GL11>8,8,GL11),0),IF(GJ11="NOR",IF(GL11>8,8,GL11),0)))) -> 8 | GN11: =IF(GJ11="NOR",IF(GL11>10,2,IF(GL11>8,(GL11-GM11),0)),0) -> 2 | GO11: =IF(GJ11="NOR",IF(GL11<10,0,IF(GL11>10,(GL11-(GM11+GN11)),0)),0) -> 0 | GP11: =IF(GJ11="DOM",GL11,0) -> 0 | GQ11: 9 | GR11: 18 | GS11: NOR | GT11: =SUM(GR11-GQ11) -> 9 | GU11: =IF(GT11>1,GT11-1,0) -> 8 | GV11: =IF(D11="STAFF",IF(GS11="NOR",IF(GU11>8.5,8.5,GU11),0),IF(GS11="NOR",IF(GU11>8,8,GU11),IF(GT11="CAMPO",IF(GS11="NOR",IF(GU11>8,8,GU11),0),IF(GS11="NOR",IF(GU11>8,8,GU11),0)))) -> 8 | GW11: =IF(GS11="NOR",IF(GU11>10,2,IF(GU11>8,(GU11-GV11),0)),0) -> 0 | GX11: =IF(GS11="NOR",IF(GU11<10,0,IF(GU11>10,(GU11-(GV11+GW11)),0)),0) -> 0 | GY11: =IF(GS11="DOM",GU11,0) -> 0 | GZ11: 0 | HA11: 0 | HB11: DS | HC11: =SUM(HA11-GZ11) -> 0 | HD11: =IF(HC11>1,HC11-1,0) -> 0 | HE11: =IF(D11="STAFF",IF(HB11="NOR",IF(HD11>8.5,8.5,HD11),0),IF(HB11="NOR",IF(HD11>8,8,HD11),IF(HC11="CAMPO",IF(HB11="NOR",IF(HD11>8,8,HD11),0),IF(HB11="NOR",IF(HD11>8,8,HD11),0)))) -> 0 | HF11: =IF(HB11="NOR",IF(HD11>10,2,IF(HD11>8,(HD11-HE11),0)),0) -> 0 | HG11: =IF(HB11="NOR",IF(HD11<10,0,IF(HD11>10,(HD11-(HE11+HF11)),0)),0) -> 0 | HH11: =IF(HB11="DOM",HD11,0) -> 0 | HI11: 7 | HJ11: 18 | HK11: NOR | HL11: =SUM(HJ11-HI11) -> 11 | HM11: =IF(HL11>1,HL11-1,0) -> 10 | HN11: =IF(D11="STAFF",IF(HK11="NOR",IF(HM11>8.5,8.5,HM11),0),IF(HK11="NOR",IF(HM11>8,8,HM11),IF(HL11="CAMPO",IF(HK11="NOR",IF(HM11>8,8,HM11),0),IF(HK11="NOR",IF(HM11>8,8,HM11),0)))) -> 8 | HO11: =IF(HK11="NOR",IF(HM11>10,2,IF(HM11>8,(HM11-HN11),0)),0) -> 2 | HP11: =IF(HK11="NOR",IF(HM11<10,0,IF(HM11>10,(HM11-(HN11+HO11)),0)),0) -> 0 | HQ11: =IF(HK11="DOM",HM11,0) -> 0 | HR11: 7 | HS11: 18 | HT11: NOR | HU11: =SUM(HS11-HR11) -> 11 | HV11: =IF(HU11>1,HU11-1,0) -> 10 | HW11: =IF(D11="STAFF",IF(HT11="NOR",IF(HV11>8.5,8.5,HV11),0),IF(HT11="NOR",IF(HV11>8,8,HV11),IF(HU11="CAMPO",IF(HT11="NOR",IF(HV11>8,8,HV11),0),IF(HT11="NOR",IF(HV11>8,8,HV11),0)))) -> 8 | HX11: =IF(HT11="NOR",IF(HV11>10,2,IF(HV11>8,(HV11-HW11),0)),0) -> 2 | HY11: =IF(HT11="NOR",IF(HV11<10,0,IF(HV11>10,(HV11-(HW11+HX11)),0)),0) -> 0 | HZ11: =IF(HT11="DOM",HV11,0) -> 0 | IA11: 7 | IB11: 14 | IC11: NOR | ID11: =SUM(IB11-IA11) -> 7 | IE11: =IF(ID11>1,ID11-1,0) -> 6 | IF11: =IF(D11="STAFF",IF(IC11="NOR",IF(IE11>8.5,8.5,IE11),0),IF(IC11="NOR",IF(IE11>8,8,IE11),IF(ID11="CAMPO",IF(IC11="NOR",IF(IE11>8,8,IE11),0),IF(IC11="NOR",IF(IE11>8,8,IE11),0)))) -> 6 | IG11: =IF(IC11="NOR",IF(IE11>10,2,IF(IE11>8,(IE11-IF11),0)),0) -> 0 | IH11: =IF(IC11="NOR",IF(IE11<10,0,IF(IE11>10,(IE11-(IF11+IG11)),0)),0) -> 0 | II11: =IF(IC11="DOM",IE11,0) -> 0 | IJ11: 7 | IK11: 18 | IL11: NOR | IM11: =SUM(IK11-IJ11) -> 11 | IN11: =IF(IM11>1,IM11-1,0) -> 10 | IO11: =IF(D11="STAFF",IF(IL11="NOR",IF(IN11>8.5,8.5,IN11),0),IF(IL11="NOR",IF(IN11>8,8,IN11),IF(IM11="CAMPO",IF(IL11="NOR",IF(IN11>8,8,IN11),0),IF(IL11="NOR",IF(IN11>8,8,IN11),0)))) -> 8 | IP11: =IF(IL11="NOR",IF(IN11>10,2,IF(IN11>8,(IN11-IO11),0)),0) -> 2 | IQ11: =IF(IL11="NOR",IF(IN11<10,0,IF(IN11>10,(IN11-(IO11+IP11)),0)),0) -> 0 | IR11: =IF(IL11="DOM",IN11,0) -> 0 | IS11: 7 | IT11: 18 | IU11: NOR | IV11: =SUM(IT11-IS11) -> 11 | IW11: =IF(IV11>1,IV11-1,0) -> 10 | IX11: =IF(D11="STAFF",IF(IU11="NOR",IF(IW11>8.5,8.5,IW11),0),IF(IU11="NOR",IF(IW11>8,8,IW11),IF(IV11="CAMPO",IF(IU11="NOR",IF(IW11>8,8,IW11),0),IF(IU11="NOR",IF(IW11>8,8,IW11),0)))) -> 8 | IY11: =IF(IU11="NOR",IF(IW11>10,2,IF(IW11>8,(IW11-IX11),0)),0) -> 2 | IZ11: =IF(IU11="NOR",IF(IW11<10,0,IF(IW11>10,(IW11-(IX11+IY11)),0)),0) -> 0 | JA11: =IF(IU11="DOM",IW11,0) -> 0 | JB11: 7 | JC11: 18 | JD11: NOR | JE11: =SUM(JC11-JB11) -> 11 | JF11: =IF(JE11>1,JE11-1,0) -> 10 | JG11: =IF(D11="STAFF",IF(JD11="NOR",IF(JF11>8.5,8.5,JF11),0),IF(JD11="NOR",IF(JF11>8,8,JF11),IF(JE11="CAMPO",IF(JD11="NOR",IF(JF11>8,8,JF11),0),IF(JD11="NOR",IF(JF11>8,8,JF11),0)))) -> 8 | JH11: =IF(JD11="NOR",IF(JF11>10,2,IF(JF11>8,(JF11-JG11),0)),0) -> 2 | JI11: =IF(JD11="NOR",IF(JF11<10,0,IF(JF11>10,(JF11-(JG11+JH11)),0)),0) -> 0 | JJ11: =IF(JD11="DOM",JF11,0) -> 0 | JK11: 0 | JL11: 0 | JM11: DS | JN11: =SUM(JL11-JK11) -> 0 | JO11: =IF(JN11>1,JN11-1,0) -> 0 | JP11: =IF(D11="STAFF",IF(JM11="NOR",IF(JO11>8.5,8.5,JO11),0),IF(JM11="NOR",IF(JO11>8,8,JO11),IF(JN11="CAMPO",IF(JM11="NOR",IF(JO11>8,8,JO11),0),IF(JM11="NOR",IF(JO11>8,8,JO11),0)))) -> 0 | JQ11: =IF(JM11="NOR",IF(JO11>10,2,IF(JO11>8,(JO11-JP11),0)),0) -> 0 | JR11: =IF(JM11="NOR",IF(JO11<10,0,IF(JO11>10,(JO11-(JP11+JQ11)),0)),0) -> 0 | JS11: =IF(JM11="DOM",JO11,0) -> 0 | JT11: 7 | JU11: 19 | JV11: NOR | JW11: =SUM(JU11-JT11) -> 12 | JX11: =IF(JW11>1,JW11-1,0) -> 11 | JY11: =IF(D11="STAFF",IF(JV11="NOR",IF(JX11>8.5,8.5,JX11),0),IF(JV11="NOR",IF(JX11>8,8,JX11),IF(JW11="CAMPO",IF(JV11="NOR",IF(JX11>8,8,JX11),0),IF(JV11="NOR",IF(JX11>8,8,JX11),0)))) -> 8 | JZ11: =IF(JV11="NOR",IF(JX11>10,2,IF(JX11>8,(JX11-JY11),0)),0) -> 2 | KA11: =IF(JV11="NOR",IF(JX11<10,0,IF(JX11>10,(JX11-(JY11+JZ11)),0)),0) -> 1 | KB11: =IF(JV11="DOM",JX11,0) -> 0 | KC11: 7 | KD11: 16 | KE11: NOR | KF11: =SUM(KD11-KC11) -> 9 | KG11: =IF(KF11>1,KF11-1,0) -> 8 | KH11: =IF(D11="STAFF",IF(KE11="NOR",IF(KG11>8.5,8.5,KG11),0),IF(KE11="NOR",IF(KG11>8,8,KG11),IF(KF11="CAMPO",IF(KE11="NOR",IF(KG11>8,8,KG11),0),IF(KE11="NOR",IF(KG11>8,8,KG11),0)))) -> 8 | KI11: =IF(KE11="NOR",IF(KG11>10,2,IF(KG11>8,(KG11-KH11),0)),0) -> 0 | KJ11: =IF(KE11="NOR",IF(KG11<10,0,IF(KG11>10,(KG11-(KH11+KI11)),0)),0) -> 0 | KK11: =IF(KE11="DOM",KG11,0) -> 0 | KL11: 7 | KM11: 16 | KN11: NOR | KO11: =SUM(KM11-KL11) -> 9 | KP11: =IF(KO11>1,KO11-1,0) -> 8 | KQ11: =IF(D11="STAFF",IF(KN11="NOR",IF(KP11>8.5,8.5,KP11),0),IF(KN11="NOR",IF(KP11>8,8,KP11),IF(KO11="CAMPO",IF(KN11="NOR",IF(KP11>8,8,KP11),0),IF(KN11="NOR",IF(KP11>8,8,KP11),0)))) -> 8 | KR11: =IF(KN11="NOR",IF(KP11>10,2,IF(KP11>8,(KP11-KQ11),0)),0) -> 0 | KS11: =IF(KN11="NOR",IF(KP11<10,0,IF(KP11>10,(KP11-(KQ11+KR11)),0)),0) -> 0 | KT11: =IF(KN11="DOM",KP11,0) -> 0 | KU11: 7 | KV11: 16 | KW11: NOR | KX11: =SUM(KV11-KU11) -> 9 | KY11: =IF(KX11>1,KX11-1,0) -> 8 | KZ11: =IF(D11="STAFF",IF(KW11="NOR",IF(KY11>8.5,8.5,KY11),0),IF(KW11="NOR",IF(KY11>8,8,KY11),IF(KX11="CAMPO",IF(KW11="NOR",IF(KY11>8,8,KY11),0),IF(KW11="NOR",IF(KY11>8,8,KY11),0)))) -> 8 | LA11: =IF(KW11="NOR",IF(KY11>10,2,IF(KY11>8,(KY11-KZ11),0)),0) -> 0 | LB11: =IF(KW11="NOR",IF(KY11<10,0,IF(KY11>10,(KY11-(KZ11+LA11)),0)),0) -> 0 | LC11: =IF(KW11="DOM",KY11,0) -> 0 | LD11: 7 | LE11: 16 | LF11: NOR | LG11: =SUM(LE11-LD11) -> 9 | LH11: =IF(LG11>1,LG11-1,0) -> 8 | LI11: =IF(D11="STAFF",IF(LF11="NOR",IF(LH11>8.5,8.5,LH11),0),IF(LF11="NOR",IF(LH11>8,8,LH11),IF(LG11="CAMPO",IF(LF11="NOR",IF(LH11>8,8,LH11),0),IF(LF11="NOR",IF(LH11>8,8,LH11),0)))) -> 8 | LJ11: =IF(LF11="NOR",IF(LH11>10,2,IF(LH11>8,(LH11-LI11),0)),0) -> 0 | LK11: =IF(LF11="NOR",IF(LH11<10,0,IF(LH11>10,(LH11-(LI11+LJ11)),0)),0) -> 0 | LL11: =IF(LF11="DOM",LH11,0) -> 0 | LM11: 7 | LN11: 16 | LO11: NOR | LP11: =SUM(LN11-LM11) -> 9 | LQ11: =IF(LP11>1,LP11-1,0) -> 8 | LR11: =IF(D11="STAFF",IF(LO11="NOR",IF(LQ11>8.5,8.5,LQ11),0),IF(LO11="NOR",IF(LQ11>8,8,LQ11),IF(LP11="CAMPO",IF(LO11="NOR",IF(LQ11>8,8,LQ11),0),IF(LO11="NOR",IF(LQ11>8,8,LQ11),0)))) -> 8 | LS11: =IF(LO11="NOR",IF(LQ11>10,2,IF(LQ11>8,(LQ11-LR11),0)),0) -> 0 | LT11: =IF(LO11="NOR",IF(LQ11<10,0,IF(LQ11>10,(LQ11-(LR11+LS11)),0)),0) -> 0 | LU11: =IF(LO11="DOM",LQ11,0) -> 0 | LV11: 7 | LW11: 16 | LX11: NOR | LY11: =SUM(LW11-LV11) -> 9 | LZ11: =IF(LY11>1,LY11-1,0) -> 8 | MA11: =IF(D11="STAFF",IF(LX11="NOR",IF(LZ11>8.5,8.5,LZ11),0),IF(LX11="NOR",IF(LZ11>8,8,LZ11),IF(LY11="CAMPO",IF(LX11="NOR",IF(LZ11>8,8,LZ11),0),IF(LX11="NOR",IF(LZ11>8,8,LZ11),0)))) -> 8 | MB11: =IF(LX11="NOR",IF(LZ11>10,2,IF(LZ11>8,(LZ11-MA11),0)),0) -> 0 | MC11: =IF(LX11="NOR",IF(LZ11<10,0,IF(LZ11>10,(LZ11-(MA11+MB11)),0)),0) -> 0 | MD11: =IF(LX11="DOM",LZ11,0) -> 0 | ME11: 7 | MF11: 16 | MG11: NOR | MH11: =SUM(MF11-ME11) -> 9 | MI11: =IF(MH11>1,MH11-1,0) -> 8 | MJ11: =IF(D11="STAFF",IF(MG11="NOR",IF(MI11>8.5,8.5,MI11),0),IF(MG11="NOR",IF(MI11>8,8,MI11),IF(MH11="CAMPO",IF(MG11="NOR",IF(MI11>8,8,MI11),0),IF(MG11="NOR",IF(MI11>8,8,MI11),0)))) -> 8 | MK11: =IF(MG11="NOR",IF(MI11>10,2,IF(MI11>8,(MI11-MJ11),0)),0) -> 0 | ML11: =IF(MG11="NOR",IF(MI11<10,0,IF(MI11>10,(MI11-(MJ11+MK11)),0)),0) -> 0 | MM11: =IF(MG11="DOM",MI11,0) -> 0 | MN11: 7 | MO11: 16 | MP11: NOR | MQ11: =SUM(MO11-MN11) -> 9 | MR11: =IF(MQ11>1,MQ11-1,0) -> 8 | MS11: =IF(D11="STAFF",IF(MP11="NOR",IF(MR11>8.5,8.5,MR11),0),IF(MP11="NOR",IF(MR11>8,8,MR11),IF(MQ11="CAMPO",IF(MP11="NOR",IF(MR11>8,8,MR11),0),IF(MP11="NOR",IF(MR11>8,8,MR11),0)))) -> 8 | MT11: =IF(MP11="NOR",IF(MR11>10,2,IF(MR11>8,(MR11-MS11),0)),0) -> 0 | MU11: =IF(MP11="NOR",IF(MR11<10,0,IF(MR11>10,(MR11-(MS11+MT11)),0)),0) -> 0 | MV11: =IF(MP11="DOM",MR11,0) -> 0 | MW11: 7 | MX11: 16 | MY11: NOR | MZ11: =SUM(MX11-MW11) -> 9 | NA11: =IF(MZ11>1,MZ11-1,0) -> 8 | NB11: =IF(D11="STAFF",IF(MY11="NOR",IF(NA11>8.5,8.5,NA11),0),IF(MY11="NOR",IF(NA11>8,8,NA11),IF(MZ11="CAMPO",IF(MY11="NOR",IF(NA11>8,8,NA11),0),IF(MY11="NOR",IF(NA11>8,8,NA11),0)))) -> 8 | NC11: =IF(MY11="NOR",IF(NA11>10,2,IF(NA11>8,(NA11-NB11),0)),0) -> 0 | ND11: =IF(MY11="NOR",IF(NA11<10,0,IF(NA11>10,(NA11-(NB11+NC11)),0)),0) -> 0 | NE11: =IF(MY11="DOM",NA11,0) -> 0 | NF11: 7 | NG11: 16 | NH11: NOR | NI11: =SUM(NG11-NF11) -> 9 | NJ11: =IF(NI11>1,NI11-1,0) -> 8 | NK11: =IF(D11="STAFF",IF(NH11="NOR",IF(NJ11>8.5,8.5,NJ11),0),IF(NH11="NOR",IF(NJ11>8,8,NJ11),IF(NI11="CAMPO",IF(NH11="NOR",IF(NJ11>8,8,NJ11),0),IF(NH11="NOR",IF(NJ11>8,8,NJ11),0)))) -> 8 | NL11: =IF(NH11="NOR",IF(NJ11>10,2,IF(NJ11>8,(NJ11-NK11),0)),0) -> 0 | NM11: =IF(NH11="NOR",IF(NJ11<10,0,IF(NJ11>10,(NJ11-(NK11+NL11)),0)),0) -> 0 | NN11: =IF(NH11="DOM",NJ11,0) -> 0 | NO11: 7 | NP11: 16 | NQ11: NOR | NR11: =SUM(NP11-NO11) -> 9 | NS11: =IF(NR11>1,NR11-1,0) -> 8 | NT11: =IF(D11="STAFF",IF(NQ11="NOR",IF(NS11>8.5,8.5,NS11),0),IF(NQ11="NOR",IF(NS11>8,8,NS11),IF(NR11="CAMPO",IF(NQ11="NOR",IF(NS11>8,8,NS11),0),IF(NQ11="NOR",IF(NS11>8,8,NS11),0)))) -> 8 | NU11: =IF(NQ11="NOR",IF(NS11>10,2,IF(NS11>8,(NS11-NT11),0)),0) -> 0 | NV11: =IF(NQ11="NOR",IF(NS11<10,0,IF(NS11>10,(NS11-(NT11+NU11)),0)),0) -> 0 | NW11: =IF(NQ11="DOM",NS11,0) -> 0 | NX11: 7 | NY11: 16 | NZ11: NOR | OA11: =SUM(NY11-NX11) -> 9 | OB11: =IF(OA11>1,OA11-1,0) -> 8 | OC11: =IF(D11="STAFF",IF(NZ11="NOR",IF(OB11>8.5,8.5,OB11),0),IF(NZ11="NOR",IF(OB11>8,8,OB11),IF(OA11="CAMPO",IF(NZ11="NOR",IF(OB11>8,8,OB11),0),IF(NZ11="NOR",IF(OB11>8,8,OB11),0)))) -> 8 | OD11: =IF(NZ11="NOR",IF(OB11>10,2,IF(OB11>8,(OB11-OC11),0)),0) -> 0 | OE11: =IF(NZ11="NOR",IF(OB11<10,0,IF(OB11>10,(OB11-(OC11+OD11)),0)),0) -> 0 | OF11: =IF(NZ11="DOM",OB11,0) -> 0 | OG11: 0 | OH11: 0 | OI11: DS | OJ11: =SUM(OH11-OG11) -> 0 | OK11: =IF(OJ11>1,OJ11-1,0) -> 0 | OL11: =IF(D11="STAFF",IF(OI11="NOR",IF(OK11>8.5,8.5,OK11),0),IF(OI11="NOR",IF(OK11>8,8,OK11),IF(OJ11="CAMPO",IF(OI11="NOR",IF(OK11>8,8,OK11),0),IF(OI11="NOR",IF(OK11>8,8,OK11),0)))) -> 0 | OM11: =IF(OI11="NOR",IF(OK11>10,2,IF(OK11>8,(OK11-OL11),0)),0) -> 0 | ON11: =IF(OI11="NOR",IF(OK11<10,0,IF(OK11>10,(OK11-(OL11+OM11)),0)),0) -> 0 | OO11: =IF(OI11="DOM",OK11,0) -> 0 | OP11: 7 | OQ11: 16 | OR11: NOR | OS11: =SUM(OQ11-OP11) -> 9 | OT11: =IF(OS11>1,OS11-1,0) -> 8 | OU11: =IF(D11="STAFF",IF(OR11="NOR",IF(OT11>8.5,8.5,OT11),0),IF(OR11="NOR",IF(OT11>8,8,OT11),IF(OS11="CAMPO",IF(OR11="NOR",IF(OT11>8,8,OT11),0),IF(OR11="NOR",IF(OT11>8,8,OT11),0)))) -> 8 | OV11: =IF(OR11="NOR",IF(OT11>10,2,IF(OT11>8,(OT11-OU11),0)),0) -> 0 | OW11: =IF(OR11="NOR",IF(OT11<10,0,IF(OT11>10,(OT11-(OU11+OV11)),0)),0) -> 0 | OX11: =IF(OR11="DOM",OT11,0) -> 0 | OY11: 0 | OZ11: 0 | PA11: FE | PB11: =SUM(OZ11-OY11) -> 0 | PC11: =IF(PB11>1,PB11-1,0) -> 0 | PD11: =IF(D11="STAFF",IF(PA11="NOR",IF(PC11>8.5,8.5,PC11),0),IF(PA11="NOR",IF(PC11>8,8,PC11),IF(PB11="CAMPO",IF(PA11="NOR",IF(PC11>8,8,PC11),0),IF(PA11="NOR",IF(PC11>8,8,PC11),0)))) -> 0 | PE11: =IF(PA11="NOR",IF(PC11>10,2,IF(PC11>8,(PC11-PD11),0)),0) -> 0 | PF11: =IF(PA11="NOR",IF(PC11<10,0,IF(PC11>10,(PC11-(PD11+PE11)),0)),0) -> 0 | PG11: =IF(PA11="DOM",PC11,0) -> 0 | PH11: 7 | PI11: 16 | PJ11: NOR | PK11: =SUM(PI11-PH11) -> 9 | PL11: =IF(PK11>1,PK11-1,0) -> 8 | PM11: =IF(M11="STAFF",IF(PJ11="NOR",IF(PL11>8.5,8.5,PL11),0),IF(PJ11="NOR",IF(PL11>8,8,PL11),IF(PK11="CAMPO",IF(PJ11="NOR",IF(PL11>8,8,PL11),0),IF(PJ11="NOR",IF(PL11>8,8,PL11),0)))) -> 8 | PN11: =IF(PJ11="NOR",IF(PL11>10,2,IF(PL11>8,(PL11-PM11),0)),0) -> 0 | PO11: =IF(PJ11="NOR",IF(PL11<10,0,IF(PL11>10,(PL11-(PM11+PN11)),0)),0) -> 0 | PP11: =IF(PJ11="DOM",PL11,0) -> 0 | PR11: =COUNTIF(FG11:PP11,"NOR") -> 26 | PS11: =COUNTIF(FG11:PP11,"DS") -> 3 | PT11: =COUNTIF(FG11:PP11,"FE") -> 1 | PU11: =SUM(PR11:PT11) -> 30 | PV11: =COUNTIF(FG11:PP11,"DM") -> 0 | PY11: =COUNTIF(FG11:PP11,"SUB") -> 0 | QB11: =COUNTIF(FG11:PP11,"VA") -> 0 | QE11: =COUNTIF(FG11:PP11,"LSG") -> 0 | QH11: =COUNTIF(FG11:PP11,"LCG") -> 0 | QK11: =COUNTIF(FG11:PP11,"FA") -> 0 | QN11: =COUNTIF(J11:FF11,"FA") -> 0 | QQ11: =PU11+PV11+PY11+QB11+QE11+QH11+QK11+QN11 -> 30 | QS11: =P11+Y11++AH11+AQ11+AZ11+BI11+BR11+CA11+CJ11+CS11+DB11+DK11+DT11+EC11+EL11+EU11+FD11+FM11+FV11+GE11+GN11+GW11+HF11+HO11+HX11+IG11+IP11+IY11+JH11+JQ11+JZ11 -> 48 | QT11: =Q11+Z11++AI11+AR11+BA11+BJ11+BS11+CB11+CK11+CT11+DC11+DL11+DU11+ED11+EM11+EV11+FE11+FN11+FW11+GF11+GO11+GX11+HG11+HP11+HY11+IH11+IQ11+IZ11+JI11+JR11+KA11 -> 1 | RG11: 0
A12: =A11+1 -> 3 | B12: 09787238 | D12: PROYECTO | E12: CALUMANI JARA JAIME ANTONIO | F12: DESPACHADOR | G12: 44263 | H12: 44264 | J12: 7 | K12: 18 | L12: NOR | M12: =SUM(K12-J12) -> 11 | N12: =IF(M12>1,M12-1,0) -> 10 | O12: =IF(D12="STAFF",IF(L12="NOR",IF(N12>8.5,8.5,N12),0),IF(L12="NOR",IF(N12>8,8,N12),IF(D12="CAMPO",IF(L12="NOR",IF(N12>8,8,N12),0),IF(L12="NOR",IF(N12>8,8,N12),0)))) -> 8 | P12: =IF(L12="NOR",IF(N12>10,2,IF(N12>8,(N12-O12),0)),0) -> 2 | Q12: =IF(L12="NOR",IF(N12<10,0,IF(N12>10,(N12-(O12+P12)),0)),0) -> 0 | R12: =IF(L12="DOM",N12,0) -> 0 | S12: 0 | T12: 0 | U12: DS | V12: =SUM(T12-S12) -> 0 | W12: =IF(V12>1,V12-1,0) -> 0 | X12: =IF(D12="STAFF",IF(U12="NOR",IF(W12>8.5,8.5,W12),0),IF(U12="NOR",IF(W12>8,8,W12),IF(M12="CAMPO",IF(U12="NOR",IF(W12>8,8,W12),0),IF(U12="NOR",IF(W12>8,8,W12),0)))) -> 0 | Y12: =IF(U12="NOR",IF(W12>10,2,IF(W12>8,(W12-X12),0)),0) -> 0 | Z12: =IF(U12="NOR",IF(W12<10,0,IF(W12>10,(W12-(X12+Y12)),0)),0) -> 0 | AA12: =IF(U12="DOM",W12,0) -> 0 | AB12: 7 | AC12: 19 | AD12: NOR | AE12: =SUM(AC12-AB12) -> 12 | AF12: =IF(AE12>1,AE12-1,0) -> 11 | AG12: =IF(D12="STAFF",IF(AD12="NOR",IF(AF12>8.5,8.5,AF12),0),IF(AD12="NOR",IF(AF12>8,8,AF12),IF(AE12="CAMPO",IF(AD12="NOR",IF(AF12>8,8,AF12),0),IF(AD12="NOR",IF(AF12>8,8,AF12),0)))) -> 8 | AH12: =IF(AD12="NOR",IF(AF12>10,2,IF(AF12>8,(AF12-AG12),0)),0) -> 2 | AI12: =IF(AD12="NOR",IF(AF12<10,0,IF(AF12>10,(AF12-(AG12+AH12)),0)),0) -> 1 | AJ12: =IF(AD12="DOM",AF12,0) -> 0 | AK12: 7 | AL12: 19 | AM12: NOR | AN12: =SUM(AL12-AK12) -> 12 | AO12: =IF(AN12>1,AN12-1,0) -> 11 | AP12: =IF(D12="PROYECTO",IF(AM12="NOR",IF(AO12>8,8,AO12),0),IF(AM12="NOR",IF(AO12>8,8,AO12),0)) -> 8 | AQ12: =IF(AM12="NOR",IF(AO12>10,2,IF(AO12>8,(AO12-AP12),0)),0) -> 2 | AR12: =IF(AM12="NOR",IF(AO12<10,0,IF(AO12>10,(AO12-(AP12+AQ12)),0)),0) -> 1 | AS12: =IF(AM12="DOM",AO12,0) -> 0 | AT12: 7 | AU12: 18 | AV12: NOR | AW12: =SUM(AU12-AT12) -> 11 | AX12: =IF(AW12>1,AW12-1,0) -> 10 | AY12: =IF(AO12="PROYECTO",IF(AV12="NOR",IF(AX12>8,8,AX12),0),IF(AV12="NOR",IF(AX12>8,8,AX12),0)) -> 8 | AZ12: =IF(AV12="NOR",IF(AX12>10,2,IF(AX12>8,(AX12-AY12),0)),0) -> 2 | BA12: =IF(AV12="NOR",IF(AX12<10,0,IF(AX12>10,(AX12-(AY12+AZ12)),0)),0) -> 0 | BB12: =IF(AV12="DOM",AX12,0) -> 0 | BC12: 7 | BD12: 18 | BE12: NOR | BF12: =SUM(BD12-BC12) -> 11 | BG12: =IF(BF12>1,BF12-1,0) -> 10 | BH12: =IF(D12="STAFF",IF(BE12="NOR",IF(BG12>8.5,8.5,BG12),0),IF(BE12="NOR",IF(BG12>8,8,BG12),IF(BF12="CAMPO",IF(BE12="NOR",IF(BG12>8,8,BG12),0),IF(BE12="NOR",IF(BG12>8,8,BG12),0)))) -> 8 | BI12: =IF(BE12="NOR",IF(BG12>10,2,IF(BG12>8,(BG12-BH12),0)),0) -> 2 | BJ12: =IF(BE12="NOR",IF(BG12<10,0,IF(BG12>10,(BG12-(BH12+BI12)),0)),0) -> 0 | BK12: =IF(BE12="DOM",BG12,0) -> 0 | BL12: 7 | BM12: 18 | BN12: NOR | BO12: =SUM(BM12-BL12) -> 11 | BP12: =IF(BO12>1,BO12-1,0) -> 10 | BQ12: =IF(D12="STAFF",IF(BN12="NOR",IF(BP12>8.5,8.5,BP12),0),IF(BN12="NOR",IF(BP12>8,8,BP12),IF(BO12="CAMPO",IF(BN12="NOR",IF(BP12>8,8,BP12),0),IF(BN12="NOR",IF(BP12>8,8,BP12),0)))) -> 8 | BR12: =IF(BN12="NOR",IF(BP12>10,2,IF(BP12>8,(BP12-BQ12),0)),0) -> 2 | BS12: =IF(BN12="NOR",IF(BP12<10,0,IF(BP12>10,(BP12-(BQ12+BR12)),0)),0) -> 0 | BT12: =IF(BN12="DOM",BP12,0) -> 0 | BU12: 7 | BV12: 16 | BW12: NOR | BX12: =SUM(BV12-BU12) -> 9 | BY12: =IF(BX12>1,BX12-1,0) -> 8 | BZ12: =IF(D12="STAFF",IF(BW12="NOR",IF(BY12>8.5,8.5,BY12),0),IF(BW12="NOR",IF(BY12>8,8,BY12),IF(BX12="CAMPO",IF(BW12="NOR",IF(BY12>8,8,BY12),0),IF(BW12="NOR",IF(BY12>8,8,BY12),0)))) -> 8 | CA12: =IF(BW12="NOR",IF(BY12>10,2,IF(BY12>8,(BY12-BZ12),0)),0) -> 0 | CB12: =IF(BW12="NOR",IF(BY12<10,0,IF(BY12>10,(BY12-(BZ12+CA12)),0)),0) -> 0 | CC12: =IF(BW12="DOM",BY12,0) -> 0 | CD12: 0 | CE12: 0 | CF12: DS | CG12: =SUM(CE12-CD12) -> 0 | CH12: =IF(CG12>1,CG12-1,0) -> 0 | CI12: =IF(D12="STAFF",IF(CF12="NOR",IF(CH12>8.5,8.5,CH12),0),IF(CF12="NOR",IF(CH12>8,8,CH12),IF(CG12="CAMPO",IF(CF12="NOR",IF(CH12>8,8,CH12),0),IF(CF12="NOR",IF(CH12>8,8,CH12),0)))) -> 0 | CJ12: =IF(CF12="NOR",IF(CH12>10,2,IF(CH12>8,(CH12-CI12),0)),0) -> 0 | CK12: =IF(CF12="NOR",IF(CH12<10,0,IF(CH12>10,(CH12-(CI12+CJ12)),0)),0) -> 0 | CL12: =IF(CF12="DOM",CH12,0) -> 0 | CM12: 7 | CN12: 18 | CO12: NOR | CP12: =SUM(CN12-CM12) -> 11 | CQ12: =IF(CP12>1,CP12-1,0) -> 10 | CR12: =IF(D12="STAFF",IF(CO12="NOR",IF(CQ12>8.5,8.5,CQ12),0),IF(CO12="NOR",IF(CQ12>8,8,CQ12),IF(CP12="CAMPO",IF(CO12="NOR",IF(CQ12>8,8,CQ12),0),IF(CO12="NOR",IF(CQ12>8,8,CQ12),0)))) -> 8 | CS12: =IF(CO12="NOR",IF(CQ12>10,2,IF(CQ12>8,(CQ12-CR12),0)),0) -> 2 | CT12: =IF(CO12="NOR",IF(CQ12<10,0,IF(CQ12>10,(CQ12-(CR12+CS12)),0)),0) -> 0 | CU12: =IF(CO12="DOM",CQ12,0) -> 0 | CV12: 7 | CW12: 18 | CX12: NOR | CY12: =SUM(CW12-CV12) -> 11 | CZ12: =IF(CY12>1,CY12-1,0) -> 10 | DA12: =IF(CQ12="PROYECTO",IF(CX12="NOR",IF(CZ12>8,8,CZ12),0),IF(CX12="NOR",IF(CZ12>8,8,CZ12),0)) -> 8 | DB12: =IF(CX12="NOR",IF(CZ12>10,2,IF(CZ12>8,(CZ12-DA12),0)),0) -> 2 | DC12: =IF(CX12="NOR",IF(CZ12<10,0,IF(CZ12>10,(CZ12-(DA12+DB12)),0)),0) -> 0 | DD12: =IF(CX12="DOM",CZ12,0) -> 0 | DE12: 7 | DF12: 17 | DG12: NOR | DH12: =SUM(DF12-DE12) -> 10 | DI12: =IF(DH12>1,DH12-1,0) -> 9 | DJ12: =IF(CZ12="PROYECTO",IF(DG12="NOR",IF(DI12>8,8,DI12),0),IF(DG12="NOR",IF(DI12>8,8,DI12),0)) -> 8 | DK12: =IF(DG12="NOR",IF(DI12>10,2,IF(DI12>8,(DI12-DJ12),0)),0) -> 1 | DL12: =IF(DG12="NOR",IF(DI12<10,0,IF(DI12>10,(DI12-(DJ12+DK12)),0)),0) -> 0 | DM12: =IF(DG12="DOM",DI12,0) -> 0 | DN12: 7 | DO12: 17 | DP12: NOR | DQ12: =SUM(DO12-DN12) -> 10 | DR12: =IF(DQ12>1,DQ12-1,0) -> 9 | DS12: =IF(D12="STAFF",IF(DP12="NOR",IF(DR12>8.5,8.5,DR12),0),IF(DP12="NOR",IF(DR12>8,8,DR12),IF(DQ12="CAMPO",IF(DP12="NOR",IF(DR12>8,8,DR12),0),IF(DP12="NOR",IF(DR12>8,8,DR12),0)))) -> 8 | DT12: =IF(DP12="NOR",IF(DR12>10,2,IF(DR12>8,(DR12-DS12),0)),0) -> 1 | DU12: =IF(DP12="NOR",IF(DR12<10,0,IF(DR12>10,(DR12-(DS12+DT12)),0)),0) -> 0 | DV12: =IF(DP12="DOM",DR12,0) -> 0 | DW12: 7 | DX12: 17 | DY12: NOR | DZ12: =SUM(DX12-DW12) -> 10 | EA12: =IF(DZ12>1,DZ12-1,0) -> 9 | EB12: =IF(D12="STAFF",IF(DY12="NOR",IF(EA12>8.5,8.5,EA12),0),IF(DY12="NOR",IF(EA12>8,8,EA12),IF(DZ12="CAMPO",IF(DY12="NOR",IF(EA12>8,8,EA12),0),IF(DY12="NOR",IF(EA12>8,8,EA12),0)))) -> 8 | EC12: =IF(DY12="NOR",IF(EA12>10,2,IF(EA12>8,(EA12-EB12),0)),0) -> 1 | ED12: =IF(DY12="NOR",IF(EA12<10,0,IF(EA12>10,(EA12-(EB12+EC12)),0)),0) -> 0 | EE12: =IF(DY12="DOM",EA12,0) -> 0 | EF12: 7 | EG12: 16 | EH12: NOR | EI12: =SUM(EG12-EF12) -> 9 | EJ12: =IF(EI12>1,EI12-1,0) -> 8 | EK12: =IF(D12="STAFF",IF(EH12="NOR",IF(EJ12>8.5,8.5,EJ12),0),IF(EH12="NOR",IF(EJ12>8,8,EJ12),IF(EI12="CAMPO",IF(EH12="NOR",IF(EJ12>8,8,EJ12),0),IF(EH12="NOR",IF(EJ12>8,8,EJ12),0)))) -> 8 | EL12: =IF(EH12="NOR",IF(EJ12>10,2,IF(EJ12>8,(EJ12-EK12),0)),0) -> 0 | EM12: =IF(EH12="NOR",IF(EJ12<10,0,IF(EJ12>10,(EJ12-(EK12+EL12)),0)),0) -> 0 | EN12: =IF(EH12="DOM",EJ12,0) -> 0 | EO12: 0 | EP12: 0 | EQ12: DS | ER12: =SUM(EP12-EO12) -> 0 | ES12: =IF(ER12>1,ER12-1,0) -> 0 | ET12: =IF(D12="STAFF",IF(EQ12="NOR",IF(ES12>8.5,8.5,ES12),0),IF(EQ12="NOR",IF(ES12>8,8,ES12),IF(ER12="CAMPO",IF(EQ12="NOR",IF(ES12>8,8,ES12),0),IF(EQ12="NOR",IF(ES12>8,8,ES12),0)))) -> 0 | EU12: =IF(EQ12="NOR",IF(ES12>10,2,IF(ES12>8,(ES12-ET12),0)),0) -> 0 | EV12: =IF(EQ12="NOR",IF(ES12<10,0,IF(ES12>10,(ES12-(ET12+EU12)),0)),0) -> 0 | EW12: =IF(EQ12="DOM",ES12,0) -> 0 | EX12: 7 | EY12: 18 | EZ12: NOR | FA12: =SUM(EY12-EX12) -> 11 | FB12: =IF(FA12>1,FA12-1,0) -> 10 | FC12: =IF(D12="STAFF",IF(EZ12="NOR",IF(FB12>8.5,8.5,FB12),0),IF(EZ12="NOR",IF(FB12>8,8,FB12),IF(FA12="CAMPO",IF(EZ12="NOR",IF(FB12>8,8,FB12),0),IF(EZ12="NOR",IF(FB12>8,8,FB12),0)))) -> 8 | FD12: =IF(EZ12="NOR",IF(FB12>10,2,IF(FB12>8,(FB12-FC12),0)),0) -> 2 | FE12: =IF(EZ12="NOR",IF(FB12<10,0,IF(FB12>10,(FB12-(FC12+FD12)),0)),0) -> 0 | FF12: =IF(EZ12="DOM",FB12,0) -> 0 | FG12: 7 | FH12: 18 | FI12: NOR | FJ12: =SUM(FH12-FG12) -> 11 | FK12: =IF(FJ12>1,FJ12-1,0) -> 10 | FL12: =IF(D12="STAFF",IF(FI12="NOR",IF(FK12>8.5,8.5,FK12),0),IF(FI12="NOR",IF(FK12>8,8,FK12),IF(FJ12="CAMPO",IF(FI12="NOR",IF(FK12>8,8,FK12),0),IF(FI12="NOR",IF(FK12>8,8,FK12),0)))) -> 8 | FM12: =IF(FI12="NOR",IF(FK12>10,2,IF(FK12>8,(FK12-FL12),0)),0) -> 2 | FN12: =IF(FI12="NOR",IF(FK12<10,0,IF(FK12>10,(FK12-(FL12+FM12)),0)),0) -> 0 | FO12: =IF(FI12="DOM",FK12,0) -> 0 | FP12: 7 | FQ12: 17 | FR12: NOR | FS12: =SUM(FQ12-FP12) -> 10 | FT12: =IF(FS12>1,FS12-1,0) -> 9 | FU12: =IF(FK12="PROYECTO",IF(FR12="NOR",IF(FT12>8,8,FT12),0),IF(FR12="NOR",IF(FT12>8,8,FT12),0)) -> 8 | FV12: =IF(FR12="NOR",IF(FT12>10,2,IF(FT12>8,(FT12-FU12),0)),0) -> 1 | FW12: =IF(FR12="NOR",IF(FT12<10,0,IF(FT12>10,(FT12-(FU12+FV12)),0)),0) -> 0 | FX12: =IF(FR12="DOM",FT12,0) -> 0 | FY12: 7 | FZ12: 17 | GA12: NOR | GB12: =SUM(FZ12-FY12) -> 10 | GC12: =IF(GB12>1,GB12-1,0) -> 9 | GD12: =IF(D12="STAFF",IF(GA12="NOR",IF(GC12>8.5,8.5,GC12),0),IF(GA12="NOR",IF(GC12>8,8,GC12),IF(GB12="CAMPO",IF(GA12="NOR",IF(GC12>8,8,GC12),0),IF(GA12="NOR",IF(GC12>8,8,GC12),0)))) -> 8 | GE12: =IF(GA12="NOR",IF(GC12>10,2,IF(GC12>8,(GC12-GD12),0)),0) -> 1 | GF12: =IF(GA12="NOR",IF(GC12<10,0,IF(GC12>10,(GC12-(GD12+GE12)),0)),0) -> 0 | GG12: =IF(GA12="DOM",GC12,0) -> 0 | GH12: 7 | GI12: 17 | GJ12: NOR | GK12: =SUM(GI12-GH12) -> 10 | GL12: =IF(GK12>1,GK12-1,0) -> 9 | GM12: =IF(D12="STAFF",IF(GJ12="NOR",IF(GL12>8.5,8.5,GL12),0),IF(GJ12="NOR",IF(GL12>8,8,GL12),IF(GK12="CAMPO",IF(GJ12="NOR",IF(GL12>8,8,GL12),0),IF(GJ12="NOR",IF(GL12>8,8,GL12),0)))) -> 8 | GN12: =IF(GJ12="NOR",IF(GL12>10,2,IF(GL12>8,(GL12-GM12),0)),0) -> 1 | GO12: =IF(GJ12="NOR",IF(GL12<10,0,IF(GL12>10,(GL12-(GM12+GN12)),0)),0) -> 0 | GP12: =IF(GJ12="DOM",GL12,0) -> 0 | GQ12: 7 | GR12: 16 | GS12: NOR | GT12: =SUM(GR12-GQ12) -> 9 | GU12: =IF(GT12>1,GT12-1,0) -> 8 | GV12: =IF(D12="STAFF",IF(GS12="NOR",IF(GU12>8.5,8.5,GU12),0),IF(GS12="NOR",IF(GU12>8,8,GU12),IF(GT12="CAMPO",IF(GS12="NOR",IF(GU12>8,8,GU12),0),IF(GS12="NOR",IF(GU12>8,8,GU12),0)))) -> 8 | GW12: =IF(GS12="NOR",IF(GU12>10,2,IF(GU12>8,(GU12-GV12),0)),0) -> 0 | GX12: =IF(GS12="NOR",IF(GU12<10,0,IF(GU12>10,(GU12-(GV12+GW12)),0)),0) -> 0 | GY12: =IF(GS12="DOM",GU12,0) -> 0 | GZ12: 0 | HA12: 0 | HB12: DS | HC12: =SUM(HA12-GZ12) -> 0 | HD12: =IF(HC12>1,HC12-1,0) -> 0 | HE12: =IF(D12="STAFF",IF(HB12="NOR",IF(HD12>8.5,8.5,HD12),0),IF(HB12="NOR",IF(HD12>8,8,HD12),IF(HC12="CAMPO",IF(HB12="NOR",IF(HD12>8,8,HD12),0),IF(HB12="NOR",IF(HD12>8,8,HD12),0)))) -> 0 | HF12: =IF(HB12="NOR",IF(HD12>10,2,IF(HD12>8,(HD12-HE12),0)),0) -> 0 | HG12: =IF(HB12="NOR",IF(HD12<10,0,IF(HD12>10,(HD12-(HE12+HF12)),0)),0) -> 0 | HH12: =IF(HB12="DOM",HD12,0) -> 0 | HI12: 7 | HJ12: 18 | HK12: NOR | HL12: =SUM(HJ12-HI12) -> 11 | HM12: =IF(HL12>1,HL12-1,0) -> 10 | HN12: =IF(D12="STAFF",IF(HK12="NOR",IF(HM12>8.5,8.5,HM12),0),IF(HK12="NOR",IF(HM12>8,8,HM12),IF(HL12="CAMPO",IF(HK12="NOR",IF(HM12>8,8,HM12),0),IF(HK12="NOR",IF(HM12>8,8,HM12),0)))) -> 8 | HO12: =IF(HK12="NOR",IF(HM12>10,2,IF(HM12>8,(HM12-HN12),0)),0) -> 2 | HP12: =IF(HK12="NOR",IF(HM12<10,0,IF(HM12>10,(HM12-(HN12+HO12)),0)),0) -> 0 | HQ12: =IF(HK12="DOM",HM12,0) -> 0 | HR12: 7 | HS12: 18 | HT12: NOR | HU12: =SUM(HS12-HR12) -> 11 | HV12: =IF(HU12>1,HU12-1,0) -> 10 | HW12: =IF(D12="STAFF",IF(HT12="NOR",IF(HV12>8.5,8.5,HV12),0),IF(HT12="NOR",IF(HV12>8,8,HV12),IF(HU12="CAMPO",IF(HT12="NOR",IF(HV12>8,8,HV12),0),IF(HT12="NOR",IF(HV12>8,8,HV12),0)))) -> 8 | HX12: =IF(HT12="NOR",IF(HV12>10,2,IF(HV12>8,(HV12-HW12),0)),0) -> 2 | HY12: =IF(HT12="NOR",IF(HV12<10,0,IF(HV12>10,(HV12-(HW12+HX12)),0)),0) -> 0 | HZ12: =IF(HT12="DOM",HV12,0) -> 0 | IA12: 7 | IB12: 17 | IC12: NOR | ID12: =SUM(IB12-IA12) -> 10 | IE12: =IF(ID12>1,ID12-1,0) -> 9 | IF12: =IF(D12="STAFF",IF(IC12="NOR",IF(IE12>8.5,8.5,IE12),0),IF(IC12="NOR",IF(IE12>8,8,IE12),IF(ID12="CAMPO",IF(IC12="NOR",IF(IE12>8,8,IE12),0),IF(IC12="NOR",IF(IE12>8,8,IE12),0)))) -> 8 | IG12: =IF(IC12="NOR",IF(IE12>10,2,IF(IE12>8,(IE12-IF12),0)),0) -> 1 | IH12: =IF(IC12="NOR",IF(IE12<10,0,IF(IE12>10,(IE12-(IF12+IG12)),0)),0) -> 0 | II12: =IF(IC12="DOM",IE12,0) -> 0 | IJ12: 7 | IK12: 17 | IL12: NOR | IM12: =SUM(IK12-IJ12) -> 10 | IN12: =IF(IM12>1,IM12-1,0) -> 9 | IO12: =IF(D12="STAFF",IF(IL12="NOR",IF(IN12>8.5,8.5,IN12),0),IF(IL12="NOR",IF(IN12>8,8,IN12),IF(IM12="CAMPO",IF(IL12="NOR",IF(IN12>8,8,IN12),0),IF(IL12="NOR",IF(IN12>8,8,IN12),0)))) -> 8 | IP12: =IF(IL12="NOR",IF(IN12>10,2,IF(IN12>8,(IN12-IO12),0)),0) -> 1 | IQ12: =IF(IL12="NOR",IF(IN12<10,0,IF(IN12>10,(IN12-(IO12+IP12)),0)),0) -> 0 | IR12: =IF(IL12="DOM",IN12,0) -> 0 | IS12: 7 | IT12: 17 | IU12: NOR | IV12: =SUM(IT12-IS12) -> 10 | IW12: =IF(IV12>1,IV12-1,0) -> 9 | IX12: =IF(D12="STAFF",IF(IU12="NOR",IF(IW12>8.5,8.5,IW12),0),IF(IU12="NOR",IF(IW12>8,8,IW12),IF(IV12="CAMPO",IF(IU12="NOR",IF(IW12>8,8,IW12),0),IF(IU12="NOR",IF(IW12>8,8,IW12),0)))) -> 8 | IY12: =IF(IU12="NOR",IF(IW12>10,2,IF(IW12>8,(IW12-IX12),0)),0) -> 1 | IZ12: =IF(IU12="NOR",IF(IW12<10,0,IF(IW12>10,(IW12-(IX12+IY12)),0)),0) -> 0 | JA12: =IF(IU12="DOM",IW12,0) -> 0 | JB12: 7 | JC12: 16 | JD12: NOR | JE12: =SUM(JC12-JB12) -> 9 | JF12: =IF(JE12>1,JE12-1,0) -> 8 | JG12: =IF(D12="STAFF",IF(JD12="NOR",IF(JF12>8.5,8.5,JF12),0),IF(JD12="NOR",IF(JF12>8,8,JF12),IF(JE12="CAMPO",IF(JD12="NOR",IF(JF12>8,8,JF12),0),IF(JD12="NOR",IF(JF12>8,8,JF12),0)))) -> 8 | JH12: =IF(JD12="NOR",IF(JF12>10,2,IF(JF12>8,(JF12-JG12),0)),0) -> 0 | JI12: =IF(JD12="NOR",IF(JF12<10,0,IF(JF12>10,(JF12-(JG12+JH12)),0)),0) -> 0 | JJ12: =IF(JD12="DOM",JF12,0) -> 0 | JK12: 0 | JL12: 0 | JM12: DS | JN12: =SUM(JL12-JK12) -> 0 | JO12: =IF(JN12>1,JN12-1,0) -> 0 | JP12: =IF(D12="STAFF",IF(JM12="NOR",IF(JO12>8.5,8.5,JO12),0),IF(JM12="NOR",IF(JO12>8,8,JO12),IF(JN12="CAMPO",IF(JM12="NOR",IF(JO12>8,8,JO12),0),IF(JM12="NOR",IF(JO12>8,8,JO12),0)))) -> 0 | JQ12: =IF(JM12="NOR",IF(JO12>10,2,IF(JO12>8,(JO12-JP12),0)),0) -> 0 | JR12: =IF(JM12="NOR",IF(JO12<10,0,IF(JO12>10,(JO12-(JP12+JQ12)),0)),0) -> 0 | JS12: =IF(JM12="DOM",JO12,0) -> 0 | JT12: 7 | JU12: 18 | JV12: NOR | JW12: =SUM(JU12-JT12) -> 11 | JX12: =IF(JW12>1,JW12-1,0) -> 10 | JY12: =IF(D12="STAFF",IF(JV12="NOR",IF(JX12>8.5,8.5,JX12),0),IF(JV12="NOR",IF(JX12>8,8,JX12),IF(JW12="CAMPO",IF(JV12="NOR",IF(JX12>8,8,JX12),0),IF(JV12="NOR",IF(JX12>8,8,JX12),0)))) -> 8 | JZ12: =IF(JV12="NOR",IF(JX12>10,2,IF(JX12>8,(JX12-JY12),0)),0) -> 2 | KA12: =IF(JV12="NOR",IF(JX12<10,0,IF(JX12>10,(JX12-(JY12+JZ12)),0)),0) -> 0 | KB12: =IF(JV12="DOM",JX12,0) -> 0 | KC12: 7 | KD12: 16 | KE12: NOR | KF12: =SUM(KD12-KC12) -> 9 | KG12: =IF(KF12>1,KF12-1,0) -> 8 | KH12: =IF(D12="STAFF",IF(KE12="NOR",IF(KG12>8.5,8.5,KG12),0),IF(KE12="NOR",IF(KG12>8,8,KG12),IF(KF12="CAMPO",IF(KE12="NOR",IF(KG12>8,8,KG12),0),IF(KE12="NOR",IF(KG12>8,8,KG12),0)))) -> 8 | KI12: =IF(KE12="NOR",IF(KG12>10,2,IF(KG12>8,(KG12-KH12),0)),0) -> 0 | KJ12: =IF(KE12="NOR",IF(KG12<10,0,IF(KG12>10,(KG12-(KH12+KI12)),0)),0) -> 0 | KK12: =IF(KE12="DOM",KG12,0) -> 0 | KL12: 7 | KM12: 16 | KN12: NOR | KO12: =SUM(KM12-KL12) -> 9 | KP12: =IF(KO12>1,KO12-1,0) -> 8 | KQ12: =IF(D12="STAFF",IF(KN12="NOR",IF(KP12>8.5,8.5,KP12),0),IF(KN12="NOR",IF(KP12>8,8,KP12),IF(KO12="CAMPO",IF(KN12="NOR",IF(KP12>8,8,KP12),0),IF(KN12="NOR",IF(KP12>8,8,KP12),0)))) -> 8 | KR12: =IF(KN12="NOR",IF(KP12>10,2,IF(KP12>8,(KP12-KQ12),0)),0) -> 0 | KS12: =IF(KN12="NOR",IF(KP12<10,0,IF(KP12>10,(KP12-(KQ12+KR12)),0)),0) -> 0 | KT12: =IF(KN12="DOM",KP12,0) -> 0 | KU12: 7 | KV12: 16 | KW12: NOR | KX12: =SUM(KV12-KU12) -> 9 | KY12: =IF(KX12>1,KX12-1,0) -> 8 | KZ12: =IF(D12="STAFF",IF(KW12="NOR",IF(KY12>8.5,8.5,KY12),0),IF(KW12="NOR",IF(KY12>8,8,KY12),IF(KX12="CAMPO",IF(KW12="NOR",IF(KY12>8,8,KY12),0),IF(KW12="NOR",IF(KY12>8,8,KY12),0)))) -> 8 | LA12: =IF(KW12="NOR",IF(KY12>10,2,IF(KY12>8,(KY12-KZ12),0)),0) -> 0 | LB12: =IF(KW12="NOR",IF(KY12<10,0,IF(KY12>10,(KY12-(KZ12+LA12)),0)),0) -> 0 | LC12: =IF(KW12="DOM",KY12,0) -> 0 | LD12: 7 | LE12: 16 | LF12: NOR | LG12: =SUM(LE12-LD12) -> 9 | LH12: =IF(LG12>1,LG12-1,0) -> 8 | LI12: =IF(D12="STAFF",IF(LF12="NOR",IF(LH12>8.5,8.5,LH12),0),IF(LF12="NOR",IF(LH12>8,8,LH12),IF(LG12="CAMPO",IF(LF12="NOR",IF(LH12>8,8,LH12),0),IF(LF12="NOR",IF(LH12>8,8,LH12),0)))) -> 8 | LJ12: =IF(LF12="NOR",IF(LH12>10,2,IF(LH12>8,(LH12-LI12),0)),0) -> 0 | LK12: =IF(LF12="NOR",IF(LH12<10,0,IF(LH12>10,(LH12-(LI12+LJ12)),0)),0) -> 0 | LL12: =IF(LF12="DOM",LH12,0) -> 0 | LM12: 7 | LN12: 16 | LO12: NOR | LP12: =SUM(LN12-LM12) -> 9 | LQ12: =IF(LP12>1,LP12-1,0) -> 8 | LR12: =IF(D12="STAFF",IF(LO12="NOR",IF(LQ12>8.5,8.5,LQ12),0),IF(LO12="NOR",IF(LQ12>8,8,LQ12),IF(LP12="CAMPO",IF(LO12="NOR",IF(LQ12>8,8,LQ12),0),IF(LO12="NOR",IF(LQ12>8,8,LQ12),0)))) -> 8 | LS12: =IF(LO12="NOR",IF(LQ12>10,2,IF(LQ12>8,(LQ12-LR12),0)),0) -> 0 | LT12: =IF(LO12="NOR",IF(LQ12<10,0,IF(LQ12>10,(LQ12-(LR12+LS12)),0)),0) -> 0 | LU12: =IF(LO12="DOM",LQ12,0) -> 0 | LV12: 7 | LW12: 16 | LX12: NOR | LY12: =SUM(LW12-LV12) -> 9 | LZ12: =IF(LY12>1,LY12-1,0) -> 8 | MA12: =IF(D12="STAFF",IF(LX12="NOR",IF(LZ12>8.5,8.5,LZ12),0),IF(LX12="NOR",IF(LZ12>8,8,LZ12),IF(LY12="CAMPO",IF(LX12="NOR",IF(LZ12>8,8,LZ12),0),IF(LX12="NOR",IF(LZ12>8,8,LZ12),0)))) -> 8 | MB12: =IF(LX12="NOR",IF(LZ12>10,2,IF(LZ12>8,(LZ12-MA12),0)),0) -> 0 | MC12: =IF(LX12="NOR",IF(LZ12<10,0,IF(LZ12>10,(LZ12-(MA12+MB12)),0)),0) -> 0 | MD12: =IF(LX12="DOM",LZ12,0) -> 0 | ME12: 7 | MF12: 16 | MG12: NOR | MH12: =SUM(MF12-ME12) -> 9 | MI12: =IF(MH12>1,MH12-1,0) -> 8 | MJ12: =IF(D12="STAFF",IF(MG12="NOR",IF(MI12>8.5,8.5,MI12),0),IF(MG12="NOR",IF(MI12>8,8,MI12),IF(MH12="CAMPO",IF(MG12="NOR",IF(MI12>8,8,MI12),0),IF(MG12="NOR",IF(MI12>8,8,MI12),0)))) -> 8 | MK12: =IF(MG12="NOR",IF(MI12>10,2,IF(MI12>8,(MI12-MJ12),0)),0) -> 0 | ML12: =IF(MG12="NOR",IF(MI12<10,0,IF(MI12>10,(MI12-(MJ12+MK12)),0)),0) -> 0 | MM12: =IF(MG12="DOM",MI12,0) -> 0 | MN12: 7 | MO12: 16 | MP12: NOR | MQ12: =SUM(MO12-MN12) -> 9 | MR12: =IF(MQ12>1,MQ12-1,0) -> 8 | MS12: =IF(D12="STAFF",IF(MP12="NOR",IF(MR12>8.5,8.5,MR12),0),IF(MP12="NOR",IF(MR12>8,8,MR12),IF(MQ12="CAMPO",IF(MP12="NOR",IF(MR12>8,8,MR12),0),IF(MP12="NOR",IF(MR12>8,8,MR12),0)))) -> 8 | MT12: =IF(MP12="NOR",IF(MR12>10,2,IF(MR12>8,(MR12-MS12),0)),0) -> 0 | MU12: =IF(MP12="NOR",IF(MR12<10,0,IF(MR12>10,(MR12-(MS12+MT12)),0)),0) -> 0 | MV12: =IF(MP12="DOM",MR12,0) -> 0 | MW12: 7 | MX12: 16 | MY12: NOR | MZ12: =SUM(MX12-MW12) -> 9 | NA12: =IF(MZ12>1,MZ12-1,0) -> 8 | NB12: =IF(D12="STAFF",IF(MY12="NOR",IF(NA12>8.5,8.5,NA12),0),IF(MY12="NOR",IF(NA12>8,8,NA12),IF(MZ12="CAMPO",IF(MY12="NOR",IF(NA12>8,8,NA12),0),IF(MY12="NOR",IF(NA12>8,8,NA12),0)))) -> 8 | NC12: =IF(MY12="NOR",IF(NA12>10,2,IF(NA12>8,(NA12-NB12),0)),0) -> 0 | ND12: =IF(MY12="NOR",IF(NA12<10,0,IF(NA12>10,(NA12-(NB12+NC12)),0)),0) -> 0 | NE12: =IF(MY12="DOM",NA12,0) -> 0 | NF12: 7 | NG12: 16 | NH12: NOR | NI12: =SUM(NG12-NF12) -> 9 | NJ12: =IF(NI12>1,NI12-1,0) -> 8 | NK12: =IF(D12="STAFF",IF(NH12="NOR",IF(NJ12>8.5,8.5,NJ12),0),IF(NH12="NOR",IF(NJ12>8,8,NJ12),IF(NI12="CAMPO",IF(NH12="NOR",IF(NJ12>8,8,NJ12),0),IF(NH12="NOR",IF(NJ12>8,8,NJ12),0)))) -> 8 | NL12: =IF(NH12="NOR",IF(NJ12>10,2,IF(NJ12>8,(NJ12-NK12),0)),0) -> 0 | NM12: =IF(NH12="NOR",IF(NJ12<10,0,IF(NJ12>10,(NJ12-(NK12+NL12)),0)),0) -> 0 | NN12: =IF(NH12="DOM",NJ12,0) -> 0 | NO12: 7 | NP12: 16 | NQ12: NOR | NR12: =SUM(NP12-NO12) -> 9 | NS12: =IF(NR12>1,NR12-1,0) -> 8 | NT12: =IF(D12="STAFF",IF(NQ12="NOR",IF(NS12>8.5,8.5,NS12),0),IF(NQ12="NOR",IF(NS12>8,8,NS12),IF(NR12="CAMPO",IF(NQ12="NOR",IF(NS12>8,8,NS12),0),IF(NQ12="NOR",IF(NS12>8,8,NS12),0)))) -> 8 | NU12: =IF(NQ12="NOR",IF(NS12>10,2,IF(NS12>8,(NS12-NT12),0)),0) -> 0 | NV12: =IF(NQ12="NOR",IF(NS12<10,0,IF(NS12>10,(NS12-(NT12+NU12)),0)),0) -> 0 | NW12: =IF(NQ12="DOM",NS12,0) -> 0 | NX12: 7 | NY12: 16 | NZ12: NOR | OA12: =SUM(NY12-NX12) -> 9 | OB12: =IF(OA12>1,OA12-1,0) -> 8 | OC12: =IF(D12="STAFF",IF(NZ12="NOR",IF(OB12>8.5,8.5,OB12),0),IF(NZ12="NOR",IF(OB12>8,8,OB12),IF(OA12="CAMPO",IF(NZ12="NOR",IF(OB12>8,8,OB12),0),IF(NZ12="NOR",IF(OB12>8,8,OB12),0)))) -> 8 | OD12: =IF(NZ12="NOR",IF(OB12>10,2,IF(OB12>8,(OB12-OC12),0)),0) -> 0 | OE12: =IF(NZ12="NOR",IF(OB12<10,0,IF(OB12>10,(OB12-(OC12+OD12)),0)),0) -> 0 | OF12: =IF(NZ12="DOM",OB12,0) -> 0 | OG12: 0 | OH12: 0 | OI12: DS | OJ12: =SUM(OH12-OG12) -> 0 | OK12: =IF(OJ12>1,OJ12-1,0) -> 0 | OL12: =IF(D12="STAFF",IF(OI12="NOR",IF(OK12>8.5,8.5,OK12),0),IF(OI12="NOR",IF(OK12>8,8,OK12),IF(OJ12="CAMPO",IF(OI12="NOR",IF(OK12>8,8,OK12),0),IF(OI12="NOR",IF(OK12>8,8,OK12),0)))) -> 0 | OM12: =IF(OI12="NOR",IF(OK12>10,2,IF(OK12>8,(OK12-OL12),0)),0) -> 0 | ON12: =IF(OI12="NOR",IF(OK12<10,0,IF(OK12>10,(OK12-(OL12+OM12)),0)),0) -> 0 | OO12: =IF(OI12="DOM",OK12,0) -> 0 | OP12: 7 | OQ12: 16 | OR12: NOR | OS12: =SUM(OQ12-OP12) -> 9 | OT12: =IF(OS12>1,OS12-1,0) -> 8 | OU12: =IF(D12="STAFF",IF(OR12="NOR",IF(OT12>8.5,8.5,OT12),0),IF(OR12="NOR",IF(OT12>8,8,OT12),IF(OS12="CAMPO",IF(OR12="NOR",IF(OT12>8,8,OT12),0),IF(OR12="NOR",IF(OT12>8,8,OT12),0)))) -> 8 | OV12: =IF(OR12="NOR",IF(OT12>10,2,IF(OT12>8,(OT12-OU12),0)),0) -> 0 | OW12: =IF(OR12="NOR",IF(OT12<10,0,IF(OT12>10,(OT12-(OU12+OV12)),0)),0) -> 0 | OX12: =IF(OR12="DOM",OT12,0) -> 0 | OY12: 0 | OZ12: 0 | PA12: FE | PB12: =SUM(OZ12-OY12) -> 0 | PC12: =IF(PB12>1,PB12-1,0) -> 0 | PD12: =IF(D12="STAFF",IF(PA12="NOR",IF(PC12>8.5,8.5,PC12),0),IF(PA12="NOR",IF(PC12>8,8,PC12),IF(PB12="CAMPO",IF(PA12="NOR",IF(PC12>8,8,PC12),0),IF(PA12="NOR",IF(PC12>8,8,PC12),0)))) -> 0 | PE12: =IF(PA12="NOR",IF(PC12>10,2,IF(PC12>8,(PC12-PD12),0)),0) -> 0 | PF12: =IF(PA12="NOR",IF(PC12<10,0,IF(PC12>10,(PC12-(PD12+PE12)),0)),0) -> 0 | PG12: =IF(PA12="DOM",PC12,0) -> 0 | PH12: 7 | PI12: 16 | PJ12: NOR | PK12: =SUM(PI12-PH12) -> 9 | PL12: =IF(PK12>1,PK12-1,0) -> 8 | PM12: =IF(M12="STAFF",IF(PJ12="NOR",IF(PL12>8.5,8.5,PL12),0),IF(PJ12="NOR",IF(PL12>8,8,PL12),IF(PK12="CAMPO",IF(PJ12="NOR",IF(PL12>8,8,PL12),0),IF(PJ12="NOR",IF(PL12>8,8,PL12),0)))) -> 8 | PN12: =IF(PJ12="NOR",IF(PL12>10,2,IF(PL12>8,(PL12-PM12),0)),0) -> 0 | PO12: =IF(PJ12="NOR",IF(PL12<10,0,IF(PL12>10,(PL12-(PM12+PN12)),0)),0) -> 0 | PP12: =IF(PJ12="DOM",PL12,0) -> 0 | PR12: =COUNTIF(FG12:PP12,"NOR") -> 26 | PS12: =COUNTIF(FG12:PP12,"DS") -> 3 | PT12: =COUNTIF(FG12:PP12,"FE") -> 1 | PU12: =SUM(PR12:PT12) -> 30 | PV12: =COUNTIF(FG12:PP12,"DM") -> 0 | PY12: =COUNTIF(FG12:PP12,"SUB") -> 0 | QB12: =COUNTIF(FG12:PP12,"VA") -> 0 | QE12: =COUNTIF(FG12:PP12,"LSG") -> 0 | QH12: =COUNTIF(FG12:PP12,"LCG") -> 0 | QK12: =COUNTIF(FG12:PP12,"FA") -> 0 | QN12: =COUNTIF(J12:FF12,"FA") -> 0 | QQ12: =PU12+PV12+PY12+QB12+QE12+QH12+QK12+QN12 -> 30 | QS12: =P12+Y12++AH12+AQ12+AZ12+BI12+BR12+CA12+CJ12+CS12+DB12+DK12+DT12+EC12+EL12+EU12+FD12+FM12+FV12+GE12+GN12+GW12+HF12+HO12+HX12+IG12+IP12+IY12+JH12+JQ12+JZ12 -> 35 | QT12: =Q12+Z12++AI12+AR12+BA12+BJ12+BS12+CB12+CK12+CT12+DC12+DL12+DU12+ED12+EM12+EV12+FE12+FN12+FW12+GF12+GO12+GX12+HG12+HP12+HY12+IH12+IQ12+IZ12+JI12+JR12+KA12 -> 2 | RG12: 0
A13: =A12+1 -> 4 | B13: 76460766 | D13: PROYECTO | E13: CASTILLA GUANILO JESICA CAROLINA | F13: VIGÍA | G13: 44319 | H13: 44323 | J13: 7 | K13: 18 | L13: NOR | M13: =SUM(K13-J13) -> 11 | N13: =IF(M13>1,M13-1,0) -> 10 | O13: =IF(D13="STAFF",IF(L13="NOR",IF(N13>8.5,8.5,N13),0),IF(L13="NOR",IF(N13>8,8,N13),IF(D13="CAMPO",IF(L13="NOR",IF(N13>8,8,N13),0),IF(L13="NOR",IF(N13>8,8,N13),0)))) -> 8 | P13: =IF(L13="NOR",IF(N13>10,2,IF(N13>8,(N13-O13),0)),0) -> 2 | Q13: =IF(L13="NOR",IF(N13<10,0,IF(N13>10,(N13-(O13+P13)),0)),0) -> 0 | R13: =IF(L13="DOM",N13,0) -> 0 | S13: 0 | T13: 0 | U13: DS | V13: =SUM(T13-S13) -> 0 | W13: =IF(V13>1,V13-1,0) -> 0 | X13: =IF(D13="STAFF",IF(U13="NOR",IF(W13>8.5,8.5,W13),0),IF(U13="NOR",IF(W13>8,8,W13),IF(M13="CAMPO",IF(U13="NOR",IF(W13>8,8,W13),0),IF(U13="NOR",IF(W13>8,8,W13),0)))) -> 0 | Y13: =IF(U13="NOR",IF(W13>10,2,IF(W13>8,(W13-X13),0)),0) -> 0 | Z13: =IF(U13="NOR",IF(W13<10,0,IF(W13>10,(W13-(X13+Y13)),0)),0) -> 0 | AA13: =IF(U13="DOM",W13,0) -> 0 | AB13: 7 | AC13: 18 | AD13: NOR | AE13: =SUM(AC13-AB13) -> 11 | AF13: =IF(AE13>1,AE13-1,0) -> 10 | AG13: =IF(D13="STAFF",IF(AD13="NOR",IF(AF13>8.5,8.5,AF13),0),IF(AD13="NOR",IF(AF13>8,8,AF13),IF(AE13="CAMPO",IF(AD13="NOR",IF(AF13>8,8,AF13),0),IF(AD13="NOR",IF(AF13>8,8,AF13),0)))) -> 8 | AH13: =IF(AD13="NOR",IF(AF13>10,2,IF(AF13>8,(AF13-AG13),0)),0) -> 2 | AI13: =IF(AD13="NOR",IF(AF13<10,0,IF(AF13>10,(AF13-(AG13+AH13)),0)),0) -> 0 | AJ13: =IF(AD13="DOM",AF13,0) -> 0 | AK13: 7 | AL13: 18 | AM13: NOR | AN13: =SUM(AL13-AK13) -> 11 | AO13: =IF(AN13>1,AN13-1,0) -> 10 | AP13: =IF(D13="PROYECTO",IF(AM13="NOR",IF(AO13>8,8,AO13),0),IF(AM13="NOR",IF(AO13>8,8,AO13),0)) -> 8 | AQ13: =IF(AM13="NOR",IF(AO13>10,2,IF(AO13>8,(AO13-AP13),0)),0) -> 2 | AR13: =IF(AM13="NOR",IF(AO13<10,0,IF(AO13>10,(AO13-(AP13+AQ13)),0)),0) -> 0 | AS13: =IF(AM13="DOM",AO13,0) -> 0 | AT13: 7 | AU13: 18 | AV13: NOR | AW13: =SUM(AU13-AT13) -> 11 | AX13: =IF(AW13>1,AW13-1,0) -> 10 | AY13: =IF(AO13="PROYECTO",IF(AV13="NOR",IF(AX13>8,8,AX13),0),IF(AV13="NOR",IF(AX13>8,8,AX13),0)) -> 8 | AZ13: =IF(AV13="NOR",IF(AX13>10,2,IF(AX13>8,(AX13-AY13),0)),0) -> 2 | BA13: =IF(AV13="NOR",IF(AX13<10,0,IF(AX13>10,(AX13-(AY13+AZ13)),0)),0) -> 0 | BB13: =IF(AV13="DOM",AX13,0) -> 0 | BC13: 7 | BD13: 18 | BE13: NOR | BF13: =SUM(BD13-BC13) -> 11 | BG13: =IF(BF13>1,BF13-1,0) -> 10 | BH13: =IF(D13="STAFF",IF(BE13="NOR",IF(BG13>8.5,8.5,BG13),0),IF(BE13="NOR",IF(BG13>8,8,BG13),IF(BF13="CAMPO",IF(BE13="NOR",IF(BG13>8,8,BG13),0),IF(BE13="NOR",IF(BG13>8,8,BG13),0)))) -> 8 | BI13: =IF(BE13="NOR",IF(BG13>10,2,IF(BG13>8,(BG13-BH13),0)),0) -> 2 | BJ13: =IF(BE13="NOR",IF(BG13<10,0,IF(BG13>10,(BG13-(BH13+BI13)),0)),0) -> 0 | BK13: =IF(BE13="DOM",BG13,0) -> 0 | BL13: 7 | BM13: 18 | BN13: NOR | BO13: =SUM(BM13-BL13) -> 11 | BP13: =IF(BO13>1,BO13-1,0) -> 10 | BQ13: =IF(D13="STAFF",IF(BN13="NOR",IF(BP13>8.5,8.5,BP13),0),IF(BN13="NOR",IF(BP13>8,8,BP13),IF(BO13="CAMPO",IF(BN13="NOR",IF(BP13>8,8,BP13),0),IF(BN13="NOR",IF(BP13>8,8,BP13),0)))) -> 8 | BR13: =IF(BN13="NOR",IF(BP13>10,2,IF(BP13>8,(BP13-BQ13),0)),0) -> 2 | BS13: =IF(BN13="NOR",IF(BP13<10,0,IF(BP13>10,(BP13-(BQ13+BR13)),0)),0) -> 0 | BT13: =IF(BN13="DOM",BP13,0) -> 0 | BU13: 7 | BV13: 18 | BW13: NOR | BX13: =SUM(BV13-BU13) -> 11 | BY13: =IF(BX13>1,BX13-1,0) -> 10 | BZ13: =IF(D13="STAFF",IF(BW13="NOR",IF(BY13>8.5,8.5,BY13),0),IF(BW13="NOR",IF(BY13>8,8,BY13),IF(BX13="CAMPO",IF(BW13="NOR",IF(BY13>8,8,BY13),0),IF(BW13="NOR",IF(BY13>8,8,BY13),0)))) -> 8 | CA13: =IF(BW13="NOR",IF(BY13>10,2,IF(BY13>8,(BY13-BZ13),0)),0) -> 2 | CB13: =IF(BW13="NOR",IF(BY13<10,0,IF(BY13>10,(BY13-(BZ13+CA13)),0)),0) -> 0 | CC13: =IF(BW13="DOM",BY13,0) -> 0 | CD13: 0 | CE13: 0 | CF13: DS | CG13: =SUM(CE13-CD13) -> 0 | CH13: =IF(CG13>1,CG13-1,0) -> 0 | CI13: =IF(D13="STAFF",IF(CF13="NOR",IF(CH13>8.5,8.5,CH13),0),IF(CF13="NOR",IF(CH13>8,8,CH13),IF(CG13="CAMPO",IF(CF13="NOR",IF(CH13>8,8,CH13),0),IF(CF13="NOR",IF(CH13>8,8,CH13),0)))) -> 0 | CJ13: =IF(CF13="NOR",IF(CH13>10,2,IF(CH13>8,(CH13-CI13),0)),0) -> 0 | CK13: =IF(CF13="NOR",IF(CH13<10,0,IF(CH13>10,(CH13-(CI13+CJ13)),0)),0) -> 0 | CL13: =IF(CF13="DOM",CH13,0) -> 0 | CM13: 7 | CN13: 18 | CO13: NOR | CP13: =SUM(CN13-CM13) -> 11 | CQ13: =IF(CP13>1,CP13-1,0) -> 10 | CR13: =IF(D13="STAFF",IF(CO13="NOR",IF(CQ13>8.5,8.5,CQ13),0),IF(CO13="NOR",IF(CQ13>8,8,CQ13),IF(CP13="CAMPO",IF(CO13="NOR",IF(CQ13>8,8,CQ13),0),IF(CO13="NOR",IF(CQ13>8,8,CQ13),0)))) -> 8 | CS13: =IF(CO13="NOR",IF(CQ13>10,2,IF(CQ13>8,(CQ13-CR13),0)),0) -> 2 | CT13: =IF(CO13="NOR",IF(CQ13<10,0,IF(CQ13>10,(CQ13-(CR13+CS13)),0)),0) -> 0 | CU13: =IF(CO13="DOM",CQ13,0) -> 0 | CV13: 7 | CW13: 18 | CX13: NOR | CY13: =SUM(CW13-CV13) -> 11 | CZ13: =IF(CY13>1,CY13-1,0) -> 10 | DA13: =IF(CQ13="PROYECTO",IF(CX13="NOR",IF(CZ13>8,8,CZ13),0),IF(CX13="NOR",IF(CZ13>8,8,CZ13),0)) -> 8 | DB13: =IF(CX13="NOR",IF(CZ13>10,2,IF(CZ13>8,(CZ13-DA13),0)),0) -> 2 | DC13: =IF(CX13="NOR",IF(CZ13<10,0,IF(CZ13>10,(CZ13-(DA13+DB13)),0)),0) -> 0 | DD13: =IF(CX13="DOM",CZ13,0) -> 0 | DE13: 7 | DF13: 18 | DG13: NOR | DH13: =SUM(DF13-DE13) -> 11 | DI13: =IF(DH13>1,DH13-1,0) -> 10 | DJ13: =IF(CZ13="PROYECTO",IF(DG13="NOR",IF(DI13>8,8,DI13),0),IF(DG13="NOR",IF(DI13>8,8,DI13),0)) -> 8 | DK13: =IF(DG13="NOR",IF(DI13>10,2,IF(DI13>8,(DI13-DJ13),0)),0) -> 2 | DL13: =IF(DG13="NOR",IF(DI13<10,0,IF(DI13>10,(DI13-(DJ13+DK13)),0)),0) -> 0 | DM13: =IF(DG13="DOM",DI13,0) -> 0 | DN13: 7 | DO13: 18 | DP13: NOR | DQ13: =SUM(DO13-DN13) -> 11 | DR13: =IF(DQ13>1,DQ13-1,0) -> 10 | DS13: =IF(D13="STAFF",IF(DP13="NOR",IF(DR13>8.5,8.5,DR13),0),IF(DP13="NOR",IF(DR13>8,8,DR13),IF(DQ13="CAMPO",IF(DP13="NOR",IF(DR13>8,8,DR13),0),IF(DP13="NOR",IF(DR13>8,8,DR13),0)))) -> 8 | DT13: =IF(DP13="NOR",IF(DR13>10,2,IF(DR13>8,(DR13-DS13),0)),0) -> 2 | DU13: =IF(DP13="NOR",IF(DR13<10,0,IF(DR13>10,(DR13-(DS13+DT13)),0)),0) -> 0 | DV13: =IF(DP13="DOM",DR13,0) -> 0 | DW13: 7 | DX13: 18 | DY13: NOR | DZ13: =SUM(DX13-DW13) -> 11 | EA13: =IF(DZ13>1,DZ13-1,0) -> 10 | EB13: =IF(D13="STAFF",IF(DY13="NOR",IF(EA13>8.5,8.5,EA13),0),IF(DY13="NOR",IF(EA13>8,8,EA13),IF(DZ13="CAMPO",IF(DY13="NOR",IF(EA13>8,8,EA13),0),IF(DY13="NOR",IF(EA13>8,8,EA13),0)))) -> 8 | EC13: =IF(DY13="NOR",IF(EA13>10,2,IF(EA13>8,(EA13-EB13),0)),0) -> 2 | ED13: =IF(DY13="NOR",IF(EA13<10,0,IF(EA13>10,(EA13-(EB13+EC13)),0)),0) -> 0 | EE13: =IF(DY13="DOM",EA13,0) -> 0 | EF13: 7 | EG13: 18 | EH13: NOR | EI13: =SUM(EG13-EF13) -> 11 | EJ13: =IF(EI13>1,EI13-1,0) -> 10 | EK13: =IF(D13="STAFF",IF(EH13="NOR",IF(EJ13>8.5,8.5,EJ13),0),IF(EH13="NOR",IF(EJ13>8,8,EJ13),IF(EI13="CAMPO",IF(EH13="NOR",IF(EJ13>8,8,EJ13),0),IF(EH13="NOR",IF(EJ13>8,8,EJ13),0)))) -> 8 | EL13: =IF(EH13="NOR",IF(EJ13>10,2,IF(EJ13>8,(EJ13-EK13),0)),0) -> 2 | EM13: =IF(EH13="NOR",IF(EJ13<10,0,IF(EJ13>10,(EJ13-(EK13+EL13)),0)),0) -> 0 | EN13: =IF(EH13="DOM",EJ13,0) -> 0 | EO13: 0 | EP13: 0 | EQ13: DS | ER13: =SUM(EP13-EO13) -> 0 | ES13: =IF(ER13>1,ER13-1,0) -> 0 | ET13: =IF(D13="STAFF",IF(EQ13="NOR",IF(ES13>8.5,8.5,ES13),0),IF(EQ13="NOR",IF(ES13>8,8,ES13),IF(ER13="CAMPO",IF(EQ13="NOR",IF(ES13>8,8,ES13),0),IF(EQ13="NOR",IF(ES13>8,8,ES13),0)))) -> 0 | EU13: =IF(EQ13="NOR",IF(ES13>10,2,IF(ES13>8,(ES13-ET13),0)),0) -> 0 | EV13: =IF(EQ13="NOR",IF(ES13<10,0,IF(ES13>10,(ES13-(ET13+EU13)),0)),0) -> 0 | EW13: =IF(EQ13="DOM",ES13,0) -> 0 | EX13: 7 | EY13: 18 | EZ13: NOR | FA13: =SUM(EY13-EX13) -> 11 | FB13: =IF(FA13>1,FA13-1,0) -> 10 | FC13: =IF(D13="STAFF",IF(EZ13="NOR",IF(FB13>8.5,8.5,FB13),0),IF(EZ13="NOR",IF(FB13>8,8,FB13),IF(FA13="CAMPO",IF(EZ13="NOR",IF(FB13>8,8,FB13),0),IF(EZ13="NOR",IF(FB13>8,8,FB13),0)))) -> 8 | FD13: =IF(EZ13="NOR",IF(FB13>10,2,IF(FB13>8,(FB13-FC13),0)),0) -> 2 | FE13: =IF(EZ13="NOR",IF(FB13<10,0,IF(FB13>10,(FB13-(FC13+FD13)),0)),0) -> 0 | FF13: =IF(EZ13="DOM",FB13,0) -> 0 | FG13: 0 | FH13: 0 | FI13: FA | FJ13: =SUM(FH13-FG13) -> 0 | FK13: =IF(FJ13>1,FJ13-1,0) -> 0 | FL13: =IF(D13="STAFF",IF(FI13="NOR",IF(FK13>8.5,8.5,FK13),0),IF(FI13="NOR",IF(FK13>8,8,FK13),IF(FJ13="CAMPO",IF(FI13="NOR",IF(FK13>8,8,FK13),0),IF(FI13="NOR",IF(FK13>8,8,FK13),0)))) -> 0 | FM13: =IF(FI13="NOR",IF(FK13>10,2,IF(FK13>8,(FK13-FL13),0)),0) -> 0 | FN13: =IF(FI13="NOR",IF(FK13<10,0,IF(FK13>10,(FK13-(FL13+FM13)),0)),0) -> 0 | FO13: =IF(FI13="DOM",FK13,0) -> 0 | FP13: 7 | FQ13: 18 | FR13: NOR | FS13: =SUM(FQ13-FP13) -> 11 | FT13: =IF(FS13>1,FS13-1,0) -> 10 | FU13: =IF(FK13="PROYECTO",IF(FR13="NOR",IF(FT13>8,8,FT13),0),IF(FR13="NOR",IF(FT13>8,8,FT13),0)) -> 8 | FV13: =IF(FR13="NOR",IF(FT13>10,2,IF(FT13>8,(FT13-FU13),0)),0) -> 2 | FW13: =IF(FR13="NOR",IF(FT13<10,0,IF(FT13>10,(FT13-(FU13+FV13)),0)),0) -> 0 | FX13: =IF(FR13="DOM",FT13,0) -> 0 | FY13: 7 | FZ13: 18 | GA13: NOR | GB13: =SUM(FZ13-FY13) -> 11 | GC13: =IF(GB13>1,GB13-1,0) -> 10 | GD13: =IF(D13="STAFF",IF(GA13="NOR",IF(GC13>8.5,8.5,GC13),0),IF(GA13="NOR",IF(GC13>8,8,GC13),IF(GB13="CAMPO",IF(GA13="NOR",IF(GC13>8,8,GC13),0),IF(GA13="NOR",IF(GC13>8,8,GC13),0)))) -> 8 | GE13: =IF(GA13="NOR",IF(GC13>10,2,IF(GC13>8,(GC13-GD13),0)),0) -> 2 | GF13: =IF(GA13="NOR",IF(GC13<10,0,IF(GC13>10,(GC13-(GD13+GE13)),0)),0) -> 0 | GG13: =IF(GA13="DOM",GC13,0) -> 0 | GH13: 7 | GI13: 18 | GJ13: NOR | GK13: =SUM(GI13-GH13) -> 11 | GL13: =IF(GK13>1,GK13-1,0) -> 10 | GM13: =IF(D13="STAFF",IF(GJ13="NOR",IF(GL13>8.5,8.5,GL13),0),IF(GJ13="NOR",IF(GL13>8,8,GL13),IF(GK13="CAMPO",IF(GJ13="NOR",IF(GL13>8,8,GL13),0),IF(GJ13="NOR",IF(GL13>8,8,GL13),0)))) -> 8 | GN13: =IF(GJ13="NOR",IF(GL13>10,2,IF(GL13>8,(GL13-GM13),0)),0) -> 2 | GO13: =IF(GJ13="NOR",IF(GL13<10,0,IF(GL13>10,(GL13-(GM13+GN13)),0)),0) -> 0 | GP13: =IF(GJ13="DOM",GL13,0) -> 0 | GQ13: 7 | GR13: 18 | GS13: NOR | GT13: =SUM(GR13-GQ13) -> 11 | GU13: =IF(GT13>1,GT13-1,0) -> 10 | GV13: =IF(D13="STAFF",IF(GS13="NOR",IF(GU13>8.5,8.5,GU13),0),IF(GS13="NOR",IF(GU13>8,8,GU13),IF(GT13="CAMPO",IF(GS13="NOR",IF(GU13>8,8,GU13),0),IF(GS13="NOR",IF(GU13>8,8,GU13),0)))) -> 8 | GW13: =IF(GS13="NOR",IF(GU13>10,2,IF(GU13>8,(GU13-GV13),0)),0) -> 2 | GX13: =IF(GS13="NOR",IF(GU13<10,0,IF(GU13>10,(GU13-(GV13+GW13)),0)),0) -> 0 | GY13: =IF(GS13="DOM",GU13,0) -> 0 | GZ13: 0 | HA13: 0 | HB13: DS | HC13: =SUM(HA13-GZ13) -> 0 | HD13: =IF(HC13>1,HC13-1,0) -> 0 | HE13: =IF(D13="STAFF",IF(HB13="NOR",IF(HD13>8.5,8.5,HD13),0),IF(HB13="NOR",IF(HD13>8,8,HD13),IF(HC13="CAMPO",IF(HB13="NOR",IF(HD13>8,8,HD13),0),IF(HB13="NOR",IF(HD13>8,8,HD13),0)))) -> 0 | HF13: =IF(HB13="NOR",IF(HD13>10,2,IF(HD13>8,(HD13-HE13),0)),0) -> 0 | HG13: =IF(HB13="NOR",IF(HD13<10,0,IF(HD13>10,(HD13-(HE13+HF13)),0)),0) -> 0 | HH13: =IF(HB13="DOM",HD13,0) -> 0 | HI13: 7 | HJ13: 18 | HK13: NOR | HL13: =SUM(HJ13-HI13) -> 11 | HM13: =IF(HL13>1,HL13-1,0) -> 10 | HN13: =IF(D13="STAFF",IF(HK13="NOR",IF(HM13>8.5,8.5,HM13),0),IF(HK13="NOR",IF(HM13>8,8,HM13),IF(HL13="CAMPO",IF(HK13="NOR",IF(HM13>8,8,HM13),0),IF(HK13="NOR",IF(HM13>8,8,HM13),0)))) -> 8 | HO13: =IF(HK13="NOR",IF(HM13>10,2,IF(HM13>8,(HM13-HN13),0)),0) -> 2 | HP13: =IF(HK13="NOR",IF(HM13<10,0,IF(HM13>10,(HM13-(HN13+HO13)),0)),0) -> 0 | HQ13: =IF(HK13="DOM",HM13,0) -> 0 | HR13: 7 | HS13: 18 | HT13: NOR | HU13: =SUM(HS13-HR13) -> 11 | HV13: =IF(HU13>1,HU13-1,0) -> 10 | HW13: =IF(D13="STAFF",IF(HT13="NOR",IF(HV13>8.5,8.5,HV13),0),IF(HT13="NOR",IF(HV13>8,8,HV13),IF(HU13="CAMPO",IF(HT13="NOR",IF(HV13>8,8,HV13),0),IF(HT13="NOR",IF(HV13>8,8,HV13),0)))) -> 8 | HX13: =IF(HT13="NOR",IF(HV13>10,2,IF(HV13>8,(HV13-HW13),0)),0) -> 2 | HY13: =IF(HT13="NOR",IF(HV13<10,0,IF(HV13>10,(HV13-(HW13+HX13)),0)),0) -> 0 | HZ13: =IF(HT13="DOM",HV13,0) -> 0 | IA13: 7 | IB13: 18 | IC13: NOR | ID13: =SUM(IB13-IA13) -> 11 | IE13: =IF(ID13>1,ID13-1,0) -> 10 | IF13: =IF(D13="STAFF",IF(IC13="NOR",IF(IE13>8.5,8.5,IE13),0),IF(IC13="NOR",IF(IE13>8,8,IE13),IF(ID13="CAMPO",IF(IC13="NOR",IF(IE13>8,8,IE13),0),IF(IC13="NOR",IF(IE13>8,8,IE13),0)))) -> 8 | IG13: =IF(IC13="NOR",IF(IE13>10,2,IF(IE13>8,(IE13-IF13),0)),0) -> 2 | IH13: =IF(IC13="NOR",IF(IE13<10,0,IF(IE13>10,(IE13-(IF13+IG13)),0)),0) -> 0 | II13: =IF(IC13="DOM",IE13,0) -> 0 | IJ13: 7 | IK13: 18 | IL13: NOR | IM13: =SUM(IK13-IJ13) -> 11 | IN13: =IF(IM13>1,IM13-1,0) -> 10 | IO13: =IF(D13="STAFF",IF(IL13="NOR",IF(IN13>8.5,8.5,IN13),0),IF(IL13="NOR",IF(IN13>8,8,IN13),IF(IM13="CAMPO",IF(IL13="NOR",IF(IN13>8,8,IN13),0),IF(IL13="NOR",IF(IN13>8,8,IN13),0)))) -> 8 | IP13: =IF(IL13="NOR",IF(IN13>10,2,IF(IN13>8,(IN13-IO13),0)),0) -> 2 | IQ13: =IF(IL13="NOR",IF(IN13<10,0,IF(IN13>10,(IN13-(IO13+IP13)),0)),0) -> 0 | IR13: =IF(IL13="DOM",IN13,0) -> 0 | IS13: 7 | IT13: 18 | IU13: NOR | IV13: =SUM(IT13-IS13) -> 11 | IW13: =IF(IV13>1,IV13-1,0) -> 10 | IX13: =IF(D13="STAFF",IF(IU13="NOR",IF(IW13>8.5,8.5,IW13),0),IF(IU13="NOR",IF(IW13>8,8,IW13),IF(IV13="CAMPO",IF(IU13="NOR",IF(IW13>8,8,IW13),0),IF(IU13="NOR",IF(IW13>8,8,IW13),0)))) -> 8 | IY13: =IF(IU13="NOR",IF(IW13>10,2,IF(IW13>8,(IW13-IX13),0)),0) -> 2 | IZ13: =IF(IU13="NOR",IF(IW13<10,0,IF(IW13>10,(IW13-(IX13+IY13)),0)),0) -> 0 | JA13: =IF(IU13="DOM",IW13,0) -> 0 | JB13: 7 | JC13: 18 | JD13: NOR | JE13: =SUM(JC13-JB13) -> 11 | JF13: =IF(JE13>1,JE13-1,0) -> 10 | JG13: =IF(D13="STAFF",IF(JD13="NOR",IF(JF13>8.5,8.5,JF13),0),IF(JD13="NOR",IF(JF13>8,8,JF13),IF(JE13="CAMPO",IF(JD13="NOR",IF(JF13>8,8,JF13),0),IF(JD13="NOR",IF(JF13>8,8,JF13),0)))) -> 8 | JH13: =IF(JD13="NOR",IF(JF13>10,2,IF(JF13>8,(JF13-JG13),0)),0) -> 2 | JI13: =IF(JD13="NOR",IF(JF13<10,0,IF(JF13>10,(JF13-(JG13+JH13)),0)),0) -> 0 | JJ13: =IF(JD13="DOM",JF13,0) -> 0 | JK13: 0 | JL13: 0 | JM13: DS | JN13: =SUM(JL13-JK13) -> 0 | JO13: =IF(JN13>1,JN13-1,0) -> 0 | JP13: =IF(D13="STAFF",IF(JM13="NOR",IF(JO13>8.5,8.5,JO13),0),IF(JM13="NOR",IF(JO13>8,8,JO13),IF(JN13="CAMPO",IF(JM13="NOR",IF(JO13>8,8,JO13),0),IF(JM13="NOR",IF(JO13>8,8,JO13),0)))) -> 0 | JQ13: =IF(JM13="NOR",IF(JO13>10,2,IF(JO13>8,(JO13-JP13),0)),0) -> 0 | JR13: =IF(JM13="NOR",IF(JO13<10,0,IF(JO13>10,(JO13-(JP13+JQ13)),0)),0) -> 0 | JS13: =IF(JM13="DOM",JO13,0) -> 0 | JT13: 7 | JU13: 18 | JV13: NOR | JW13: =SUM(JU13-JT13) -> 11 | JX13: =IF(JW13>1,JW13-1,0) -> 10 | JY13: =IF(D13="STAFF",IF(JV13="NOR",IF(JX13>8.5,8.5,JX13),0),IF(JV13="NOR",IF(JX13>8,8,JX13),IF(JW13="CAMPO",IF(JV13="NOR",IF(JX13>8,8,JX13),0),IF(JV13="NOR",IF(JX13>8,8,JX13),0)))) -> 8 | JZ13: =IF(JV13="NOR",IF(JX13>10,2,IF(JX13>8,(JX13-JY13),0)),0) -> 2 | KA13: =IF(JV13="NOR",IF(JX13<10,0,IF(JX13>10,(JX13-(JY13+JZ13)),0)),0) -> 0 | KB13: =IF(JV13="DOM",JX13,0) -> 0 | KC13: 7 | KD13: 16 | KE13: NOR | KF13: =SUM(KD13-KC13) -> 9 | KG13: =IF(KF13>1,KF13-1,0) -> 8 | KH13: =IF(D13="STAFF",IF(KE13="NOR",IF(KG13>8.5,8.5,KG13),0),IF(KE13="NOR",IF(KG13>8,8,KG13),IF(KF13="CAMPO",IF(KE13="NOR",IF(KG13>8,8,KG13),0),IF(KE13="NOR",IF(KG13>8,8,KG13),0)))) -> 8 | KI13: =IF(KE13="NOR",IF(KG13>10,2,IF(KG13>8,(KG13-KH13),0)),0) -> 0 | KJ13: =IF(KE13="NOR",IF(KG13<10,0,IF(KG13>10,(KG13-(KH13+KI13)),0)),0) -> 0 | KK13: =IF(KE13="DOM",KG13,0) -> 0 | KL13: 7 | KM13: 16 | KN13: NOR | KO13: =SUM(KM13-KL13) -> 9 | KP13: =IF(KO13>1,KO13-1,0) -> 8 | KQ13: =IF(D13="STAFF",IF(KN13="NOR",IF(KP13>8.5,8.5,KP13),0),IF(KN13="NOR",IF(KP13>8,8,KP13),IF(KO13="CAMPO",IF(KN13="NOR",IF(KP13>8,8,KP13),0),IF(KN13="NOR",IF(KP13>8,8,KP13),0)))) -> 8 | KR13: =IF(KN13="NOR",IF(KP13>10,2,IF(KP13>8,(KP13-KQ13),0)),0) -> 0 | KS13: =IF(KN13="NOR",IF(KP13<10,0,IF(KP13>10,(KP13-(KQ13+KR13)),0)),0) -> 0 | KT13: =IF(KN13="DOM",KP13,0) -> 0 | KU13: 7 | KV13: 16 | KW13: NOR | KX13: =SUM(KV13-KU13) -> 9 | KY13: =IF(KX13>1,KX13-1,0) -> 8 | KZ13: =IF(D13="STAFF",IF(KW13="NOR",IF(KY13>8.5,8.5,KY13),0),IF(KW13="NOR",IF(KY13>8,8,KY13),IF(KX13="CAMPO",IF(KW13="NOR",IF(KY13>8,8,KY13),0),IF(KW13="NOR",IF(KY13>8,8,KY13),0)))) -> 8 | LA13: =IF(KW13="NOR",IF(KY13>10,2,IF(KY13>8,(KY13-KZ13),0)),0) -> 0 | LB13: =IF(KW13="NOR",IF(KY13<10,0,IF(KY13>10,(KY13-(KZ13+LA13)),0)),0) -> 0 | LC13: =IF(KW13="DOM",KY13,0) -> 0 | LD13: 7 | LE13: 16 | LF13: NOR | LG13: =SUM(LE13-LD13) -> 9 | LH13: =IF(LG13>1,LG13-1,0) -> 8 | LI13: =IF(D13="STAFF",IF(LF13="NOR",IF(LH13>8.5,8.5,LH13),0),IF(LF13="NOR",IF(LH13>8,8,LH13),IF(LG13="CAMPO",IF(LF13="NOR",IF(LH13>8,8,LH13),0),IF(LF13="NOR",IF(LH13>8,8,LH13),0)))) -> 8 | LJ13: =IF(LF13="NOR",IF(LH13>10,2,IF(LH13>8,(LH13-LI13),0)),0) -> 0 | LK13: =IF(LF13="NOR",IF(LH13<10,0,IF(LH13>10,(LH13-(LI13+LJ13)),0)),0) -> 0 | LL13: =IF(LF13="DOM",LH13,0) -> 0 | LM13: 7 | LN13: 16 | LO13: NOR | LP13: =SUM(LN13-LM13) -> 9 | LQ13: =IF(LP13>1,LP13-1,0) -> 8 | LR13: =IF(D13="STAFF",IF(LO13="NOR",IF(LQ13>8.5,8.5,LQ13),0),IF(LO13="NOR",IF(LQ13>8,8,LQ13),IF(LP13="CAMPO",IF(LO13="NOR",IF(LQ13>8,8,LQ13),0),IF(LO13="NOR",IF(LQ13>8,8,LQ13),0)))) -> 8 | LS13: =IF(LO13="NOR",IF(LQ13>10,2,IF(LQ13>8,(LQ13-LR13),0)),0) -> 0 | LT13: =IF(LO13="NOR",IF(LQ13<10,0,IF(LQ13>10,(LQ13-(LR13+LS13)),0)),0) -> 0 | LU13: =IF(LO13="DOM",LQ13,0) -> 0 | LV13: 7 | LW13: 16 | LX13: NOR | LY13: =SUM(LW13-LV13) -> 9 | LZ13: =IF(LY13>1,LY13-1,0) -> 8 | MA13: =IF(D13="STAFF",IF(LX13="NOR",IF(LZ13>8.5,8.5,LZ13),0),IF(LX13="NOR",IF(LZ13>8,8,LZ13),IF(LY13="CAMPO",IF(LX13="NOR",IF(LZ13>8,8,LZ13),0),IF(LX13="NOR",IF(LZ13>8,8,LZ13),0)))) -> 8 | MB13: =IF(LX13="NOR",IF(LZ13>10,2,IF(LZ13>8,(LZ13-MA13),0)),0) -> 0 | MC13: =IF(LX13="NOR",IF(LZ13<10,0,IF(LZ13>10,(LZ13-(MA13+MB13)),0)),0) -> 0 | MD13: =IF(LX13="DOM",LZ13,0) -> 0 | ME13: 7 | MF13: 16 | MG13: NOR | MH13: =SUM(MF13-ME13) -> 9 | MI13: =IF(MH13>1,MH13-1,0) -> 8 | MJ13: =IF(D13="STAFF",IF(MG13="NOR",IF(MI13>8.5,8.5,MI13),0),IF(MG13="NOR",IF(MI13>8,8,MI13),IF(MH13="CAMPO",IF(MG13="NOR",IF(MI13>8,8,MI13),0),IF(MG13="NOR",IF(MI13>8,8,MI13),0)))) -> 8 | MK13: =IF(MG13="NOR",IF(MI13>10,2,IF(MI13>8,(MI13-MJ13),0)),0) -> 0 | ML13: =IF(MG13="NOR",IF(MI13<10,0,IF(MI13>10,(MI13-(MJ13+MK13)),0)),0) -> 0 | MM13: =IF(MG13="DOM",MI13,0) -> 0 | MN13: 7 | MO13: 16 | MP13: NOR | MQ13: =SUM(MO13-MN13) -> 9 | MR13: =IF(MQ13>1,MQ13-1,0) -> 8 | MS13: =IF(D13="STAFF",IF(MP13="NOR",IF(MR13>8.5,8.5,MR13),0),IF(MP13="NOR",IF(MR13>8,8,MR13),IF(MQ13="CAMPO",IF(MP13="NOR",IF(MR13>8,8,MR13),0),IF(MP13="NOR",IF(MR13>8,8,MR13),0)))) -> 8 | MT13: =IF(MP13="NOR",IF(MR13>10,2,IF(MR13>8,(MR13-MS13),0)),0) -> 0 | MU13: =IF(MP13="NOR",IF(MR13<10,0,IF(MR13>10,(MR13-(MS13+MT13)),0)),0) -> 0 | MV13: =IF(MP13="DOM",MR13,0) -> 0 | MW13: 7 | MX13: 16 | MY13: NOR | MZ13: =SUM(MX13-MW13) -> 9 | NA13: =IF(MZ13>1,MZ13-1,0) -> 8 | NB13: =IF(D13="STAFF",IF(MY13="NOR",IF(NA13>8.5,8.5,NA13),0),IF(MY13="NOR",IF(NA13>8,8,NA13),IF(MZ13="CAMPO",IF(MY13="NOR",IF(NA13>8,8,NA13),0),IF(MY13="NOR",IF(NA13>8,8,NA13),0)))) -> 8 | NC13: =IF(MY13="NOR",IF(NA13>10,2,IF(NA13>8,(NA13-NB13),0)),0) -> 0 | ND13: =IF(MY13="NOR",IF(NA13<10,0,IF(NA13>10,(NA13-(NB13+NC13)),0)),0) -> 0 | NE13: =IF(MY13="DOM",NA13,0) -> 0 | NF13: 7 | NG13: 16 | NH13: NOR | NI13: =SUM(NG13-NF13) -> 9 | NJ13: =IF(NI13>1,NI13-1,0) -> 8 | NK13: =IF(D13="STAFF",IF(NH13="NOR",IF(NJ13>8.5,8.5,NJ13),0),IF(NH13="NOR",IF(NJ13>8,8,NJ13),IF(NI13="CAMPO",IF(NH13="NOR",IF(NJ13>8,8,NJ13),0),IF(NH13="NOR",IF(NJ13>8,8,NJ13),0)))) -> 8 | NL13: =IF(NH13="NOR",IF(NJ13>10,2,IF(NJ13>8,(NJ13-NK13),0)),0) -> 0 | NM13: =IF(NH13="NOR",IF(NJ13<10,0,IF(NJ13>10,(NJ13-(NK13+NL13)),0)),0) -> 0 | NN13: =IF(NH13="DOM",NJ13,0) -> 0 | NO13: 7 | NP13: 16 | NQ13: NOR | NR13: =SUM(NP13-NO13) -> 9 | NS13: =IF(NR13>1,NR13-1,0) -> 8 | NT13: =IF(D13="STAFF",IF(NQ13="NOR",IF(NS13>8.5,8.5,NS13),0),IF(NQ13="NOR",IF(NS13>8,8,NS13),IF(NR13="CAMPO",IF(NQ13="NOR",IF(NS13>8,8,NS13),0),IF(NQ13="NOR",IF(NS13>8,8,NS13),0)))) -> 8 | NU13: =IF(NQ13="NOR",IF(NS13>10,2,IF(NS13>8,(NS13-NT13),0)),0) -> 0 | NV13: =IF(NQ13="NOR",IF(NS13<10,0,IF(NS13>10,(NS13-(NT13+NU13)),0)),0) -> 0 | NW13: =IF(NQ13="DOM",NS13,0) -> 0 | NX13: 7 | NY13: 16 | NZ13: NOR | OA13: =SUM(NY13-NX13) -> 9 | OB13: =IF(OA13>1,OA13-1,0) -> 8 | OC13: =IF(D13="STAFF",IF(NZ13="NOR",IF(OB13>8.5,8.5,OB13),0),IF(NZ13="NOR",IF(OB13>8,8,OB13),IF(OA13="CAMPO",IF(NZ13="NOR",IF(OB13>8,8,OB13),0),IF(NZ13="NOR",IF(OB13>8,8,OB13),0)))) -> 8 | OD13: =IF(NZ13="NOR",IF(OB13>10,2,IF(OB13>8,(OB13-OC13),0)),0) -> 0 | OE13: =IF(NZ13="NOR",IF(OB13<10,0,IF(OB13>10,(OB13-(OC13+OD13)),0)),0) -> 0 | OF13: =IF(NZ13="DOM",OB13,0) -> 0 | OG13: 0 | OH13: 0 | OI13: DS | OJ13: =SUM(OH13-OG13) -> 0 | OK13: =IF(OJ13>1,OJ13-1,0) -> 0 | OL13: =IF(D13="STAFF",IF(OI13="NOR",IF(OK13>8.5,8.5,OK13),0),IF(OI13="NOR",IF(OK13>8,8,OK13),IF(OJ13="CAMPO",IF(OI13="NOR",IF(OK13>8,8,OK13),0),IF(OI13="NOR",IF(OK13>8,8,OK13),0)))) -> 0 | OM13: =IF(OI13="NOR",IF(OK13>10,2,IF(OK13>8,(OK13-OL13),0)),0) -> 0 | ON13: =IF(OI13="NOR",IF(OK13<10,0,IF(OK13>10,(OK13-(OL13+OM13)),0)),0) -> 0 | OO13: =IF(OI13="DOM",OK13,0) -> 0 | OP13: 7 | OQ13: 16 | OR13: NOR | OS13: =SUM(OQ13-OP13) -> 9 | OT13: =IF(OS13>1,OS13-1,0) -> 8 | OU13: =IF(D13="STAFF",IF(OR13="NOR",IF(OT13>8.5,8.5,OT13),0),IF(OR13="NOR",IF(OT13>8,8,OT13),IF(OS13="CAMPO",IF(OR13="NOR",IF(OT13>8,8,OT13),0),IF(OR13="NOR",IF(OT13>8,8,OT13),0)))) -> 8 | OV13: =IF(OR13="NOR",IF(OT13>10,2,IF(OT13>8,(OT13-OU13),0)),0) -> 0 | OW13: =IF(OR13="NOR",IF(OT13<10,0,IF(OT13>10,(OT13-(OU13+OV13)),0)),0) -> 0 | OX13: =IF(OR13="DOM",OT13,0) -> 0 | OY13: 0 | OZ13: 0 | PA13: FE | PB13: =SUM(OZ13-OY13) -> 0 | PC13: =IF(PB13>1,PB13-1,0) -> 0 | PD13: =IF(D13="STAFF",IF(PA13="NOR",IF(PC13>8.5,8.5,PC13),0),IF(PA13="NOR",IF(PC13>8,8,PC13),IF(PB13="CAMPO",IF(PA13="NOR",IF(PC13>8,8,PC13),0),IF(PA13="NOR",IF(PC13>8,8,PC13),0)))) -> 0 | PE13: =IF(PA13="NOR",IF(PC13>10,2,IF(PC13>8,(PC13-PD13),0)),0) -> 0 | PF13: =IF(PA13="NOR",IF(PC13<10,0,IF(PC13>10,(PC13-(PD13+PE13)),0)),0) -> 0 | PG13: =IF(PA13="DOM",PC13,0) -> 0 | PH13: 7 | PI13: 16 | PJ13: NOR | PK13: =SUM(PI13-PH13) -> 9 | PL13: =IF(PK13>1,PK13-1,0) -> 8 | PM13: =IF(M13="STAFF",IF(PJ13="NOR",IF(PL13>8.5,8.5,PL13),0),IF(PJ13="NOR",IF(PL13>8,8,PL13),IF(PK13="CAMPO",IF(PJ13="NOR",IF(PL13>8,8,PL13),0),IF(PJ13="NOR",IF(PL13>8,8,PL13),0)))) -> 8 | PN13: =IF(PJ13="NOR",IF(PL13>10,2,IF(PL13>8,(PL13-PM13),0)),0) -> 0 | PO13: =IF(PJ13="NOR",IF(PL13<10,0,IF(PL13>10,(PL13-(PM13+PN13)),0)),0) -> 0 | PP13: =IF(PJ13="DOM",PL13,0) -> 0 | PR13: =COUNTIF(FG13:PP13,"NOR") -> 25 | PS13: =COUNTIF(FG13:PP13,"DS") -> 3 | PT13: =COUNTIF(FG13:PP13,"FE") -> 1 | PU13: =SUM(PR13:PT13) -> 29 | PV13: =COUNTIF(FG13:PP13,"DM") -> 0 | PY13: =COUNTIF(FG13:PP13,"SUB") -> 0 | QB13: =COUNTIF(FG13:PP13,"VA") -> 0 | QE13: =COUNTIF(FG13:PP13,"LSG") -> 0 | QH13: =COUNTIF(FG13:PP13,"LCG") -> 0 | QK13: =COUNTIF(FG13:PP13,"FA") -> 1 | QL13: 44348 | QM13: 44348 | QN13: =COUNTIF(J13:FF13,"FA") -> 0 | QQ13: =PU13+PV13+PY13+QB13+QE13+QH13+QK13+QN13 -> 30 | QS13: =P13+Y13++AH13+AQ13+AZ13+BI13+BR13+CA13+CJ13+CS13+DB13+DK13+DT13+EC13+EL13+EU13+FD13+FM13+FV13+GE13+GN13+GW13+HF13+HO13+HX13+IG13+IP13+IY13+JH13+JQ13+JZ13 -> 50 | QT13: =Q13+Z13++AI13+AR13+BA13+BJ13+BS13+CB13+CK13+CT13+DC13+DL13+DU13+ED13+EM13+EV13+FE13+FN13+FW13+GF13+GO13+GX13+HG13+HP13+HY13+IH13+IQ13+IZ13+JI13+JR13+KA13 -> 0 | RG13: 12
A14: =A13+1 -> 5 | B14: 43998041 | D14: PROYECTO | E14: CUEVA MARTINEZ YAHAIRA ROSENDA | F14: VIGÍA | G14: 44319 | H14: 44328 | J14: 0 | K14: 0 | L14: FA | M14: =SUM(K14-J14) -> 0 | N14: =IF(M14>1,M14-1,0) -> 0 | O14: =IF(D14="STAFF",IF(L14="NOR",IF(N14>8.5,8.5,N14),0),IF(L14="NOR",IF(N14>8,8,N14),IF(D14="CAMPO",IF(L14="NOR",IF(N14>8,8,N14),0),IF(L14="NOR",IF(N14>8,8,N14),0)))) -> 0 | P14: =IF(L14="NOR",IF(N14>10,2,IF(N14>8,(N14-O14),0)),0) -> 0 | Q14: =IF(L14="NOR",IF(N14<10,0,IF(N14>10,(N14-(O14+P14)),0)),0) -> 0 | R14: =IF(L14="DOM",N14,0) -> 0 | S14: 0 | T14: 0 | U14: DS | V14: =SUM(T14-S14) -> 0 | W14: =IF(V14>1,V14-1,0) -> 0 | X14: =IF(D14="STAFF",IF(U14="NOR",IF(W14>8.5,8.5,W14),0),IF(U14="NOR",IF(W14>8,8,W14),IF(M14="CAMPO",IF(U14="NOR",IF(W14>8,8,W14),0),IF(U14="NOR",IF(W14>8,8,W14),0)))) -> 0 | Y14: =IF(U14="NOR",IF(W14>10,2,IF(W14>8,(W14-X14),0)),0) -> 0 | Z14: =IF(U14="NOR",IF(W14<10,0,IF(W14>10,(W14-(X14+Y14)),0)),0) -> 0 | AA14: =IF(U14="DOM",W14,0) -> 0 | AB14: 7 | AC14: 18 | AD14: NOR | AE14: =SUM(AC14-AB14) -> 11 | AF14: =IF(AE14>1,AE14-1,0) -> 10 | AG14: =IF(D14="STAFF",IF(AD14="NOR",IF(AF14>8.5,8.5,AF14),0),IF(AD14="NOR",IF(AF14>8,8,AF14),IF(AE14="CAMPO",IF(AD14="NOR",IF(AF14>8,8,AF14),0),IF(AD14="NOR",IF(AF14>8,8,AF14),0)))) -> 8 | AH14: =IF(AD14="NOR",IF(AF14>10,2,IF(AF14>8,(AF14-AG14),0)),0) -> 2 | AI14: =IF(AD14="NOR",IF(AF14<10,0,IF(AF14>10,(AF14-(AG14+AH14)),0)),0) -> 0 | AJ14: =IF(AD14="DOM",AF14,0) -> 0 | AK14: 7 | AL14: 18 | AM14: NOR | AN14: =SUM(AL14-AK14) -> 11 | AO14: =IF(AN14>1,AN14-1,0) -> 10 | AP14: =IF(D14="PROYECTO",IF(AM14="NOR",IF(AO14>8,8,AO14),0),IF(AM14="NOR",IF(AO14>8,8,AO14),0)) -> 8 | AQ14: =IF(AM14="NOR",IF(AO14>10,2,IF(AO14>8,(AO14-AP14),0)),0) -> 2 | AR14: =IF(AM14="NOR",IF(AO14<10,0,IF(AO14>10,(AO14-(AP14+AQ14)),0)),0) -> 0 | AS14: =IF(AM14="DOM",AO14,0) -> 0 | AT14: 7 | AU14: 18 | AV14: NOR | AW14: =SUM(AU14-AT14) -> 11 | AX14: =IF(AW14>1,AW14-1,0) -> 10 | AY14: =IF(AO14="PROYECTO",IF(AV14="NOR",IF(AX14>8,8,AX14),0),IF(AV14="NOR",IF(AX14>8,8,AX14),0)) -> 8 | AZ14: =IF(AV14="NOR",IF(AX14>10,2,IF(AX14>8,(AX14-AY14),0)),0) -> 2 | BA14: =IF(AV14="NOR",IF(AX14<10,0,IF(AX14>10,(AX14-(AY14+AZ14)),0)),0) -> 0 | BB14: =IF(AV14="DOM",AX14,0) -> 0 | BC14: 7 | BD14: 18 | BE14: NOR | BF14: =SUM(BD14-BC14) -> 11 | BG14: =IF(BF14>1,BF14-1,0) -> 10 | BH14: =IF(D14="STAFF",IF(BE14="NOR",IF(BG14>8.5,8.5,BG14),0),IF(BE14="NOR",IF(BG14>8,8,BG14),IF(BF14="CAMPO",IF(BE14="NOR",IF(BG14>8,8,BG14),0),IF(BE14="NOR",IF(BG14>8,8,BG14),0)))) -> 8 | BI14: =IF(BE14="NOR",IF(BG14>10,2,IF(BG14>8,(BG14-BH14),0)),0) -> 2 | BJ14: =IF(BE14="NOR",IF(BG14<10,0,IF(BG14>10,(BG14-(BH14+BI14)),0)),0) -> 0 | BK14: =IF(BE14="DOM",BG14,0) -> 0 | BL14: 7 | BM14: 18 | BN14: NOR | BO14: =SUM(BM14-BL14) -> 11 | BP14: =IF(BO14>1,BO14-1,0) -> 10 | BQ14: =IF(D14="STAFF",IF(BN14="NOR",IF(BP14>8.5,8.5,BP14),0),IF(BN14="NOR",IF(BP14>8,8,BP14),IF(BO14="CAMPO",IF(BN14="NOR",IF(BP14>8,8,BP14),0),IF(BN14="NOR",IF(BP14>8,8,BP14),0)))) -> 8 | BR14: =IF(BN14="NOR",IF(BP14>10,2,IF(BP14>8,(BP14-BQ14),0)),0) -> 2 | BS14: =IF(BN14="NOR",IF(BP14<10,0,IF(BP14>10,(BP14-(BQ14+BR14)),0)),0) -> 0 | BT14: =IF(BN14="DOM",BP14,0) -> 0 | BU14: 7 | BV14: 18 | BW14: NOR | BX14: =SUM(BV14-BU14) -> 11 | BY14: =IF(BX14>1,BX14-1,0) -> 10 | BZ14: =IF(D14="STAFF",IF(BW14="NOR",IF(BY14>8.5,8.5,BY14),0),IF(BW14="NOR",IF(BY14>8,8,BY14),IF(BX14="CAMPO",IF(BW14="NOR",IF(BY14>8,8,BY14),0),IF(BW14="NOR",IF(BY14>8,8,BY14),0)))) -> 8 | CA14: =IF(BW14="NOR",IF(BY14>10,2,IF(BY14>8,(BY14-BZ14),0)),0) -> 2 | CB14: =IF(BW14="NOR",IF(BY14<10,0,IF(BY14>10,(BY14-(BZ14+CA14)),0)),0) -> 0 | CC14: =IF(BW14="DOM",BY14,0) -> 0 | CD14: 0 | CE14: 0 | CF14: DS | CG14: =SUM(CE14-CD14) -> 0 | CH14: =IF(CG14>1,CG14-1,0) -> 0 | CI14: =IF(D14="STAFF",IF(CF14="NOR",IF(CH14>8.5,8.5,CH14),0),IF(CF14="NOR",IF(CH14>8,8,CH14),IF(CG14="CAMPO",IF(CF14="NOR",IF(CH14>8,8,CH14),0),IF(CF14="NOR",IF(CH14>8,8,CH14),0)))) -> 0 | CJ14: =IF(CF14="NOR",IF(CH14>10,2,IF(CH14>8,(CH14-CI14),0)),0) -> 0 | CK14: =IF(CF14="NOR",IF(CH14<10,0,IF(CH14>10,(CH14-(CI14+CJ14)),0)),0) -> 0 | CL14: =IF(CF14="DOM",CH14,0) -> 0 | CM14: 7 | CN14: 18 | CO14: NOR | CP14: =SUM(CN14-CM14) -> 11 | CQ14: =IF(CP14>1,CP14-1,0) -> 10 | CR14: =IF(D14="STAFF",IF(CO14="NOR",IF(CQ14>8.5,8.5,CQ14),0),IF(CO14="NOR",IF(CQ14>8,8,CQ14),IF(CP14="CAMPO",IF(CO14="NOR",IF(CQ14>8,8,CQ14),0),IF(CO14="NOR",IF(CQ14>8,8,CQ14),0)))) -> 8 | CS14: =IF(CO14="NOR",IF(CQ14>10,2,IF(CQ14>8,(CQ14-CR14),0)),0) -> 2 | CT14: =IF(CO14="NOR",IF(CQ14<10,0,IF(CQ14>10,(CQ14-(CR14+CS14)),0)),0) -> 0 | CU14: =IF(CO14="DOM",CQ14,0) -> 0 | CV14: 7 | CW14: 18 | CX14: NOR | CY14: =SUM(CW14-CV14) -> 11 | CZ14: =IF(CY14>1,CY14-1,0) -> 10 | DA14: =IF(CQ14="PROYECTO",IF(CX14="NOR",IF(CZ14>8,8,CZ14),0),IF(CX14="NOR",IF(CZ14>8,8,CZ14),0)) -> 8 | DB14: =IF(CX14="NOR",IF(CZ14>10,2,IF(CZ14>8,(CZ14-DA14),0)),0) -> 2 | DC14: =IF(CX14="NOR",IF(CZ14<10,0,IF(CZ14>10,(CZ14-(DA14+DB14)),0)),0) -> 0 | DD14: =IF(CX14="DOM",CZ14,0) -> 0 | DE14: 7 | DF14: 19 | DG14: NOR | DH14: =SUM(DF14-DE14) -> 12 | DI14: =IF(DH14>1,DH14-1,0) -> 11 | DJ14: =IF(CZ14="PROYECTO",IF(DG14="NOR",IF(DI14>8,8,DI14),0),IF(DG14="NOR",IF(DI14>8,8,DI14),0)) -> 8 | DK14: =IF(DG14="NOR",IF(DI14>10,2,IF(DI14>8,(DI14-DJ14),0)),0) -> 2 | DL14: =IF(DG14="NOR",IF(DI14<10,0,IF(DI14>10,(DI14-(DJ14+DK14)),0)),0) -> 1 | DM14: =IF(DG14="DOM",DI14,0) -> 0 | DN14: 7 | DO14: 18 | DP14: NOR | DQ14: =SUM(DO14-DN14) -> 11 | DR14: =IF(DQ14>1,DQ14-1,0) -> 10 | DS14: =IF(D14="STAFF",IF(DP14="NOR",IF(DR14>8.5,8.5,DR14),0),IF(DP14="NOR",IF(DR14>8,8,DR14),IF(DQ14="CAMPO",IF(DP14="NOR",IF(DR14>8,8,DR14),0),IF(DP14="NOR",IF(DR14>8,8,DR14),0)))) -> 8 | DT14: =IF(DP14="NOR",IF(DR14>10,2,IF(DR14>8,(DR14-DS14),0)),0) -> 2 | DU14: =IF(DP14="NOR",IF(DR14<10,0,IF(DR14>10,(DR14-(DS14+DT14)),0)),0) -> 0 | DV14: =IF(DP14="DOM",DR14,0) -> 0 | DW14: 7 | DX14: 18 | DY14: NOR | DZ14: =SUM(DX14-DW14) -> 11 | EA14: =IF(DZ14>1,DZ14-1,0) -> 10 | EB14: =IF(D14="STAFF",IF(DY14="NOR",IF(EA14>8.5,8.5,EA14),0),IF(DY14="NOR",IF(EA14>8,8,EA14),IF(DZ14="CAMPO",IF(DY14="NOR",IF(EA14>8,8,EA14),0),IF(DY14="NOR",IF(EA14>8,8,EA14),0)))) -> 8 | EC14: =IF(DY14="NOR",IF(EA14>10,2,IF(EA14>8,(EA14-EB14),0)),0) -> 2 | ED14: =IF(DY14="NOR",IF(EA14<10,0,IF(EA14>10,(EA14-(EB14+EC14)),0)),0) -> 0 | EE14: =IF(DY14="DOM",EA14,0) -> 0 | EF14: 7 | EG14: 18 | EH14: NOR | EI14: =SUM(EG14-EF14) -> 11 | EJ14: =IF(EI14>1,EI14-1,0) -> 10 | EK14: =IF(D14="STAFF",IF(EH14="NOR",IF(EJ14>8.5,8.5,EJ14),0),IF(EH14="NOR",IF(EJ14>8,8,EJ14),IF(EI14="CAMPO",IF(EH14="NOR",IF(EJ14>8,8,EJ14),0),IF(EH14="NOR",IF(EJ14>8,8,EJ14),0)))) -> 8 | EL14: =IF(EH14="NOR",IF(EJ14>10,2,IF(EJ14>8,(EJ14-EK14),0)),0) -> 2 | EM14: =IF(EH14="NOR",IF(EJ14<10,0,IF(EJ14>10,(EJ14-(EK14+EL14)),0)),0) -> 0 | EN14: =IF(EH14="DOM",EJ14,0) -> 0 | EO14: 0 | EP14: 0 | EQ14: DS | ER14: =SUM(EP14-EO14) -> 0 | ES14: =IF(ER14>1,ER14-1,0) -> 0 | ET14: =IF(D14="STAFF",IF(EQ14="NOR",IF(ES14>8.5,8.5,ES14),0),IF(EQ14="NOR",IF(ES14>8,8,ES14),IF(ER14="CAMPO",IF(EQ14="NOR",IF(ES14>8,8,ES14),0),IF(EQ14="NOR",IF(ES14>8,8,ES14),0)))) -> 0 | EU14: =IF(EQ14="NOR",IF(ES14>10,2,IF(ES14>8,(ES14-ET14),0)),0) -> 0 | EV14: =IF(EQ14="NOR",IF(ES14<10,0,IF(ES14>10,(ES14-(ET14+EU14)),0)),0) -> 0 | EW14: =IF(EQ14="DOM",ES14,0) -> 0 | EX14: 7 | EY14: 18 | EZ14: NOR | FA14: =SUM(EY14-EX14) -> 11 | FB14: =IF(FA14>1,FA14-1,0) -> 10 | FC14: =IF(D14="STAFF",IF(EZ14="NOR",IF(FB14>8.5,8.5,FB14),0),IF(EZ14="NOR",IF(FB14>8,8,FB14),IF(FA14="CAMPO",IF(EZ14="NOR",IF(FB14>8,8,FB14),0),IF(EZ14="NOR",IF(FB14>8,8,FB14),0)))) -> 8 | FD14: =IF(EZ14="NOR",IF(FB14>10,2,IF(FB14>8,(FB14-FC14),0)),0) -> 2 | FE14: =IF(EZ14="NOR",IF(FB14<10,0,IF(FB14>10,(FB14-(FC14+FD14)),0)),0) -> 0 | FF14: =IF(EZ14="DOM",FB14,0) -> 0 | FG14: 7 | FH14: 18 | FI14: NOR | FJ14: =SUM(FH14-FG14) -> 11 | FK14: =IF(FJ14>1,FJ14-1,0) -> 10 | FL14: =IF(D14="STAFF",IF(FI14="NOR",IF(FK14>8.5,8.5,FK14),0),IF(FI14="NOR",IF(FK14>8,8,FK14),IF(FJ14="CAMPO",IF(FI14="NOR",IF(FK14>8,8,FK14),0),IF(FI14="NOR",IF(FK14>8,8,FK14),0)))) -> 8 | FM14: =IF(FI14="NOR",IF(FK14>10,2,IF(FK14>8,(FK14-FL14),0)),0) -> 2 | FN14: =IF(FI14="NOR",IF(FK14<10,0,IF(FK14>10,(FK14-(FL14+FM14)),0)),0) -> 0 | FO14: =IF(FI14="DOM",FK14,0) -> 0 | FP14: 7 | FQ14: 18 | FR14: NOR | FS14: =SUM(FQ14-FP14) -> 11 | FT14: =IF(FS14>1,FS14-1,0) -> 10 | FU14: =IF(FK14="PROYECTO",IF(FR14="NOR",IF(FT14>8,8,FT14),0),IF(FR14="NOR",IF(FT14>8,8,FT14),0)) -> 8 | FV14: =IF(FR14="NOR",IF(FT14>10,2,IF(FT14>8,(FT14-FU14),0)),0) -> 2 | FW14: =IF(FR14="NOR",IF(FT14<10,0,IF(FT14>10,(FT14-(FU14+FV14)),0)),0) -> 0 | FX14: =IF(FR14="DOM",FT14,0) -> 0 | FY14: 7 | FZ14: 18 | GA14: NOR | GB14: =SUM(FZ14-FY14) -> 11 | GC14: =IF(GB14>1,GB14-1,0) -> 10 | GD14: =IF(D14="STAFF",IF(GA14="NOR",IF(GC14>8.5,8.5,GC14),0),IF(GA14="NOR",IF(GC14>8,8,GC14),IF(GB14="CAMPO",IF(GA14="NOR",IF(GC14>8,8,GC14),0),IF(GA14="NOR",IF(GC14>8,8,GC14),0)))) -> 8 | GE14: =IF(GA14="NOR",IF(GC14>10,2,IF(GC14>8,(GC14-GD14),0)),0) -> 2 | GF14: =IF(GA14="NOR",IF(GC14<10,0,IF(GC14>10,(GC14-(GD14+GE14)),0)),0) -> 0 | GG14: =IF(GA14="DOM",GC14,0) -> 0 | GH14: 7 | GI14: 18 | GJ14: NOR | GK14: =SUM(GI14-GH14) -> 11 | GL14: =IF(GK14>1,GK14-1,0) -> 10 | GM14: =IF(D14="STAFF",IF(GJ14="NOR",IF(GL14>8.5,8.5,GL14),0),IF(GJ14="NOR",IF(GL14>8,8,GL14),IF(GK14="CAMPO",IF(GJ14="NOR",IF(GL14>8,8,GL14),0),IF(GJ14="NOR",IF(GL14>8,8,GL14),0)))) -> 8 | GN14: =IF(GJ14="NOR",IF(GL14>10,2,IF(GL14>8,(GL14-GM14),0)),0) -> 2 | GO14: =IF(GJ14="NOR",IF(GL14<10,0,IF(GL14>10,(GL14-(GM14+GN14)),0)),0) -> 0 | GP14: =IF(GJ14="DOM",GL14,0) -> 0 | GQ14: 7 | GR14: 18 | GS14: NOR | GT14: =SUM(GR14-GQ14) -> 11 | GU14: =IF(GT14>1,GT14-1,0) -> 10 | GV14: =IF(D14="STAFF",IF(GS14="NOR",IF(GU14>8.5,8.5,GU14),0),IF(GS14="NOR",IF(GU14>8,8,GU14),IF(GT14="CAMPO",IF(GS14="NOR",IF(GU14>8,8,GU14),0),IF(GS14="NOR",IF(GU14>8,8,GU14),0)))) -> 8 | GW14: =IF(GS14="NOR",IF(GU14>10,2,IF(GU14>8,(GU14-GV14),0)),0) -> 2 | GX14: =IF(GS14="NOR",IF(GU14<10,0,IF(GU14>10,(GU14-(GV14+GW14)),0)),0) -> 0 | GY14: =IF(GS14="DOM",GU14,0) -> 0 | GZ14: 0 | HA14: 0 | HB14: DS | HC14: =SUM(HA14-GZ14) -> 0 | HD14: =IF(HC14>1,HC14-1,0) -> 0 | HE14: =IF(D14="STAFF",IF(HB14="NOR",IF(HD14>8.5,8.5,HD14),0),IF(HB14="NOR",IF(HD14>8,8,HD14),IF(HC14="CAMPO",IF(HB14="NOR",IF(HD14>8,8,HD14),0),IF(HB14="NOR",IF(HD14>8,8,HD14),0)))) -> 0 | HF14: =IF(HB14="NOR",IF(HD14>10,2,IF(HD14>8,(HD14-HE14),0)),0) -> 0 | HG14: =IF(HB14="NOR",IF(HD14<10,0,IF(HD14>10,(HD14-(HE14+HF14)),0)),0) -> 0 | HH14: =IF(HB14="DOM",HD14,0) -> 0 | HI14: 7 | HJ14: 18 | HK14: NOR | HL14: =SUM(HJ14-HI14) -> 11 | HM14: =IF(HL14>1,HL14-1,0) -> 10 | HN14: =IF(D14="STAFF",IF(HK14="NOR",IF(HM14>8.5,8.5,HM14),0),IF(HK14="NOR",IF(HM14>8,8,HM14),IF(HL14="CAMPO",IF(HK14="NOR",IF(HM14>8,8,HM14),0),IF(HK14="NOR",IF(HM14>8,8,HM14),0)))) -> 8 | HO14: =IF(HK14="NOR",IF(HM14>10,2,IF(HM14>8,(HM14-HN14),0)),0) -> 2 | HP14: =IF(HK14="NOR",IF(HM14<10,0,IF(HM14>10,(HM14-(HN14+HO14)),0)),0) -> 0 | HQ14: =IF(HK14="DOM",HM14,0) -> 0 | HR14: 7 | HS14: 18 | HT14: NOR | HU14: =SUM(HS14-HR14) -> 11 | HV14: =IF(HU14>1,HU14-1,0) -> 10 | HW14: =IF(D14="STAFF",IF(HT14="NOR",IF(HV14>8.5,8.5,HV14),0),IF(HT14="NOR",IF(HV14>8,8,HV14),IF(HU14="CAMPO",IF(HT14="NOR",IF(HV14>8,8,HV14),0),IF(HT14="NOR",IF(HV14>8,8,HV14),0)))) -> 8 | HX14: =IF(HT14="NOR",IF(HV14>10,2,IF(HV14>8,(HV14-HW14),0)),0) -> 2 | HY14: =IF(HT14="NOR",IF(HV14<10,0,IF(HV14>10,(HV14-(HW14+HX14)),0)),0) -> 0 | HZ14: =IF(HT14="DOM",HV14,0) -> 0 | IA14: 7 | IB14: 18 | IC14: NOR | ID14: =SUM(IB14-IA14) -> 11 | IE14: =IF(ID14>1,ID14-1,0) -> 10 | IF14: =IF(D14="STAFF",IF(IC14="NOR",IF(IE14>8.5,8.5,IE14),0),IF(IC14="NOR",IF(IE14>8,8,IE14),IF(ID14="CAMPO",IF(IC14="NOR",IF(IE14>8,8,IE14),0),IF(IC14="NOR",IF(IE14>8,8,IE14),0)))) -> 8 | IG14: =IF(IC14="NOR",IF(IE14>10,2,IF(IE14>8,(IE14-IF14),0)),0) -> 2 | IH14: =IF(IC14="NOR",IF(IE14<10,0,IF(IE14>10,(IE14-(IF14+IG14)),0)),0) -> 0 | II14: =IF(IC14="DOM",IE14,0) -> 0 | IJ14: 7 | IK14: 18 | IL14: NOR | IM14: =SUM(IK14-IJ14) -> 11 | IN14: =IF(IM14>1,IM14-1,0) -> 10 | IO14: =IF(D14="STAFF",IF(IL14="NOR",IF(IN14>8.5,8.5,IN14),0),IF(IL14="NOR",IF(IN14>8,8,IN14),IF(IM14="CAMPO",IF(IL14="NOR",IF(IN14>8,8,IN14),0),IF(IL14="NOR",IF(IN14>8,8,IN14),0)))) -> 8 | IP14: =IF(IL14="NOR",IF(IN14>10,2,IF(IN14>8,(IN14-IO14),0)),0) -> 2 | IQ14: =IF(IL14="NOR",IF(IN14<10,0,IF(IN14>10,(IN14-(IO14+IP14)),0)),0) -> 0 | IR14: =IF(IL14="DOM",IN14,0) -> 0 | IS14: 7 | IT14: 18 | IU14: NOR | IV14: =SUM(IT14-IS14) -> 11 | IW14: =IF(IV14>1,IV14-1,0) -> 10 | IX14: =IF(D14="STAFF",IF(IU14="NOR",IF(IW14>8.5,8.5,IW14),0),IF(IU14="NOR",IF(IW14>8,8,IW14),IF(IV14="CAMPO",IF(IU14="NOR",IF(IW14>8,8,IW14),0),IF(IU14="NOR",IF(IW14>8,8,IW14),0)))) -> 8 | IY14: =IF(IU14="NOR",IF(IW14>10,2,IF(IW14>8,(IW14-IX14),0)),0) -> 2 | IZ14: =IF(IU14="NOR",IF(IW14<10,0,IF(IW14>10,(IW14-(IX14+IY14)),0)),0) -> 0 | JA14: =IF(IU14="DOM",IW14,0) -> 0 | JB14: 7 | JC14: 18 | JD14: NOR | JE14: =SUM(JC14-JB14) -> 11 | JF14: =IF(JE14>1,JE14-1,0) -> 10 | JG14: =IF(D14="STAFF",IF(JD14="NOR",IF(JF14>8.5,8.5,JF14),0),IF(JD14="NOR",IF(JF14>8,8,JF14),IF(JE14="CAMPO",IF(JD14="NOR",IF(JF14>8,8,JF14),0),IF(JD14="NOR",IF(JF14>8,8,JF14),0)))) -> 8 | JH14: =IF(JD14="NOR",IF(JF14>10,2,IF(JF14>8,(JF14-JG14),0)),0) -> 2 | JI14: =IF(JD14="NOR",IF(JF14<10,0,IF(JF14>10,(JF14-(JG14+JH14)),0)),0) -> 0 | JJ14: =IF(JD14="DOM",JF14,0) -> 0 | JK14: 0 | JL14: 0 | JM14: DS | JN14: =SUM(JL14-JK14) -> 0 | JO14: =IF(JN14>1,JN14-1,0) -> 0 | JP14: =IF(D14="STAFF",IF(JM14="NOR",IF(JO14>8.5,8.5,JO14),0),IF(JM14="NOR",IF(JO14>8,8,JO14),IF(JN14="CAMPO",IF(JM14="NOR",IF(JO14>8,8,JO14),0),IF(JM14="NOR",IF(JO14>8,8,JO14),0)))) -> 0 | JQ14: =IF(JM14="NOR",IF(JO14>10,2,IF(JO14>8,(JO14-JP14),0)),0) -> 0 | JR14: =IF(JM14="NOR",IF(JO14<10,0,IF(JO14>10,(JO14-(JP14+JQ14)),0)),0) -> 0 | JS14: =IF(JM14="DOM",JO14,0) -> 0 | JT14: 7 | JU14: 18 | JV14: NOR | JW14: =SUM(JU14-JT14) -> 11 | JX14: =IF(JW14>1,JW14-1,0) -> 10 | JY14: =IF(D14="STAFF",IF(JV14="NOR",IF(JX14>8.5,8.5,JX14),0),IF(JV14="NOR",IF(JX14>8,8,JX14),IF(JW14="CAMPO",IF(JV14="NOR",IF(JX14>8,8,JX14),0),IF(JV14="NOR",IF(JX14>8,8,JX14),0)))) -> 8 | JZ14: =IF(JV14="NOR",IF(JX14>10,2,IF(JX14>8,(JX14-JY14),0)),0) -> 2 | KA14: =IF(JV14="NOR",IF(JX14<10,0,IF(JX14>10,(JX14-(JY14+JZ14)),0)),0) -> 0 | KB14: =IF(JV14="DOM",JX14,0) -> 0 | KC14: 7 | KD14: 16 | KE14: NOR | KF14: =SUM(KD14-KC14) -> 9 | KG14: =IF(KF14>1,KF14-1,0) -> 8 | KH14: =IF(D14="STAFF",IF(KE14="NOR",IF(KG14>8.5,8.5,KG14),0),IF(KE14="NOR",IF(KG14>8,8,KG14),IF(KF14="CAMPO",IF(KE14="NOR",IF(KG14>8,8,KG14),0),IF(KE14="NOR",IF(KG14>8,8,KG14),0)))) -> 8 | KI14: =IF(KE14="NOR",IF(KG14>10,2,IF(KG14>8,(KG14-KH14),0)),0) -> 0 | KJ14: =IF(KE14="NOR",IF(KG14<10,0,IF(KG14>10,(KG14-(KH14+KI14)),0)),0) -> 0 | KK14: =IF(KE14="DOM",KG14,0) -> 0 | KL14: 7 | KM14: 16 | KN14: NOR | KO14: =SUM(KM14-KL14) -> 9 | KP14: =IF(KO14>1,KO14-1,0) -> 8 | KQ14: =IF(D14="STAFF",IF(KN14="NOR",IF(KP14>8.5,8.5,KP14),0),IF(KN14="NOR",IF(KP14>8,8,KP14),IF(KO14="CAMPO",IF(KN14="NOR",IF(KP14>8,8,KP14),0),IF(KN14="NOR",IF(KP14>8,8,KP14),0)))) -> 8 | KR14: =IF(KN14="NOR",IF(KP14>10,2,IF(KP14>8,(KP14-KQ14),0)),0) -> 0 | KS14: =IF(KN14="NOR",IF(KP14<10,0,IF(KP14>10,(KP14-(KQ14+KR14)),0)),0) -> 0 | KT14: =IF(KN14="DOM",KP14,0) -> 0 | KU14: 7 | KV14: 16 | KW14: NOR | KX14: =SUM(KV14-KU14) -> 9 | KY14: =IF(KX14>1,KX14-1,0) -> 8 | KZ14: =IF(D14="STAFF",IF(KW14="NOR",IF(KY14>8.5,8.5,KY14),0),IF(KW14="NOR",IF(KY14>8,8,KY14),IF(KX14="CAMPO",IF(KW14="NOR",IF(KY14>8,8,KY14),0),IF(KW14="NOR",IF(KY14>8,8,KY14),0)))) -> 8 | LA14: =IF(KW14="NOR",IF(KY14>10,2,IF(KY14>8,(KY14-KZ14),0)),0) -> 0 | LB14: =IF(KW14="NOR",IF(KY14<10,0,IF(KY14>10,(KY14-(KZ14+LA14)),0)),0) -> 0 | LC14: =IF(KW14="DOM",KY14,0) -> 0 | LD14: 7 | LE14: 16 | LF14: NOR | LG14: =SUM(LE14-LD14) -> 9 | LH14: =IF(LG14>1,LG14-1,0) -> 8 | LI14: =IF(D14="STAFF",IF(LF14="NOR",IF(LH14>8.5,8.5,LH14),0),IF(LF14="NOR",IF(LH14>8,8,LH14),IF(LG14="CAMPO",IF(LF14="NOR",IF(LH14>8,8,LH14),0),IF(LF14="NOR",IF(LH14>8,8,LH14),0)))) -> 8 | LJ14: =IF(LF14="NOR",IF(LH14>10,2,IF(LH14>8,(LH14-LI14),0)),0) -> 0 | LK14: =IF(LF14="NOR",IF(LH14<10,0,IF(LH14>10,(LH14-(LI14+LJ14)),0)),0) -> 0 | LL14: =IF(LF14="DOM",LH14,0) -> 0 | LM14: 7 | LN14: 16 | LO14: NOR | LP14: =SUM(LN14-LM14) -> 9 | LQ14: =IF(LP14>1,LP14-1,0) -> 8 | LR14: =IF(D14="STAFF",IF(LO14="NOR",IF(LQ14>8.5,8.5,LQ14),0),IF(LO14="NOR",IF(LQ14>8,8,LQ14),IF(LP14="CAMPO",IF(LO14="NOR",IF(LQ14>8,8,LQ14),0),IF(LO14="NOR",IF(LQ14>8,8,LQ14),0)))) -> 8 | LS14: =IF(LO14="NOR",IF(LQ14>10,2,IF(LQ14>8,(LQ14-LR14),0)),0) -> 0 | LT14: =IF(LO14="NOR",IF(LQ14<10,0,IF(LQ14>10,(LQ14-(LR14+LS14)),0)),0) -> 0 | LU14: =IF(LO14="DOM",LQ14,0) -> 0 | LV14: 7 | LW14: 16 | LX14: NOR | LY14: =SUM(LW14-LV14) -> 9 | LZ14: =IF(LY14>1,LY14-1,0) -> 8 | MA14: =IF(D14="STAFF",IF(LX14="NOR",IF(LZ14>8.5,8.5,LZ14),0),IF(LX14="NOR",IF(LZ14>8,8,LZ14),IF(LY14="CAMPO",IF(LX14="NOR",IF(LZ14>8,8,LZ14),0),IF(LX14="NOR",IF(LZ14>8,8,LZ14),0)))) -> 8 | MB14: =IF(LX14="NOR",IF(LZ14>10,2,IF(LZ14>8,(LZ14-MA14),0)),0) -> 0 | MC14: =IF(LX14="NOR",IF(LZ14<10,0,IF(LZ14>10,(LZ14-(MA14+MB14)),0)),0) -> 0 | MD14: =IF(LX14="DOM",LZ14,0) -> 0 | ME14: 7 | MF14: 16 | MG14: NOR | MH14: =SUM(MF14-ME14) -> 9 | MI14: =IF(MH14>1,MH14-1,0) -> 8 | MJ14: =IF(D14="STAFF",IF(MG14="NOR",IF(MI14>8.5,8.5,MI14),0),IF(MG14="NOR",IF(MI14>8,8,MI14),IF(MH14="CAMPO",IF(MG14="NOR",IF(MI14>8,8,MI14),0),IF(MG14="NOR",IF(MI14>8,8,MI14),0)))) -> 8 | MK14: =IF(MG14="NOR",IF(MI14>10,2,IF(MI14>8,(MI14-MJ14),0)),0) -> 0 | ML14: =IF(MG14="NOR",IF(MI14<10,0,IF(MI14>10,(MI14-(MJ14+MK14)),0)),0) -> 0 | MM14: =IF(MG14="DOM",MI14,0) -> 0 | MN14: 7 | MO14: 16 | MP14: NOR | MQ14: =SUM(MO14-MN14) -> 9 | MR14: =IF(MQ14>1,MQ14-1,0) -> 8 | MS14: =IF(D14="STAFF",IF(MP14="NOR",IF(MR14>8.5,8.5,MR14),0),IF(MP14="NOR",IF(MR14>8,8,MR14),IF(MQ14="CAMPO",IF(MP14="NOR",IF(MR14>8,8,MR14),0),IF(MP14="NOR",IF(MR14>8,8,MR14),0)))) -> 8 | MT14: =IF(MP14="NOR",IF(MR14>10,2,IF(MR14>8,(MR14-MS14),0)),0) -> 0 | MU14: =IF(MP14="NOR",IF(MR14<10,0,IF(MR14>10,(MR14-(MS14+MT14)),0)),0) -> 0 | MV14: =IF(MP14="DOM",MR14,0) -> 0 | MW14: 7 | MX14: 16 | MY14: NOR | MZ14: =SUM(MX14-MW14) -> 9 | NA14: =IF(MZ14>1,MZ14-1,0) -> 8 | NB14: =IF(D14="STAFF",IF(MY14="NOR",IF(NA14>8.5,8.5,NA14),0),IF(MY14="NOR",IF(NA14>8,8,NA14),IF(MZ14="CAMPO",IF(MY14="NOR",IF(NA14>8,8,NA14),0),IF(MY14="NOR",IF(NA14>8,8,NA14),0)))) -> 8 | NC14: =IF(MY14="NOR",IF(NA14>10,2,IF(NA14>8,(NA14-NB14),0)),0) -> 0 | ND14: =IF(MY14="NOR",IF(NA14<10,0,IF(NA14>10,(NA14-(NB14+NC14)),0)),0) -> 0 | NE14: =IF(MY14="DOM",NA14,0) -> 0 | NF14: 7 | NG14: 16 | NH14: NOR | NI14: =SUM(NG14-NF14) -> 9 | NJ14: =IF(NI14>1,NI14-1,0) -> 8 | NK14: =IF(D14="STAFF",IF(NH14="NOR",IF(NJ14>8.5,8.5,NJ14),0),IF(NH14="NOR",IF(NJ14>8,8,NJ14),IF(NI14="CAMPO",IF(NH14="NOR",IF(NJ14>8,8,NJ14),0),IF(NH14="NOR",IF(NJ14>8,8,NJ14),0)))) -> 8 | NL14: =IF(NH14="NOR",IF(NJ14>10,2,IF(NJ14>8,(NJ14-NK14),0)),0) -> 0 | NM14: =IF(NH14="NOR",IF(NJ14<10,0,IF(NJ14>10,(NJ14-(NK14+NL14)),0)),0) -> 0 | NN14: =IF(NH14="DOM",NJ14,0) -> 0 | NO14: 7 | NP14: 16 | NQ14: NOR | NR14: =SUM(NP14-NO14) -> 9 | NS14: =IF(NR14>1,NR14-1,0) -> 8 | NT14: =IF(D14="STAFF",IF(NQ14="NOR",IF(NS14>8.5,8.5,NS14),0),IF(NQ14="NOR",IF(NS14>8,8,NS14),IF(NR14="CAMPO",IF(NQ14="NOR",IF(NS14>8,8,NS14),0),IF(NQ14="NOR",IF(NS14>8,8,NS14),0)))) -> 8 | NU14: =IF(NQ14="NOR",IF(NS14>10,2,IF(NS14>8,(NS14-NT14),0)),0) -> 0 | NV14: =IF(NQ14="NOR",IF(NS14<10,0,IF(NS14>10,(NS14-(NT14+NU14)),0)),0) -> 0 | NW14: =IF(NQ14="DOM",NS14,0) -> 0 | NX14: 7 | NY14: 16 | NZ14: NOR | OA14: =SUM(NY14-NX14) -> 9 | OB14: =IF(OA14>1,OA14-1,0) -> 8 | OC14: =IF(D14="STAFF",IF(NZ14="NOR",IF(OB14>8.5,8.5,OB14),0),IF(NZ14="NOR",IF(OB14>8,8,OB14),IF(OA14="CAMPO",IF(NZ14="NOR",IF(OB14>8,8,OB14),0),IF(NZ14="NOR",IF(OB14>8,8,OB14),0)))) -> 8 | OD14: =IF(NZ14="NOR",IF(OB14>10,2,IF(OB14>8,(OB14-OC14),0)),0) -> 0 | OE14: =IF(NZ14="NOR",IF(OB14<10,0,IF(OB14>10,(OB14-(OC14+OD14)),0)),0) -> 0 | OF14: =IF(NZ14="DOM",OB14,0) -> 0 | OG14: 0 | OH14: 0 | OI14: DS | OJ14: =SUM(OH14-OG14) -> 0 | OK14: =IF(OJ14>1,OJ14-1,0) -> 0 | OL14: =IF(D14="STAFF",IF(OI14="NOR",IF(OK14>8.5,8.5,OK14),0),IF(OI14="NOR",IF(OK14>8,8,OK14),IF(OJ14="CAMPO",IF(OI14="NOR",IF(OK14>8,8,OK14),0),IF(OI14="NOR",IF(OK14>8,8,OK14),0)))) -> 0 | OM14: =IF(OI14="NOR",IF(OK14>10,2,IF(OK14>8,(OK14-OL14),0)),0) -> 0 | ON14: =IF(OI14="NOR",IF(OK14<10,0,IF(OK14>10,(OK14-(OL14+OM14)),0)),0) -> 0 | OO14: =IF(OI14="DOM",OK14,0) -> 0 | OP14: 7 | OQ14: 16 | OR14: NOR | OS14: =SUM(OQ14-OP14) -> 9 | OT14: =IF(OS14>1,OS14-1,0) -> 8 | OU14: =IF(D14="STAFF",IF(OR14="NOR",IF(OT14>8.5,8.5,OT14),0),IF(OR14="NOR",IF(OT14>8,8,OT14),IF(OS14="CAMPO",IF(OR14="NOR",IF(OT14>8,8,OT14),0),IF(OR14="NOR",IF(OT14>8,8,OT14),0)))) -> 8 | OV14: =IF(OR14="NOR",IF(OT14>10,2,IF(OT14>8,(OT14-OU14),0)),0) -> 0 | OW14: =IF(OR14="NOR",IF(OT14<10,0,IF(OT14>10,(OT14-(OU14+OV14)),0)),0) -> 0 | OX14: =IF(OR14="DOM",OT14,0) -> 0 | OY14: 0 | OZ14: 0 | PA14: FE | PB14: =SUM(OZ14-OY14) -> 0 | PC14: =IF(PB14>1,PB14-1,0) -> 0 | PD14: =IF(D14="STAFF",IF(PA14="NOR",IF(PC14>8.5,8.5,PC14),0),IF(PA14="NOR",IF(PC14>8,8,PC14),IF(PB14="CAMPO",IF(PA14="NOR",IF(PC14>8,8,PC14),0),IF(PA14="NOR",IF(PC14>8,8,PC14),0)))) -> 0 | PE14: =IF(PA14="NOR",IF(PC14>10,2,IF(PC14>8,(PC14-PD14),0)),0) -> 0 | PF14: =IF(PA14="NOR",IF(PC14<10,0,IF(PC14>10,(PC14-(PD14+PE14)),0)),0) -> 0 | PG14: =IF(PA14="DOM",PC14,0) -> 0 | PH14: 7 | PI14: 16 | PJ14: NOR | PK14: =SUM(PI14-PH14) -> 9 | PL14: =IF(PK14>1,PK14-1,0) -> 8 | PM14: =IF(M14="STAFF",IF(PJ14="NOR",IF(PL14>8.5,8.5,PL14),0),IF(PJ14="NOR",IF(PL14>8,8,PL14),IF(PK14="CAMPO",IF(PJ14="NOR",IF(PL14>8,8,PL14),0),IF(PJ14="NOR",IF(PL14>8,8,PL14),0)))) -> 8 | PN14: =IF(PJ14="NOR",IF(PL14>10,2,IF(PL14>8,(PL14-PM14),0)),0) -> 0 | PO14: =IF(PJ14="NOR",IF(PL14<10,0,IF(PL14>10,(PL14-(PM14+PN14)),0)),0) -> 0 | PP14: =IF(PJ14="DOM",PL14,0) -> 0 | PR14: =COUNTIF(FG14:PP14,"NOR") -> 26 | PS14: =COUNTIF(FG14:PP14,"DS") -> 3 | PT14: =COUNTIF(FG14:PP14,"FE") -> 1 | PU14: =SUM(PR14:PT14) -> 30 | PV14: =COUNTIF(FG14:PP14,"DM") -> 0 | PY14: =COUNTIF(FG14:PP14,"SUB") -> 0 | QB14: =COUNTIF(FG14:PP14,"VA") -> 0 | QE14: =COUNTIF(FG14:PP14,"LSG") -> 0 | QH14: =COUNTIF(FG14:PP14,"LCG") -> 0 | QK14: =COUNTIF(FG14:PP14,"FA") -> 0 | QN14: =COUNTIF(J14:FF14,"FA") -> 1 | QQ14: =PU14+PV14+PY14+QB14+QE14+QH14+QK14+QN14 -> 31 | QS14: =P14+Y14++AH14+AQ14+AZ14+BI14+BR14+CA14+CJ14+CS14+DB14+DK14+DT14+EC14+EL14+EU14+FD14+FM14+FV14+GE14+GN14+GW14+HF14+HO14+HX14+IG14+IP14+IY14+JH14+JQ14+JZ14 -> 50 | QT14: =Q14+Z14++AI14+AR14+BA14+BJ14+BS14+CB14+CK14+CT14+DC14+DL14+DU14+ED14+EM14+EV14+FE14+FN14+FW14+GF14+GO14+GX14+HG14+HP14+HY14+IH14+IQ14+IZ14+JI14+JR14+KA14 -> 1 | RG14: 12
A15: =A14+1 -> 6 | B15: 42989188 | D15: PROYECTO | E15: FRANCIA PAJUELO BEATRIZ JACQUELIN | F15: VIGÍA | G15: 44242 | H15: 44243 | J15: 7 | K15: 18 | L15: NOR | M15: =SUM(K15-J15) -> 11 | N15: =IF(M15>1,M15-1,0) -> 10 | O15: =IF(D15="STAFF",IF(L15="NOR",IF(N15>8.5,8.5,N15),0),IF(L15="NOR",IF(N15>8,8,N15),IF(D15="CAMPO",IF(L15="NOR",IF(N15>8,8,N15),0),IF(L15="NOR",IF(N15>8,8,N15),0)))) -> 8 | P15: =IF(L15="NOR",IF(N15>10,2,IF(N15>8,(N15-O15),0)),0) -> 2 | Q15: =IF(L15="NOR",IF(N15<10,0,IF(N15>10,(N15-(O15+P15)),0)),0) -> 0 | R15: =IF(L15="DOM",N15,0) -> 0 | S15: 0 | T15: 0 | U15: DS | V15: =SUM(T15-S15) -> 0 | W15: =IF(V15>1,V15-1,0) -> 0 | X15: =IF(D15="STAFF",IF(U15="NOR",IF(W15>8.5,8.5,W15),0),IF(U15="NOR",IF(W15>8,8,W15),IF(M15="CAMPO",IF(U15="NOR",IF(W15>8,8,W15),0),IF(U15="NOR",IF(W15>8,8,W15),0)))) -> 0 | Y15: =IF(U15="NOR",IF(W15>10,2,IF(W15>8,(W15-X15),0)),0) -> 0 | Z15: =IF(U15="NOR",IF(W15<10,0,IF(W15>10,(W15-(X15+Y15)),0)),0) -> 0 | AA15: =IF(U15="DOM",W15,0) -> 0 | AB15: 7 | AC15: 19 | AD15: NOR | AE15: =SUM(AC15-AB15) -> 12 | AF15: =IF(AE15>1,AE15-1,0) -> 11 | AG15: =IF(D15="STAFF",IF(AD15="NOR",IF(AF15>8.5,8.5,AF15),0),IF(AD15="NOR",IF(AF15>8,8,AF15),IF(AE15="CAMPO",IF(AD15="NOR",IF(AF15>8,8,AF15),0),IF(AD15="NOR",IF(AF15>8,8,AF15),0)))) -> 8 | AH15: =IF(AD15="NOR",IF(AF15>10,2,IF(AF15>8,(AF15-AG15),0)),0) -> 2 | AI15: =IF(AD15="NOR",IF(AF15<10,0,IF(AF15>10,(AF15-(AG15+AH15)),0)),0) -> 1 | AJ15: =IF(AD15="DOM",AF15,0) -> 0 | AK15: 7 | AL15: 19 | AM15: NOR | AN15: =SUM(AL15-AK15) -> 12 | AO15: =IF(AN15>1,AN15-1,0) -> 11 | AP15: =IF(D15="PROYECTO",IF(AM15="NOR",IF(AO15>8,8,AO15),0),IF(AM15="NOR",IF(AO15>8,8,AO15),0)) -> 8 | AQ15: =IF(AM15="NOR",IF(AO15>10,2,IF(AO15>8,(AO15-AP15),0)),0) -> 2 | AR15: =IF(AM15="NOR",IF(AO15<10,0,IF(AO15>10,(AO15-(AP15+AQ15)),0)),0) -> 1 | AS15: =IF(AM15="DOM",AO15,0) -> 0 | AT15: 7 | AU15: 19 | AV15: NOR | AW15: =SUM(AU15-AT15) -> 12 | AX15: =IF(AW15>1,AW15-1,0) -> 11 | AY15: =IF(AO15="PROYECTO",IF(AV15="NOR",IF(AX15>8,8,AX15),0),IF(AV15="NOR",IF(AX15>8,8,AX15),0)) -> 8 | AZ15: =IF(AV15="NOR",IF(AX15>10,2,IF(AX15>8,(AX15-AY15),0)),0) -> 2 | BA15: =IF(AV15="NOR",IF(AX15<10,0,IF(AX15>10,(AX15-(AY15+AZ15)),0)),0) -> 1 | BB15: =IF(AV15="DOM",AX15,0) -> 0 | BC15: 7 | BD15: 19 | BE15: NOR | BF15: =SUM(BD15-BC15) -> 12 | BG15: =IF(BF15>1,BF15-1,0) -> 11 | BH15: =IF(D15="STAFF",IF(BE15="NOR",IF(BG15>8.5,8.5,BG15),0),IF(BE15="NOR",IF(BG15>8,8,BG15),IF(BF15="CAMPO",IF(BE15="NOR",IF(BG15>8,8,BG15),0),IF(BE15="NOR",IF(BG15>8,8,BG15),0)))) -> 8 | BI15: =IF(BE15="NOR",IF(BG15>10,2,IF(BG15>8,(BG15-BH15),0)),0) -> 2 | BJ15: =IF(BE15="NOR",IF(BG15<10,0,IF(BG15>10,(BG15-(BH15+BI15)),0)),0) -> 1 | BK15: =IF(BE15="DOM",BG15,0) -> 0 | BL15: 7 | BM15: 19 | BN15: NOR | BO15: =SUM(BM15-BL15) -> 12 | BP15: =IF(BO15>1,BO15-1,0) -> 11 | BQ15: =IF(D15="STAFF",IF(BN15="NOR",IF(BP15>8.5,8.5,BP15),0),IF(BN15="NOR",IF(BP15>8,8,BP15),IF(BO15="CAMPO",IF(BN15="NOR",IF(BP15>8,8,BP15),0),IF(BN15="NOR",IF(BP15>8,8,BP15),0)))) -> 8 | BR15: =IF(BN15="NOR",IF(BP15>10,2,IF(BP15>8,(BP15-BQ15),0)),0) -> 2 | BS15: =IF(BN15="NOR",IF(BP15<10,0,IF(BP15>10,(BP15-(BQ15+BR15)),0)),0) -> 1 | BT15: =IF(BN15="DOM",BP15,0) -> 0 | BU15: 7 | BV15: 18 | BW15: NOR | BX15: =SUM(BV15-BU15) -> 11 | BY15: =IF(BX15>1,BX15-1,0) -> 10 | BZ15: =IF(D15="STAFF",IF(BW15="NOR",IF(BY15>8.5,8.5,BY15),0),IF(BW15="NOR",IF(BY15>8,8,BY15),IF(BX15="CAMPO",IF(BW15="NOR",IF(BY15>8,8,BY15),0),IF(BW15="NOR",IF(BY15>8,8,BY15),0)))) -> 8 | CA15: =IF(BW15="NOR",IF(BY15>10,2,IF(BY15>8,(BY15-BZ15),0)),0) -> 2 | CB15: =IF(BW15="NOR",IF(BY15<10,0,IF(BY15>10,(BY15-(BZ15+CA15)),0)),0) -> 0 | CC15: =IF(BW15="DOM",BY15,0) -> 0 | CD15: 0 | CE15: 0 | CF15: DS | CG15: =SUM(CE15-CD15) -> 0 | CH15: =IF(CG15>1,CG15-1,0) -> 0 | CI15: =IF(D15="STAFF",IF(CF15="NOR",IF(CH15>8.5,8.5,CH15),0),IF(CF15="NOR",IF(CH15>8,8,CH15),IF(CG15="CAMPO",IF(CF15="NOR",IF(CH15>8,8,CH15),0),IF(CF15="NOR",IF(CH15>8,8,CH15),0)))) -> 0 | CJ15: =IF(CF15="NOR",IF(CH15>10,2,IF(CH15>8,(CH15-CI15),0)),0) -> 0 | CK15: =IF(CF15="NOR",IF(CH15<10,0,IF(CH15>10,(CH15-(CI15+CJ15)),0)),0) -> 0 | CL15: =IF(CF15="DOM",CH15,0) -> 0 | CM15: 7 | CN15: 18 | CO15: NOR | CP15: =SUM(CN15-CM15) -> 11 | CQ15: =IF(CP15>1,CP15-1,0) -> 10 | CR15: =IF(D15="STAFF",IF(CO15="NOR",IF(CQ15>8.5,8.5,CQ15),0),IF(CO15="NOR",IF(CQ15>8,8,CQ15),IF(CP15="CAMPO",IF(CO15="NOR",IF(CQ15>8,8,CQ15),0),IF(CO15="NOR",IF(CQ15>8,8,CQ15),0)))) -> 8 | CS15: =IF(CO15="NOR",IF(CQ15>10,2,IF(CQ15>8,(CQ15-CR15),0)),0) -> 2 | CT15: =IF(CO15="NOR",IF(CQ15<10,0,IF(CQ15>10,(CQ15-(CR15+CS15)),0)),0) -> 0 | CU15: =IF(CO15="DOM",CQ15,0) -> 0 | CV15: 7 | CW15: 19 | CX15: NOR | CY15: =SUM(CW15-CV15) -> 12 | CZ15: =IF(CY15>1,CY15-1,0) -> 11 | DA15: =IF(CQ15="PROYECTO",IF(CX15="NOR",IF(CZ15>8,8,CZ15),0),IF(CX15="NOR",IF(CZ15>8,8,CZ15),0)) -> 8 | DB15: =IF(CX15="NOR",IF(CZ15>10,2,IF(CZ15>8,(CZ15-DA15),0)),0) -> 2 | DC15: =IF(CX15="NOR",IF(CZ15<10,0,IF(CZ15>10,(CZ15-(DA15+DB15)),0)),0) -> 1 | DD15: =IF(CX15="DOM",CZ15,0) -> 0 | DE15: 7 | DF15: 19 | DG15: NOR | DH15: =SUM(DF15-DE15) -> 12 | DI15: =IF(DH15>1,DH15-1,0) -> 11 | DJ15: =IF(CZ15="PROYECTO",IF(DG15="NOR",IF(DI15>8,8,DI15),0),IF(DG15="NOR",IF(DI15>8,8,DI15),0)) -> 8 | DK15: =IF(DG15="NOR",IF(DI15>10,2,IF(DI15>8,(DI15-DJ15),0)),0) -> 2 | DL15: =IF(DG15="NOR",IF(DI15<10,0,IF(DI15>10,(DI15-(DJ15+DK15)),0)),0) -> 1 | DM15: =IF(DG15="DOM",DI15,0) -> 0 | DN15: 7 | DO15: 19 | DP15: NOR | DQ15: =SUM(DO15-DN15) -> 12 | DR15: =IF(DQ15>1,DQ15-1,0) -> 11 | DS15: =IF(D15="STAFF",IF(DP15="NOR",IF(DR15>8.5,8.5,DR15),0),IF(DP15="NOR",IF(DR15>8,8,DR15),IF(DQ15="CAMPO",IF(DP15="NOR",IF(DR15>8,8,DR15),0),IF(DP15="NOR",IF(DR15>8,8,DR15),0)))) -> 8 | DT15: =IF(DP15="NOR",IF(DR15>10,2,IF(DR15>8,(DR15-DS15),0)),0) -> 2 | DU15: =IF(DP15="NOR",IF(DR15<10,0,IF(DR15>10,(DR15-(DS15+DT15)),0)),0) -> 1 | DV15: =IF(DP15="DOM",DR15,0) -> 0 | DW15: 7 | DX15: 19 | DY15: NOR | DZ15: =SUM(DX15-DW15) -> 12 | EA15: =IF(DZ15>1,DZ15-1,0) -> 11 | EB15: =IF(D15="STAFF",IF(DY15="NOR",IF(EA15>8.5,8.5,EA15),0),IF(DY15="NOR",IF(EA15>8,8,EA15),IF(DZ15="CAMPO",IF(DY15="NOR",IF(EA15>8,8,EA15),0),IF(DY15="NOR",IF(EA15>8,8,EA15),0)))) -> 8 | EC15: =IF(DY15="NOR",IF(EA15>10,2,IF(EA15>8,(EA15-EB15),0)),0) -> 2 | ED15: =IF(DY15="NOR",IF(EA15<10,0,IF(EA15>10,(EA15-(EB15+EC15)),0)),0) -> 1 | EE15: =IF(DY15="DOM",EA15,0) -> 0 | EF15: 7 | EG15: 18 | EH15: NOR | EI15: =SUM(EG15-EF15) -> 11 | EJ15: =IF(EI15>1,EI15-1,0) -> 10 | EK15: =IF(D15="STAFF",IF(EH15="NOR",IF(EJ15>8.5,8.5,EJ15),0),IF(EH15="NOR",IF(EJ15>8,8,EJ15),IF(EI15="CAMPO",IF(EH15="NOR",IF(EJ15>8,8,EJ15),0),IF(EH15="NOR",IF(EJ15>8,8,EJ15),0)))) -> 8 | EL15: =IF(EH15="NOR",IF(EJ15>10,2,IF(EJ15>8,(EJ15-EK15),0)),0) -> 2 | EM15: =IF(EH15="NOR",IF(EJ15<10,0,IF(EJ15>10,(EJ15-(EK15+EL15)),0)),0) -> 0 | EN15: =IF(EH15="DOM",EJ15,0) -> 0 | EO15: 0 | EP15: 0 | EQ15: DS | ER15: =SUM(EP15-EO15) -> 0 | ES15: =IF(ER15>1,ER15-1,0) -> 0 | ET15: =IF(D15="STAFF",IF(EQ15="NOR",IF(ES15>8.5,8.5,ES15),0),IF(EQ15="NOR",IF(ES15>8,8,ES15),IF(ER15="CAMPO",IF(EQ15="NOR",IF(ES15>8,8,ES15),0),IF(EQ15="NOR",IF(ES15>8,8,ES15),0)))) -> 0 | EU15: =IF(EQ15="NOR",IF(ES15>10,2,IF(ES15>8,(ES15-ET15),0)),0) -> 0 | EV15: =IF(EQ15="NOR",IF(ES15<10,0,IF(ES15>10,(ES15-(ET15+EU15)),0)),0) -> 0 | EW15: =IF(EQ15="DOM",ES15,0) -> 0 | EX15: 7 | EY15: 18 | EZ15: NOR | FA15: =SUM(EY15-EX15) -> 11 | FB15: =IF(FA15>1,FA15-1,0) -> 10 | FC15: =IF(D15="STAFF",IF(EZ15="NOR",IF(FB15>8.5,8.5,FB15),0),IF(EZ15="NOR",IF(FB15>8,8,FB15),IF(FA15="CAMPO",IF(EZ15="NOR",IF(FB15>8,8,FB15),0),IF(EZ15="NOR",IF(FB15>8,8,FB15),0)))) -> 8 | FD15: =IF(EZ15="NOR",IF(FB15>10,2,IF(FB15>8,(FB15-FC15),0)),0) -> 2 | FE15: =IF(EZ15="NOR",IF(FB15<10,0,IF(FB15>10,(FB15-(FC15+FD15)),0)),0) -> 0 | FF15: =IF(EZ15="DOM",FB15,0) -> 0 | FG15: 7 | FH15: 18 | FI15: NOR | FJ15: =SUM(FH15-FG15) -> 11 | FK15: =IF(FJ15>1,FJ15-1,0) -> 10 | FL15: =IF(D15="STAFF",IF(FI15="NOR",IF(FK15>8.5,8.5,FK15),0),IF(FI15="NOR",IF(FK15>8,8,FK15),IF(FJ15="CAMPO",IF(FI15="NOR",IF(FK15>8,8,FK15),0),IF(FI15="NOR",IF(FK15>8,8,FK15),0)))) -> 8 | FM15: =IF(FI15="NOR",IF(FK15>10,2,IF(FK15>8,(FK15-FL15),0)),0) -> 2 | FN15: =IF(FI15="NOR",IF(FK15<10,0,IF(FK15>10,(FK15-(FL15+FM15)),0)),0) -> 0 | FO15: =IF(FI15="DOM",FK15,0) -> 0 | FP15: 7 | FQ15: 18 | FR15: NOR | FS15: =SUM(FQ15-FP15) -> 11 | FT15: =IF(FS15>1,FS15-1,0) -> 10 | FU15: =IF(FK15="PROYECTO",IF(FR15="NOR",IF(FT15>8,8,FT15),0),IF(FR15="NOR",IF(FT15>8,8,FT15),0)) -> 8 | FV15: =IF(FR15="NOR",IF(FT15>10,2,IF(FT15>8,(FT15-FU15),0)),0) -> 2 | FW15: =IF(FR15="NOR",IF(FT15<10,0,IF(FT15>10,(FT15-(FU15+FV15)),0)),0) -> 0 | FX15: =IF(FR15="DOM",FT15,0) -> 0 | FY15: 7 | FZ15: 18 | GA15: NOR | GB15: =SUM(FZ15-FY15) -> 11 | GC15: =IF(GB15>1,GB15-1,0) -> 10 | GD15: =IF(D15="STAFF",IF(GA15="NOR",IF(GC15>8.5,8.5,GC15),0),IF(GA15="NOR",IF(GC15>8,8,GC15),IF(GB15="CAMPO",IF(GA15="NOR",IF(GC15>8,8,GC15),0),IF(GA15="NOR",IF(GC15>8,8,GC15),0)))) -> 8 | GE15: =IF(GA15="NOR",IF(GC15>10,2,IF(GC15>8,(GC15-GD15),0)),0) -> 2 | GF15: =IF(GA15="NOR",IF(GC15<10,0,IF(GC15>10,(GC15-(GD15+GE15)),0)),0) -> 0 | GG15: =IF(GA15="DOM",GC15,0) -> 0 | GH15: 7 | GI15: 18 | GJ15: NOR | GK15: =SUM(GI15-GH15) -> 11 | GL15: =IF(GK15>1,GK15-1,0) -> 10 | GM15: =IF(D15="STAFF",IF(GJ15="NOR",IF(GL15>8.5,8.5,GL15),0),IF(GJ15="NOR",IF(GL15>8,8,GL15),IF(GK15="CAMPO",IF(GJ15="NOR",IF(GL15>8,8,GL15),0),IF(GJ15="NOR",IF(GL15>8,8,GL15),0)))) -> 8 | GN15: =IF(GJ15="NOR",IF(GL15>10,2,IF(GL15>8,(GL15-GM15),0)),0) -> 2 | GO15: =IF(GJ15="NOR",IF(GL15<10,0,IF(GL15>10,(GL15-(GM15+GN15)),0)),0) -> 0 | GP15: =IF(GJ15="DOM",GL15,0) -> 0 | GQ15: 7 | GR15: 18 | GS15: NOR | GT15: =SUM(GR15-GQ15) -> 11 | GU15: =IF(GT15>1,GT15-1,0) -> 10 | GV15: =IF(D15="STAFF",IF(GS15="NOR",IF(GU15>8.5,8.5,GU15),0),IF(GS15="NOR",IF(GU15>8,8,GU15),IF(GT15="CAMPO",IF(GS15="NOR",IF(GU15>8,8,GU15),0),IF(GS15="NOR",IF(GU15>8,8,GU15),0)))) -> 8 | GW15: =IF(GS15="NOR",IF(GU15>10,2,IF(GU15>8,(GU15-GV15),0)),0) -> 2 | GX15: =IF(GS15="NOR",IF(GU15<10,0,IF(GU15>10,(GU15-(GV15+GW15)),0)),0) -> 0 | GY15: =IF(GS15="DOM",GU15,0) -> 0 | GZ15: 0 | HA15: 0 | HB15: DS | HC15: =SUM(HA15-GZ15) -> 0 | HD15: =IF(HC15>1,HC15-1,0) -> 0 | HE15: =IF(D15="STAFF",IF(HB15="NOR",IF(HD15>8.5,8.5,HD15),0),IF(HB15="NOR",IF(HD15>8,8,HD15),IF(HC15="CAMPO",IF(HB15="NOR",IF(HD15>8,8,HD15),0),IF(HB15="NOR",IF(HD15>8,8,HD15),0)))) -> 0 | HF15: =IF(HB15="NOR",IF(HD15>10,2,IF(HD15>8,(HD15-HE15),0)),0) -> 0 | HG15: =IF(HB15="NOR",IF(HD15<10,0,IF(HD15>10,(HD15-(HE15+HF15)),0)),0) -> 0 | HH15: =IF(HB15="DOM",HD15,0) -> 0 | HI15: 7 | HJ15: 18 | HK15: NOR | HL15: =SUM(HJ15-HI15) -> 11 | HM15: =IF(HL15>1,HL15-1,0) -> 10 | HN15: =IF(D15="STAFF",IF(HK15="NOR",IF(HM15>8.5,8.5,HM15),0),IF(HK15="NOR",IF(HM15>8,8,HM15),IF(HL15="CAMPO",IF(HK15="NOR",IF(HM15>8,8,HM15),0),IF(HK15="NOR",IF(HM15>8,8,HM15),0)))) -> 8 | HO15: =IF(HK15="NOR",IF(HM15>10,2,IF(HM15>8,(HM15-HN15),0)),0) -> 2 | HP15: =IF(HK15="NOR",IF(HM15<10,0,IF(HM15>10,(HM15-(HN15+HO15)),0)),0) -> 0 | HQ15: =IF(HK15="DOM",HM15,0) -> 0 | HR15: 7 | HS15: 18 | HT15: NOR | HU15: =SUM(HS15-HR15) -> 11 | HV15: =IF(HU15>1,HU15-1,0) -> 10 | HW15: =IF(D15="STAFF",IF(HT15="NOR",IF(HV15>8.5,8.5,HV15),0),IF(HT15="NOR",IF(HV15>8,8,HV15),IF(HU15="CAMPO",IF(HT15="NOR",IF(HV15>8,8,HV15),0),IF(HT15="NOR",IF(HV15>8,8,HV15),0)))) -> 8 | HX15: =IF(HT15="NOR",IF(HV15>10,2,IF(HV15>8,(HV15-HW15),0)),0) -> 2 | HY15: =IF(HT15="NOR",IF(HV15<10,0,IF(HV15>10,(HV15-(HW15+HX15)),0)),0) -> 0 | HZ15: =IF(HT15="DOM",HV15,0) -> 0 | IA15: 7 | IB15: 18 | IC15: NOR | ID15: =SUM(IB15-IA15) -> 11 | IE15: =IF(ID15>1,ID15-1,0) -> 10 | IF15: =IF(D15="STAFF",IF(IC15="NOR",IF(IE15>8.5,8.5,IE15),0),IF(IC15="NOR",IF(IE15>8,8,IE15),IF(ID15="CAMPO",IF(IC15="NOR",IF(IE15>8,8,IE15),0),IF(IC15="NOR",IF(IE15>8,8,IE15),0)))) -> 8 | IG15: =IF(IC15="NOR",IF(IE15>10,2,IF(IE15>8,(IE15-IF15),0)),0) -> 2 | IH15: =IF(IC15="NOR",IF(IE15<10,0,IF(IE15>10,(IE15-(IF15+IG15)),0)),0) -> 0 | II15: =IF(IC15="DOM",IE15,0) -> 0 | IJ15: 7 | IK15: 18 | IL15: NOR | IM15: =SUM(IK15-IJ15) -> 11 | IN15: =IF(IM15>1,IM15-1,0) -> 10 | IO15: =IF(D15="STAFF",IF(IL15="NOR",IF(IN15>8.5,8.5,IN15),0),IF(IL15="NOR",IF(IN15>8,8,IN15),IF(IM15="CAMPO",IF(IL15="NOR",IF(IN15>8,8,IN15),0),IF(IL15="NOR",IF(IN15>8,8,IN15),0)))) -> 8 | IP15: =IF(IL15="NOR",IF(IN15>10,2,IF(IN15>8,(IN15-IO15),0)),0) -> 2 | IQ15: =IF(IL15="NOR",IF(IN15<10,0,IF(IN15>10,(IN15-(IO15+IP15)),0)),0) -> 0 | IR15: =IF(IL15="DOM",IN15,0) -> 0 | IS15: 7 | IT15: 18 | IU15: NOR | IV15: =SUM(IT15-IS15) -> 11 | IW15: =IF(IV15>1,IV15-1,0) -> 10 | IX15: =IF(D15="STAFF",IF(IU15="NOR",IF(IW15>8.5,8.5,IW15),0),IF(IU15="NOR",IF(IW15>8,8,IW15),IF(IV15="CAMPO",IF(IU15="NOR",IF(IW15>8,8,IW15),0),IF(IU15="NOR",IF(IW15>8,8,IW15),0)))) -> 8 | IY15: =IF(IU15="NOR",IF(IW15>10,2,IF(IW15>8,(IW15-IX15),0)),0) -> 2 | IZ15: =IF(IU15="NOR",IF(IW15<10,0,IF(IW15>10,(IW15-(IX15+IY15)),0)),0) -> 0 | JA15: =IF(IU15="DOM",IW15,0) -> 0 | JB15: 7 | JC15: 18 | JD15: NOR | JE15: =SUM(JC15-JB15) -> 11 | JF15: =IF(JE15>1,JE15-1,0) -> 10 | JG15: =IF(D15="STAFF",IF(JD15="NOR",IF(JF15>8.5,8.5,JF15),0),IF(JD15="NOR",IF(JF15>8,8,JF15),IF(JE15="CAMPO",IF(JD15="NOR",IF(JF15>8,8,JF15),0),IF(JD15="NOR",IF(JF15>8,8,JF15),0)))) -> 8 | JH15: =IF(JD15="NOR",IF(JF15>10,2,IF(JF15>8,(JF15-JG15),0)),0) -> 2 | JI15: =IF(JD15="NOR",IF(JF15<10,0,IF(JF15>10,(JF15-(JG15+JH15)),0)),0) -> 0 | JJ15: =IF(JD15="DOM",JF15,0) -> 0 | JK15: 0 | JL15: 0 | JM15: DS | JN15: =SUM(JL15-JK15) -> 0 | JO15: =IF(JN15>1,JN15-1,0) -> 0 | JP15: =IF(D15="STAFF",IF(JM15="NOR",IF(JO15>8.5,8.5,JO15),0),IF(JM15="NOR",IF(JO15>8,8,JO15),IF(JN15="CAMPO",IF(JM15="NOR",IF(JO15>8,8,JO15),0),IF(JM15="NOR",IF(JO15>8,8,JO15),0)))) -> 0 | JQ15: =IF(JM15="NOR",IF(JO15>10,2,IF(JO15>8,(JO15-JP15),0)),0) -> 0 | JR15: =IF(JM15="NOR",IF(JO15<10,0,IF(JO15>10,(JO15-(JP15+JQ15)),0)),0) -> 0 | JS15: =IF(JM15="DOM",JO15,0) -> 0 | JT15: 7 | JU15: 19 | JV15: NOR | JW15: =SUM(JU15-JT15) -> 12 | JX15: =IF(JW15>1,JW15-1,0) -> 11 | JY15: =IF(D15="STAFF",IF(JV15="NOR",IF(JX15>8.5,8.5,JX15),0),IF(JV15="NOR",IF(JX15>8,8,JX15),IF(JW15="CAMPO",IF(JV15="NOR",IF(JX15>8,8,JX15),0),IF(JV15="NOR",IF(JX15>8,8,JX15),0)))) -> 8 | JZ15: =IF(JV15="NOR",IF(JX15>10,2,IF(JX15>8,(JX15-JY15),0)),0) -> 2 | KA15: =IF(JV15="NOR",IF(JX15<10,0,IF(JX15>10,(JX15-(JY15+JZ15)),0)),0) -> 1 | KB15: =IF(JV15="DOM",JX15,0) -> 0 | KC15: 7 | KD15: 16 | KE15: NOR | KF15: =SUM(KD15-KC15) -> 9 | KG15: =IF(KF15>1,KF15-1,0) -> 8 | KH15: =IF(D15="STAFF",IF(KE15="NOR",IF(KG15>8.5,8.5,KG15),0),IF(KE15="NOR",IF(KG15>8,8,KG15),IF(KF15="CAMPO",IF(KE15="NOR",IF(KG15>8,8,KG15),0),IF(KE15="NOR",IF(KG15>8,8,KG15),0)))) -> 8 | KI15: =IF(KE15="NOR",IF(KG15>10,2,IF(KG15>8,(KG15-KH15),0)),0) -> 0 | KJ15: =IF(KE15="NOR",IF(KG15<10,0,IF(KG15>10,(KG15-(KH15+KI15)),0)),0) -> 0 | KK15: =IF(KE15="DOM",KG15,0) -> 0 | KL15: 7 | KM15: 16 | KN15: NOR | KO15: =SUM(KM15-KL15) -> 9 | KP15: =IF(KO15>1,KO15-1,0) -> 8 | KQ15: =IF(D15="STAFF",IF(KN15="NOR",IF(KP15>8.5,8.5,KP15),0),IF(KN15="NOR",IF(KP15>8,8,KP15),IF(KO15="CAMPO",IF(KN15="NOR",IF(KP15>8,8,KP15),0),IF(KN15="NOR",IF(KP15>8,8,KP15),0)))) -> 8 | KR15: =IF(KN15="NOR",IF(KP15>10,2,IF(KP15>8,(KP15-KQ15),0)),0) -> 0 | KS15: =IF(KN15="NOR",IF(KP15<10,0,IF(KP15>10,(KP15-(KQ15+KR15)),0)),0) -> 0 | KT15: =IF(KN15="DOM",KP15,0) -> 0 | KU15: 7 | KV15: 16 | KW15: NOR | KX15: =SUM(KV15-KU15) -> 9 | KY15: =IF(KX15>1,KX15-1,0) -> 8 | KZ15: =IF(D15="STAFF",IF(KW15="NOR",IF(KY15>8.5,8.5,KY15),0),IF(KW15="NOR",IF(KY15>8,8,KY15),IF(KX15="CAMPO",IF(KW15="NOR",IF(KY15>8,8,KY15),0),IF(KW15="NOR",IF(KY15>8,8,KY15),0)))) -> 8 | LA15: =IF(KW15="NOR",IF(KY15>10,2,IF(KY15>8,(KY15-KZ15),0)),0) -> 0 | LB15: =IF(KW15="NOR",IF(KY15<10,0,IF(KY15>10,(KY15-(KZ15+LA15)),0)),0) -> 0 | LC15: =IF(KW15="DOM",KY15,0) -> 0 | LD15: 7 | LE15: 16 | LF15: NOR | LG15: =SUM(LE15-LD15) -> 9 | LH15: =IF(LG15>1,LG15-1,0) -> 8 | LI15: =IF(D15="STAFF",IF(LF15="NOR",IF(LH15>8.5,8.5,LH15),0),IF(LF15="NOR",IF(LH15>8,8,LH15),IF(LG15="CAMPO",IF(LF15="NOR",IF(LH15>8,8,LH15),0),IF(LF15="NOR",IF(LH15>8,8,LH15),0)))) -> 8 | LJ15: =IF(LF15="NOR",IF(LH15>10,2,IF(LH15>8,(LH15-LI15),0)),0) -> 0 | LK15: =IF(LF15="NOR",IF(LH15<10,0,IF(LH15>10,(LH15-(LI15+LJ15)),0)),0) -> 0 | LL15: =IF(LF15="DOM",LH15,0) -> 0 | LM15: 7 | LN15: 16 | LO15: NOR | LP15: =SUM(LN15-LM15) -> 9 | LQ15: =IF(LP15>1,LP15-1,0) -> 8 | LR15: =IF(D15="STAFF",IF(LO15="NOR",IF(LQ15>8.5,8.5,LQ15),0),IF(LO15="NOR",IF(LQ15>8,8,LQ15),IF(LP15="CAMPO",IF(LO15="NOR",IF(LQ15>8,8,LQ15),0),IF(LO15="NOR",IF(LQ15>8,8,LQ15),0)))) -> 8 | LS15: =IF(LO15="NOR",IF(LQ15>10,2,IF(LQ15>8,(LQ15-LR15),0)),0) -> 0 | LT15: =IF(LO15="NOR",IF(LQ15<10,0,IF(LQ15>10,(LQ15-(LR15+LS15)),0)),0) -> 0 | LU15: =IF(LO15="DOM",LQ15,0) -> 0 | LV15: 7 | LW15: 16 | LX15: NOR | LY15: =SUM(LW15-LV15) -> 9 | LZ15: =IF(LY15>1,LY15-1,0) -> 8 | MA15: =IF(D15="STAFF",IF(LX15="NOR",IF(LZ15>8.5,8.5,LZ15),0),IF(LX15="NOR",IF(LZ15>8,8,LZ15),IF(LY15="CAMPO",IF(LX15="NOR",IF(LZ15>8,8,LZ15),0),IF(LX15="NOR",IF(LZ15>8,8,LZ15),0)))) -> 8 | MB15: =IF(LX15="NOR",IF(LZ15>10,2,IF(LZ15>8,(LZ15-MA15),0)),0) -> 0 | MC15: =IF(LX15="NOR",IF(LZ15<10,0,IF(LZ15>10,(LZ15-(MA15+MB15)),0)),0) -> 0 | MD15: =IF(LX15="DOM",LZ15,0) -> 0 | ME15: 7 | MF15: 16 | MG15: NOR | MH15: =SUM(MF15-ME15) -> 9 | MI15: =IF(MH15>1,MH15-1,0) -> 8 | MJ15: =IF(D15="STAFF",IF(MG15="NOR",IF(MI15>8.5,8.5,MI15),0),IF(MG15="NOR",IF(MI15>8,8,MI15),IF(MH15="CAMPO",IF(MG15="NOR",IF(MI15>8,8,MI15),0),IF(MG15="NOR",IF(MI15>8,8,MI15),0)))) -> 8 | MK15: =IF(MG15="NOR",IF(MI15>10,2,IF(MI15>8,(MI15-MJ15),0)),0) -> 0 | ML15: =IF(MG15="NOR",IF(MI15<10,0,IF(MI15>10,(MI15-(MJ15+MK15)),0)),0) -> 0 | MM15: =IF(MG15="DOM",MI15,0) -> 0 | MN15: 7 | MO15: 16 | MP15: NOR | MQ15: =SUM(MO15-MN15) -> 9 | MR15: =IF(MQ15>1,MQ15-1,0) -> 8 | MS15: =IF(D15="STAFF",IF(MP15="NOR",IF(MR15>8.5,8.5,MR15),0),IF(MP15="NOR",IF(MR15>8,8,MR15),IF(MQ15="CAMPO",IF(MP15="NOR",IF(MR15>8,8,MR15),0),IF(MP15="NOR",IF(MR15>8,8,MR15),0)))) -> 8 | MT15: =IF(MP15="NOR",IF(MR15>10,2,IF(MR15>8,(MR15-MS15),0)),0) -> 0 | MU15: =IF(MP15="NOR",IF(MR15<10,0,IF(MR15>10,(MR15-(MS15+MT15)),0)),0) -> 0 | MV15: =IF(MP15="DOM",MR15,0) -> 0 | MW15: 7 | MX15: 16 | MY15: NOR | MZ15: =SUM(MX15-MW15) -> 9 | NA15: =IF(MZ15>1,MZ15-1,0) -> 8 | NB15: =IF(D15="STAFF",IF(MY15="NOR",IF(NA15>8.5,8.5,NA15),0),IF(MY15="NOR",IF(NA15>8,8,NA15),IF(MZ15="CAMPO",IF(MY15="NOR",IF(NA15>8,8,NA15),0),IF(MY15="NOR",IF(NA15>8,8,NA15),0)))) -> 8 | NC15: =IF(MY15="NOR",IF(NA15>10,2,IF(NA15>8,(NA15-NB15),0)),0) -> 0 | ND15: =IF(MY15="NOR",IF(NA15<10,0,IF(NA15>10,(NA15-(NB15+NC15)),0)),0) -> 0 | NE15: =IF(MY15="DOM",NA15,0) -> 0 | NF15: 7 | NG15: 16 | NH15: NOR | NI15: =SUM(NG15-NF15) -> 9 | NJ15: =IF(NI15>1,NI15-1,0) -> 8 | NK15: =IF(D15="STAFF",IF(NH15="NOR",IF(NJ15>8.5,8.5,NJ15),0),IF(NH15="NOR",IF(NJ15>8,8,NJ15),IF(NI15="CAMPO",IF(NH15="NOR",IF(NJ15>8,8,NJ15),0),IF(NH15="NOR",IF(NJ15>8,8,NJ15),0)))) -> 8 | NL15: =IF(NH15="NOR",IF(NJ15>10,2,IF(NJ15>8,(NJ15-NK15),0)),0) -> 0 | NM15: =IF(NH15="NOR",IF(NJ15<10,0,IF(NJ15>10,(NJ15-(NK15+NL15)),0)),0) -> 0 | NN15: =IF(NH15="DOM",NJ15,0) -> 0 | NO15: 7 | NP15: 16 | NQ15: NOR | NR15: =SUM(NP15-NO15) -> 9 | NS15: =IF(NR15>1,NR15-1,0) -> 8 | NT15: =IF(D15="STAFF",IF(NQ15="NOR",IF(NS15>8.5,8.5,NS15),0),IF(NQ15="NOR",IF(NS15>8,8,NS15),IF(NR15="CAMPO",IF(NQ15="NOR",IF(NS15>8,8,NS15),0),IF(NQ15="NOR",IF(NS15>8,8,NS15),0)))) -> 8 | NU15: =IF(NQ15="NOR",IF(NS15>10,2,IF(NS15>8,(NS15-NT15),0)),0) -> 0 | NV15: =IF(NQ15="NOR",IF(NS15<10,0,IF(NS15>10,(NS15-(NT15+NU15)),0)),0) -> 0 | NW15: =IF(NQ15="DOM",NS15,0) -> 0 | NX15: 7 | NY15: 16 | NZ15: NOR | OA15: =SUM(NY15-NX15) -> 9 | OB15: =IF(OA15>1,OA15-1,0) -> 8 | OC15: =IF(D15="STAFF",IF(NZ15="NOR",IF(OB15>8.5,8.5,OB15),0),IF(NZ15="NOR",IF(OB15>8,8,OB15),IF(OA15="CAMPO",IF(NZ15="NOR",IF(OB15>8,8,OB15),0),IF(NZ15="NOR",IF(OB15>8,8,OB15),0)))) -> 8 | OD15: =IF(NZ15="NOR",IF(OB15>10,2,IF(OB15>8,(OB15-OC15),0)),0) -> 0 | OE15: =IF(NZ15="NOR",IF(OB15<10,0,IF(OB15>10,(OB15-(OC15+OD15)),0)),0) -> 0 | OF15: =IF(NZ15="DOM",OB15,0) -> 0 | OG15: 0 | OH15: 0 | OI15: DS | OJ15: =SUM(OH15-OG15) -> 0 | OK15: =IF(OJ15>1,OJ15-1,0) -> 0 | OL15: =IF(D15="STAFF",IF(OI15="NOR",IF(OK15>8.5,8.5,OK15),0),IF(OI15="NOR",IF(OK15>8,8,OK15),IF(OJ15="CAMPO",IF(OI15="NOR",IF(OK15>8,8,OK15),0),IF(OI15="NOR",IF(OK15>8,8,OK15),0)))) -> 0 | OM15: =IF(OI15="NOR",IF(OK15>10,2,IF(OK15>8,(OK15-OL15),0)),0) -> 0 | ON15: =IF(OI15="NOR",IF(OK15<10,0,IF(OK15>10,(OK15-(OL15+OM15)),0)),0) -> 0 | OO15: =IF(OI15="DOM",OK15,0) -> 0 | OP15: 7 | OQ15: 16 | OR15: NOR | OS15: =SUM(OQ15-OP15) -> 9 | OT15: =IF(OS15>1,OS15-1,0) -> 8 | OU15: =IF(D15="STAFF",IF(OR15="NOR",IF(OT15>8.5,8.5,OT15),0),IF(OR15="NOR",IF(OT15>8,8,OT15),IF(OS15="CAMPO",IF(OR15="NOR",IF(OT15>8,8,OT15),0),IF(OR15="NOR",IF(OT15>8,8,OT15),0)))) -> 8 | OV15: =IF(OR15="NOR",IF(OT15>10,2,IF(OT15>8,(OT15-OU15),0)),0) -> 0 | OW15: =IF(OR15="NOR",IF(OT15<10,0,IF(OT15>10,(OT15-(OU15+OV15)),0)),0) -> 0 | OX15: =IF(OR15="DOM",OT15,0) -> 0 | OY15: 0 | OZ15: 0 | PA15: FE | PB15: =SUM(OZ15-OY15) -> 0 | PC15: =IF(PB15>1,PB15-1,0) -> 0 | PD15: =IF(D15="STAFF",IF(PA15="NOR",IF(PC15>8.5,8.5,PC15),0),IF(PA15="NOR",IF(PC15>8,8,PC15),IF(PB15="CAMPO",IF(PA15="NOR",IF(PC15>8,8,PC15),0),IF(PA15="NOR",IF(PC15>8,8,PC15),0)))) -> 0 | PE15: =IF(PA15="NOR",IF(PC15>10,2,IF(PC15>8,(PC15-PD15),0)),0) -> 0 | PF15: =IF(PA15="NOR",IF(PC15<10,0,IF(PC15>10,(PC15-(PD15+PE15)),0)),0) -> 0 | PG15: =IF(PA15="DOM",PC15,0) -> 0 | PH15: 7 | PI15: 16 | PJ15: NOR | PK15: =SUM(PI15-PH15) -> 9 | PL15: =IF(PK15>1,PK15-1,0) -> 8 | PM15: =IF(M15="STAFF",IF(PJ15="NOR",IF(PL15>8.5,8.5,PL15),0),IF(PJ15="NOR",IF(PL15>8,8,PL15),IF(PK15="CAMPO",IF(PJ15="NOR",IF(PL15>8,8,PL15),0),IF(PJ15="NOR",IF(PL15>8,8,PL15),0)))) -> 8 | PN15: =IF(PJ15="NOR",IF(PL15>10,2,IF(PL15>8,(PL15-PM15),0)),0) -> 0 | PO15: =IF(PJ15="NOR",IF(PL15<10,0,IF(PL15>10,(PL15-(PM15+PN15)),0)),0) -> 0 | PP15: =IF(PJ15="DOM",PL15,0) -> 0 | PR15: =COUNTIF(FG15:PP15,"NOR") -> 26 | PS15: =COUNTIF(FG15:PP15,"DS") -> 3 | PT15: =COUNTIF(FG15:PP15,"FE") -> 1 | PU15: =SUM(PR15:PT15) -> 30 | PV15: =COUNTIF(FG15:PP15,"DM") -> 0 | PY15: =COUNTIF(FG15:PP15,"SUB") -> 0 | QB15: =COUNTIF(FG15:PP15,"VA") -> 0 | QE15: =COUNTIF(FG15:PP15,"LSG") -> 0 | QH15: =COUNTIF(FG15:PP15,"LCG") -> 0 | QK15: =COUNTIF(FG15:PP15,"FA") -> 0 | QN15: =COUNTIF(J15:FF15,"FA") -> 0 | QQ15: =PU15+PV15+PY15+QB15+QE15+QH15+QK15+QN15 -> 30 | QS15: =P15+Y15++AH15+AQ15+AZ15+BI15+BR15+CA15+CJ15+CS15+DB15+DK15+DT15+EC15+EL15+EU15+FD15+FM15+FV15+GE15+GN15+GW15+HF15+HO15+HX15+IG15+IP15+IY15+JH15+JQ15+JZ15 -> 52 | QT15: =Q15+Z15++AI15+AR15+BA15+BJ15+BS15+CB15+CK15+CT15+DC15+DL15+DU15+ED15+EM15+EV15+FE15+FN15+FW15+GF15+GO15+GX15+HG15+HP15+HY15+IH15+IQ15+IZ15+JI15+JR15+KA15 -> 10 | RG15: 11
A16: =A15+1 -> 7 | B16: 44592899 | D16: PROYECTO | E16: GAMBOA PALOMINO DIANA MERCID | F16: VIGÍA | G16: 44291 | H16: 44295 | J16: 7 | K16: 18 | L16: NOR | M16: =SUM(K16-J16) -> 11 | N16: =IF(M16>1,M16-1,0) -> 10 | O16: =IF(D16="STAFF",IF(L16="NOR",IF(N16>8.5,8.5,N16),0),IF(L16="NOR",IF(N16>8,8,N16),IF(D16="CAMPO",IF(L16="NOR",IF(N16>8,8,N16),0),IF(L16="NOR",IF(N16>8,8,N16),0)))) -> 8 | P16: =IF(L16="NOR",IF(N16>10,2,IF(N16>8,(N16-O16),0)),0) -> 2 | Q16: =IF(L16="NOR",IF(N16<10,0,IF(N16>10,(N16-(O16+P16)),0)),0) -> 0 | R16: =IF(L16="DOM",N16,0) -> 0 | S16: 0 | T16: 0 | U16: DS | V16: =SUM(T16-S16) -> 0 | W16: =IF(V16>1,V16-1,0) -> 0 | X16: =IF(D16="STAFF",IF(U16="NOR",IF(W16>8.5,8.5,W16),0),IF(U16="NOR",IF(W16>8,8,W16),IF(M16="CAMPO",IF(U16="NOR",IF(W16>8,8,W16),0),IF(U16="NOR",IF(W16>8,8,W16),0)))) -> 0 | Y16: =IF(U16="NOR",IF(W16>10,2,IF(W16>8,(W16-X16),0)),0) -> 0 | Z16: =IF(U16="NOR",IF(W16<10,0,IF(W16>10,(W16-(X16+Y16)),0)),0) -> 0 | AA16: =IF(U16="DOM",W16,0) -> 0 | AB16: 7 | AC16: 18 | AD16: NOR | AE16: =SUM(AC16-AB16) -> 11 | AF16: =IF(AE16>1,AE16-1,0) -> 10 | AG16: =IF(D16="STAFF",IF(AD16="NOR",IF(AF16>8.5,8.5,AF16),0),IF(AD16="NOR",IF(AF16>8,8,AF16),IF(AE16="CAMPO",IF(AD16="NOR",IF(AF16>8,8,AF16),0),IF(AD16="NOR",IF(AF16>8,8,AF16),0)))) -> 8 | AH16: =IF(AD16="NOR",IF(AF16>10,2,IF(AF16>8,(AF16-AG16),0)),0) -> 2 | AI16: =IF(AD16="NOR",IF(AF16<10,0,IF(AF16>10,(AF16-(AG16+AH16)),0)),0) -> 0 | AJ16: =IF(AD16="DOM",AF16,0) -> 0 | AK16: 7 | AL16: 18 | AM16: NOR | AN16: =SUM(AL16-AK16) -> 11 | AO16: =IF(AN16>1,AN16-1,0) -> 10 | AP16: =IF(D16="PROYECTO",IF(AM16="NOR",IF(AO16>8,8,AO16),0),IF(AM16="NOR",IF(AO16>8,8,AO16),0)) -> 8 | AQ16: =IF(AM16="NOR",IF(AO16>10,2,IF(AO16>8,(AO16-AP16),0)),0) -> 2 | AR16: =IF(AM16="NOR",IF(AO16<10,0,IF(AO16>10,(AO16-(AP16+AQ16)),0)),0) -> 0 | AS16: =IF(AM16="DOM",AO16,0) -> 0 | AT16: 7 | AU16: 18 | AV16: NOR | AW16: =SUM(AU16-AT16) -> 11 | AX16: =IF(AW16>1,AW16-1,0) -> 10 | AY16: =IF(AO16="PROYECTO",IF(AV16="NOR",IF(AX16>8,8,AX16),0),IF(AV16="NOR",IF(AX16>8,8,AX16),0)) -> 8 | AZ16: =IF(AV16="NOR",IF(AX16>10,2,IF(AX16>8,(AX16-AY16),0)),0) -> 2 | BA16: =IF(AV16="NOR",IF(AX16<10,0,IF(AX16>10,(AX16-(AY16+AZ16)),0)),0) -> 0 | BB16: =IF(AV16="DOM",AX16,0) -> 0 | BC16: 7 | BD16: 19 | BE16: NOR | BF16: =SUM(BD16-BC16) -> 12 | BG16: =IF(BF16>1,BF16-1,0) -> 11 | BH16: =IF(D16="STAFF",IF(BE16="NOR",IF(BG16>8.5,8.5,BG16),0),IF(BE16="NOR",IF(BG16>8,8,BG16),IF(BF16="CAMPO",IF(BE16="NOR",IF(BG16>8,8,BG16),0),IF(BE16="NOR",IF(BG16>8,8,BG16),0)))) -> 8 | BI16: =IF(BE16="NOR",IF(BG16>10,2,IF(BG16>8,(BG16-BH16),0)),0) -> 2 | BJ16: =IF(BE16="NOR",IF(BG16<10,0,IF(BG16>10,(BG16-(BH16+BI16)),0)),0) -> 1 | BK16: =IF(BE16="DOM",BG16,0) -> 0 | BL16: 7 | BM16: 18 | BN16: NOR | BO16: =SUM(BM16-BL16) -> 11 | BP16: =IF(BO16>1,BO16-1,0) -> 10 | BQ16: =IF(D16="STAFF",IF(BN16="NOR",IF(BP16>8.5,8.5,BP16),0),IF(BN16="NOR",IF(BP16>8,8,BP16),IF(BO16="CAMPO",IF(BN16="NOR",IF(BP16>8,8,BP16),0),IF(BN16="NOR",IF(BP16>8,8,BP16),0)))) -> 8 | BR16: =IF(BN16="NOR",IF(BP16>10,2,IF(BP16>8,(BP16-BQ16),0)),0) -> 2 | BS16: =IF(BN16="NOR",IF(BP16<10,0,IF(BP16>10,(BP16-(BQ16+BR16)),0)),0) -> 0 | BT16: =IF(BN16="DOM",BP16,0) -> 0 | BU16: 7 | BV16: 18 | BW16: NOR | BX16: =SUM(BV16-BU16) -> 11 | BY16: =IF(BX16>1,BX16-1,0) -> 10 | BZ16: =IF(D16="STAFF",IF(BW16="NOR",IF(BY16>8.5,8.5,BY16),0),IF(BW16="NOR",IF(BY16>8,8,BY16),IF(BX16="CAMPO",IF(BW16="NOR",IF(BY16>8,8,BY16),0),IF(BW16="NOR",IF(BY16>8,8,BY16),0)))) -> 8 | CA16: =IF(BW16="NOR",IF(BY16>10,2,IF(BY16>8,(BY16-BZ16),0)),0) -> 2 | CB16: =IF(BW16="NOR",IF(BY16<10,0,IF(BY16>10,(BY16-(BZ16+CA16)),0)),0) -> 0 | CC16: =IF(BW16="DOM",BY16,0) -> 0 | CD16: 0 | CE16: 0 | CF16: DS | CG16: =SUM(CE16-CD16) -> 0 | CH16: =IF(CG16>1,CG16-1,0) -> 0 | CI16: =IF(D16="STAFF",IF(CF16="NOR",IF(CH16>8.5,8.5,CH16),0),IF(CF16="NOR",IF(CH16>8,8,CH16),IF(CG16="CAMPO",IF(CF16="NOR",IF(CH16>8,8,CH16),0),IF(CF16="NOR",IF(CH16>8,8,CH16),0)))) -> 0 | CJ16: =IF(CF16="NOR",IF(CH16>10,2,IF(CH16>8,(CH16-CI16),0)),0) -> 0 | CK16: =IF(CF16="NOR",IF(CH16<10,0,IF(CH16>10,(CH16-(CI16+CJ16)),0)),0) -> 0 | CL16: =IF(CF16="DOM",CH16,0) -> 0 | CM16: 7 | CN16: 18 | CO16: NOR | CP16: =SUM(CN16-CM16) -> 11 | CQ16: =IF(CP16>1,CP16-1,0) -> 10 | CR16: =IF(D16="STAFF",IF(CO16="NOR",IF(CQ16>8.5,8.5,CQ16),0),IF(CO16="NOR",IF(CQ16>8,8,CQ16),IF(CP16="CAMPO",IF(CO16="NOR",IF(CQ16>8,8,CQ16),0),IF(CO16="NOR",IF(CQ16>8,8,CQ16),0)))) -> 8 | CS16: =IF(CO16="NOR",IF(CQ16>10,2,IF(CQ16>8,(CQ16-CR16),0)),0) -> 2 | CT16: =IF(CO16="NOR",IF(CQ16<10,0,IF(CQ16>10,(CQ16-(CR16+CS16)),0)),0) -> 0 | CU16: =IF(CO16="DOM",CQ16,0) -> 0 | CV16: 7 | CW16: 18 | CX16: NOR | CY16: =SUM(CW16-CV16) -> 11 | CZ16: =IF(CY16>1,CY16-1,0) -> 10 | DA16: =IF(CQ16="PROYECTO",IF(CX16="NOR",IF(CZ16>8,8,CZ16),0),IF(CX16="NOR",IF(CZ16>8,8,CZ16),0)) -> 8 | DB16: =IF(CX16="NOR",IF(CZ16>10,2,IF(CZ16>8,(CZ16-DA16),0)),0) -> 2 | DC16: =IF(CX16="NOR",IF(CZ16<10,0,IF(CZ16>10,(CZ16-(DA16+DB16)),0)),0) -> 0 | DD16: =IF(CX16="DOM",CZ16,0) -> 0 | DE16: 7 | DF16: 18 | DG16: NOR | DH16: =SUM(DF16-DE16) -> 11 | DI16: =IF(DH16>1,DH16-1,0) -> 10 | DJ16: =IF(CZ16="PROYECTO",IF(DG16="NOR",IF(DI16>8,8,DI16),0),IF(DG16="NOR",IF(DI16>8,8,DI16),0)) -> 8 | DK16: =IF(DG16="NOR",IF(DI16>10,2,IF(DI16>8,(DI16-DJ16),0)),0) -> 2 | DL16: =IF(DG16="NOR",IF(DI16<10,0,IF(DI16>10,(DI16-(DJ16+DK16)),0)),0) -> 0 | DM16: =IF(DG16="DOM",DI16,0) -> 0 | DN16: 7 | DO16: 18 | DP16: NOR | DQ16: =SUM(DO16-DN16) -> 11 | DR16: =IF(DQ16>1,DQ16-1,0) -> 10 | DS16: =IF(D16="STAFF",IF(DP16="NOR",IF(DR16>8.5,8.5,DR16),0),IF(DP16="NOR",IF(DR16>8,8,DR16),IF(DQ16="CAMPO",IF(DP16="NOR",IF(DR16>8,8,DR16),0),IF(DP16="NOR",IF(DR16>8,8,DR16),0)))) -> 8 | DT16: =IF(DP16="NOR",IF(DR16>10,2,IF(DR16>8,(DR16-DS16),0)),0) -> 2 | DU16: =IF(DP16="NOR",IF(DR16<10,0,IF(DR16>10,(DR16-(DS16+DT16)),0)),0) -> 0 | DV16: =IF(DP16="DOM",DR16,0) -> 0 | DW16: 7 | DX16: 18 | DY16: NOR | DZ16: =SUM(DX16-DW16) -> 11 | EA16: =IF(DZ16>1,DZ16-1,0) -> 10 | EB16: =IF(D16="STAFF",IF(DY16="NOR",IF(EA16>8.5,8.5,EA16),0),IF(DY16="NOR",IF(EA16>8,8,EA16),IF(DZ16="CAMPO",IF(DY16="NOR",IF(EA16>8,8,EA16),0),IF(DY16="NOR",IF(EA16>8,8,EA16),0)))) -> 8 | EC16: =IF(DY16="NOR",IF(EA16>10,2,IF(EA16>8,(EA16-EB16),0)),0) -> 2 | ED16: =IF(DY16="NOR",IF(EA16<10,0,IF(EA16>10,(EA16-(EB16+EC16)),0)),0) -> 0 | EE16: =IF(DY16="DOM",EA16,0) -> 0 | EF16: 7 | EG16: 18 | EH16: NOR | EI16: =SUM(EG16-EF16) -> 11 | EJ16: =IF(EI16>1,EI16-1,0) -> 10 | EK16: =IF(D16="STAFF",IF(EH16="NOR",IF(EJ16>8.5,8.5,EJ16),0),IF(EH16="NOR",IF(EJ16>8,8,EJ16),IF(EI16="CAMPO",IF(EH16="NOR",IF(EJ16>8,8,EJ16),0),IF(EH16="NOR",IF(EJ16>8,8,EJ16),0)))) -> 8 | EL16: =IF(EH16="NOR",IF(EJ16>10,2,IF(EJ16>8,(EJ16-EK16),0)),0) -> 2 | EM16: =IF(EH16="NOR",IF(EJ16<10,0,IF(EJ16>10,(EJ16-(EK16+EL16)),0)),0) -> 0 | EN16: =IF(EH16="DOM",EJ16,0) -> 0 | EO16: 0 | EP16: 0 | EQ16: DS | ER16: =SUM(EP16-EO16) -> 0 | ES16: =IF(ER16>1,ER16-1,0) -> 0 | ET16: =IF(D16="STAFF",IF(EQ16="NOR",IF(ES16>8.5,8.5,ES16),0),IF(EQ16="NOR",IF(ES16>8,8,ES16),IF(ER16="CAMPO",IF(EQ16="NOR",IF(ES16>8,8,ES16),0),IF(EQ16="NOR",IF(ES16>8,8,ES16),0)))) -> 0 | EU16: =IF(EQ16="NOR",IF(ES16>10,2,IF(ES16>8,(ES16-ET16),0)),0) -> 0 | EV16: =IF(EQ16="NOR",IF(ES16<10,0,IF(ES16>10,(ES16-(ET16+EU16)),0)),0) -> 0 | EW16: =IF(EQ16="DOM",ES16,0) -> 0 | EX16: 7 | EY16: 18 | EZ16: NOR | FA16: =SUM(EY16-EX16) -> 11 | FB16: =IF(FA16>1,FA16-1,0) -> 10 | FC16: =IF(D16="STAFF",IF(EZ16="NOR",IF(FB16>8.5,8.5,FB16),0),IF(EZ16="NOR",IF(FB16>8,8,FB16),IF(FA16="CAMPO",IF(EZ16="NOR",IF(FB16>8,8,FB16),0),IF(EZ16="NOR",IF(FB16>8,8,FB16),0)))) -> 8 | FD16: =IF(EZ16="NOR",IF(FB16>10,2,IF(FB16>8,(FB16-FC16),0)),0) -> 2 | FE16: =IF(EZ16="NOR",IF(FB16<10,0,IF(FB16>10,(FB16-(FC16+FD16)),0)),0) -> 0 | FF16: =IF(EZ16="DOM",FB16,0) -> 0 | FG16: 7 | FH16: 18 | FI16: NOR | FJ16: =SUM(FH16-FG16) -> 11 | FK16: =IF(FJ16>1,FJ16-1,0) -> 10 | FL16: =IF(D16="STAFF",IF(FI16="NOR",IF(FK16>8.5,8.5,FK16),0),IF(FI16="NOR",IF(FK16>8,8,FK16),IF(FJ16="CAMPO",IF(FI16="NOR",IF(FK16>8,8,FK16),0),IF(FI16="NOR",IF(FK16>8,8,FK16),0)))) -> 8 | FM16: =IF(FI16="NOR",IF(FK16>10,2,IF(FK16>8,(FK16-FL16),0)),0) -> 2 | FN16: =IF(FI16="NOR",IF(FK16<10,0,IF(FK16>10,(FK16-(FL16+FM16)),0)),0) -> 0 | FO16: =IF(FI16="DOM",FK16,0) -> 0 | FP16: 7 | FQ16: 18 | FR16: NOR | FS16: =SUM(FQ16-FP16) -> 11 | FT16: =IF(FS16>1,FS16-1,0) -> 10 | FU16: =IF(FK16="PROYECTO",IF(FR16="NOR",IF(FT16>8,8,FT16),0),IF(FR16="NOR",IF(FT16>8,8,FT16),0)) -> 8 | FV16: =IF(FR16="NOR",IF(FT16>10,2,IF(FT16>8,(FT16-FU16),0)),0) -> 2 | FW16: =IF(FR16="NOR",IF(FT16<10,0,IF(FT16>10,(FT16-(FU16+FV16)),0)),0) -> 0 | FX16: =IF(FR16="DOM",FT16,0) -> 0 | FY16: 7 | FZ16: 18 | GA16: NOR | GB16: =SUM(FZ16-FY16) -> 11 | GC16: =IF(GB16>1,GB16-1,0) -> 10 | GD16: =IF(D16="STAFF",IF(GA16="NOR",IF(GC16>8.5,8.5,GC16),0),IF(GA16="NOR",IF(GC16>8,8,GC16),IF(GB16="CAMPO",IF(GA16="NOR",IF(GC16>8,8,GC16),0),IF(GA16="NOR",IF(GC16>8,8,GC16),0)))) -> 8 | GE16: =IF(GA16="NOR",IF(GC16>10,2,IF(GC16>8,(GC16-GD16),0)),0) -> 2 | GF16: =IF(GA16="NOR",IF(GC16<10,0,IF(GC16>10,(GC16-(GD16+GE16)),0)),0) -> 0 | GG16: =IF(GA16="DOM",GC16,0) -> 0 | GH16: 7 | GI16: 18 | GJ16: NOR | GK16: =SUM(GI16-GH16) -> 11 | GL16: =IF(GK16>1,GK16-1,0) -> 10 | GM16: =IF(D16="STAFF",IF(GJ16="NOR",IF(GL16>8.5,8.5,GL16),0),IF(GJ16="NOR",IF(GL16>8,8,GL16),IF(GK16="CAMPO",IF(GJ16="NOR",IF(GL16>8,8,GL16),0),IF(GJ16="NOR",IF(GL16>8,8,GL16),0)))) -> 8 | GN16: =IF(GJ16="NOR",IF(GL16>10,2,IF(GL16>8,(GL16-GM16),0)),0) -> 2 | GO16: =IF(GJ16="NOR",IF(GL16<10,0,IF(GL16>10,(GL16-(GM16+GN16)),0)),0) -> 0 | GP16: =IF(GJ16="DOM",GL16,0) -> 0 | GQ16: 7 | GR16: 18 | GS16: NOR | GT16: =SUM(GR16-GQ16) -> 11 | GU16: =IF(GT16>1,GT16-1,0) -> 10 | GV16: =IF(D16="STAFF",IF(GS16="NOR",IF(GU16>8.5,8.5,GU16),0),IF(GS16="NOR",IF(GU16>8,8,GU16),IF(GT16="CAMPO",IF(GS16="NOR",IF(GU16>8,8,GU16),0),IF(GS16="NOR",IF(GU16>8,8,GU16),0)))) -> 8 | GW16: =IF(GS16="NOR",IF(GU16>10,2,IF(GU16>8,(GU16-GV16),0)),0) -> 2 | GX16: =IF(GS16="NOR",IF(GU16<10,0,IF(GU16>10,(GU16-(GV16+GW16)),0)),0) -> 0 | GY16: =IF(GS16="DOM",GU16,0) -> 0 | GZ16: 0 | HA16: 0 | HB16: DS | HC16: =SUM(HA16-GZ16) -> 0 | HD16: =IF(HC16>1,HC16-1,0) -> 0 | HE16: =IF(D16="STAFF",IF(HB16="NOR",IF(HD16>8.5,8.5,HD16),0),IF(HB16="NOR",IF(HD16>8,8,HD16),IF(HC16="CAMPO",IF(HB16="NOR",IF(HD16>8,8,HD16),0),IF(HB16="NOR",IF(HD16>8,8,HD16),0)))) -> 0 | HF16: =IF(HB16="NOR",IF(HD16>10,2,IF(HD16>8,(HD16-HE16),0)),0) -> 0 | HG16: =IF(HB16="NOR",IF(HD16<10,0,IF(HD16>10,(HD16-(HE16+HF16)),0)),0) -> 0 | HH16: =IF(HB16="DOM",HD16,0) -> 0 | HI16: 7 | HJ16: 18 | HK16: NOR | HL16: =SUM(HJ16-HI16) -> 11 | HM16: =IF(HL16>1,HL16-1,0) -> 10 | HN16: =IF(D16="STAFF",IF(HK16="NOR",IF(HM16>8.5,8.5,HM16),0),IF(HK16="NOR",IF(HM16>8,8,HM16),IF(HL16="CAMPO",IF(HK16="NOR",IF(HM16>8,8,HM16),0),IF(HK16="NOR",IF(HM16>8,8,HM16),0)))) -> 8 | HO16: =IF(HK16="NOR",IF(HM16>10,2,IF(HM16>8,(HM16-HN16),0)),0) -> 2 | HP16: =IF(HK16="NOR",IF(HM16<10,0,IF(HM16>10,(HM16-(HN16+HO16)),0)),0) -> 0 | HQ16: =IF(HK16="DOM",HM16,0) -> 0 | HR16: 7 | HS16: 18 | HT16: NOR | HU16: =SUM(HS16-HR16) -> 11 | HV16: =IF(HU16>1,HU16-1,0) -> 10 | HW16: =IF(D16="STAFF",IF(HT16="NOR",IF(HV16>8.5,8.5,HV16),0),IF(HT16="NOR",IF(HV16>8,8,HV16),IF(HU16="CAMPO",IF(HT16="NOR",IF(HV16>8,8,HV16),0),IF(HT16="NOR",IF(HV16>8,8,HV16),0)))) -> 8 | HX16: =IF(HT16="NOR",IF(HV16>10,2,IF(HV16>8,(HV16-HW16),0)),0) -> 2 | HY16: =IF(HT16="NOR",IF(HV16<10,0,IF(HV16>10,(HV16-(HW16+HX16)),0)),0) -> 0 | HZ16: =IF(HT16="DOM",HV16,0) -> 0 | IA16: 7 | IB16: 18 | IC16: NOR | ID16: =SUM(IB16-IA16) -> 11 | IE16: =IF(ID16>1,ID16-1,0) -> 10 | IF16: =IF(D16="STAFF",IF(IC16="NOR",IF(IE16>8.5,8.5,IE16),0),IF(IC16="NOR",IF(IE16>8,8,IE16),IF(ID16="CAMPO",IF(IC16="NOR",IF(IE16>8,8,IE16),0),IF(IC16="NOR",IF(IE16>8,8,IE16),0)))) -> 8 | IG16: =IF(IC16="NOR",IF(IE16>10,2,IF(IE16>8,(IE16-IF16),0)),0) -> 2 | IH16: =IF(IC16="NOR",IF(IE16<10,0,IF(IE16>10,(IE16-(IF16+IG16)),0)),0) -> 0 | II16: =IF(IC16="DOM",IE16,0) -> 0 | IJ16: 7 | IK16: 18 | IL16: NOR | IM16: =SUM(IK16-IJ16) -> 11 | IN16: =IF(IM16>1,IM16-1,0) -> 10 | IO16: =IF(D16="STAFF",IF(IL16="NOR",IF(IN16>8.5,8.5,IN16),0),IF(IL16="NOR",IF(IN16>8,8,IN16),IF(IM16="CAMPO",IF(IL16="NOR",IF(IN16>8,8,IN16),0),IF(IL16="NOR",IF(IN16>8,8,IN16),0)))) -> 8 | IP16: =IF(IL16="NOR",IF(IN16>10,2,IF(IN16>8,(IN16-IO16),0)),0) -> 2 | IQ16: =IF(IL16="NOR",IF(IN16<10,0,IF(IN16>10,(IN16-(IO16+IP16)),0)),0) -> 0 | IR16: =IF(IL16="DOM",IN16,0) -> 0 | IS16: 7 | IT16: 18 | IU16: NOR | IV16: =SUM(IT16-IS16) -> 11 | IW16: =IF(IV16>1,IV16-1,0) -> 10 | IX16: =IF(D16="STAFF",IF(IU16="NOR",IF(IW16>8.5,8.5,IW16),0),IF(IU16="NOR",IF(IW16>8,8,IW16),IF(IV16="CAMPO",IF(IU16="NOR",IF(IW16>8,8,IW16),0),IF(IU16="NOR",IF(IW16>8,8,IW16),0)))) -> 8 | IY16: =IF(IU16="NOR",IF(IW16>10,2,IF(IW16>8,(IW16-IX16),0)),0) -> 2 | IZ16: =IF(IU16="NOR",IF(IW16<10,0,IF(IW16>10,(IW16-(IX16+IY16)),0)),0) -> 0 | JA16: =IF(IU16="DOM",IW16,0) -> 0 | JB16: 7 | JC16: 18 | JD16: NOR | JE16: =SUM(JC16-JB16) -> 11 | JF16: =IF(JE16>1,JE16-1,0) -> 10 | JG16: =IF(D16="STAFF",IF(JD16="NOR",IF(JF16>8.5,8.5,JF16),0),IF(JD16="NOR",IF(JF16>8,8,JF16),IF(JE16="CAMPO",IF(JD16="NOR",IF(JF16>8,8,JF16),0),IF(JD16="NOR",IF(JF16>8,8,JF16),0)))) -> 8 | JH16: =IF(JD16="NOR",IF(JF16>10,2,IF(JF16>8,(JF16-JG16),0)),0) -> 2 | JI16: =IF(JD16="NOR",IF(JF16<10,0,IF(JF16>10,(JF16-(JG16+JH16)),0)),0) -> 0 | JJ16: =IF(JD16="DOM",JF16,0) -> 0 | JK16: 0 | JL16: 0 | JM16: DS | JN16: =SUM(JL16-JK16) -> 0 | JO16: =IF(JN16>1,JN16-1,0) -> 0 | JP16: =IF(D16="STAFF",IF(JM16="NOR",IF(JO16>8.5,8.5,JO16),0),IF(JM16="NOR",IF(JO16>8,8,JO16),IF(JN16="CAMPO",IF(JM16="NOR",IF(JO16>8,8,JO16),0),IF(JM16="NOR",IF(JO16>8,8,JO16),0)))) -> 0 | JQ16: =IF(JM16="NOR",IF(JO16>10,2,IF(JO16>8,(JO16-JP16),0)),0) -> 0 | JR16: =IF(JM16="NOR",IF(JO16<10,0,IF(JO16>10,(JO16-(JP16+JQ16)),0)),0) -> 0 | JS16: =IF(JM16="DOM",JO16,0) -> 0 | JT16: 7 | JU16: 18 | JV16: NOR | JW16: =SUM(JU16-JT16) -> 11 | JX16: =IF(JW16>1,JW16-1,0) -> 10 | JY16: =IF(D16="STAFF",IF(JV16="NOR",IF(JX16>8.5,8.5,JX16),0),IF(JV16="NOR",IF(JX16>8,8,JX16),IF(JW16="CAMPO",IF(JV16="NOR",IF(JX16>8,8,JX16),0),IF(JV16="NOR",IF(JX16>8,8,JX16),0)))) -> 8 | JZ16: =IF(JV16="NOR",IF(JX16>10,2,IF(JX16>8,(JX16-JY16),0)),0) -> 2 | KA16: =IF(JV16="NOR",IF(JX16<10,0,IF(JX16>10,(JX16-(JY16+JZ16)),0)),0) -> 0 | KB16: =IF(JV16="DOM",JX16,0) -> 0 | KC16: 7 | KD16: 16 | KE16: NOR | KF16: =SUM(KD16-KC16) -> 9 | KG16: =IF(KF16>1,KF16-1,0) -> 8 | KH16: =IF(D16="STAFF",IF(KE16="NOR",IF(KG16>8.5,8.5,KG16),0),IF(KE16="NOR",IF(KG16>8,8,KG16),IF(KF16="CAMPO",IF(KE16="NOR",IF(KG16>8,8,KG16),0),IF(KE16="NOR",IF(KG16>8,8,KG16),0)))) -> 8 | KI16: =IF(KE16="NOR",IF(KG16>10,2,IF(KG16>8,(KG16-KH16),0)),0) -> 0 | KJ16: =IF(KE16="NOR",IF(KG16<10,0,IF(KG16>10,(KG16-(KH16+KI16)),0)),0) -> 0 | KK16: =IF(KE16="DOM",KG16,0) -> 0 | KL16: 7 | KM16: 16 | KN16: NOR | KO16: =SUM(KM16-KL16) -> 9 | KP16: =IF(KO16>1,KO16-1,0) -> 8 | KQ16: =IF(D16="STAFF",IF(KN16="NOR",IF(KP16>8.5,8.5,KP16),0),IF(KN16="NOR",IF(KP16>8,8,KP16),IF(KO16="CAMPO",IF(KN16="NOR",IF(KP16>8,8,KP16),0),IF(KN16="NOR",IF(KP16>8,8,KP16),0)))) -> 8 | KR16: =IF(KN16="NOR",IF(KP16>10,2,IF(KP16>8,(KP16-KQ16),0)),0) -> 0 | KS16: =IF(KN16="NOR",IF(KP16<10,0,IF(KP16>10,(KP16-(KQ16+KR16)),0)),0) -> 0 | KT16: =IF(KN16="DOM",KP16,0) -> 0 | KU16: 7 | KV16: 16 | KW16: NOR | KX16: =SUM(KV16-KU16) -> 9 | KY16: =IF(KX16>1,KX16-1,0) -> 8 | KZ16: =IF(D16="STAFF",IF(KW16="NOR",IF(KY16>8.5,8.5,KY16),0),IF(KW16="NOR",IF(KY16>8,8,KY16),IF(KX16="CAMPO",IF(KW16="NOR",IF(KY16>8,8,KY16),0),IF(KW16="NOR",IF(KY16>8,8,KY16),0)))) -> 8 | LA16: =IF(KW16="NOR",IF(KY16>10,2,IF(KY16>8,(KY16-KZ16),0)),0) -> 0 | LB16: =IF(KW16="NOR",IF(KY16<10,0,IF(KY16>10,(KY16-(KZ16+LA16)),0)),0) -> 0 | LC16: =IF(KW16="DOM",KY16,0) -> 0 | LD16: 7 | LE16: 16 | LF16: NOR | LG16: =SUM(LE16-LD16) -> 9 | LH16: =IF(LG16>1,LG16-1,0) -> 8 | LI16: =IF(D16="STAFF",IF(LF16="NOR",IF(LH16>8.5,8.5,LH16),0),IF(LF16="NOR",IF(LH16>8,8,LH16),IF(LG16="CAMPO",IF(LF16="NOR",IF(LH16>8,8,LH16),0),IF(LF16="NOR",IF(LH16>8,8,LH16),0)))) -> 8 | LJ16: =IF(LF16="NOR",IF(LH16>10,2,IF(LH16>8,(LH16-LI16),0)),0) -> 0 | LK16: =IF(LF16="NOR",IF(LH16<10,0,IF(LH16>10,(LH16-(LI16+LJ16)),0)),0) -> 0 | LL16: =IF(LF16="DOM",LH16,0) -> 0 | LM16: 7 | LN16: 16 | LO16: NOR | LP16: =SUM(LN16-LM16) -> 9 | LQ16: =IF(LP16>1,LP16-1,0) -> 8 | LR16: =IF(D16="STAFF",IF(LO16="NOR",IF(LQ16>8.5,8.5,LQ16),0),IF(LO16="NOR",IF(LQ16>8,8,LQ16),IF(LP16="CAMPO",IF(LO16="NOR",IF(LQ16>8,8,LQ16),0),IF(LO16="NOR",IF(LQ16>8,8,LQ16),0)))) -> 8 | LS16: =IF(LO16="NOR",IF(LQ16>10,2,IF(LQ16>8,(LQ16-LR16),0)),0) -> 0 | LT16: =IF(LO16="NOR",IF(LQ16<10,0,IF(LQ16>10,(LQ16-(LR16+LS16)),0)),0) -> 0 | LU16: =IF(LO16="DOM",LQ16,0) -> 0 | LV16: 7 | LW16: 16 | LX16: NOR | LY16: =SUM(LW16-LV16) -> 9 | LZ16: =IF(LY16>1,LY16-1,0) -> 8 | MA16: =IF(D16="STAFF",IF(LX16="NOR",IF(LZ16>8.5,8.5,LZ16),0),IF(LX16="NOR",IF(LZ16>8,8,LZ16),IF(LY16="CAMPO",IF(LX16="NOR",IF(LZ16>8,8,LZ16),0),IF(LX16="NOR",IF(LZ16>8,8,LZ16),0)))) -> 8 | MB16: =IF(LX16="NOR",IF(LZ16>10,2,IF(LZ16>8,(LZ16-MA16),0)),0) -> 0 | MC16: =IF(LX16="NOR",IF(LZ16<10,0,IF(LZ16>10,(LZ16-(MA16+MB16)),0)),0) -> 0 | MD16: =IF(LX16="DOM",LZ16,0) -> 0 | ME16: 7 | MF16: 16 | MG16: NOR | MH16: =SUM(MF16-ME16) -> 9 | MI16: =IF(MH16>1,MH16-1,0) -> 8 | MJ16: =IF(D16="STAFF",IF(MG16="NOR",IF(MI16>8.5,8.5,MI16),0),IF(MG16="NOR",IF(MI16>8,8,MI16),IF(MH16="CAMPO",IF(MG16="NOR",IF(MI16>8,8,MI16),0),IF(MG16="NOR",IF(MI16>8,8,MI16),0)))) -> 8 | MK16: =IF(MG16="NOR",IF(MI16>10,2,IF(MI16>8,(MI16-MJ16),0)),0) -> 0 | ML16: =IF(MG16="NOR",IF(MI16<10,0,IF(MI16>10,(MI16-(MJ16+MK16)),0)),0) -> 0 | MM16: =IF(MG16="DOM",MI16,0) -> 0 | MN16: 7 | MO16: 16 | MP16: NOR | MQ16: =SUM(MO16-MN16) -> 9 | MR16: =IF(MQ16>1,MQ16-1,0) -> 8 | MS16: =IF(D16="STAFF",IF(MP16="NOR",IF(MR16>8.5,8.5,MR16),0),IF(MP16="NOR",IF(MR16>8,8,MR16),IF(MQ16="CAMPO",IF(MP16="NOR",IF(MR16>8,8,MR16),0),IF(MP16="NOR",IF(MR16>8,8,MR16),0)))) -> 8 | MT16: =IF(MP16="NOR",IF(MR16>10,2,IF(MR16>8,(MR16-MS16),0)),0) -> 0 | MU16: =IF(MP16="NOR",IF(MR16<10,0,IF(MR16>10,(MR16-(MS16+MT16)),0)),0) -> 0 | MV16: =IF(MP16="DOM",MR16,0) -> 0 | MW16: 7 | MX16: 16 | MY16: NOR | MZ16: =SUM(MX16-MW16) -> 9 | NA16: =IF(MZ16>1,MZ16-1,0) -> 8 | NB16: =IF(D16="STAFF",IF(MY16="NOR",IF(NA16>8.5,8.5,NA16),0),IF(MY16="NOR",IF(NA16>8,8,NA16),IF(MZ16="CAMPO",IF(MY16="NOR",IF(NA16>8,8,NA16),0),IF(MY16="NOR",IF(NA16>8,8,NA16),0)))) -> 8 | NC16: =IF(MY16="NOR",IF(NA16>10,2,IF(NA16>8,(NA16-NB16),0)),0) -> 0 | ND16: =IF(MY16="NOR",IF(NA16<10,0,IF(NA16>10,(NA16-(NB16+NC16)),0)),0) -> 0 | NE16: =IF(MY16="DOM",NA16,0) -> 0 | NF16: 7 | NG16: 16 | NH16: NOR | NI16: =SUM(NG16-NF16) -> 9 | NJ16: =IF(NI16>1,NI16-1,0) -> 8 | NK16: =IF(D16="STAFF",IF(NH16="NOR",IF(NJ16>8.5,8.5,NJ16),0),IF(NH16="NOR",IF(NJ16>8,8,NJ16),IF(NI16="CAMPO",IF(NH16="NOR",IF(NJ16>8,8,NJ16),0),IF(NH16="NOR",IF(NJ16>8,8,NJ16),0)))) -> 8 | NL16: =IF(NH16="NOR",IF(NJ16>10,2,IF(NJ16>8,(NJ16-NK16),0)),0) -> 0 | NM16: =IF(NH16="NOR",IF(NJ16<10,0,IF(NJ16>10,(NJ16-(NK16+NL16)),0)),0) -> 0 | NN16: =IF(NH16="DOM",NJ16,0) -> 0 | NO16: 7 | NP16: 16 | NQ16: NOR | NR16: =SUM(NP16-NO16) -> 9 | NS16: =IF(NR16>1,NR16-1,0) -> 8 | NT16: =IF(D16="STAFF",IF(NQ16="NOR",IF(NS16>8.5,8.5,NS16),0),IF(NQ16="NOR",IF(NS16>8,8,NS16),IF(NR16="CAMPO",IF(NQ16="NOR",IF(NS16>8,8,NS16),0),IF(NQ16="NOR",IF(NS16>8,8,NS16),0)))) -> 8 | NU16: =IF(NQ16="NOR",IF(NS16>10,2,IF(NS16>8,(NS16-NT16),0)),0) -> 0 | NV16: =IF(NQ16="NOR",IF(NS16<10,0,IF(NS16>10,(NS16-(NT16+NU16)),0)),0) -> 0 | NW16: =IF(NQ16="DOM",NS16,0) -> 0 | NX16: 7 | NY16: 16 | NZ16: NOR | OA16: =SUM(NY16-NX16) -> 9 | OB16: =IF(OA16>1,OA16-1,0) -> 8 | OC16: =IF(D16="STAFF",IF(NZ16="NOR",IF(OB16>8.5,8.5,OB16),0),IF(NZ16="NOR",IF(OB16>8,8,OB16),IF(OA16="CAMPO",IF(NZ16="NOR",IF(OB16>8,8,OB16),0),IF(NZ16="NOR",IF(OB16>8,8,OB16),0)))) -> 8 | OD16: =IF(NZ16="NOR",IF(OB16>10,2,IF(OB16>8,(OB16-OC16),0)),0) -> 0 | OE16: =IF(NZ16="NOR",IF(OB16<10,0,IF(OB16>10,(OB16-(OC16+OD16)),0)),0) -> 0 | OF16: =IF(NZ16="DOM",OB16,0) -> 0 | OG16: 0 | OH16: 0 | OI16: DS | OJ16: =SUM(OH16-OG16) -> 0 | OK16: =IF(OJ16>1,OJ16-1,0) -> 0 | OL16: =IF(D16="STAFF",IF(OI16="NOR",IF(OK16>8.5,8.5,OK16),0),IF(OI16="NOR",IF(OK16>8,8,OK16),IF(OJ16="CAMPO",IF(OI16="NOR",IF(OK16>8,8,OK16),0),IF(OI16="NOR",IF(OK16>8,8,OK16),0)))) -> 0 | OM16: =IF(OI16="NOR",IF(OK16>10,2,IF(OK16>8,(OK16-OL16),0)),0) -> 0 | ON16: =IF(OI16="NOR",IF(OK16<10,0,IF(OK16>10,(OK16-(OL16+OM16)),0)),0) -> 0 | OO16: =IF(OI16="DOM",OK16,0) -> 0 | OP16: 7 | OQ16: 16 | OR16: NOR | OS16: =SUM(OQ16-OP16) -> 9 | OT16: =IF(OS16>1,OS16-1,0) -> 8 | OU16: =IF(D16="STAFF",IF(OR16="NOR",IF(OT16>8.5,8.5,OT16),0),IF(OR16="NOR",IF(OT16>8,8,OT16),IF(OS16="CAMPO",IF(OR16="NOR",IF(OT16>8,8,OT16),0),IF(OR16="NOR",IF(OT16>8,8,OT16),0)))) -> 8 | OV16: =IF(OR16="NOR",IF(OT16>10,2,IF(OT16>8,(OT16-OU16),0)),0) -> 0 | OW16: =IF(OR16="NOR",IF(OT16<10,0,IF(OT16>10,(OT16-(OU16+OV16)),0)),0) -> 0 | OX16: =IF(OR16="DOM",OT16,0) -> 0 | OY16: 0 | OZ16: 0 | PA16: FE | PB16: =SUM(OZ16-OY16) -> 0 | PC16: =IF(PB16>1,PB16-1,0) -> 0 | PD16: =IF(D16="STAFF",IF(PA16="NOR",IF(PC16>8.5,8.5,PC16),0),IF(PA16="NOR",IF(PC16>8,8,PC16),IF(PB16="CAMPO",IF(PA16="NOR",IF(PC16>8,8,PC16),0),IF(PA16="NOR",IF(PC16>8,8,PC16),0)))) -> 0 | PE16: =IF(PA16="NOR",IF(PC16>10,2,IF(PC16>8,(PC16-PD16),0)),0) -> 0 | PF16: =IF(PA16="NOR",IF(PC16<10,0,IF(PC16>10,(PC16-(PD16+PE16)),0)),0) -> 0 | PG16: =IF(PA16="DOM",PC16,0) -> 0 | PH16: 7 | PI16: 16 | PJ16: NOR | PK16: =SUM(PI16-PH16) -> 9 | PL16: =IF(PK16>1,PK16-1,0) -> 8 | PM16: =IF(M16="STAFF",IF(PJ16="NOR",IF(PL16>8.5,8.5,PL16),0),IF(PJ16="NOR",IF(PL16>8,8,PL16),IF(PK16="CAMPO",IF(PJ16="NOR",IF(PL16>8,8,PL16),0),IF(PJ16="NOR",IF(PL16>8,8,PL16),0)))) -> 8 | PN16: =IF(PJ16="NOR",IF(PL16>10,2,IF(PL16>8,(PL16-PM16),0)),0) -> 0 | PO16: =IF(PJ16="NOR",IF(PL16<10,0,IF(PL16>10,(PL16-(PM16+PN16)),0)),0) -> 0 | PP16: =IF(PJ16="DOM",PL16,0) -> 0 | PR16: =COUNTIF(FG16:PP16,"NOR") -> 26 | PS16: =COUNTIF(FG16:PP16,"DS") -> 3 | PT16: =COUNTIF(FG16:PP16,"FE") -> 1 | PU16: =SUM(PR16:PT16) -> 30 | PV16: =COUNTIF(FG16:PP16,"DM") -> 0 | PY16: =COUNTIF(FG16:PP16,"SUB") -> 0 | QB16: =COUNTIF(FG16:PP16,"VA") -> 0 | QE16: =COUNTIF(FG16:PP16,"LSG") -> 0 | QH16: =COUNTIF(FG16:PP16,"LCG") -> 0 | QK16: =COUNTIF(FG16:PP16,"FA") -> 0 | QN16: =COUNTIF(J16:FF16,"FA") -> 0 | QQ16: =PU16+PV16+PY16+QB16+QE16+QH16+QK16+QN16 -> 30 | QS16: =P16+Y16++AH16+AQ16+AZ16+BI16+BR16+CA16+CJ16+CS16+DB16+DK16+DT16+EC16+EL16+EU16+FD16+FM16+FV16+GE16+GN16+GW16+HF16+HO16+HX16+IG16+IP16+IY16+JH16+JQ16+JZ16 -> 52 | QT16: =Q16+Z16++AI16+AR16+BA16+BJ16+BS16+CB16+CK16+CT16+DC16+DL16+DU16+ED16+EM16+EV16+FE16+FN16+FW16+GF16+GO16+GX16+HG16+HP16+HY16+IH16+IQ16+IZ16+JI16+JR16+KA16 -> 1 | RG16: 0
A17: =A16+1 -> 8 | B17: 47021678 | D17: PROYECTO | E17: GARCIA CANCHUMANI ARACELY MILAGROS | F17: VIGÍA | G17: 44319 | H17: 44330 | J17: 7 | K17: 18 | L17: NOR | M17: =SUM(K17-J17) -> 11 | N17: =IF(M17>1,M17-1,0) -> 10 | O17: =IF(D17="STAFF",IF(L17="NOR",IF(N17>8.5,8.5,N17),0),IF(L17="NOR",IF(N17>8,8,N17),IF(D17="CAMPO",IF(L17="NOR",IF(N17>8,8,N17),0),IF(L17="NOR",IF(N17>8,8,N17),0)))) -> 8 | P17: =IF(L17="NOR",IF(N17>10,2,IF(N17>8,(N17-O17),0)),0) -> 2 | Q17: =IF(L17="NOR",IF(N17<10,0,IF(N17>10,(N17-(O17+P17)),0)),0) -> 0 | R17: =IF(L17="DOM",N17,0) -> 0 | S17: 0 | T17: 0 | U17: DS | V17: =SUM(T17-S17) -> 0 | W17: =IF(V17>1,V17-1,0) -> 0 | X17: =IF(D17="STAFF",IF(U17="NOR",IF(W17>8.5,8.5,W17),0),IF(U17="NOR",IF(W17>8,8,W17),IF(M17="CAMPO",IF(U17="NOR",IF(W17>8,8,W17),0),IF(U17="NOR",IF(W17>8,8,W17),0)))) -> 0 | Y17: =IF(U17="NOR",IF(W17>10,2,IF(W17>8,(W17-X17),0)),0) -> 0 | Z17: =IF(U17="NOR",IF(W17<10,0,IF(W17>10,(W17-(X17+Y17)),0)),0) -> 0 | AA17: =IF(U17="DOM",W17,0) -> 0 | AB17: 7 | AC17: 18 | AD17: NOR | AE17: =SUM(AC17-AB17) -> 11 | AF17: =IF(AE17>1,AE17-1,0) -> 10 | AG17: =IF(D17="STAFF",IF(AD17="NOR",IF(AF17>8.5,8.5,AF17),0),IF(AD17="NOR",IF(AF17>8,8,AF17),IF(AE17="CAMPO",IF(AD17="NOR",IF(AF17>8,8,AF17),0),IF(AD17="NOR",IF(AF17>8,8,AF17),0)))) -> 8 | AH17: =IF(AD17="NOR",IF(AF17>10,2,IF(AF17>8,(AF17-AG17),0)),0) -> 2 | AI17: =IF(AD17="NOR",IF(AF17<10,0,IF(AF17>10,(AF17-(AG17+AH17)),0)),0) -> 0 | AJ17: =IF(AD17="DOM",AF17,0) -> 0 | AK17: 7 | AL17: 19 | AM17: NOR | AN17: =SUM(AL17-AK17) -> 12 | AO17: =IF(AN17>1,AN17-1,0) -> 11 | AP17: =IF(D17="PROYECTO",IF(AM17="NOR",IF(AO17>8,8,AO17),0),IF(AM17="NOR",IF(AO17>8,8,AO17),0)) -> 8 | AQ17: =IF(AM17="NOR",IF(AO17>10,2,IF(AO17>8,(AO17-AP17),0)),0) -> 2 | AR17: =IF(AM17="NOR",IF(AO17<10,0,IF(AO17>10,(AO17-(AP17+AQ17)),0)),0) -> 1 | AS17: =IF(AM17="DOM",AO17,0) -> 0 | AT17: 7 | AU17: 19 | AV17: NOR | AW17: =SUM(AU17-AT17) -> 12 | AX17: =IF(AW17>1,AW17-1,0) -> 11 | AY17: =IF(AO17="PROYECTO",IF(AV17="NOR",IF(AX17>8,8,AX17),0),IF(AV17="NOR",IF(AX17>8,8,AX17),0)) -> 8 | AZ17: =IF(AV17="NOR",IF(AX17>10,2,IF(AX17>8,(AX17-AY17),0)),0) -> 2 | BA17: =IF(AV17="NOR",IF(AX17<10,0,IF(AX17>10,(AX17-(AY17+AZ17)),0)),0) -> 1 | BB17: =IF(AV17="DOM",AX17,0) -> 0 | BC17: 7 | BD17: 19 | BE17: NOR | BF17: =SUM(BD17-BC17) -> 12 | BG17: =IF(BF17>1,BF17-1,0) -> 11 | BH17: =IF(D17="STAFF",IF(BE17="NOR",IF(BG17>8.5,8.5,BG17),0),IF(BE17="NOR",IF(BG17>8,8,BG17),IF(BF17="CAMPO",IF(BE17="NOR",IF(BG17>8,8,BG17),0),IF(BE17="NOR",IF(BG17>8,8,BG17),0)))) -> 8 | BI17: =IF(BE17="NOR",IF(BG17>10,2,IF(BG17>8,(BG17-BH17),0)),0) -> 2 | BJ17: =IF(BE17="NOR",IF(BG17<10,0,IF(BG17>10,(BG17-(BH17+BI17)),0)),0) -> 1 | BK17: =IF(BE17="DOM",BG17,0) -> 0 | BL17: 7 | BM17: 19 | BN17: NOR | BO17: =SUM(BM17-BL17) -> 12 | BP17: =IF(BO17>1,BO17-1,0) -> 11 | BQ17: =IF(D17="STAFF",IF(BN17="NOR",IF(BP17>8.5,8.5,BP17),0),IF(BN17="NOR",IF(BP17>8,8,BP17),IF(BO17="CAMPO",IF(BN17="NOR",IF(BP17>8,8,BP17),0),IF(BN17="NOR",IF(BP17>8,8,BP17),0)))) -> 8 | BR17: =IF(BN17="NOR",IF(BP17>10,2,IF(BP17>8,(BP17-BQ17),0)),0) -> 2 | BS17: =IF(BN17="NOR",IF(BP17<10,0,IF(BP17>10,(BP17-(BQ17+BR17)),0)),0) -> 1 | BT17: =IF(BN17="DOM",BP17,0) -> 0 | BU17: 7 | BV17: 18 | BW17: NOR | BX17: =SUM(BV17-BU17) -> 11 | BY17: =IF(BX17>1,BX17-1,0) -> 10 | BZ17: =IF(D17="STAFF",IF(BW17="NOR",IF(BY17>8.5,8.5,BY17),0),IF(BW17="NOR",IF(BY17>8,8,BY17),IF(BX17="CAMPO",IF(BW17="NOR",IF(BY17>8,8,BY17),0),IF(BW17="NOR",IF(BY17>8,8,BY17),0)))) -> 8 | CA17: =IF(BW17="NOR",IF(BY17>10,2,IF(BY17>8,(BY17-BZ17),0)),0) -> 2 | CB17: =IF(BW17="NOR",IF(BY17<10,0,IF(BY17>10,(BY17-(BZ17+CA17)),0)),0) -> 0 | CC17: =IF(BW17="DOM",BY17,0) -> 0 | CD17: 0 | CE17: 0 | CF17: DS | CG17: =SUM(CE17-CD17) -> 0 | CH17: =IF(CG17>1,CG17-1,0) -> 0 | CI17: =IF(D17="STAFF",IF(CF17="NOR",IF(CH17>8.5,8.5,CH17),0),IF(CF17="NOR",IF(CH17>8,8,CH17),IF(CG17="CAMPO",IF(CF17="NOR",IF(CH17>8,8,CH17),0),IF(CF17="NOR",IF(CH17>8,8,CH17),0)))) -> 0 | CJ17: =IF(CF17="NOR",IF(CH17>10,2,IF(CH17>8,(CH17-CI17),0)),0) -> 0 | CK17: =IF(CF17="NOR",IF(CH17<10,0,IF(CH17>10,(CH17-(CI17+CJ17)),0)),0) -> 0 | CL17: =IF(CF17="DOM",CH17,0) -> 0 | CM17: 7 | CN17: 19 | CO17: NOR | CP17: =SUM(CN17-CM17) -> 12 | CQ17: =IF(CP17>1,CP17-1,0) -> 11 | CR17: =IF(D17="STAFF",IF(CO17="NOR",IF(CQ17>8.5,8.5,CQ17),0),IF(CO17="NOR",IF(CQ17>8,8,CQ17),IF(CP17="CAMPO",IF(CO17="NOR",IF(CQ17>8,8,CQ17),0),IF(CO17="NOR",IF(CQ17>8,8,CQ17),0)))) -> 8 | CS17: =IF(CO17="NOR",IF(CQ17>10,2,IF(CQ17>8,(CQ17-CR17),0)),0) -> 2 | CT17: =IF(CO17="NOR",IF(CQ17<10,0,IF(CQ17>10,(CQ17-(CR17+CS17)),0)),0) -> 1 | CU17: =IF(CO17="DOM",CQ17,0) -> 0 | CV17: 7 | CW17: 19 | CX17: NOR | CY17: =SUM(CW17-CV17) -> 12 | CZ17: =IF(CY17>1,CY17-1,0) -> 11 | DA17: =IF(CQ17="PROYECTO",IF(CX17="NOR",IF(CZ17>8,8,CZ17),0),IF(CX17="NOR",IF(CZ17>8,8,CZ17),0)) -> 8 | DB17: =IF(CX17="NOR",IF(CZ17>10,2,IF(CZ17>8,(CZ17-DA17),0)),0) -> 2 | DC17: =IF(CX17="NOR",IF(CZ17<10,0,IF(CZ17>10,(CZ17-(DA17+DB17)),0)),0) -> 1 | DD17: =IF(CX17="DOM",CZ17,0) -> 0 | DE17: 7 | DF17: 19 | DG17: NOR | DH17: =SUM(DF17-DE17) -> 12 | DI17: =IF(DH17>1,DH17-1,0) -> 11 | DJ17: =IF(CZ17="PROYECTO",IF(DG17="NOR",IF(DI17>8,8,DI17),0),IF(DG17="NOR",IF(DI17>8,8,DI17),0)) -> 8 | DK17: =IF(DG17="NOR",IF(DI17>10,2,IF(DI17>8,(DI17-DJ17),0)),0) -> 2 | DL17: =IF(DG17="NOR",IF(DI17<10,0,IF(DI17>10,(DI17-(DJ17+DK17)),0)),0) -> 1 | DM17: =IF(DG17="DOM",DI17,0) -> 0 | DN17: 7 | DO17: 19 | DP17: NOR | DQ17: =SUM(DO17-DN17) -> 12 | DR17: =IF(DQ17>1,DQ17-1,0) -> 11 | DS17: =IF(D17="STAFF",IF(DP17="NOR",IF(DR17>8.5,8.5,DR17),0),IF(DP17="NOR",IF(DR17>8,8,DR17),IF(DQ17="CAMPO",IF(DP17="NOR",IF(DR17>8,8,DR17),0),IF(DP17="NOR",IF(DR17>8,8,DR17),0)))) -> 8 | DT17: =IF(DP17="NOR",IF(DR17>10,2,IF(DR17>8,(DR17-DS17),0)),0) -> 2 | DU17: =IF(DP17="NOR",IF(DR17<10,0,IF(DR17>10,(DR17-(DS17+DT17)),0)),0) -> 1 | DV17: =IF(DP17="DOM",DR17,0) -> 0 | DW17: 7 | DX17: 19 | DY17: NOR | DZ17: =SUM(DX17-DW17) -> 12 | EA17: =IF(DZ17>1,DZ17-1,0) -> 11 | EB17: =IF(D17="STAFF",IF(DY17="NOR",IF(EA17>8.5,8.5,EA17),0),IF(DY17="NOR",IF(EA17>8,8,EA17),IF(DZ17="CAMPO",IF(DY17="NOR",IF(EA17>8,8,EA17),0),IF(DY17="NOR",IF(EA17>8,8,EA17),0)))) -> 8 | EC17: =IF(DY17="NOR",IF(EA17>10,2,IF(EA17>8,(EA17-EB17),0)),0) -> 2 | ED17: =IF(DY17="NOR",IF(EA17<10,0,IF(EA17>10,(EA17-(EB17+EC17)),0)),0) -> 1 | EE17: =IF(DY17="DOM",EA17,0) -> 0 | EF17: 7 | EG17: 18 | EH17: NOR | EI17: =SUM(EG17-EF17) -> 11 | EJ17: =IF(EI17>1,EI17-1,0) -> 10 | EK17: =IF(D17="STAFF",IF(EH17="NOR",IF(EJ17>8.5,8.5,EJ17),0),IF(EH17="NOR",IF(EJ17>8,8,EJ17),IF(EI17="CAMPO",IF(EH17="NOR",IF(EJ17>8,8,EJ17),0),IF(EH17="NOR",IF(EJ17>8,8,EJ17),0)))) -> 8 | EL17: =IF(EH17="NOR",IF(EJ17>10,2,IF(EJ17>8,(EJ17-EK17),0)),0) -> 2 | EM17: =IF(EH17="NOR",IF(EJ17<10,0,IF(EJ17>10,(EJ17-(EK17+EL17)),0)),0) -> 0 | EN17: =IF(EH17="DOM",EJ17,0) -> 0 | EO17: 0 | EP17: 0 | EQ17: DS | ER17: =SUM(EP17-EO17) -> 0 | ES17: =IF(ER17>1,ER17-1,0) -> 0 | ET17: =IF(D17="STAFF",IF(EQ17="NOR",IF(ES17>8.5,8.5,ES17),0),IF(EQ17="NOR",IF(ES17>8,8,ES17),IF(ER17="CAMPO",IF(EQ17="NOR",IF(ES17>8,8,ES17),0),IF(EQ17="NOR",IF(ES17>8,8,ES17),0)))) -> 0 | EU17: =IF(EQ17="NOR",IF(ES17>10,2,IF(ES17>8,(ES17-ET17),0)),0) -> 0 | EV17: =IF(EQ17="NOR",IF(ES17<10,0,IF(ES17>10,(ES17-(ET17+EU17)),0)),0) -> 0 | EW17: =IF(EQ17="DOM",ES17,0) -> 0 | EX17: 7 | EY17: 18 | EZ17: NOR | FA17: =SUM(EY17-EX17) -> 11 | FB17: =IF(FA17>1,FA17-1,0) -> 10 | FC17: =IF(D17="STAFF",IF(EZ17="NOR",IF(FB17>8.5,8.5,FB17),0),IF(EZ17="NOR",IF(FB17>8,8,FB17),IF(FA17="CAMPO",IF(EZ17="NOR",IF(FB17>8,8,FB17),0),IF(EZ17="NOR",IF(FB17>8,8,FB17),0)))) -> 8 | FD17: =IF(EZ17="NOR",IF(FB17>10,2,IF(FB17>8,(FB17-FC17),0)),0) -> 2 | FE17: =IF(EZ17="NOR",IF(FB17<10,0,IF(FB17>10,(FB17-(FC17+FD17)),0)),0) -> 0 | FF17: =IF(EZ17="DOM",FB17,0) -> 0 | FG17: 7 | FH17: 18 | FI17: NOR | FJ17: =SUM(FH17-FG17) -> 11 | FK17: =IF(FJ17>1,FJ17-1,0) -> 10 | FL17: =IF(D17="STAFF",IF(FI17="NOR",IF(FK17>8.5,8.5,FK17),0),IF(FI17="NOR",IF(FK17>8,8,FK17),IF(FJ17="CAMPO",IF(FI17="NOR",IF(FK17>8,8,FK17),0),IF(FI17="NOR",IF(FK17>8,8,FK17),0)))) -> 8 | FM17: =IF(FI17="NOR",IF(FK17>10,2,IF(FK17>8,(FK17-FL17),0)),0) -> 2 | FN17: =IF(FI17="NOR",IF(FK17<10,0,IF(FK17>10,(FK17-(FL17+FM17)),0)),0) -> 0 | FO17: =IF(FI17="DOM",FK17,0) -> 0 | FP17: 7 | FQ17: 18 | FR17: NOR | FS17: =SUM(FQ17-FP17) -> 11 | FT17: =IF(FS17>1,FS17-1,0) -> 10 | FU17: =IF(FK17="PROYECTO",IF(FR17="NOR",IF(FT17>8,8,FT17),0),IF(FR17="NOR",IF(FT17>8,8,FT17),0)) -> 8 | FV17: =IF(FR17="NOR",IF(FT17>10,2,IF(FT17>8,(FT17-FU17),0)),0) -> 2 | FW17: =IF(FR17="NOR",IF(FT17<10,0,IF(FT17>10,(FT17-(FU17+FV17)),0)),0) -> 0 | FX17: =IF(FR17="DOM",FT17,0) -> 0 | FY17: 7 | FZ17: 18 | GA17: NOR | GB17: =SUM(FZ17-FY17) -> 11 | GC17: =IF(GB17>1,GB17-1,0) -> 10 | GD17: =IF(D17="STAFF",IF(GA17="NOR",IF(GC17>8.5,8.5,GC17),0),IF(GA17="NOR",IF(GC17>8,8,GC17),IF(GB17="CAMPO",IF(GA17="NOR",IF(GC17>8,8,GC17),0),IF(GA17="NOR",IF(GC17>8,8,GC17),0)))) -> 8 | GE17: =IF(GA17="NOR",IF(GC17>10,2,IF(GC17>8,(GC17-GD17),0)),0) -> 2 | GF17: =IF(GA17="NOR",IF(GC17<10,0,IF(GC17>10,(GC17-(GD17+GE17)),0)),0) -> 0 | GG17: =IF(GA17="DOM",GC17,0) -> 0 | GH17: 7 | GI17: 18 | GJ17: NOR | GK17: =SUM(GI17-GH17) -> 11 | GL17: =IF(GK17>1,GK17-1,0) -> 10 | GM17: =IF(D17="STAFF",IF(GJ17="NOR",IF(GL17>8.5,8.5,GL17),0),IF(GJ17="NOR",IF(GL17>8,8,GL17),IF(GK17="CAMPO",IF(GJ17="NOR",IF(GL17>8,8,GL17),0),IF(GJ17="NOR",IF(GL17>8,8,GL17),0)))) -> 8 | GN17: =IF(GJ17="NOR",IF(GL17>10,2,IF(GL17>8,(GL17-GM17),0)),0) -> 2 | GO17: =IF(GJ17="NOR",IF(GL17<10,0,IF(GL17>10,(GL17-(GM17+GN17)),0)),0) -> 0 | GP17: =IF(GJ17="DOM",GL17,0) -> 0 | GQ17: 7 | GR17: 18 | GS17: NOR | GT17: =SUM(GR17-GQ17) -> 11 | GU17: =IF(GT17>1,GT17-1,0) -> 10 | GV17: =IF(D17="STAFF",IF(GS17="NOR",IF(GU17>8.5,8.5,GU17),0),IF(GS17="NOR",IF(GU17>8,8,GU17),IF(GT17="CAMPO",IF(GS17="NOR",IF(GU17>8,8,GU17),0),IF(GS17="NOR",IF(GU17>8,8,GU17),0)))) -> 8 | GW17: =IF(GS17="NOR",IF(GU17>10,2,IF(GU17>8,(GU17-GV17),0)),0) -> 2 | GX17: =IF(GS17="NOR",IF(GU17<10,0,IF(GU17>10,(GU17-(GV17+GW17)),0)),0) -> 0 | GY17: =IF(GS17="DOM",GU17,0) -> 0 | GZ17: 0 | HA17: 0 | HB17: DS | HC17: =SUM(HA17-GZ17) -> 0 | HD17: =IF(HC17>1,HC17-1,0) -> 0 | HE17: =IF(D17="STAFF",IF(HB17="NOR",IF(HD17>8.5,8.5,HD17),0),IF(HB17="NOR",IF(HD17>8,8,HD17),IF(HC17="CAMPO",IF(HB17="NOR",IF(HD17>8,8,HD17),0),IF(HB17="NOR",IF(HD17>8,8,HD17),0)))) -> 0 | HF17: =IF(HB17="NOR",IF(HD17>10,2,IF(HD17>8,(HD17-HE17),0)),0) -> 0 | HG17: =IF(HB17="NOR",IF(HD17<10,0,IF(HD17>10,(HD17-(HE17+HF17)),0)),0) -> 0 | HH17: =IF(HB17="DOM",HD17,0) -> 0 | HI17: 7 | HJ17: 18 | HK17: NOR | HL17: =SUM(HJ17-HI17) -> 11 | HM17: =IF(HL17>1,HL17-1,0) -> 10 | HN17: =IF(D17="STAFF",IF(HK17="NOR",IF(HM17>8.5,8.5,HM17),0),IF(HK17="NOR",IF(HM17>8,8,HM17),IF(HL17="CAMPO",IF(HK17="NOR",IF(HM17>8,8,HM17),0),IF(HK17="NOR",IF(HM17>8,8,HM17),0)))) -> 8 | HO17: =IF(HK17="NOR",IF(HM17>10,2,IF(HM17>8,(HM17-HN17),0)),0) -> 2 | HP17: =IF(HK17="NOR",IF(HM17<10,0,IF(HM17>10,(HM17-(HN17+HO17)),0)),0) -> 0 | HQ17: =IF(HK17="DOM",HM17,0) -> 0 | HR17: 7 | HS17: 18 | HT17: NOR | HU17: =SUM(HS17-HR17) -> 11 | HV17: =IF(HU17>1,HU17-1,0) -> 10 | HW17: =IF(D17="STAFF",IF(HT17="NOR",IF(HV17>8.5,8.5,HV17),0),IF(HT17="NOR",IF(HV17>8,8,HV17),IF(HU17="CAMPO",IF(HT17="NOR",IF(HV17>8,8,HV17),0),IF(HT17="NOR",IF(HV17>8,8,HV17),0)))) -> 8 | HX17: =IF(HT17="NOR",IF(HV17>10,2,IF(HV17>8,(HV17-HW17),0)),0) -> 2 | HY17: =IF(HT17="NOR",IF(HV17<10,0,IF(HV17>10,(HV17-(HW17+HX17)),0)),0) -> 0 | HZ17: =IF(HT17="DOM",HV17,0) -> 0 | IA17: 0 | IB17: 0 | IC17: FA | ID17: =SUM(IB17-IA17) -> 0 | IE17: =IF(ID17>1,ID17-1,0) -> 0 | IF17: =IF(D17="STAFF",IF(IC17="NOR",IF(IE17>8.5,8.5,IE17),0),IF(IC17="NOR",IF(IE17>8,8,IE17),IF(ID17="CAMPO",IF(IC17="NOR",IF(IE17>8,8,IE17),0),IF(IC17="NOR",IF(IE17>8,8,IE17),0)))) -> 0 | IG17: =IF(IC17="NOR",IF(IE17>10,2,IF(IE17>8,(IE17-IF17),0)),0) -> 0 | IH17: =IF(IC17="NOR",IF(IE17<10,0,IF(IE17>10,(IE17-(IF17+IG17)),0)),0) -> 0 | II17: =IF(IC17="DOM",IE17,0) -> 0 | IJ17: 7 | IK17: 18 | IL17: NOR | IM17: =SUM(IK17-IJ17) -> 11 | IN17: =IF(IM17>1,IM17-1,0) -> 10 | IO17: =IF(D17="STAFF",IF(IL17="NOR",IF(IN17>8.5,8.5,IN17),0),IF(IL17="NOR",IF(IN17>8,8,IN17),IF(IM17="CAMPO",IF(IL17="NOR",IF(IN17>8,8,IN17),0),IF(IL17="NOR",IF(IN17>8,8,IN17),0)))) -> 8 | IP17: =IF(IL17="NOR",IF(IN17>10,2,IF(IN17>8,(IN17-IO17),0)),0) -> 2 | IQ17: =IF(IL17="NOR",IF(IN17<10,0,IF(IN17>10,(IN17-(IO17+IP17)),0)),0) -> 0 | IR17: =IF(IL17="DOM",IN17,0) -> 0 | IS17: 7 | IT17: 18 | IU17: NOR | IV17: =SUM(IT17-IS17) -> 11 | IW17: =IF(IV17>1,IV17-1,0) -> 10 | IX17: =IF(D17="STAFF",IF(IU17="NOR",IF(IW17>8.5,8.5,IW17),0),IF(IU17="NOR",IF(IW17>8,8,IW17),IF(IV17="CAMPO",IF(IU17="NOR",IF(IW17>8,8,IW17),0),IF(IU17="NOR",IF(IW17>8,8,IW17),0)))) -> 8 | IY17: =IF(IU17="NOR",IF(IW17>10,2,IF(IW17>8,(IW17-IX17),0)),0) -> 2 | IZ17: =IF(IU17="NOR",IF(IW17<10,0,IF(IW17>10,(IW17-(IX17+IY17)),0)),0) -> 0 | JA17: =IF(IU17="DOM",IW17,0) -> 0 | JB17: 7 | JC17: 18 | JD17: NOR | JE17: =SUM(JC17-JB17) -> 11 | JF17: =IF(JE17>1,JE17-1,0) -> 10 | JG17: =IF(D17="STAFF",IF(JD17="NOR",IF(JF17>8.5,8.5,JF17),0),IF(JD17="NOR",IF(JF17>8,8,JF17),IF(JE17="CAMPO",IF(JD17="NOR",IF(JF17>8,8,JF17),0),IF(JD17="NOR",IF(JF17>8,8,JF17),0)))) -> 8 | JH17: =IF(JD17="NOR",IF(JF17>10,2,IF(JF17>8,(JF17-JG17),0)),0) -> 2 | JI17: =IF(JD17="NOR",IF(JF17<10,0,IF(JF17>10,(JF17-(JG17+JH17)),0)),0) -> 0 | JJ17: =IF(JD17="DOM",JF17,0) -> 0 | JK17: 0 | JL17: 0 | JM17: DS | JN17: =SUM(JL17-JK17) -> 0 | JO17: =IF(JN17>1,JN17-1,0) -> 0 | JP17: =IF(D17="STAFF",IF(JM17="NOR",IF(JO17>8.5,8.5,JO17),0),IF(JM17="NOR",IF(JO17>8,8,JO17),IF(JN17="CAMPO",IF(JM17="NOR",IF(JO17>8,8,JO17),0),IF(JM17="NOR",IF(JO17>8,8,JO17),0)))) -> 0 | JQ17: =IF(JM17="NOR",IF(JO17>10,2,IF(JO17>8,(JO17-JP17),0)),0) -> 0 | JR17: =IF(JM17="NOR",IF(JO17<10,0,IF(JO17>10,(JO17-(JP17+JQ17)),0)),0) -> 0 | JS17: =IF(JM17="DOM",JO17,0) -> 0 | JT17: 7 | JU17: 19 | JV17: NOR | JW17: =SUM(JU17-JT17) -> 12 | JX17: =IF(JW17>1,JW17-1,0) -> 11 | JY17: =IF(D17="STAFF",IF(JV17="NOR",IF(JX17>8.5,8.5,JX17),0),IF(JV17="NOR",IF(JX17>8,8,JX17),IF(JW17="CAMPO",IF(JV17="NOR",IF(JX17>8,8,JX17),0),IF(JV17="NOR",IF(JX17>8,8,JX17),0)))) -> 8 | JZ17: =IF(JV17="NOR",IF(JX17>10,2,IF(JX17>8,(JX17-JY17),0)),0) -> 2 | KA17: =IF(JV17="NOR",IF(JX17<10,0,IF(JX17>10,(JX17-(JY17+JZ17)),0)),0) -> 1 | KB17: =IF(JV17="DOM",JX17,0) -> 0 | KC17: 7 | KD17: 16 | KE17: NOR | KF17: =SUM(KD17-KC17) -> 9 | KG17: =IF(KF17>1,KF17-1,0) -> 8 | KH17: =IF(D17="STAFF",IF(KE17="NOR",IF(KG17>8.5,8.5,KG17),0),IF(KE17="NOR",IF(KG17>8,8,KG17),IF(KF17="CAMPO",IF(KE17="NOR",IF(KG17>8,8,KG17),0),IF(KE17="NOR",IF(KG17>8,8,KG17),0)))) -> 8 | KI17: =IF(KE17="NOR",IF(KG17>10,2,IF(KG17>8,(KG17-KH17),0)),0) -> 0 | KJ17: =IF(KE17="NOR",IF(KG17<10,0,IF(KG17>10,(KG17-(KH17+KI17)),0)),0) -> 0 | KK17: =IF(KE17="DOM",KG17,0) -> 0 | KL17: 7 | KM17: 16 | KN17: NOR | KO17: =SUM(KM17-KL17) -> 9 | KP17: =IF(KO17>1,KO17-1,0) -> 8 | KQ17: =IF(D17="STAFF",IF(KN17="NOR",IF(KP17>8.5,8.5,KP17),0),IF(KN17="NOR",IF(KP17>8,8,KP17),IF(KO17="CAMPO",IF(KN17="NOR",IF(KP17>8,8,KP17),0),IF(KN17="NOR",IF(KP17>8,8,KP17),0)))) -> 8 | KR17: =IF(KN17="NOR",IF(KP17>10,2,IF(KP17>8,(KP17-KQ17),0)),0) -> 0 | KS17: =IF(KN17="NOR",IF(KP17<10,0,IF(KP17>10,(KP17-(KQ17+KR17)),0)),0) -> 0 | KT17: =IF(KN17="DOM",KP17,0) -> 0 | KU17: 7 | KV17: 16 | KW17: NOR | KX17: =SUM(KV17-KU17) -> 9 | KY17: =IF(KX17>1,KX17-1,0) -> 8 | KZ17: =IF(D17="STAFF",IF(KW17="NOR",IF(KY17>8.5,8.5,KY17),0),IF(KW17="NOR",IF(KY17>8,8,KY17),IF(KX17="CAMPO",IF(KW17="NOR",IF(KY17>8,8,KY17),0),IF(KW17="NOR",IF(KY17>8,8,KY17),0)))) -> 8 | LA17: =IF(KW17="NOR",IF(KY17>10,2,IF(KY17>8,(KY17-KZ17),0)),0) -> 0 | LB17: =IF(KW17="NOR",IF(KY17<10,0,IF(KY17>10,(KY17-(KZ17+LA17)),0)),0) -> 0 | LC17: =IF(KW17="DOM",KY17,0) -> 0 | LD17: 7 | LE17: 16 | LF17: NOR | LG17: =SUM(LE17-LD17) -> 9 | LH17: =IF(LG17>1,LG17-1,0) -> 8 | LI17: =IF(D17="STAFF",IF(LF17="NOR",IF(LH17>8.5,8.5,LH17),0),IF(LF17="NOR",IF(LH17>8,8,LH17),IF(LG17="CAMPO",IF(LF17="NOR",IF(LH17>8,8,LH17),0),IF(LF17="NOR",IF(LH17>8,8,LH17),0)))) -> 8 | LJ17: =IF(LF17="NOR",IF(LH17>10,2,IF(LH17>8,(LH17-LI17),0)),0) -> 0 | LK17: =IF(LF17="NOR",IF(LH17<10,0,IF(LH17>10,(LH17-(LI17+LJ17)),0)),0) -> 0 | LL17: =IF(LF17="DOM",LH17,0) -> 0 | LM17: 7 | LN17: 16 | LO17: NOR | LP17: =SUM(LN17-LM17) -> 9 | LQ17: =IF(LP17>1,LP17-1,0) -> 8 | LR17: =IF(D17="STAFF",IF(LO17="NOR",IF(LQ17>8.5,8.5,LQ17),0),IF(LO17="NOR",IF(LQ17>8,8,LQ17),IF(LP17="CAMPO",IF(LO17="NOR",IF(LQ17>8,8,LQ17),0),IF(LO17="NOR",IF(LQ17>8,8,LQ17),0)))) -> 8 | LS17: =IF(LO17="NOR",IF(LQ17>10,2,IF(LQ17>8,(LQ17-LR17),0)),0) -> 0 | LT17: =IF(LO17="NOR",IF(LQ17<10,0,IF(LQ17>10,(LQ17-(LR17+LS17)),0)),0) -> 0 | LU17: =IF(LO17="DOM",LQ17,0) -> 0 | LV17: 7 | LW17: 16 | LX17: NOR | LY17: =SUM(LW17-LV17) -> 9 | LZ17: =IF(LY17>1,LY17-1,0) -> 8 | MA17: =IF(D17="STAFF",IF(LX17="NOR",IF(LZ17>8.5,8.5,LZ17),0),IF(LX17="NOR",IF(LZ17>8,8,LZ17),IF(LY17="CAMPO",IF(LX17="NOR",IF(LZ17>8,8,LZ17),0),IF(LX17="NOR",IF(LZ17>8,8,LZ17),0)))) -> 8 | MB17: =IF(LX17="NOR",IF(LZ17>10,2,IF(LZ17>8,(LZ17-MA17),0)),0) -> 0 | MC17: =IF(LX17="NOR",IF(LZ17<10,0,IF(LZ17>10,(LZ17-(MA17+MB17)),0)),0) -> 0 | MD17: =IF(LX17="DOM",LZ17,0) -> 0 | ME17: 7 | MF17: 16 | MG17: NOR | MH17: =SUM(MF17-ME17) -> 9 | MI17: =IF(MH17>1,MH17-1,0) -> 8 | MJ17: =IF(D17="STAFF",IF(MG17="NOR",IF(MI17>8.5,8.5,MI17),0),IF(MG17="NOR",IF(MI17>8,8,MI17),IF(MH17="CAMPO",IF(MG17="NOR",IF(MI17>8,8,MI17),0),IF(MG17="NOR",IF(MI17>8,8,MI17),0)))) -> 8 | MK17: =IF(MG17="NOR",IF(MI17>10,2,IF(MI17>8,(MI17-MJ17),0)),0) -> 0 | ML17: =IF(MG17="NOR",IF(MI17<10,0,IF(MI17>10,(MI17-(MJ17+MK17)),0)),0) -> 0 | MM17: =IF(MG17="DOM",MI17,0) -> 0 | MN17: 7 | MO17: 16 | MP17: NOR | MQ17: =SUM(MO17-MN17) -> 9 | MR17: =IF(MQ17>1,MQ17-1,0) -> 8 | MS17: =IF(D17="STAFF",IF(MP17="NOR",IF(MR17>8.5,8.5,MR17),0),IF(MP17="NOR",IF(MR17>8,8,MR17),IF(MQ17="CAMPO",IF(MP17="NOR",IF(MR17>8,8,MR17),0),IF(MP17="NOR",IF(MR17>8,8,MR17),0)))) -> 8 | MT17: =IF(MP17="NOR",IF(MR17>10,2,IF(MR17>8,(MR17-MS17),0)),0) -> 0 | MU17: =IF(MP17="NOR",IF(MR17<10,0,IF(MR17>10,(MR17-(MS17+MT17)),0)),0) -> 0 | MV17: =IF(MP17="DOM",MR17,0) -> 0 | MW17: 7 | MX17: 16 | MY17: NOR | MZ17: =SUM(MX17-MW17) -> 9 | NA17: =IF(MZ17>1,MZ17-1,0) -> 8 | NB17: =IF(D17="STAFF",IF(MY17="NOR",IF(NA17>8.5,8.5,NA17),0),IF(MY17="NOR",IF(NA17>8,8,NA17),IF(MZ17="CAMPO",IF(MY17="NOR",IF(NA17>8,8,NA17),0),IF(MY17="NOR",IF(NA17>8,8,NA17),0)))) -> 8 | NC17: =IF(MY17="NOR",IF(NA17>10,2,IF(NA17>8,(NA17-NB17),0)),0) -> 0 | ND17: =IF(MY17="NOR",IF(NA17<10,0,IF(NA17>10,(NA17-(NB17+NC17)),0)),0) -> 0 | NE17: =IF(MY17="DOM",NA17,0) -> 0 | NF17: 7 | NG17: 16 | NH17: NOR | NI17: =SUM(NG17-NF17) -> 9 | NJ17: =IF(NI17>1,NI17-1,0) -> 8 | NK17: =IF(D17="STAFF",IF(NH17="NOR",IF(NJ17>8.5,8.5,NJ17),0),IF(NH17="NOR",IF(NJ17>8,8,NJ17),IF(NI17="CAMPO",IF(NH17="NOR",IF(NJ17>8,8,NJ17),0),IF(NH17="NOR",IF(NJ17>8,8,NJ17),0)))) -> 8 | NL17: =IF(NH17="NOR",IF(NJ17>10,2,IF(NJ17>8,(NJ17-NK17),0)),0) -> 0 | NM17: =IF(NH17="NOR",IF(NJ17<10,0,IF(NJ17>10,(NJ17-(NK17+NL17)),0)),0) -> 0 | NN17: =IF(NH17="DOM",NJ17,0) -> 0 | NO17: 7 | NP17: 16 | NQ17: NOR | NR17: =SUM(NP17-NO17) -> 9 | NS17: =IF(NR17>1,NR17-1,0) -> 8 | NT17: =IF(D17="STAFF",IF(NQ17="NOR",IF(NS17>8.5,8.5,NS17),0),IF(NQ17="NOR",IF(NS17>8,8,NS17),IF(NR17="CAMPO",IF(NQ17="NOR",IF(NS17>8,8,NS17),0),IF(NQ17="NOR",IF(NS17>8,8,NS17),0)))) -> 8 | NU17: =IF(NQ17="NOR",IF(NS17>10,2,IF(NS17>8,(NS17-NT17),0)),0) -> 0 | NV17: =IF(NQ17="NOR",IF(NS17<10,0,IF(NS17>10,(NS17-(NT17+NU17)),0)),0) -> 0 | NW17: =IF(NQ17="DOM",NS17,0) -> 0 | NX17: 7 | NY17: 16 | NZ17: NOR | OA17: =SUM(NY17-NX17) -> 9 | OB17: =IF(OA17>1,OA17-1,0) -> 8 | OC17: =IF(D17="STAFF",IF(NZ17="NOR",IF(OB17>8.5,8.5,OB17),0),IF(NZ17="NOR",IF(OB17>8,8,OB17),IF(OA17="CAMPO",IF(NZ17="NOR",IF(OB17>8,8,OB17),0),IF(NZ17="NOR",IF(OB17>8,8,OB17),0)))) -> 8 | OD17: =IF(NZ17="NOR",IF(OB17>10,2,IF(OB17>8,(OB17-OC17),0)),0) -> 0 | OE17: =IF(NZ17="NOR",IF(OB17<10,0,IF(OB17>10,(OB17-(OC17+OD17)),0)),0) -> 0 | OF17: =IF(NZ17="DOM",OB17,0) -> 0 | OG17: 0 | OH17: 0 | OI17: DS | OJ17: =SUM(OH17-OG17) -> 0 | OK17: =IF(OJ17>1,OJ17-1,0) -> 0 | OL17: =IF(D17="STAFF",IF(OI17="NOR",IF(OK17>8.5,8.5,OK17),0),IF(OI17="NOR",IF(OK17>8,8,OK17),IF(OJ17="CAMPO",IF(OI17="NOR",IF(OK17>8,8,OK17),0),IF(OI17="NOR",IF(OK17>8,8,OK17),0)))) -> 0 | OM17: =IF(OI17="NOR",IF(OK17>10,2,IF(OK17>8,(OK17-OL17),0)),0) -> 0 | ON17: =IF(OI17="NOR",IF(OK17<10,0,IF(OK17>10,(OK17-(OL17+OM17)),0)),0) -> 0 | OO17: =IF(OI17="DOM",OK17,0) -> 0 | OP17: 7 | OQ17: 16 | OR17: NOR | OS17: =SUM(OQ17-OP17) -> 9 | OT17: =IF(OS17>1,OS17-1,0) -> 8 | OU17: =IF(D17="STAFF",IF(OR17="NOR",IF(OT17>8.5,8.5,OT17),0),IF(OR17="NOR",IF(OT17>8,8,OT17),IF(OS17="CAMPO",IF(OR17="NOR",IF(OT17>8,8,OT17),0),IF(OR17="NOR",IF(OT17>8,8,OT17),0)))) -> 8 | OV17: =IF(OR17="NOR",IF(OT17>10,2,IF(OT17>8,(OT17-OU17),0)),0) -> 0 | OW17: =IF(OR17="NOR",IF(OT17<10,0,IF(OT17>10,(OT17-(OU17+OV17)),0)),0) -> 0 | OX17: =IF(OR17="DOM",OT17,0) -> 0 | OY17: 0 | OZ17: 0 | PA17: FE | PB17: =SUM(OZ17-OY17) -> 0 | PC17: =IF(PB17>1,PB17-1,0) -> 0 | PD17: =IF(D17="STAFF",IF(PA17="NOR",IF(PC17>8.5,8.5,PC17),0),IF(PA17="NOR",IF(PC17>8,8,PC17),IF(PB17="CAMPO",IF(PA17="NOR",IF(PC17>8,8,PC17),0),IF(PA17="NOR",IF(PC17>8,8,PC17),0)))) -> 0 | PE17: =IF(PA17="NOR",IF(PC17>10,2,IF(PC17>8,(PC17-PD17),0)),0) -> 0 | PF17: =IF(PA17="NOR",IF(PC17<10,0,IF(PC17>10,(PC17-(PD17+PE17)),0)),0) -> 0 | PG17: =IF(PA17="DOM",PC17,0) -> 0 | PH17: 7 | PI17: 16 | PJ17: NOR | PK17: =SUM(PI17-PH17) -> 9 | PL17: =IF(PK17>1,PK17-1,0) -> 8 | PM17: =IF(M17="STAFF",IF(PJ17="NOR",IF(PL17>8.5,8.5,PL17),0),IF(PJ17="NOR",IF(PL17>8,8,PL17),IF(PK17="CAMPO",IF(PJ17="NOR",IF(PL17>8,8,PL17),0),IF(PJ17="NOR",IF(PL17>8,8,PL17),0)))) -> 8 | PN17: =IF(PJ17="NOR",IF(PL17>10,2,IF(PL17>8,(PL17-PM17),0)),0) -> 0 | PO17: =IF(PJ17="NOR",IF(PL17<10,0,IF(PL17>10,(PL17-(PM17+PN17)),0)),0) -> 0 | PP17: =IF(PJ17="DOM",PL17,0) -> 0 | PR17: =COUNTIF(FG17:PP17,"NOR") -> 25 | PS17: =COUNTIF(FG17:PP17,"DS") -> 3 | PT17: =COUNTIF(FG17:PP17,"FE") -> 1 | PU17: =SUM(PR17:PT17) -> 29 | PV17: =COUNTIF(FG17:PP17,"DM") -> 0 | PY17: =COUNTIF(FG17:PP17,"SUB") -> 0 | QB17: =COUNTIF(FG17:PP17,"VA") -> 0 | QE17: =COUNTIF(FG17:PP17,"LSG") -> 0 | QH17: =COUNTIF(FG17:PP17,"LCG") -> 0 | QK17: =COUNTIF(FG17:PP17,"FA") -> 1 | QL17: 44356 | QM17: 44356 | QN17: =COUNTIF(J17:FF17,"FA") -> 0 | QQ17: =PU17+PV17+PY17+QB17+QE17+QH17+QK17+QN17 -> 30 | QS17: =P17+Y17++AH17+AQ17+AZ17+BI17+BR17+CA17+CJ17+CS17+DB17+DK17+DT17+EC17+EL17+EU17+FD17+FM17+FV17+GE17+GN17+GW17+HF17+HO17+HX17+IG17+IP17+IY17+JH17+JQ17+JZ17 -> 50 | QT17: =Q17+Z17++AI17+AR17+BA17+BJ17+BS17+CB17+CK17+CT17+DC17+DL17+DU17+ED17+EM17+EV17+FE17+FN17+FW17+GF17+GO17+GX17+HG17+HP17+HY17+IH17+IQ17+IZ17+JI17+JR17+KA17 -> 10 | RG17: 11
