Workbook

Sheet Matriz contrato Activos
A1: Item | B1: DNI O CE | C1: APELLIDOS Y NOMBRES | D1: CORREO | E1: CARGO | F1: AREA | G1: DIRECCION | H1: DISTRITO | I1: PROVINCIA | J1: DEPARTAMENTO | K1: TIPO DE CONTRATO | L1: BASICO | M1: ALIMENTACION | N1: HOSPEDAJE | O1: FECHA DE INGRESO A NOMINA | P1: TERMINO DE CONTRATO | Q1: 01 Prorroga | R1: 02 Prorroga | S1: 03 Prorroga | T1: 04 Prorroga | U1: 05 Prorroga | V1: 06 Prorroga | W1: 07 Prorroga | X1: 08 Prorroga | Y1: 09 Prorroga | Z1: 10 Prorroga | AA1: 11 Prorroga | AB1: 12 Prorroga | AC1: 13 Prorroga | AD1: 14 Prorroga | AE1: 15 Prorroga | AF1: 16 Prorroga | AG1: 17 Prorroga | AH1: 18 Prorroga | AI1: ULTIMA PRORROGA
A3: =A2+1 -> 1 | B3: 43290334 | C3: ABAD SALAS CARLOS ALBERTO | D3: caas30@hotmail.com | E3: AUXILIAR DE SEGURIDAD PATRIMONIAL | F3: SEGURIDAD PATRIMONIAL | G3: ESQUINA CUATRO TORRES Y KAWARINAS FRAC 2 DPTO 503 | H3: WANCHAQ | I3: CUSCO | J3: CUSCO | K3: FISCALIZABLE | L3: 1970 | M3: 0 | N3: 0 | O3: 46034 | P3: 46142 | AI3: =+MAX(O3:AH3) -> 46142
A4: =A3+1 -> 2 | B4: 48000903 | C4: ACUÑA OBREGON JULIE TERESA | D4: julie.acunaobregon@gmail.com | E4: COORDINADOR DE OFICINA TÉCNICA | F4: OFICINA TECNICA | G4: URB. UCCHULLO GRANDE P-15 | H4: CUSCO | I4: CUSCO | J4: CUSCO | K4: CONFIANZA | L4: 8000 | M4: 800 | N4: 800 | O4: 45386 | P4: 45473 | Q4: 45565 | R4: 45657 | S4: 45747 | T4: 45838 | U4: 45930 | V4: 46022 | W4: 46081 | X4: 46112 | AI4: =+MAX(O4:AH4) -> 46112
A5: =A4+1 -> 3 | B5: 43600466 | C5: AGUIRRE CAHUANA YAN PAUL | D5: tunokri@gmail.com | E5: ASISTENTE DE ALMACEN | F5: SERVICIOS GENERALES Y LOGISTICA | G5: CA. PUMACAHUA 222 URB TAHUANTINSUYO | H5: CUSCO | I5: CUSCO | J5: CUSCO | K5: FISCALIZABLE | L5: 2700 | M5: 0 | N5: 0 | O5: 45558 | P5: 45657 | Q5: 45747 | R5: 45838 | S5: 45930 | T5: 46022 | U5: 46112 | AI5: =+MAX(O5:AH5) -> 46112
A6: =A5+1 -> 4 | B6: 71405212 | C6: ALBERCA CASTILLO RUBEN AUGUSTO | D6: rb.alberca@gmail.com | E6: MODELADOR BIM | F6: BIM | G6: ASENT.H. LA PRIMAVERA MZ. F1 LT. 14 | H6: CASTILLA | I6: PIURA | J6: PIURA | K6: FISCALIZABLE | L6: 3700 | M6: 500 | N6: 500 | O6: 45909 | P6: 45991 | Q6: 46053 | R6: 46142 | AI6: =+MAX(O6:AH6) -> 46142
A7: =A6+1 -> 5 | B7: 75682513 | C7: ALFARO MARTINEZ GRECIA XIOMARA | D7: greshia.15@gmail.com | E7: ASISTENTE DE PROCURA | F7: PROCURA | G7: URB ALAMEDA LIMA NORTE II ETAPA MZ. C9 LT. 10 | H7: SANTA ROSA | I7: LIMA | J7: LIMA | K7: FISCALIZABLE | L7: 3800 | M7: 800 | N7: 800 | O7: 45787 | P7: 45869 | Q7: 45961 | R7: 46053 | S7: 46112 | AI7: =+MAX(O7:AH7) -> 46112
A8: =A7+1 -> 6 | B8: 48177998 | C8: ALVARO CASTRO JOSE LUIS | D8: jlalvarocastro@gmail.com | E8: INSTALADOR DE PVC Y VIDRIOS | F8: PRODUCCION-INTERVENCION FACONSE | G8: ASOC. PRO VIV. CAMINO REAL CUSCO MZ. T LT. 7 | H8: CUSCO | I8: CUSCO | J8: CUSCO | K8: FISCALIZABLE | L8: 3000 | M8: 0 | N8: 0 | O8: 18/10/2025 | P8: 46022 | Q8: 46053 | R8: 46081 | S8: 46112 | AI8: =+MAX(O8:AH8) -> 46112
A9: =A8+1 -> 7 | B9: 46275287 | C9: ANDRADE ROJAS MELISSA JANE | D9: melar2204@gmail.com | E9: ASISTENTE DE OFICINA TECNICA | F9: OFICINA TECNICA-INTERVENCION EISSA | G9: JR. TARAPACA 365 INT. 05 1ER. | H9: HUANUCO | I9: HUANUCO | J9: HUANUCO | K9: FISCALIZABLE | L9: 5000 | M9: 500 | N9: 500 | O9: 45727 | P9: 45808 | Q9: 45900 | R9: 45991 | S9: 46053 | T9: 46112 | AI9: =+MAX(O9:AH9) -> 46112
A10: =A9+1 -> 8 | B10: 73451822 | C10: AÑANCA QUISPE JHON WILMER | D10: jhonaaanancaquispe51@gmail.com | E10: AUXILIAR DE SEGURIDAD PATRIMONIAL | F10: SEGURIDAD PATRIMONIAL | G10: MZ R2 LT 2 ASENT.H. BAYOVAR AMPLIACION | H10: SAN JUAN DE LURIGANCHO | I10: LIMA | J10: LIMA | K10: FISCALIZABLE | L10: 1970 | M10: 0 | N10: 0 | O10: 45937 | P10: 46022 | Q10: 46053 | R10: 46081 | S10: 46112 | AI10: =+MAX(O10:AH10) -> 46112
A11: =Liquidados!A286+1 -> 11 | B11: 40548472 | C11: APAZA TITO ANTENOR | D11: antenorapazatito3@gmail.com | E11: CONDUCTOR DE VEHICULO LIVIANO | F11: SERVICIOS GENERALES Y LOGISTICA | G11: AV. LOS LIBERTADORES S/N C.POBLADO KEPASHIATO | H11: KUMPIRUSHIATO | I11: LA CONVENCION | J11: CUSCO | K11: FISCALIZABLE | L11: 2000 | M11: 375 | N11: 0 | O11: 44932 | P11: 45107 | Q11: 45199 | R11: 45291 | S11: 45473 | T11: 45382 | U11: 45565 | V11: 45657 | W11: 45688 | X11: 45716 | Y11: 45808 | Z11: 45900 | AA11: 45991 | AB11: 46053 | AC11: 46142 | AI11: =+MAX(O11:AH11) -> 46142
A12: =A11+1 -> 12 | B12: 45917823 | C12: ATAHUAMAN CHAVEZ LEYDI ODA | D12: arq.leydi.ach@gmail.com | E12: ARQUITECTO ESPECIALISTA | F12: OFICINA TECNICA | G12: URB SANTA VICTORIA B-13 | H12: HUANUCO | I12: HUANUCO | J12: HUANUCO | K12: CONFIANZA | L12: 9200 | M12: 800 | N12: 800 | O12: 45279 | P12: 45382 | Q12: 45473 | R12: 45565 | S12: 45657 | T12: 45747 | U12: 45838 | V12: 45930 | W12: 46022 | X12: 46081 | Y12: 46112 | AI12: =+MAX(O12:AH12) -> 46112
A13: =A12+1 -> 13 | B13: 03689683 | C13: ATOCHE MEDINA CARMEN LILIANA | D13: carmenatomed@gmail.com | E13: AUXILIAR DE LIMPIEZA | F13: SERVICIOS GENERALES Y LOGISTICA | G13: CALLE EL CONDOR 114 URB.SANTA ROSA | H13: SULLANA | I13: SULLANA | J13: PIURA | K13: FISCALIZABLE | L13: 1800 | M13: 375 | N13: 0 | O13: 45688 | P13: 45777 | Q13: 45869 | R13: 45961 | S13: 46053 | T13: 46142 | AI13: =+MAX(O13:AH13) -> 46142
A14: =A13+1 -> 14 | B14: 43935996 | C14: ATOCHE PECHO RANDY ARNALDO | D14: randy.atoche@gmail.com | E14: INGENIERO DE INSTALACIONES ELECTROMECANICAS | F14: COMMISSIONING | G14: JR. ALMTE. MARTIN GUISSE 1564 | H14: LINCE | I14: LIMA | J14: LIMA | K14: CONFIANZA | L14: 11000 | M14: 800 | N14: 800 | O14: 45545 | P14: 45626 | Q14: 45716 | R14: 45808 | S14: 45900 | T14: 45991 | U14: 46081 | V14: 46112 | AI14: =+MAX(O14:AH14) -> 46112
A15: =A14+1 -> 15 | B15: 46127028 | C15: AURICH ROJAS VICTOR ALBERTO | D15: krissvic_7@hotmail.com | E15: CAPATAZ ELECTRICISTA | F15: PRODUCCION-INTERVENCION EISSA | G15: MZ 42 LT 11 CENT PTAPO CENTRO | H15: PATAPO | I15: CHICLAYO | J15: LAMBAYEQUE | K15: FISCALIZABLE | L15: 5000 | M15: 500 | N15: 500 | O15: 45931 | P15: 46022 | Q15: 46053 | R15: 46112 | AI15: =+MAX(O15:AH15) -> 46112
A16: =A15+1 -> 16 | B16: 71706552 | C16: BARRETO PUMACHARA HONORIO DAVID | D16: cosmo_07_97@outlook.es | E16: OPERADOR DE RETROEXCAVADORA | F16: PRODUCCION | G16: CALLE PRINCIPAL S/N | H16: HUANCARANI | I16: PAUCARTAMBO | J16: CUSCO | K16: FISCALIZABLE | L16: 1130 | M16: 0 | N16: 0 | O16: 45894 | P16: 45991 | Q16: 46022 | R16: 46053 | S16: 46081 | T16: 46112 | AI16: =+MAX(O16:AH16) -> 46112
A17: =A16+1 -> 17 | B17: 75337871 | C17: BEDOYA ARANDA NICKOLL AILYN | D17: nickollbedoya.a@gmail.com | E17: JEFE DE ADMINISTRACION CONTRACTUAL | F17: ADMINISTRACION CONTRATUAL Y LEGAL | G17: CALLE ESPERANZA 239 DPTO. 401 | H17: MIRAFLORES | I17: LIMA | J17: LIMA | K17: CONFIANZA | L17: 14000 | M17: 1000 | N17: 1200 | O17: 44866 | P17: 45230 | Q17: 45322 | R17: 45504 | S17: 45596 | T17: 45777 | U17: 45961 | V17: 46053 | W17: 46142 | AI17: =+MAX(O17:AH17) -> 46142
A18: =A17+1 -> 18 | B18: 71414045 | C18: BERNABLE PALOMINO, ALEXANDRA DEL CARMEN | D18: carmenbernanlepalomino@gmail.com | E18: ASISTENTE DE PRODUCCIÓN | F18: PRODUCCION | G18: URB. BUENA VISTA MZ. A LT. 13 | H18: CUSCO | I18: CUSCO | J18: CUSCO | K18: NO FISCALIZABLE | L18: 4000 | M18: 375 | O18: 46028 | P18: 46112 | AI18: =+MAX(O18:AH18) -> 46112
A19: =A18+1 -> 19 | B19: 72553778 | C19: CABANILLAS VILCHEZ LUIS ALEJANDRO | D19: lcabanillasvilchez@gmail.com | E19: MODELADOR BIM | F19: BIM-INTERVENCION FACONSE | G19: URB LOS CEDROS DE LA PRADERA MZ. F LT. 04 | H19: CHICLAYO | I19: CHICLAYO | J19: LAMBAYEQUE | K19: FISCALIZABLE | L19: 3500 | M19: 500 | N19: 500 | O19: 45947 | P19: 46022 | Q19: 46081 | R19: 46112 | AI19: =+MAX(O19:AH19) -> 46112
A20: =A19+1 -> 20 | B20: 77296315 | C20: CABRERA CACERES MILLENI DARMELLY | D20: millenicabrera@gmail.com | E20: INGENIERO DE OFICINA TÉCNICA | F20: OFICINA TECNICA | G20: PJ PRIMAVERA N-152 BARRIO CONO ALUVIONICO OESTE | H20: HUARAZ | I20: HUARAZ | J20: ANCASH | K20: FISCALIZABLE | L20: 4000 | M20: 800 | N20: 800 | O20: 45386 | P20: 45473 | Q20: 45535 | R20: 45596 | S20: 45688 | T20: 45777 | U20: 45869 | V20: 45961 | W20: 46053 | X20: 46142 | AI20: =+MAX(O20:AH20) -> 46142
A21: =A20+1 -> 21 | B21: 74657049 | C21: CANALES RIOS CESAR AUGUSTO | D21: cesar.canrios@gmail.com | E21: ASISTENTE DE CALIDAD | F21: CALIDAD-INTERVENCION EISSA | G21: JR. AREQUIPA MZ. A LT. 2 | H21: EL ALTO | I21: TALARA | J21: PIURA | K21: FISCALIZABLE | L21: 4000 | M21: 500 | N21: 500 | O21: 45909 | P21: 45991 | Q21: 46053 | R21: 46142 | AI21: =+MAX(O21:AH21) -> 46142
A22: =A21+1 -> 22 | B22: 005892606 | C22: CANIZA VIERCI JOAQUIN JOSE | D22: jcaniza@consorciosrt.com | E22: Gerente Tecnico | F22: PRODUCCION | G22: CALLE LOS NARANJOS 346 | H22: SAN ISIDRO | I22: LIMA | J22: LIMA | K22: NO FISCALIZABLE | L22: 38370 | M22: 0 | N22: 0 | O22: 01/07/2025 | P22: 46203 | AI22: =+MAX(O22:AH22) -> 46203
A23: =A22+1 -> 23 | B23: 60117582 | C23: CAPARO OCHOA JOSE LUIS | D23: strong.jlco@gmail.com | E23: ASISTENTE DE CONTABILIDAD | F23: ADMINISTRACION | G23: PARQUE INDUSTRIAL MZ. E LT. 17 | H23: WANCHAQ | I23: CUSCO | J23: CUSCO | K23: FISCALIZABLE | L23: 2500 | M23: 300 | N23: 0 | O23: 45798 | P23: 45900 | Q23: 45991 | R23: 46053 | S23: 46112 | AI23: =+MAX(O23:AH23) -> 46112
A24: =A23+1 -> 24 | B24: 45656788 | C24: CARBAJAL ZUÑIGA EDWIN | D24: ednig11@gmail.com | E24: TECNICO ELECTRICISTA | F24: COMMISSIONING | G24: P.JOVEN LA ESTRELLA 2 ETAPA M-6 | H24: SANTIAGO | I24: CUSCO | J24: CUSCO | K24: FISCALIZABLE | L24: 4500 | M24: 0 | N24: 0 | O24: 45792 | P24: 45869 | Q24: 45961 | R24: 46053 | S24: 46142 | AI24: =+MAX(O24:AH24) -> 46142
A25: =A24+1 -> 25 | B25: 72217746 | C25: CASANOVA VISE FRANCO ENRIQUE | D25: franco.casanovav@gmail.com | E25: JEFE DE ADMINISTRACION DE SUBCONTRATOS | F25: PROCURA | G25: JR. SAN JACINTO 155 URB CENTRO COMERCIAL DE MONTERRICO | H25: SANTIAGO DE SURCO | I25: LIMA | J25: LIMA | K25: CONFIANZA | L25: 10500 | M25: 1000 | N25: 900 | O25: 45201 | P25: 45291 | Q25: 45473 | R25: 45565 | S25: 45657 | T25: 45382 | U25: 45747 | V25: 45838 | W25: 45930 | X25: 46022 | Y25: 46112 | AI25: =+MAX(O25:AH25) -> 46112
A26: =A25+1 -> 26 | B26: 70024630 | C26: CASTAÑEDA LOPEZ, JOHN ALDAIR | D26: ing.castanedalopez@gmail.com | E26: SUPERVISOR SSOMA | F26: SSOMA | G26: AV. TUPAC AMARU S/N C.P.M PAMPA GRANDE | H26: CHONGOYAPE | I26: CHICLAYO | J26: LAMBAYEQUE | K26: NO FISCALIZABLE | L26: 5000 | M26: 800 | N26: 800 | O26: 45996 | P26: 46081 | Q26: 46112 | AI26: =+MAX(O26:AH26) -> 46112
A27: =A26+1 -> 27 | B27: 005835751 | C27: CASTILLO AQUINO ANA LAURA | D27: anitacas321@gmail.com | E27: INGENIERO RESPONSABLE DE VALORIZACIONES | F27: COSTOS Y PRESUPUESTOS | G27: AVENIDA JAVIER PRADO OESTE 1818 | H27: SAN ISIDRO | I27: LIMA | J27: LIMA | K27: NO FISCALIZABLE | L27: 16690 | M27: 0 | N27: 0 | O27: 01/12/2024 | P27: 45991 | Q27: 46173 | AI27: =+MAX(O27:AH27) -> 46173
A28: =A27+1 -> 28 | B28: 48191321 | C28: CASTILLO LEQUERNAQUE YOJANI ANTONIA | D28: antoniacastillo93@hotmail.com | E28: ASISTENTE DE RECURSOS HUMANOS | F28: GESTION HUMANA | G28: MARISCAL CASTILLA S/N | H28: VICHAYAL | I28: PAITA | J28: PIURA | K28: FISCALIZABLE | L28: 2100 | M28: 400 | N28: 400 | O28: 45870 | P28: 45961 | Q28: 46022 | R28: 46112 | AI28: =+MAX(O28:AH28) -> 46112
A29: =A28+1 -> 29 | B29: 73111816 | C29: CASTILLO PISCOYA GUSTAVO EDUARDO | D29: gustavo080398@gmail.com | E29: ADMINISTRADOR DE SUBCONTRATOS | F29: PROCURA | G29: CALLE TACNA 231 | H29: CHICLAYO | I29: CHICLAYO | J29: LAMBAYEQUE | K29: CONFIANZA | L29: 6500 | M29: 800 | N29: 800 | O29: 45856 | P29: 45961 | Q29: 46053 | R29: 46112 | AI29: =+MAX(O29:AH29) -> 46112
A30: =A29+1 -> 30 | B30: 10105707 | C30: CASTRO LLANOS CARLOS RAUL | D30: carlos.castro@crcll.com.pe | E30: DIRECTOR DE PROYECTO | F30: PRODUCCION | G30: SEPARADORA INDUSTRIAL 3110 DPTO. 406 | H30: LA MOLINA | I30: LIMA | J30: LIMA | K30: DIRECCION | L30: 27000 | M30: 1500 | N30: 1500 | O30: 45597 | P30: 45777 | Q30: 45961 | R30: 46142 | AI30: =+MAX(O30:AH30) -> 46142
A31: =Liquidados!A287+1 -> 32 | B31: 70786569 | C31: CAYAHUALLPA QUISPE CESAR ANDRES | D31: cesar_andres1807@hotmail.com | E31: MODELADOR BIM | F31: BIM | G31: URB.SAN AGUSTIN MZ.U LT.6 | H31: SAN VICENTE DE CAÑETE | I31: CAÑETE | J31: LIMA | K31: FISCALIZABLE | L31: 4000 | M31: 500 | N31: 500 | O31: 45691 | P31: 45777 | Q31: 45869 | R31: 45961 | S31: 46053 | T31: 46142 | AI31: =+MAX(O31:AH31) -> 46142
A32: =A31+1 -> 33 | B32: 75196505 | C32: CCAPA ESPINOZA YOHELMIR | D32: yohelmirccapaespinoza@gmail.com | E32: ASISTENTE DE TI | F32: TI | G32: ASOC. PRO VIV. ALTO CUSCO MZ. F LT. 2 | H32: CUSCO | I32: CUSCO | J32: CUSCO | K32: FISCALIZABLE | L32: 2400 | M32: 0 | N32: 0 | O32: 45782 | P32: 45869 | Q32: 45961 | R32: 46053 | S32: 46142 | AI32: =+MAX(O32:AH32) -> 46142
A33: =A32+1 -> 34 | B33: 73202371 | C33: CENTURION LINARES JAIR ALEXANDER | D33: centurionjair23@gmail.com | E33: INGENIERO DE VALORIZACION Y FACTURACION | F33: PROCURA | G33: CALLE 4 MZ.C1 LT.27 URB.LOS JARDINES DE VENTANILLA 1RA.ETAPA | H33: VENTANI | I33: CALLAO | J33: PROV. CONST. DEL CALLAO | K33: CONFIANZA | L33: 6000 | M33: 800 | N33: 800 | O33: 45923 | P33: 46022 | Q33: 46112 | AI33: =+MAX(O33:AH33) -> 46112
A34: =A33+1 -> 35 | B34: 77127124 | C34: CHAPARRO CHACMANI KATHIUSCA ABIGAID | D34: abigaid.1221@gmail.com | E34: ASISTENTE DE RECURSOS HUMANOS | F34: GESTION HUMANA | G34: BELENPAMPA G-9 | H34: SANTIAGO | I34: CUSCO | J34: CUSCO | K34: CONFIANZA | L34: 3000 | M34: 375 | N34: 0 | O34: 45251 | P34: 45351 | Q34: 45443 | R34: 45535 | S34: 45626 | T34: 45716 | U34: 45808 | V34: 45900 | W34: 45991 | X34: 46053 | Y34: 46142 | AI34: =+MAX(O34:AH34) -> 46142
A35: =A34+1 -> 36 | B35: 75581956 | C35: CHILCON QUISPE LIZBETH | D35: lizbethchilcon@gmail.com | E35: MODELADOR BIM | F35: BIM | G35: JR. B. DUBLE S/N | H35: CUTERVO | I35: CUTERVO | J35: CAJAMARCA | K35: FISCALIZABLE | L35: 3500 | M35: 500 | N35: 500 | O35: 45901 | P35: 45991 | Q35: 46053 | R35: 46142 | AI35: =+MAX(O35:AH35) -> 46142
A36: =A35+1 -> 37 | B36: 23981390 | C36: CONDORHUACHO CORNEJO MARGOT | D36: margot.4540@gmail.com | E36: AUXILIAR DE LIMPIEZA | F36: SERVICIOS GENERALES Y LOGISTICA | G36: ASOC. PRO.VIV. CAMINO REAL MZ. E LT. 1 | H36: CUSCO | I36: CUSCO | J36: CUSCO | K36: FISCALIZABLE | L36: 1800 | M36: 375 | N36: 0 | O36: 44575 | P36: 44666 | Q36: 44681 | R36: 44696 | S36: 44834 | T36: 45351 | U36: 44865 | V36: 45322 | W36: 45138 | X36: 45230 | Y36: 45260 | Z36: 45443 | AA36: 45535 | AB36: 45626 | AC36: 45716 | AD36: 45808 | AE36: 45991 | AF36: 46022 | AG36: 46112 | AI36: =+MAX(O36:AH36) -> 46112
A37: =A36+1 -> 38 | B37: 40308469 | C37: CORAHUA CHALCO KATY | D37: katty_c_ch@hotmail.com | E37: ASISTENTE DE TESORERIA | F37: FINANZAS | G37: ASOC. LOS INCAS MZ. F LT. 5 | H37: CUSCO | I37: CUSCO | J37: CUSCO | K37: FISCALIZABLE | L37: 4000 | M37: 375 | N37: 0 | O37: 44962 | P37: 45138 | Q37: 45230 | R37: 45260 | S37: 45443 | T37: 45351 | U37: 45535 | V37: 45626 | W37: 45716 | X37: 45808 | Y37: 45900 | Z37: 45991 | AA37: 46081 | AB37: 46112 | AI37: =+MAX(O37:AH37) -> 46112
A38: =Liquidados!A288+1 -> 40 | B38: 47110375 | C38: CRUZADO LOLOY ANCELMO | D38: acloloy2020@gmail.com | E38: CAPATAZ ALBAÑIL | F38: PRODUCCION | G38: CALLE VICTOR ANDRES BELAUNDE 115 CENTRO MONSEFU | H38: MONSEFU | I38: CHICLAYO | J38: LAMBAYEQUE | K38: FISCALIZABLE | L38: 5000 | M38: 500 | N38: 500 | O38: 45616 | P38: 45716 | Q38: 45808 | R38: 45900 | S38: 45961 | T38: 46022 | U38: 46112 | AI38: =+MAX(O38:AH38) -> 46112
A39: =A38+1 -> 41 | B39: 43801267 | C39: CRUZADO LOLOY HUGO FELIX | D39: hugocruzadololoy@gmail.com | E39: CAPATAZ ALBAÑIL | F39: PRODUCCION | G39: ASOC. PROVIV. VIRGEN DE LA PUERTA MZ. B LT. 15 | H39: CARABAYLLO | I39: LIMA | J39: LIMA | K39: FISCALIZABLE | L39: 5000 | M39: 500 | N39: 500 | O39: 45610 | P39: 45688 | Q39: 45777 | R39: 45869 | S39: 45961 | T39: 46053 | U39: 46112 | AI39: =+MAX(O39:AH39) -> 46112
A40: =A39+1 -> 42 | B40: 70887797 | C40: CUELLAR OVALLE BURGOS ANTERO | D40: 144952@unsaac.edu.pe | E40: ASISTENTE DE PRODUCCIÓN | F40: PRODUCCION | G40: URB. LOS JARDINES B-15 | H40: WANCHAQ | I40: CUSCO | J40: CUSCO | K40: FISCALIZABLE | L40: 4000 | M40: 0 | N40: 0 | O40: 45627 | P40: 45716 | Q40: 45808 | R40: 45900 | S40: 45961 | T40: 46022 | U40: 46112 | AI40: =+MAX(O40:AH40) -> 46112
A41: =A40+1 -> 43 | B41: 007453650 | C41: CUELLAR TERAN VANESSA | D41: vanessa.cuellar@hotmail.com | E41: Responsable de Subcontratos | F41: PRODUCCION | G41: CALLE MANUEL UGARTE Y MOSC 991 | H41: SAN ISIDRO | I41: LIMA | J41: LIMA | K41: NO FISCALIZABLE | L41: 21870.9 | M41: 0 | N41: 0 | O41: 01/12/2024 | P41: 45991 | Q41: 46081 | AI41: =+MAX(O41:AH41) -> 46081
A42: =A41+1 -> 44 | B42: 08851995 | C42: CUYA CHAVEZ LUIS ENRIQUE | D42: lucuya@hotmail.com | E42: PROCURA EQUIPAMIENTO MEDICO | F42: EQUIPAMIENTO | G42: AV.TOMAS GUZMAN 821 | H42: SAN JUAN DE MIRAFLORES | I42: LIMA | J42: LIMA | K42: CONFIANZA | L42: 6000 | M42: 1000 | N42: 900 | O42: 44966 | P42: 45138 | Q42: 45322 | R42: 45473 | S42: 45565 | T42: 45382 | U42: 45657 | V42: 45747 | W42: 45838 | X42: 45930 | Y42: 46022 | Z42: 46112 | AI42: =+MAX(O42:AH42) -> 46112
A43: =A42+1 -> 45 | B43: 72268347 | C43: DIAZ QUISPE, ELIZABETH DIANA | D43: diazquispeelizabethdiana@gmail.com | E43: TRABAJADORA SOCIAL | F43: GESTION HUMANA | G43: ZONA B CASIMIRO CUADROS I MZ B LT 13 | H43: CAYMA | I43: AREQUIPA | J43: AREQUIPA | K43: FISCALIZABLE | L43: 3500 | M43: 500 | N43: 500 | O43: 45972 | P43: 46053 | Q43: 46142 | AI43: =+MAX(O43:AH43) -> 46142
A44: =Liquidados!A289+1 -> 47 | B44: 75810956 | C44: ECHE ZAVALETA DANY MIGUEL | D44: danyechezava@gmail.com | E44: MODELADOR BIM | F44: BIM | G44: CALLE SUCRE 404 | H44: SECHURA | I44: SECHURA | J44: PIURA | K44: FISCALIZABLE | L44: 4000 | M44: 500 | N44: 500 | O44: 45726 | P44: 45808 | Q44: 45900 | R44: 45961 | S44: 46053 | T44: 46142 | AI44: =+MAX(O44:AH44) -> 46142
A45: =A44+1 -> 48 | B45: 46686215 | C45: ENDARA CONDORI JESUS AFDIEL | D45: jesusemdara90@gmail.com | E45: GERENTE DE CALIDAD | F45: CALIDAD | G45: JR. OTAWA A8-5 URB. MAGISTERIAL AMAUTA | H45: JULIACA | I45: SAN ROMAN | J45: PUNO | K45: CONFIANZA | L45: 14500 | M45: 800 | N45: 800 | O45: 45369 | P45: 45473 | Q45: 45565 | R45: 45596 | S45: 45688 | T45: 45777 | U45: 45961 | V45: 46142 | AI45: =+MAX(O45:AH45) -> 46142
A46: =A45+1 -> 49 | B46: 45676771 | C46: ESCALANTE CARTAGENA ALDO ERIC | D46: ae.escalante88@gmail.com | E46: INGENIERO ELECTRICISTA | F46: PRODUCCION-INTERVENCION EISSA | G46: JR. ACOMAYO B-6 URB PROGRESO | H46: WANCHAQ | I46: CUSCO | J46: CUSCO | K46: FISCALIZABLE | L46: 3200 | M46: 0 | N46: 0 | O46: 45870 | P46: 45900 | Q46: 45930 | R46: 45961 | S46: 46022 | T46: 46081 | U46: 46112 | AI46: =+MAX(O46:AH46) -> 46112
A47: =A46+1 -> 50 | B47: 41598491 | C47: ESPEJO MONTESTRUQUE CARLOS OMAR | D47: carlosomar_espejo@hotmail.com | E47: ESPECIALISTA DE COMUNICACIONES | F47: COMMISSIONING | G47: LAS DELICIAS 140 URB LAS DELICIAS | H47: CHICLAYO | I47: CHICLAYO | J47: LAMBAYEQUE | K47: CONFIANZA | L47: 11000 | M47: 800 | N47: 800 | O47: 45423 | P47: 45504 | Q47: 45596 | R47: 45688 | S47: 45777 | T47: 45869 | U47: 45961 | V47: 46053 | W47: 46142 | AI47: =+MAX(O47:AH47) -> 46142
A48: =A47+1 -> 51 | B48: 74144528 | C48: ESPEJO VALDEZ YEYSON ANTONY | D48: yeysonev@gmail.com | E48: JEFE DE PLANEAMIENTO | F48: PLANEAMIENTO Y PROGRAMACION | G48: JR. MARIANO MELGAR 107 INT. 201 SECTOR LA MARQUEZA | H48: TRUJILLO | I48: TRUJILLO | J48: LA LIBERTAD | K48: CONFIANZA | L48: 9500 | M48: 800 | N48: 800 | O48: 45280 | P48: 45382 | Q48: 45473 | R48: 45565 | S48: 45657 | T48: 45716 | U48: 45808 | V48: 45900 | W48: 46081 | X48: 46173 | AI48: =+MAX(O48:AH48) -> 46173
A49: =A48+1 -> 52 | B49: 72257483 | C49: ESPINOZA MACHADO CARLOS DANIEL | D49: carlos.cdem01@gmail.com | E49: MODELADOR BIM | F49: BIM | G49: AV. ROSA DE AMERICA 150-B ASOC. ROSA DE AMERICA | H49: COMAS | I49: LIMA | J49: LIMA | K49: FISCALIZABLE | L49: 3800 | M49: 500 | N49: 500 | O49: 45580 | P49: 45657 | Q49: 45688 | R49: 45747 | S49: 45777 | T49: 45869 | U49: 45961 | V49: 46053 | W49: 46142 | AI49: =+MAX(O49:AH49) -> 46142
A50: =A49+1 -> 53 | B50: 76801259 | C50: ESTRADA MOGOLLON GERALD PEDRO | D50: gerald.estradam@gmail.com | E50: COORDINADOR BIM | F50: BIM | G50: CALLE CUZCO 402 | H50: CASTILLA | I50: PIURA | J50: PIURA | K50: CONFIANZA | L50: 6000 | M50: 800 | N50: 800 | O50: 45677 | P50: 45777 | Q50: 45869 | R50: 45961 | S50: 46053 | T50: 46142 | AI50: =+MAX(O50:AH50) -> 46142
A51: =A50+1 -> 54 | B51: 43495610 | C51: FERRER ASTOCONDOR JORGE JESUS | D51: jorgejfa27@gmail.com | E51: COORDINADOR DE SUBCONTRATOS | F51: ADMINISTRACION CONTRATUAL Y LEGAL | G51: CALLE 3 MZ E LT 2 ASOC. PROP. URB. VILLA UNIVERSITARIA | H51: SAN MARTIN DE PORRES | I51: LIMA | J51: LIMA | K51: CONFIANZA | L51: 9000 | M51: 1000 | N51: 900 | O51: 44998 | P51: 45169 | Q51: 45351 | R51: 45808 | S51: 45535 | T51: 45626 | U51: 45716 | V51: 45808 | W51: 45900 | X51: 45991 | Y51: 46081 | Z51: 46112 | AI51: =+MAX(O51:AH51) -> 46112
A52: =A51+1 -> 55 | B52: 47964954 | C52: FLORES HUAMAN JUAN CARLOS | D52: juancarlosim@outlook.es | E52: INGENIERO DE COSTOS Y PRESUPUESTOS | F52: COSTOS Y PRESUPUESTOS | G52: CALLE FITZCARRAL 338 PJ. DIEGO FERRE | H52: CHICLAYO | I52: CHICLAYO | J52: LAMBAYEQUE | K52: CONFIANZA | L52: 6500 | M52: 1000 | N52: 900 | O52: 45201 | P52: 45291 | Q52: 45473 | R52: 45565 | S52: 45657 | T52: 45382 | U52: 45747 | V52: 45838 | W52: 45930 | X52: 46022 | Y52: 46112 | AI52: =+MAX(O52:AH52) -> 46112
A53: =Liquidados!A290+1 -> 57 | B53: 74634862 | C53: FUENTES ALVAREZ, AZUCENA | D53: azucenafuentes.a@gmail.com | E53: ASISTENTE DE SEGURIDAD | F53: SSOMA | G53: ASOC. PRO VIV. PICOL ORCCOMPUGIO MZ. L LT. 4 | H53: SAN JERONIMO | I53: CUSCO | J53: CUSCO | K53: NO FISCALIZABLE | L53: 3000 | M53: 357 | N53: 0 | O53: 45992 | P53: 46081 | Q53: 46112 | AI53: =+MAX(O53:AH53) -> 46112
A54: =A53+1 -> 58 | B54: 76306720 | C54: FUENTES ENRIQUEZ GIANELLA JEANETTE | D54: gianella.fuentes147@gmail.com | E54: COORDINADORA DE COMISIONAMIENTO EN EQUIPAMIENTO MEDICO | F54: EQUIPAMIENTO | G54: AMAZONAS 1005 | H54: ALTO SELVA ALEGRE | I54: AREQUIPA | J54: AREQUIPA | K54: CONFIANZA | L54: 5800 | M54: 800 | N54: 800 | O54: 45748 | P54: 45838 | Q54: 45930 | R54: 46022 | S54: 46112 | AI54: =+MAX(O54:AH54) -> 46112
A55: =A54+1 -> 59 | B55: 71334912 | C55: GAMARRA ARIAS EBERT | D55: ebertsanetti16@gmail.com | E55: ASISTENTE DE TOPOGRAFÍA | F55: PRODUCCION | G55: APV. LOS ANDES B-1 | H55: SAN SEBASTIAN | I55: CUSCO | J55: CUSCO | K55: FISCALIZABLE | L55: 2800 | M55: 0 | N55: 0 | O55: 45439 | P55: 45535 | Q55: 45626 | R55: 45716 | S55: 45808 | T55: 45900 | U55: 45961 | V55: 46022 | W55: 46053 | X55: 46081 | Y55: 46112 | AI55: =+MAX(O55:AH55) -> 46112
A56: =A55+1 -> 60 | B56: 45275146 | C56: GARCIA ALVAREZ, GABRIELA | D56: gabrielagarciaalvarez4@gmail.com | E56: ASISTENTE DE RECURSOS HUMANOS | F56: ADMINISTRACION | G56: AV. TULLUMAYO 2025 | H56: WANCHAQ | I56: CUSCO | J56: CUSCO | K56: NO FISCALIZABLE | L56: 2100 | M56: 375 | O56: 46020 | P56: 46112 | AI56: =+MAX(O56:AH56) -> 46112
A57: =A56+1 -> 61 | B57: 76675994 | C57: GARCIA MOGOLLON CLAUDIA CAROLINA | D57: gar21ccm@gmail.com | E57: ASISTENTE DE PRODUCCIÓN | F57: PRODUCCION | G57: CALLE LA BREA 314 ASENT.H. SANTA TERESITA | H57: SULLANA | I57: SULLANA | J57: PIURA | K57: FISCALIZABLE | L57: 4000 | M57: 500 | N57: 500 | O57: 45677 | P57: 45777 | Q57: 45869 | R57: 45930 | S57: 46022 | T57: 46112 | AI57: =+MAX(O57:AH57) -> 46112
A58: =A57+1 -> 62 | B58: 42051852 | C58: GOMEZ PINEDA KRISS EILEEN | D58: krissgp5@gmail.com | E58: ASISTENTE ADMINISTRATIVO | F58: ADMINISTRACION | G58: URB OVALO DE PACHACUTEQ D01 | H58: WANCHAQ | I58: CUSCO | J58: CUSCO | K58: FISCALIZABLE | L58: 2500 | M58: 375 | N58: - | O58: 46039 | P58: 46142 | AI58: =+MAX(O58:AH58) -> 46142
A59: =A58+1 -> 63 | B59: 73962431 | C59: GONZALES DE LA CRUZ AYRTON JUNNIOR | D59: ayrtonggonzales@gmail.com | E59: MODELADOR BIM | F59: BIM | G59: JR. PEDRO PAULET 142 URB INGENIERﾍA | H59: SAN MARTIN DE PORRES | I59: LIMA | J59: LIMA | K59: FISCALIZABLE | L59: 3700 | M59: 500 | N59: 500 | O59: 45887 | P59: 45961 | Q59: 46053 | R59: 46142 | AI59: =+MAX(O59:AH59) -> 46142
A60: =A59+1 -> 64 | B60: 70495252 | C60: GONZALES LIMBER FAVIO JUNIOR JESUS | D60: faviogl22@gmail.com | E60: INGENIERO ASISTENTE DE COMISIONAMIENTO | F60: COMMISSIONING | G60: JR. 12 DE OCTUBRE 659 URB EL CARMEN | H60: COMAS | I60: LIMA | J60: LIMA | K60: CONFIANZA | L60: 5000 | M60: 800 | N60: 800 | O60: 45709 | P60: 45808 | Q60: 45900 | R60: 45991 | S60: 46081 | T60: 46112 | AI60: =+MAX(O60:AH60) -> 46112
A61: =A60+1 -> 65 | B61: 43382768 | C61: GUERRERO ALBERCA JACSER JESUS | D61: jacserguerrero@gmail.com | E61: JEFE DE COSTOS Y PRESUPUESTOS | F61: COSTOS Y PRESUPUESTOS | G61: URB SANTA ISABEL CALLE LOS CEIBOS 136 | H61: PIURA | I61: PIURA | J61: PIURA | K61: CONFIANZA | L61: 13040 | M61: 1000 | N61: 900 | O61: 44927 | P61: 45107 | Q61: 45199 | R61: 45291 | S61: 45565 | T61: 45382 | U61: 45747 | V61: 45930 | W61: 46081 | AI61: =+MAX(O61:AH61) -> 46081
A62: =A61+1 -> 66 | B62: 005419022 | C62: GUTIERREZ FERRER ERNESTO MARTIN | D62: megutierrez@consorciosrt.com | E62: Gerente Tecnico | F62: PRODUCCION | G62: CALLE JUAN ARIAS ARAGUEZ 250 | H62: MIRAFLORES | I62: LIMA | J62: LIMA | K62: NO FISCALIZABLE | L62: 42322.13 | O62: 01/12/2024 | P62: 45991 | Q62: 46173 | AI62: =+MAX(O62:AH62) -> 46173
A63: =A62+1 -> 67 | B63: 41818325 | C63: GUTIERREZ NAJARRO JUAN CARLOS | D63: juancarlosgutierreznajarro17@gmail.com | E63: CAPATAZ SANITARIO | F63: PRODUCCION | G63: ASENT.H. HUAYCAN ZONA.D UCV.67 LT.189 | H63: ATE | I63: LIMA | J63: LIMA | K63: FISCALIZABLE | L63: 4500 | M63: 500 | N63: 500 | O63: 45931 | P63: 46022 | Q63: 46053 | R63: 46081 | S63: 46112 | AI63: =+MAX(O63:AH63) -> 46112
A64: =A63+1 -> 68 | B64: 70574711 | C64: HAMANCCAY BAEZ ORLANDO | D64: orlandohamanccaybaez001@gmail.com | E64: AUXILIAR DE TOPOGRAFIA | F64: PRODUCCION | G64: CALLE BOLIVAR S/N | H64: SANGARARA | I64: ACOMAYO | J64: CUSCO | K64: FISCALIZABLE | L64: 2100 | M64: 0 | N64: 0 | O64: 45615 | P64: 45716 | Q64: 45808 | R64: 45900 | S64: 45930 | T64: 46022 | U64: 46053 | V64: 46081 | W64: 46112 | AI64: =+MAX(O64:AH64) -> 46112
A65: =A64+1 -> 69 | B65: 001993770 | C65: HIDALGO OROZCO CARLOS ARTURO | D65: carlos_hidalgo71@yahoo.com | E65: GERENTE DE EQUIPAMIENTO MEDICO | F65: EQUIPAMIENTO | G65: AVENIDA 02 DE MAYO 1385 | H65: SAN ISIDRO | I65: LIMA | J65: LIMA | K65: FISCALIZABLE | L65: 17000 | M65: 1000 | N65: 0 | O65: 45009 | P65: 45382 | Q65: 45565 | R65: 45747 | S65: 45930 | T65: 46081 | U65: 46173 | AI65: =+MAX(O65:AH65) -> 46173
A66: =A65+1 -> 70 | B66: 72166636 | C66: HORNA FLORES ALFRED JUNNIOR | D66: alfhf31997@gmail.com | E66: MODELADOR BIM | F66: BIM | G66: CALLE HUSARES DE JUNIN 1301 C.P.M.URRUNAGA | H66: JOSE LEONARDO ORTI | I66: CHICLAYO | J66: LAMBAYEQUE | K66: FISCALIZABLE | L66: 4000 | M66: 500 | N66: 500 | O66: 45677 | P66: 45777 | Q66: 45869 | R66: 45961 | S66: 46053 | T66: 46142 | AI66: =+MAX(O66:AH66) -> 46142
A67: =A66+1 -> 71 | B67: 47605746 | C67: HUACAC OSORIO HENRRY | D67: henryhuacacosorio@gmail.com | E67: ASISTENTE DE TOPOGRAFÍA | F67: PRODUCCION | G67: CUSIPATA S/N | H67: CALCA | I67: CALCA | J67: CUSCO | K67: FISCALIZABLE | L67: 2500 | M67: 0 | N67: 0 | O67: 45594 | P67: 45688 | Q67: 45777 | R67: 45869 | S67: 45930 | T67: 46022 | U67: 46053 | V67: 46081 | W67: 46112 | AI67: =+MAX(O67:AH67) -> 46112
A68: =A67+1 -> 72 | B68: 41670147 | C68: HUAMAN CACERES YOVANA | D68: hcyovana@hotmail.com | E68: RESPONSABLE FINANCIERO | F68: FINANZAS | G68: URB.STA.ROSA T-5 | H68: SAN SEBASTIAN | I68: CUSCO | J68: CUSCO | K68: CONFIANZA | L68: 8500 | M68: 375 | N68: 0 | O68: 44956 | P68: 45138 | Q68: 45230 | R68: 45322 | S68: 45473 | T68: 45382 | U68: 45565 | V68: 45657 | W68: 45747 | X68: 45838 | Y68: 45930 | Z68: 46022 | AA68: 46112 | AI68: =+MAX(O68:AH68) -> 46112
A69: =A68+1 -> 73 | B69: 42319767 | C69: HUAMAN CORDOVA ARMANDO ALAIN | D69: armandoalainhc@gmail.com | E69: CADISTA | F69: OFICINA TECNICA-INTERVENCION EISSA | G69: A.P.V SAN BLAS E-9 | H69: CUSCO | I69: CUSCO | J69: CUSCO | K69: FISCALIZABLE | L69: 2000 | M69: 0 | N69: 0 | O69: 45870 | P69: 45900 | Q69: 45930 | R69: 45961 | S69: 45991 | T69: 46022 | U69: 46053 | V69: 46081 | W69: 46112 | AI69: =+MAX(O69:AH69) -> 46112
A70: =A69+1 -> 74 | B70: 23925262 | C70: HUAMAN RAYME JOSE ALFREDO | D70: joshue_rayme888@hotmail.com | E70: CAPATAZ ELECTRICISTA | F70: COMMISSIONING | G70: URB. TTIO PSJ CONSTITUCION B-2-13 | H70: WANCHAQ | I70: CUSCO | J70: CUSCO | K70: FISCALIZABLE | L70: 5000 | M70: - | N70: - | O70: 46048 | P70: 46142 | AI70: =+MAX(O70:AH70) -> 46142
A71: =A70+1 -> 75 | B71: 72020477 | C71: HUAMANI CHAÑI ROSA DEL RIO | D71: rosse_ch15@hotmail.com | E71: ASISTENTE DE CALIDAD | F71: CALIDAD | G71: CALLE SAN PEDRO SN | H71: ESPINAR | I71: ESPINAR | J71: CUSCO | K71: FISCALIZABLE | L71: 4000 | O71: 45925 | P71: 46022 | Q71: 46112 | AI71: =+MAX(O71:AH71) -> 46112
A72: =A71+1 -> 76 | B72: 73823718 | C72: HUARACHA GARCIA PIERO ANDRES | D72: pieroandres.h@gmail.com | E72: SUPERVISIOR DE INSTALACIONES MECANICAS | F72: COMMISSIONING | G72: JR. MAXIMO GORBITZ 851 SAN JUAN | H72: SAN JUAN DE MIRAFLORES | I72: LIMA | J72: LIMA | K72: CONFIANZA | L72: 6000 | M72: 800 | N72: 800 | O72: 46049 | P72: 46142 | AI72: =+MAX(O72:AH72) -> 46142
A73: =A72+1 -> 77 | B73: 45796382 | C73: HUAYTAN PATRICIO ENDERSON FELIX | D73: enderson.huaytan0112@gmail.com | E73: INGENIERO DE INSTALACIONES ELECTRICAS | F73: COMMISSIONING | G73: ASENT.H. ESTRELLA SIMON BOLIVAR MZ. B LT. 24 | H73: PUENTE PIEDRA | I73: LIMA | J73: LIMA | K73: CONFIANZA | L73: 6500 | M73: 800 | N73: 800 | O73: 45689 | P73: 45777 | Q73: 45869 | R73: 45961 | S73: 46053 | T73: 46142 | AI73: =+MAX(O73:AH73) -> 46142
A74: =A73+1 -> 78 | B74: 76278558 | C74: HUISA FERNANDEZ TOLY KUPER | D74: kuper.huisa.fernandez@gmail.com | E74: CADISTA | F74: OFICINA TECNICA-INTERVENCION EISSA | G74: AV. TOMAS TUYRU TUPAC 15 | H74: SAN SEBASTIAN | I74: CUSCO | J74: CUSCO | K74: FISCALIZABLE | L74: 2000 | M74: 0 | N74: 0 | O74: 45925 | P74: 45961 | Q74: 45991 | R74: 46022 | S74: 46053 | T74: 46081 | AI74: =+MAX(O74:AH74) -> 46081 | AJ74: CESE
A75: =A74+1 -> 79 | B75: 72129488 | C75: JIMENEZ HUANCAS SEGUNDO ALFONSO | D75: segun1890@gmail.com | E75: MODELADOR BIM | F75: BIM | G75: URB EL BOSQUE MZ. Ñ LT. 04 | H75: CASTILLA | I75: PIURA | J75: PIURA | K75: FISCALIZABLE | L75: 4000 | M75: 500 | N75: 500 | O75: 45691 | P75: 45777 | Q75: 45869 | R75: 45961 | S75: 46053 | T75: 46142 | AI75: =+MAX(O75:AH75) -> 46142
A76: =A75+1 -> 80 | B76: 70614124 | C76: LA ROSA SANCHEZ ARELLAN MARCO GIOVANNI | D76: marco.lrsa@gmail.com | E76: COORDINADOR GENERAL BIM E INGENIERO DE OFICINA TECNICA | F76: BIM | G76: AV. VIRREY CONDE DE LEMOS 668 BLOCK 2 EDIF. 508 COND. RESIDENCIAL VILLA BONITA 1 ETAPA | H76: CALLAO | I76: CALLAO | J76: PROV. CONST. DEL CALLAO | K76: CONFIANZA | L76: 7500 | M76: 1000 | N76: 900 | O76: 44924 | P76: 45105 | Q76: 45199 | R76: 45291 | S76: 45473 | T76: 45382 | U76: 45565 | V76: 45657 | W76: 45747 | X76: 45838 | Y76: 45930 | Z76: 46022 | AA76: 46112 | AI76: =+MAX(O76:AH76) -> 46112
A77: =A76+1 -> 81 | B77: 42390562 | C77: LARA BRAVO ROBERTO JORGE | D77: roberto.lara@outlook.com | E77: GERENTE CONTRACTUAL Y LEGAL | F77: ADMINISTRACION CONTRATUAL Y LEGAL | G77: AV. CESAR VALLEJO 350 DPTO. 1502 URB EL FUNDO LOBATON | H77: LINCE | I77: LIMA | J77: LIMA | K77: CONFIANZA | L77: 20000 | M77: 440 | N77: 0 | O77: 45261 | P77: 45657 | Q77: 45747 | R77: 45930 | S77: 46081 | AI77: =+MAX(O77:AH77) -> 46081
A78: =A77+1 -> 82 | B78: 74784658 | C78: LAURENCIO CASTRO JHOSEP DARIO | D78: infinitejhosep,12@gmail.com | E78: INSTALADOR DE PVC Y VIDRIOS | F78: PRODUCCION-INTERVENCION FACONSE | G78: MZ. Z LT. 5 | H78: CUSCO | I78: CUSCO | J78: CUSCO | K78: FISCALIZABLE | L78: 3000 | M78: 0 | N78: 0 | O78: 45948 | P78: 46022 | Q78: 46053 | R78: 46081 | S78: 46089 | AI78: =+MAX(O78:AH78) -> 46089
A79: =A78+1 -> 83 | B79: 73147728 | C79: LIZA LIZA MARIA DEL PILAR | D79: mpliza20@gmail.com | E79: ANALISTA DE COSTOS | F79: COSTOS Y PRESUPUESTOS | G79: CALLE LOS INCAS 115 P.JOVEN SAN FRANCISCO | H79: CHICLAYO | I79: CHICLAYO | J79: LAMBAYEQUE | K79: CONFIANZA | L79: 5200 | M79: 800 | N79: 1100 | O79: 45215 | P79: 45322 | Q79: 45504 | R79: 45596 | S79: 45688 | T79: 45412 | U79: 45777 | V79: 45869 | W79: 45961 | X79: 46053 | Y79: 46142 | AI79: =+MAX(O79:AH79) -> 46142
A80: =A79+1 -> 84 | B80: 70275978 | C80: LLAPAPASCA CRUZ IRMA MARIA GRACIA | D80: irma.llapapasca@gmail.com | E80: MODELADOR BIM | F80: BIM | G80: JR.SAN CRISTOBAL 295 URB.SANTA ISABEL | H80: PIURA | I80: PIURA | J80: PIURA | K80: FISCALIZABLE | L80: 3700 | M80: 500 | N80: 500 | O80: 45904 | P80: 45991 | Q80: 46053 | R80: 46142 | AI80: =+MAX(O80:AH80) -> 46142
A81: =A80+1 -> 85 | B81: 74471124 | C81: LOAYZA LAYME MARIVY | D81: loayzalaymemarivy@gmail.com | E81: ASISTENTE ADMINISTRATIVO | F81: ADMINISTRACION | G81: JR. ANTA URB PROGRESO MZ. B LT. 16 | H81: WANCHAQ | I81: CUSCO | J81: CUSCO | K81: FISCALIZABLE | L81: 2100 | M81: 375 | N81: 0 | O81: 45818 | P81: 45900 | Q81: 45991 | R81: 46081 | S81: 46112 | AI81: =+MAX(O81:AH81) -> 46112
A82: =A81+1 -> 86 | B82: 70919188 | C82: LOPEZ TORRE EDWIN FERMIN | D82: eflopezt@gmail.com | E82: ANALISTA DE NOMINA | F82: GESTION HUMANA | G82: JR REJULGAR 518 | H82: SAN JUAN DE LURIGANCHO | I82: LIMA | J82: LIMA | K82: FISCALIZABLE | L82: 4000 | M82: 800 | N82: 800 | O82: 46041 | P82: 46142 | AI82: =+MAX(O82:AH82) -> 46142
A83: =Liquidados!A291+1 -> 88 | B83: 71075941 | C83: LOZANO FLORES DERIQ KEVIN | D83: lozanoderiq@gmail.com | E83: MODELADOR BIM | F83: BIM-INTERVENCION EISSA | G83: COROTO S/N | H83: CALCA | I83: CALCA | J83: CUSCO | K83: FISCALIZABLE | L83: 4000 | M83: 500 | N83: 0 | O83: 45946 | P83: 46022 | Q83: 46081 | R83: 46112 | AI83: =+MAX(O83:AH83) -> 46112
A84: =A83+1 -> 89 | B84: 74076597 | C84: LUJAN VILLANQUE JUAN GUILLERMO | D84: juanguille171095@gmail.com | E84: ESPECIALISTA AMBIENTAL | F84: SSOMA | G84: CALLE 115 STA LUZMILA 2 ETAPA MZ. N3 LT. 35 | H84: COMAS | I84: LIMA | J84: LIMA | K84: FISCALIZABLE | L84: 6000 | M84: 800 | N84: 800 | O84: 45691 | P84: 45777 | Q84: 45869 | R84: 45961 | S84: 46053 | T84: 46142 | AI84: =+MAX(O84:AH84) -> 46142
A85: =A84+1 -> 90 | B85: 43156036 | C85: LUNA MENDIETA JHON CARLOS | D85: jhonlunamendieta@gmail.com | E85: CAPATAZ DE DRYWALL | F85: PRODUCCION | G85: CALLE BALCEROS MZ.28 LT.14 CESAR VALLEJO | H85: VILLA MARIA DEL TRIUNFO | I85: LIMA | J85: LIMA | K85: FISCALIZABLE | L85: 5500 | M85: 500 | N85: 500 | O85: 45607 | P85: 45688 | Q85: 45777 | R85: 45869 | S85: 45930 | T85: 46022 | U85: 46081 | V85: 46112 | AI85: =+MAX(O85:AH85) -> 46112
A86: =A85+1 -> 91 | B86: 73445337 | C86: MACHADO RIOS CLAUDIA FABIOLA | D86: claudia.machado.rios@gmail.com | E86: MODELADOR BIM | F86: BIM | G86: MZ. 226 02-01 PQ. IND. ZONA INDUSTRIAL | H86: VEINTISEIS DE OCTUBRE | I86: PIURA | J86: PIURA | K86: FISCALIZABLE | L86: 4000 | M86: 500 | N86: 500 | O86: 45684 | P86: 45777 | Q86: 45869 | R86: 45961 | S86: 46053 | T86: 46142 | AI86: =+MAX(O86:AH86) -> 46142
A87: =A86+1 -> 92 | B87: 70393462 | C87: MANRIQUE FERNANDEZ BACA ANDREA MARIA | D87: manriquefernandezbacaandrea@gmail.com | E87: CADISTA | F87: OFICINA TECNICA-INTERVENCION EISSA | G87: CALLE JORGE OCHOA 241 | H87: SANTIAGO | I87: CUSCO | J87: CUSCO | K87: FISCALIZABLE | L87: 2000 | M87: 0 | N87: 0 | O87: 45925 | P87: 45961 | Q87: 45991 | R87: 46022 | S87: 46081 | T87: 46112 | AI87: =+MAX(O87:AH87) -> 46112
A88: =A87+1 -> 93 | B88: 70415206 | C88: MARQUEZ LLAMOCCA JOSE MANUEL | D88: jmmarquez296@gmail.com | E88: ASISTENTE DE OFICINA TECNICA | F88: OFICINA TECNICA | G88: VILLA PARAISO F-1 | H88: WANCHAQ | I88: CUSCO | J88: CUSCO | K88: FISCALIZABLE | L88: 4000 | M88: 500 | N88: 0 | O88: 45908 | P88: 45991 | Q88: 46053 | R88: 46142 | AI88: =+MAX(O88:AH88) -> 46142
A89: =A88+1 -> 94 | B89: 10515850 | C89: MENDEZ GONZALES AURELIO | D89: aureliomendez12@gmail.com | E89: CAPATAZ DE ACABADOS | F89: PRODUCCION-INTERVENCION LAYO | G89: AV.SAN MARTIN MZ.C LT.3 ASENT.H.MIGUEL GRAU | H89: SAN JUAN DE LURIGANCHO | I89: LIMA | J89: LIMA | K89: FISCALIZABLE | L89: 4500 | M89: 500 | N89: 500 | O89: 45785 | P89: 45869 | Q89: 45900 | R89: 45961 | S89: 45991 | T89: 46022 | U89: 46081 | V89: 46112 | AI89: =+MAX(O89:AH89) -> 46112
A90: =A89+1 -> 95 | B90: 21811280 | C90: MENDOZA GARCIA JULIO CESAR | D90: jumegarel@yahoo.es | E90: RESIDENTE DE OBRA | F90: PRODUCCION | G90: AV. DOMINGO ORUE 456 BLOCK 1 DPTO. 601 | H90: SURQUILLO | I90: LIMA | J90: LIMA | K90: DIRECCION | L90: 22000 | M90: 800 | N90: 1200 | O90: 45720 | P90: 45899 | Q90: 46081 | R90: 46173 | AI90: =+MAX(O90:AH90) -> 46173
A91: =A90+1 -> 96 | B91: 45507761 | C91: MENDOZA LORO LUIS ROLANDO | D91: rollyml20@gmail.com | E91: CONTADOR | F91: CONTABILIDAD | G91: CALLE COMERCIO MZ 12 LT 07 | H91: BERNAL | I91: SECHURA | J91: PIURA | K91: CONFIANZA | L91: 8000 | M91: 800 | N91: 800 | O91: 46041 | P91: 46142 | AI91: =+MAX(O91:AH91) -> 46142
A92: =A91+1 -> 97 | B92: 001526140 | C92: MESTRE SALORT VICENTE | D92: vmestre@consorciosrt.com | E92: Gerente General | F92: GERENCIA | G92: CALLE ALBERTO DEL CAMPO 411 | H92: MAGDALENA DEL MAR | I92: LIMA | J92: LIMA | K92: NO FISCALIZABLE | L92: 6800 | O92: 21/12/2023 | P92: 45646 | Q92: 46022 | R92: 46234 | AI92: =+MAX(O92:AH92) -> 46234
A93: =Liquidados!A292+1 -> 99 | B93: 41496841 | C93: MEZA MORI KATTY | D93: katty19@gmail.com | E93: JEFE DE RECURSOS HUMANOS | F93: GESTION HUMANA | G93: AV. AREQUIPA 1480 DPTO. 709 URB.RES. SANTA BEATRIZ CERCADO DE LIMA | H93: LIMA | I93: LIMA | J93: LIMA | K93: CONFIANZA | L93: 9500 | M93: 800 | N93: 800 | O93: 45931 | P93: 46022 | Q93: 46112 | AI93: =+MAX(O93:AH93) -> 46112
A94: =A93+1 -> 100 | B94: 73644767 | C94: MORALES MONRROY, GABRIEL FRANCISCO | D94: gmoralesm@pucp.edu.pe | E94: INGENIERO DE ESTRUCTURAS | F94: OFICINA TECNICA | G94: CALLE MARIANO PACHECO 922 URB SANTA CATALINA | H94: LA VICTORIA | I94: LIMA | J94: LIMA | K94: NO FISCALIZABLE | L94: 4000 | M94: 800 | N94: 800 | O94: 45999 | P94: 46081 | Q94: 46112 | AI94: =+MAX(O94:AH94) -> 46112
A95: =A94+1 -> 101 | B95: 48091922 | C95: MOSCOSO RIOS ALAIN JOSE LUIS | D95: alainmoscosorios@gmail.com | E95: TOPOGRAFO | F95: PRODUCCION | G95: CALLE ESPINAR 911 | H95: CALCA | I95: CALCA | J95: CUSCO | K95: FISCALIZABLE | L95: 4500 | M95: 0 | N95: 0 | O95: 45629 | P95: 45716 | Q95: 45808 | R95: 45900 | S95: 45961 | T95: 46022 | U95: 46053 | V95: 46081 | W95: 46112 | AI95: =+MAX(O95:AH95) -> 46112
A96: =A95+1 -> 102 | B96: 43567961 | C96: MOTTA COAQUIRA, JHONATAN BENIGNO | D96: jhonatanbmotta@gmail.com | E96: ASISTENTE DE ALMACEN | F96: ADMINISTRACION | G96: P.J ALTO DE LA LIBERTAD MZA. 16 LOTE. 3B-1 JR INDEPENDENCIA | H96: CERRO COLORADO | I96: AREQUIPA | J96: AREQUIPA | K96: NO FISCALIZABLE | L96: 2700 | M96: 375 | O96: 46030 | P96: 46112 | AI96: =+MAX(O96:AH96) -> 46112
A97: =A96+1 -> 103 | B97: 73990329 | C97: NINA QUISPE RONNY MICHAEL | D97: ronnymichael1820@gmail.com | E97: ASISTENTE DE CALIDAD | F97: CALIDAD-INTERVENCION SEAL TELECOM | G97: JR. JULI 115 | H97: PUNO | I97: PUNO | J97: PUNO | K97: FISCALIZABLE | L97: 4000 | M97: 500 | N97: 500 | O97: 45954 | P97: 46022 | Q97: 46081 | R97: 46112 | AI97: =+MAX(O97:AH97) -> 46112
A98: =A97+1 -> 104 | B98: 47330689 | C98: NOA CAHUANA PAUL YURI | D98: pync.im@gmail.com | E98: SUPERVISOR SSOMA | F98: SSOMA | G98: AV SAN FELIPE 729 | H98: SICUANI | I98: CANCHIS | J98: CUSCO | K98: CONFIANZA | L98: 4500 | M98: 375 | N98: 0 | O98: 45241 | P98: 45322 | Q98: 45504 | R98: 45596 | S98: 45688 | T98: 45412 | U98: 45777 | V98: 45869 | W98: 45961 | X98: 46053 | Y98: 46142 | AI98: =+MAX(O98:AH98) -> 46142
A99: =A98+1 -> 105 | B99: 44616975 | C99: NORIEGA VILLALOBOS LUIS CARLOS | D99: lcnoriegav@gmail.com | E99: TECNICO INFORMATICO | F99: TI | G99: ASENT.H. ARAHUAY MZ. E LT. 20 | H99: SANTIAGO | I99: CUSCO | J99: CUSCO | K99: FISCALIZABLE | L99: 3500 | M99: 500 | N99: 0 | O99: 45261 | P99: 45351 | Q99: 45443 | R99: 45535 | S99: 45626 | T99: 45716 | U99: 45808 | V99: 45900 | W99: 45991 | X99: 46081 | Y99: 46112 | AI99: =+MAX(O99:AH99) -> 46112
A100: =A99+1 -> 106 | B100: 48056430 | C100: OBREGON SOMOZA YONER CRISTIAN | D100: yonercristian.obregon@gmail.com | E100: INGENIERO DE CALIDAD | F100: CALIDAD | G100: CALLE GRECIA MZ. Z LT. 27 AA.HH LOS OLIVOS | H100: VENTANI | I100: CALLAO | J100: PROV. CONST. DEL CALLAO | K100: CONFIANZA | L100: 5000 | M100: 800 | N100: 800 | O100: 45658 | P100: 45747 | Q100: 45838 | R100: 45930 | S100: 46022 | T100: 46112 | AI100: =+MAX(O100:AH100) -> 46112
A101: =A100+1 -> 107 | B101: 47987309 | C101: OLIVA RAMOS JULIA TERESA | D101: ju.corporativo21@gmail.com | E101: SUPERVISOR SSOMA | F101: SSOMA-INTERVENCION LOS INKAS | G101: URB SOL DE LAMBAYEQUE II MZ. E2 LT. 10 | H101: LAMBAYEQUE | I101: LAMBAYEQUE | J101: LAMBAYEQUE | K101: FISCALIZABLE | L101: 5000 | M101: 800 | N101: 800 | O101: 45909 | P101: 45991 | Q101: 46022 | R101: 46081 | S101: 46112 | AI101: =+MAX(O101:AH101) -> 46112
...

Sheet Liquidados
A2: Item | B2: DNI O CE | C2: APELLIDOS Y NOMBRES | E2: CARGO | G2: DIRECCIÓN | H2: Distrito | I2: PROVINCIA | J2: DEPARTAMENTO | L2: FECHA INGRESO NOMINA | M2: TERMINO DE CONTRATO | N2: 1° PRORROGA | O2: 2° PRORROGA | P2: 3° PRORROGA | Q2: 4° PRORROGA | R2: 5° PRORROGA | S2: 6° PRORROGA | T2: 7° PRORROGA | U2: 8° PRORROGA | V2: 9° PRORROGA | W2: 10° PRORROGA | X2: 11° PRORROGA | Y2: 12° PRORROGA | Z2: 13° PRORROGA | AA2: 14° PRORROGA | AB2: 15° PRORROGA | AC2: 16° PRORROGA | AD2: 17° PRORROGA | AE2: 18° PRORROGA | AF2: 19° PRORROGA | AG2: 20° PRORROGA | AH2: 21° PRORROGA | AI2: ULTIMA PRORROGA | AJ2: OBS
A3: 3 | B3: 71432911 | C3: ANGELES PUMA JESSICA MELISSA | E3: ASISTENTE DE RECURSOS HUMANOS | G3: 44918 | H3: 44948 | L3: 44918 | M3: 44948
A4: 9 | B4: 46112567 | C4: BALLENA CASTILLO PEDRO ENRIQUE | E4: INGENIERO DE INSTALACIONES | L4: 44927 | M4: 45107 | N4: 45199 | AK4: FALTA FIRMA AITCIN Y HAVAI
A5: 12 | B5: 42407819 | C5: BOLOÑOS SARAVIA LUDWEG | E5: MEDICO OCUPACIONAL | G5: 44994 | H5: 45015 | L5: 44994 | M5: 45015
A6: 35 | B6: 10001181 | C6: FLORES DURAN JAIME ENRIQUE | E6: GERENTE GENERAL | G6: 44958 | H6: 45322 | L6: 44958 | M6: 45322
A7: 52 | B7: 46003549 | C7: JUAREZ DIOSES JUAN JESUS | E7: JEFE DE RECURSOS HUMANOS | G7: 44914 | H7: 45064 | L7: 44914 | M7: 45064
A8: 61 | B8: 40738865 | C8: LOPEZ ZARATE ROGER JAVIER | E8: JEFE DE SSOMA | G8: 44767 | H8: 44834 | L8: 44767 | M8: 44834
A9: 62 | B9: 40738865 | C9: LOPEZ ZARATE ROGER JAVIER | E9: JEFE DE SSOMA | G9: 44564 | H9: 44666 | L9: 44564 | M9: 44666
A10: 69 | B10: 42064066 | C10: MATA REINOZO WILLIAM FERNANDO | E10: JEFE DE COSTOS Y PRESUPUESTOS | L10: 44545 | M10: 44681 | N10: 44712 | O10: liquidado | P10: 44834 | Q10: 44865 | R10: 44957 | S10: 30/06/2023 | AK10: BARRIOS, HAVAI Y GANDINI (FALTA) | AL10: 44835 | AM10: 44865 | AN10: BARRIOS, HAVAI Y GANDINI
A11: 70 | B11: 06719981 | C11: MAXIMO SANDOVAL FRANCISCO AGUSTIN | G11: 44564 | H11: 44681 | L11: 44564 | M11: 44681
B12: 44628256 | C12: RODRIGUEZ MONROY CESAR RAUL | E12: ADMINISTRADOR DE CONTRATOS | L12: OK | M12: OK | N12: 01/03/2022 AL 31/10/2022
A13: 87 | B13: 43799720 | C13: RODRIGUEZ ZAPATA LUIS FELIPE | E13: GERENTE DE CALIDAD | G13: 44565 | H13: 44666 | L13: 44565 | M13: 44666
A14: 89 | B14: 23996122 | C14: ROJAS ZAPANA WILLIAM WASHINGTON | E14: AUXILIAR DE MANTENIMIENTO | G14: 44571 | H14: 44666 | I14: 45199 | L14: 44571 | M14: 44666
A15: 92 | B15: 73330160 | C15: ROSALES SALINAS RENATO | E15: ASISTENTE DE RECURSOS HUMANOS | G15: 44927 | H15: 44948 | L15: 44927 | M15: 44948
A16: 93 | B16: 40801957 | C16: SAAVEDRA SANCARRANCO CONCEPCION ANABELI | E16: JEFE DE PROCURA | L16: OK | M16: OK
A17: 102 | B17: 70103838 | C17: VALLE SALAS KATIANA DANAIT | E17: ADMINISTRADOR DE OBRA | L17: OK | M17: OK | N17: 25/01/2022 AL 30/09/2022 | O17: 44865 | AK17: HERNIQUE GANDINI | AM17: 44865 | AN17: HERNIQUE GANDINI
A18: 104 | B18: 23990472 | C18: VENERO DORADO JOHN PAVEL | G18: 44580 | H18: 44666 | L18: 44580 | M18: 44666
A19: 111 | B19: 71656130 | C19: ZAMBRANO VARGAS GERARDO JOSE | E19: MODELADOR BIM | G19: 45040 | H19: 45138 | L19: 45040 | M19: 45138
A20: 50 | B20: 40403833 | C20: LEON JIMENEZ MARCO ANTONIO | E20: JEFE DE ADMINISTRACION | G20: 44550 | H20: 45031 | I20: 45291 | L20: 44550 | M20: 44666
A21: 53 | B21: 43247579 | C21: LLERENA HUARMIYURI CARLOS MAGNO | E21: CONTROL DOCUMENTARIO | L21: 44964 | M21: 45138 | N21: 45230
A22: 3 | B22: 63436592 | C22: APASA CRUZ ABEL | E22: AUXILIAR DE MANTENIMIENTO | L22: 44935 | M22: 45107 | N22: 45199 | AK22: FALTA FIRMA AITCIN Y HAVAI
A23: 11 | B23: 24000956 | C23: CARBAJAL LAURA ROBERTO CARLOS | E23: GERENTE DE OFICINA TECNICA | L23: 44998 | M23: 45382
A24: 25 | B24: 48184564 | C24: CRUZ GARAVITO ANTONY | E24: FINANCIERO | L24: 44958 | M24: 45138 | N24: 45230
A25: 35 | B25: 46108362 | C25: GONZALES CERVANTES MARIA ADRIANA | E25: ARQUITECTA ESPECIALISTA | L25: 44986 | M25: 45169
A26: 69 | B26: 45283241 | C26: PAREDES TRUJILLO VILLY RICHARD | E26: INGENIERO DE PROCURA | L26: 44998 | M26: 45169
A27: 78 | B27: 23996122 | C27: ROJAS ZAPANA WILLIAM WASHINGTON | E27: AUXILIAR DE MANTENIMIENTO | L27: 44935 | M27: 45107 | N27: 45199 | AK27: FALTA FIRMA AITCIN Y HAVAI
B28: 48515190 | C28: MENDEZ TORRES ALEXIS HUMBERTO | E28: ANALISTA DE COSTOS | L28: 45114 | M28: 45199
B29: 43467715 | C29: SILVA MAMANI DAVID | E29: CONDUCTOR DE VEHICULO LIVIANO | L29: 45193 | M29: 45199
B30: 10723251 | C30: FLORES VARGAS EDWIN CARLOS | E30: PARAMEDICO CONDUCTOR DE AMBULANCIA | L30: 45089 | M30: 45169
A31: 62 | B31: 16731445 | C31: AMENERO RIVERA RICARDO | E31: GERENTE DE DISEÑO | G31: ARQUITECTURA | L31: 44593 | M31: 44681 | P31: 01/05/2022 al 30/06/2022 | Q31: 44834 | R31: 44865 | T31: 44926 | U31: 44957 | V31: 45107 | W31: 45291 | AK31: OK | AM31: 44743 | AN31: 44834 | AO31: BARRIOS, HAVAI Y GANDINI (FALTA) | AP31: 44835 | AQ31: 44865 | AR31: BARRIOS, HAVAI Y GANDINI | AS31: 44866 | AT31: 44926 | AU31: BARRIOS, HAVAI Y GANDINI | AV31: 44958 | AW31: 45107 | AX31: BARRIOS Y HAVAI | AY31: 45108 | AZ31: 45291 | BA31: AITCIN Y HAVAI
A32: 112 | B32: 07885306 | C32: ARATA DELGADO, MARIA PIA | E32: JEFE DE DISEÑO | G32: DISEÑO | L32: 45159 | M32: 45291
A33: 5 | B33: 45119589 | C33: ARISTA MAS CARLOS MARX | E33: JEFE DE PLANEAMIENTO | G33: PLANEAMIENTO | L33: 44861 | M33: 45042 | P33: 45291 | AK33: HAVAI Y AITCIN | AM33: 45043 | AN33: 45137 | AO33: FALTA FIRMA AITCIN Y HAVAI | BC33: L
A34: 6 | B34: 41335487 | C34: BACA SOTOMAYOR YENI | E34: ENFERMERA OCUPACIONAL | L34: 45096 | M34: 45199 | P34: 45291 | AK34: HAVAI Y AITCIN | BC34: L
A35: 9 | B35: 23945249 | C35: CABALLERO COELLO ALCIRA SIRLEY | E35: ENFERMERA | L35: 44581 | M35: 44666 | P35: 16/04/2022 al 30/06/2022 | Q35: 44834 | R35: 44865 | T35: 44957 | U35: 45138 | V35: 45230 | AK35: ROJAS CLAUDIO | AM35: 44743 | AN35: 44834 | AO35: BARRIOS, HAVAI Y GANDINI (FALTA) | AP35: 44866 | AQ35: 44957 | AR35: BARRIOS Y GANDINI | AS35: 44958 | AT35: 45138 | AU35: BARRIOS Y HAVAI | BC35: X
A36: 97 | B36: 42249108 | C36: CARRION PEREZ, ALAN JOSHEP | E36: SUPERVISOR SSOMA | L36: 45139 | M36: 45230 | BC36: X
A37: 14 | B37: 46168855 | C37: CCAULLA GOMEZ CARLOS EDUARDO | E37: ASISTENTE DE VALORIZACIONES | L37: 44566 | M37: 44666 | P37: 16/04/2022 al 30/06/2022 | Q37: 44834 | R37: 44865 | T37: 44957 | U37: 44985 | V37: 45138 | W37: 45230 | AK37: OK | AM37: 44743 | AN37: 44834 | AO37: BARRIOS, HAVAI Y GANDINI (FALTA) | AP37: 44866 | AQ37: 44957 | AR37: BARRIOS, HAVAI Y GANDINI | AS37: 44958 | AT37: 44985 | AU37: BARRIOS Y HAVAI | AV37: 44986 | AW37: 45138 | AX37: BARRIOS Y HAVAI | BC37: X
A38: 27 | B38: 40023502 | C38: ESPINOZA RIVERA ELIZABETH | E38: INGENIERO DE CALIDAD | L38: 44967 | M38: 45138 | P38: 45322 | AK38: BARRIOS Y HAVAI
A39: 119 | B39: 10723251 | C39: FLORES VARGAS EDWIN CARLOS | L39: 45089 | M39: 45169
A40: 30 | B40: 73512089 | C40: GARAY CHAMORRO DERLY KIARA | E40: ARQUITECTA DE OFICINA TECNICA | G40: OFICINA TECNICA | L40: 44958 | M40: 45137 | P40: 45230 | Q40: 45260 | R40: 45291 | AK40: BARRIOS Y HAVAI | BC40: L
A41: 61 | B41: 23967045 | C41: PACHECO LETONA JULIO CESAR | E41: RESPONSABLE DE SITIO | G41: PRODUCCION | L41: 44760 | M41: 44834 | P41: 44865 | Q41: 44957 | R41: 45138 | T41: 45230 | U41: 45322 | AK41: GANDINI | AM41: 44866 | AN41: 44957 | AO41: BARRIOS Y GANDINI | AP41: 44958 | AQ41: 45138 | AR41: BARRIOS Y HAVAI | BC41: L
A42: 68 | B42: 02894816 | C42: QUINTO NEGLIA ISAYO | E42: GERENTE TECNICO DE PROYECTO | G42: DISEÑO | L42: 44893 | M42: 45291 | AK42: BARRIOS Y HAVAI
A43: 76 | B43: 32966805 | C43: SILVA VERGARA JUAN CARLOS | E43: ANALISTA DE PRESUPUESTOS | L43: 44593 | M43: 44666 | P43: 16/04/2022 AL 30/06/2022 | Q43: 44834 | R43: 44865 | S43: 01/11/2022 AL 31/10/2023 | T43: 44926 | U43: 44957 | V43: 45138 | W43: 45230 | AK43: OK | AM43: 44743 | AN43: 44834 | AO43: BARRIOS, HAVAI Y GANDINI (FALTA) | AP43: 44866 | AQ43: 44926 | AR43: BARRIOS, HAVAI Y GANDINI | AS43: 44866 | AT43: 44957 | AU43: BARRIOS, HAVAI Y GANDINI | AV43: 44958 | AW43: 45138 | AX43: BARRIOS Y HAVAI | BC43: X
A44: 105 | B44: 46554034 | C44: TOMAYLLA ROLDAN BERZAYDA | E44: CONTROL DOCUMENTARIO | L44: 45201 | M44: 45291 | BC44: L
A45: 98 | B45: 72887054 | C45: YACO LOAIZA, JEAN MARCO | E45: ASISTENTE DE COSTOS | L45: 45139 | M45: 45230 | P45: LIQUIDAR | BC45: X
A46: 113 | B46: 46112598 | C46: AYALA MEJIA, ANGELLA DEL MILAGRO | E46: CONSULTOR EN EQUIPAMIENTO MEDICO | L46: 45170 | M46: 45260 | P46: 45291 | S46: 45322 | BC46: L
A47: 17 | B47: 40114288 | C47: CHAMORRO BANDA GUILLERMO ALEJANDRO | E47: INGENIERO EN EQUIPAMIENTO MEDICO | L47: 45084 | M47: 45169 | P47: 45260 | Q47: 45291 | S47: 45322 | AK47: HAVAI Y AITCIN | BC47: L
A48: 31 | B48: 42787098 | C48: GIRON RONDINEL ROSALYNN MAYBEE | E48: ING COSTOS Y PROCURA | G48: PRODUCCION | L48: 44760 | M48: 44834 | P48: 44865 | Q48: 44957 | R48: 45138 | T48: 45322 | AL48: 44866 | AM48: 44957 | AN48: BARRIOS Y GANDINI | AO48: 44958 | AP48: 45138 | AQ48: BARRIOS Y GANDINI | BB48: L
A49: 82 | B49: 09640941 | C49: PATIÑO SAMUDIO BENDEZU, OSWALDO ALFONSO | E49: RESIDENTE DE OBRA | G49: PRODUCCION | L49: 45154 | M49: 45350
A50: 74 | B50: 07643177 | C50: MIRANDA DE LA VEGA JUAN CARLOS | E50: GERENTE DE OFICINA TECNICA (KP) | G50: OFICINA TECNICA | L50: 44565 | M50: 44666 | P50: 16/04/2022 al 30/06/2022 | Q50: 44834 | R50: 44865 | S50: 45351 | T50: 01/11/2022 al 31/12/2022 | U50: 45077 | V50: 45169 | W50: 45260 | AL50: 44743 | AM50: 44834 | AN50: BARRIOS, HAVAI Y GANDINI (FALTA) | AO50: 44866 | AP50: 44926 | AQ50: BARRIOS, HAVAI Y GANDINI | AR50: 44927 | AS50: 45077 | AT50: BARRIOS Y HAVAI | AU50: 45078 | AV50: 31/08/20233 | AW50: AITCIN Y HAVAI
A51: 4 | B51: 44417814 | C51: ANTEZANO CHAVEZ, GERMAN | E51: 45176 | G51: 45260 | N51: 45351 | T51: 45351
A52: 16 | B52: 08301967 | C52: CARDENAS BONILLA JAIME ANTONIO | E52: 45033 | G52: 45124 | J52: 45230 | L52: 45260 | M52: 45291 | N52: 45351 | T52: 45351 | U52: X
A53: 48 | B53: 09412568 | C53: GUTIERREZ HUARACA, EDWIN JHONY | E53: 45152 | G53: 45260 | J53: 45291 | L53: 45322 | N53: 45351
A54: 77 | B54: 48383546 | C54: MENDOZA FLORES SANDRA CAROLINA | E54: MODELADOR BIM | L54: 45068 | M54: 45169 | P54: 45260 | Q54: 45382 | S54: 45351
A55: 99 | B55: 43799720 | C55: RODRIGUEZ ZAPATA LUIS FELIPE | E55: GERENTE DE CALIDAD (KP) | G55: CALIDAD | L55: 45001 | M55: 45199 | P55: 45291 | S55: 45382
A56: 11 | B56: 74568094 | C56: BECERRA PIEROLA JESUS DARLENY | E56: ASISTENTE DE ARQUITECTURA | L56: 44594 | M56: 44666 | P56: 16/04/2022 al 30/06/2022 | Q56: 44834 | R56: 44865 | S56: 45382 | T56: 44926 | U56: 44957 | V56: 45107 | W56: 45199 | X56: 45291 | AL56: 44743 | AM56: 44834 | AN56: BARRIOS, HAVAI Y GANDINI (FALTA) | AO56: 44866 | AP56: 44926 | AQ56: BARRIOS, HAVAI Y GANDINI | AR56: 44927 | AS56: 44957 | AT56: BARRIOS, HAVAI Y GANDINI | AU56: 44958 | AV56: 45107 | AW56: BARRIOS, HAVAI Y GANDINI | AX56: 45108 | AY56: 45199 | AZ56: AITCIN Y HAVAI | BB56: ok
A57: 66 | B57: 42596183 | C57: LONCONI CHAVEZ EDWAR ALEX | E57: CONDUCTOR | L57: 44935 | M57: 45199 | P57: 45291 | S57: 45382 | AL57: 45108 | AM57: 45199 | AN57: FALTA FIRMA AITCIN Y HAVAI
A58: 122 | B58: 10392064 | C58: VERAMENDI GUERRERO DOLA EVILI | E58: JEFE DE RECURSOS HUMANOS | L58: 44986 | M58: 45169 | P58: 45291 | S58: 45382
A59: 89 | B59: 46519874 | C59: PECEROS VENEGAS, DOSTOIEVSKI | E59: Ingeniero Asistente de Instalaciones | L59: 45139 | M59: 45230 | P59: 45260 | Q59: 45443 | S59: 45351
A60: 91 | B60: 25854644 | C60: PERALTA VELARDE WALKER MOISES | L60: 45248 | M60: 45351 | P60: 45443
A61: 15 | B61: 72737047 | C61: BOCANEGRA PASHANASTE PEDRO JAVIER | L61: 45341 | M61: 45412
A62: 54 | B62: 41544282 | C62: HERNANDEZ VILLALOBOS NANCY RUBI | E62: JEFE SIG | L62: 44966 | M62: 45138 | P62: 45322 | S62: 45412
A63: 87 | B63: 46831109 | C63: PEÑA PAREDES BURNO MIGUEL | L63: 45343 | M63: 45412
B64: 72150924 | C64: BERAUN RIVERA GERARDINO LUIS | D64: beraunrivera@gmail.com | E64: MODELADOR BIM | F64: BIM | G64: VALLE RIESTRA 1484 | H64: PUEBLO LIBRE | I64: LIMA | J64: LIMA | K64: FISCALIZABLE | L64: 45691 | M64: 45777 | N64: 45778 | O64: 45869 | P64: 45870 | Q64: 45961
B65: 71890446 | C65: CAMIZAN MEZA YANCARLOS | D65: yan802086@gamil.com | E65: AUXILIAR DE SEGURIDAD PATRIMONIAL | F65: SEGURIDAD PATRIMONIAL | G65: AV HEROES DEL CENEPA 1279 - B-BAGUA | H65: BAGUA | I65: BAGUA | J65: AMAZONAS | K65: FISCALIZABLE | L65: 45937 | M65: 46022
B66: 46428608 | C66: ESCALANTE CHAVEZ FRANTY LEONEL | D66: frantyleonel@gmail.com | E66: CADISTA | F66: OFICINA TECNICA | G66: URB LOS SAUCES MZ F-2 LT B | H66: WANCHAQ | I66: CUSCO | J66: CUSCO | K66: FISCALIZABLE | L66: 45925 | M66: 45961
B67: 002857071 | C67: GONZALEZ CARRILLO ROSMAR SAMARITH | D67: samarith29@gmail.com | E67: INGENIERO BIOMEDICO | F67: EQPM | G67: AV LOS FAISANES N° 535 | H67: CHORRILLOS | I67: LIMA | J67: LIMA | K67: CONFIANZA | L67: 45474 | M67: 45565 | N67: 45566 | O67: 45657 | P67: 45658 | Q67: 45688 | R67: 45689 | S67: 45777 | T67: 45778 | U67: 45869 | V67: 45870 | W67: 45961
B68: 72665283 | C68: HOLGADO CORNEJO CLAUDIA LUCIA | D68: claudiaholgado@outlook.com | E68: INGENIERO DE CALIDAD | F68: CALIDAD | G68: VICTOR ANDRES BELANUNDE URB. MAGISTERIAL MZ C LT 13 | H68: AREQUIPA | I68: AREQUIPA | J68: AREQUIPA | K68: CONFIANZA | L68: 45677 | M68: 45777 | N68: 45778 | O68: 45869 | P68: 45870 | Q68: 45961
B69: 48319539 | C69: HUAMANGUILLA QUISPE ARNOLD JAIME | D69: arnoldhuamanguilla@gmail.com | E69: AUXILIAR DE SEGURIDAD PATRIMONIAL | F69: SEGURIDAD PATRIMONIAL | G69: AV BELAUNDE | H69: CHINCHAYPUJIO | I69: ANTA | J69: CUSCO | K69: FISCALIZABLE | L69: 45945 | M69: 46022
B70: 72170700 | C70: INQUILTUPA CRUZ FERNANDO FABRICIO | D70: fabri130918@gmail.com | E70: MODELADOR BIM | F70: BIM | G70: URB SAN FRANCISCO A-5 | H70: WANCHAQ | I70: CUSCO | J70: CUSCO | K70: FISCALIZABLE | L70: 45358 | M70: 45443 | N70: 45444 | O70: 45535 | P70: 45536 | Q70: 45626 | R70: 45627 | S70: 45716 | T70: 45717 | U70: 45808 | V70: 45809 | W70: 45900 | X70: 45901 | Y70: 45961
B71: 47729001 | C71: MARTINEZ CLAUDIO TATIANA MARIA VILMA | D71: tatiana.mmartinezc@gmail.com | E71: ESPECILISTA DE ARQUITECTURA | F71: OFICINA TECNICA | G71: PRL BOLIVIA 151 | H71: HUANUCO | I71: HUANUCO | J71: HUANUCO | K71: CONFIANZA | L71: 45090 | M71: 45199 | N71: 45200 | O71: 45291 | P71: 45383 | Q71: 45473 | R71: 45474 | S71: 45565 | T71: 45566 | U71: 45657 | V71: 45658 | W71: 45747 | X71: 45748 | Y71: 45838 | Z71: 45839 | AA71: 45930 | AB71: 45931 | AC71: 45961
B72: 73123971 | C72: QUISPE CUSIRIMAY ANIBAL | D72: anibalquispecusirimay34@gmail.com | E72: OPERADOR DE RETROEXCAVCADROA | F72: PRODUCCION | G72: COMUNIDAD CAMPESINA TAMBO REAL S/N | H72: ZURITE | I72: ANTA | J72: CUSCO | K72: FISCALIZABLE | L72: 45925 | M72: 46022
C73: HUAMANI RODRIGUEZ KEVIN ALONSO | D73: alonso.huamani@urp.edu.pe | E73: MODELADOR BIM | F73: BIM | H73: ZONA VALLE DE JESUS MZ C LT 21 | I73: VILLA EL SALVADOR | J73: LIMA | K73: LIMA | L73: FISCALIZABLE | M73: 45040 | N73: 45138 | O73: 45139 | P73: 45230 | Q73: 45231 | R73: 45260 | S73: 45352 | T73: 45382 | U73: 45261 | V73: 45351 | W73: 45383 | X73: 45412
B74: 73962431 | C74: GONZALES DE LA CRUZ AYRTON JUNNIOR | D74: agonzalesd@uni.pe | E74: MODELADOR BIM | F74: BIM | H74: JR PEDRO PAULET 142 URB INGENIERIA | I74: SAN MARTIN DE PORRES | J74: LIMA | K74: LIMA | L74: FISCALIZABLE | M74: 45363 | N74: 45443
B75: 72020477 | C75: HUAMANI CHAÑI ROSA DEL RIO | D75: rosse_ch15@hotmail.com | E75: CONTROL DOCUMENTARIO | F75: CONTROL DOCUMENTARIO | H75: URB. VERSALLES MZ L 10 LARAPA | I75: SAN JERONIMO | J75: CUSCO | K75: CUSCO | L75: CONFIANZA | M75: 45505 | N75: 45596 | O75: 45597 | P75: 45688 | Q75: 45689 | R75: 45777 | S75: 45778 | T75: 45869
B76: 70415206 | C76: MARQUEZ LLAMOCCA JOSE MANUEL | D76: 131054@unsaac.edu.pe | E76: ASISTENTE DE OFICINA TECNICA | F76: OFICINA TECNICA | H76: AV LOS GIRASOLES 18 VILLA PARAISO MZ LT F DPTO 40 | I76: SAN SEBASTIAN | J76: CUSCO | K76: CUSCO | L76: FISCALIZABLE | M76: 44995 | N76: 45169 | O76: 45170 | P76: 45260 | Q76: 45352 | R76: 45443 | S76: 45444 | T76: 45535 | U76: 45261 | V76: 45351 | W76: 45536 | X76: 45626 | Y76: 45627 | Z76: 45716 | AA76: 45717 | AB76: 45808
B77: 73990329 | C77: NINA QUISPE RONNY MICHAEL | D77: ronnymichael1820@gmail.com | E77: ASISTENTE DE CALIDAD | F77: CALIDAD | H77: JR. JULI 115 | I77: PUNO | J77: PUNO | K77: PUNO | L77: FISCALIZABLE | M77: 45726 | N77: 45808 | O77: 45809 | P77: 45900
B78: 70829013 | C78: VENERO VARGAS, MARCELO | D78: marcelovenerov@gmail.com | E78: MODELADOR BIM | F78: BIM | H78: CD. SACASHUAYLLA - TICAPATA G-10 | I78: SAN SEBASTIAN | J78: CUSCO | K78: CUSCO | L78: FISCALIZABLE | M78: 45139 | N78: 45230 | O78: 45231 | P78: 45260 | Q78: 45352 | R78: 45443 | S78: 45444 | T78: 45535 | U78: 45261 | V78: 45351 | W78: 45536 | X78: 45626
B79: 45630170 | C79: AGAPITO CORDOVA DIEGO IVAN | D79: diego.agapito.cordova@gmail.com | E79: JEFE DE COSTOS Y PRESUPUESTOS | F79: COSTOS | H79: AV LOS PROCURSORES 630 DPTO 301 URB VALLE HERMOSO DE MONTERRICO | I79: SANTIAGO DE SURCO | J79: LIMA | K79: LIMA | L79: CONFIANZA | M79: 45110 | N79: 45291 | O79: 45565 | R79: 45292 | S79: 45382 | AD79: =+MAX(M79:AC79) -> 45565 | AE79: BAJA
B80: 72766723 | C80: AGUIRRE ZUÑIGA CESAR LUIS | D80: celuazu@hotmail.com | E80: INGENIERO DE PROCURA | F80: PROCURA | H80: CALLE CIRO ALEGRI URB. VILLA MIRAFLORES MZ E LT 4 | I80: SAN JERONIMO | J80: CUSCO | K80: CUSCO | L80: CONFIANZA | M80: 45201 | N80: 45291 | O80: 45473 | P80: 45504 | R80: 45292 | S80: 45382 | AD80: =+MAX(M80:AC80) -> 45504 | AE80: BAJA
B81: 40849478 | C81: ALAYO AGUILAR CHRISTIAN ALDO | D81: c_alayo@hotmail.com | E81: RESPONSABLE DE RECURSOS HUMANOS | F81: RRHH | H81: CALLE RIO RIMAC 259 MZ E1 LT 03 URB LA VIÑA | I81: SAN LUIS | J81: LIMA | K81: LIMA | L81: CONFIANZA | M81: 45383 | N81: 45473 | O81: 45565 | P81: 45657 | Q81: 45747 | T81: 45838 | U81: 45930 | AD81: =+MAX(M81:AC81) -> 45930 | AE81: BAJA
B82: 70939076 | C82: ALARCON RODAS ROBERT | D82: rob.alarcon07@gmail.com | E82: ASISTENTE DE ADMINISTRACION DE DSUBCONTRATOS | F82: PROCURA | H82: AV. SAN JUAN 971BLOCK 3 EDIF 3 VEREDA QUEDA EN UNA AVENIDA | I82: SAN JUAN DE MIRAFLORES | J82: LIMA | K82: LIMA | L82: FISCALIZABLE | M82: 45696 | N82: 45777 | O82: 45869 | AD82: =+MAX(M82:AC82) -> 45869 | AE82: BAJA
B83: 8177998 | C83: ALVARO CASTRO JOSE LUIS | D83: jalvarocastro@gmail.com | E83: APLICADOR DE ACABADOS EN VENTANAS | F83: PRODUCCION LORENA VIDRIOS | H83: ASOC. PRO VIV CAMINO REAL CUSCO MZ. T LT. 7 | I83: CUSCO | J83: CUSCO | K83: CUSCO | L83: FISCALIZABLE | M83: 45948 | N83: 46022 | AD83: =+MAX(M83:AC83) -> 46022 | AE83: ACTIVO
B84: 23853643 | C84: AMANCA HUAMAN, PAULINA | D84: paulita6765@hotmail.com | E84: ASISTENTA SOCIAL | F84: RRHH | H84: URB UCCHULLO GRANDE AV ARGENTINA T9 | I84: CUSCO | J84: CUSCO | K84: CUSCO | L84: CONFIANZA | M84: 45147 | N84: 45230 | O84: 45260 | P84: 45443 | Q84: 45535 | R84: 45323 | S84: 45351 | T84: 45626 | U84: 45688 | AD84: =+MAX(M84:AC84) -> 45688 | AE84: BAJA
B85: 71420266 | C85: AMORIN COLOMA LUIS ARMANDO | D85: amorin11.laac@hotmail.com | E85: INGENIERO DE PRODUCCION | F85: PRODUCCION | H85: JR CERRO DE PASCO 205 | I85: CALLERIA | J85: CORONEL PORTILLO | K85: UCAYALI | L85: CONFIANZA | M85: 45355 | N85: 45443 | O85: 45535 | P85: 45626 | AD85: =+MAX(M85:AC85) -> 45626 | AE85: BAJA
B86: 48449679 | C86: ARANIBAR GAVIÑO MONICA | D86: paty081208@gmail.com | E86: MODELADOR BIM | F86: BIM - ESPECIALIDADES | H86: CAMINOS DEL INCA MZ J-5 LT 17 IER PISO | I86: SANTIAGO DE SURCO | J86: LIMA | K86: LIMA | L86: FISCALIZABLE | M86: 45589 | N86: 45657 | O86: 45747 | P86: 45838 | Q86: 45930 | AD86: =+MAX(M86:AC86) -> 45930 | AE86: BAJA
B87: 70792140 | C87: ARGUEDAS BALDEÓN MARIA JOSE DEL ROSARIO | D87: marba20@gmail.com | E87: ASISTENTE DE CALIDAD SIG | F87: CALIDAD | H87: AV COLOMBIA 171 DPTO 401 | I87: PUEBLO LIBRE | J87: LIMA | K87: LIMA | L87: CONFIANZA | M87: 45117 | N87: 45199 | O87: 45291 | P87: 45473 | Q87: 45565 | R87: 45292 | S87: 45382 | T87: 45657 | U87: 45747 | AD87: =+MAX(M87:AC87) -> 45747 | AE87: BAJA
B88: 72244007 | C88: ARRAMBIDE QUISPE, JULIO CESAR | D88: julitojw2411@gmail.com | E88: AUXILIAR DE TOPOGRAFIA | H88: APV ALTO SAN MARTIN LT30 | I88: SANTIAGO | J88: CUSCO | K88: CUSCO | L88: FISCALIZABLE | M88: 45264 | N88: 45351 | O88: 45443 | AD88: =+MAX(M88:AC88) -> 45443 | AE88: BAJA
B89: 7420354 | C89: ARROYO MANRIQUE ESTANISLAO | D89: yorcharroyomanrique@gmail.com | E89: INSTALADOR DE PVC Y VIDRIOS | F89: PRODUCCION LORENA VIDRIOS | G89: PRODUCCION | H89: ANEXO ALTO TIWINZA | I89: PANGOA | J89: SATIPPO | K89: JUNIN | L89: FISCALIZABLE | M89: 45947 | N89: 46022 | AD89: =+MAX(M89:AC89) -> 46022 | AE89: ACTIVO
B90: 72912472 | C90: ARROYO TARMEÑO SUSAN STEFHANIE | D90: susan.arrts@gmail.com | E90: INGENIERA SANITARIA | H90: ASC. DE ABRIL MZ 18 LT 05 | I90: TUPAC AMARU INCA | J90: PISCO | K90: ICA | L90: CONFIANZA | M90: 45278 | N90: 45382 | O90: 45412 | AD90: =+MAX(M90:AC90) -> 45412 | AE90: BAJA
B91: 09521328 | C91: AYALA VENTOSILLA DENEGRI EDGARDO | D91: ayala995164006@gmail.com | E91: CAPATAZ SANITARIO | F91: ESPECIALIDADES | H91: CALLE LOS CLAVELES MZ A LT 15 PRO VIV ATLANTA | I91: SAN MARTIN DE PORRES | J91: LIMA | K91: LIMA | L91: FISCALIZABLE | M91: 45647 | N91: 45657 | O91: 45747 | P91: 45777 | Q91: 45808 | AD91: =+MAX(M91:AC91) -> 45808 | AE91: BAJA
B92: 44975577 | C92: AYALA ESCALANTE JUAN CARLOS | D92: jcayalae@gmail.com | E92: JEFE SIG | F92: CALIDAD | H92: AV. CONDOMINIO VILLA VERDE 2 EDIFICIO E03 DPTO 703 LT F3 | I92: CERRO COLORADO | J92: AREQUIPA | K92: AREQUIPA | L92: CONFIANZA | M92: 45399 | N92: 45473 | AD92: =+MAX(M92:AC92) -> 45473 | AE92: BAJA
B93: 76214921 | C93: BERRIOS PAUCAR ED DARWIN | D93: darwinricardoberrios@gmail.com | E93: ASISTENTE DE SEGURIDAD PATRIMONIAL | F93: SEGURIDAD PATRIMONIAL | H93: CALLE FRANCISCO ROMAÑA 297 | I93: SANTIAGO | J93: CUSCO | K93: CUSCO | L93: FISCALIZABLE | M93: 45741 | N93: 45838 | AD93: =+MAX(M93:AC93) -> 45838 | AE93: BAJA
B94: 77470723 | C94: BERMEJO TABOADA EDWAR | D94: bermejo.2504@gmail.com | E94: ASISTENTE DE INSTALACIONES MECANICAS | F94: ESPECIALIDADES | H94: JR. PIURA 500 | I94: BAGUA | J94: BAGUA | K94: AMAZONAS | L94: FISCALIZABLE | M94: 45818 | N94: 45900 | AD94: =+MAX(M94:AC94) -> 45900 | AE94: BAJA
B95: 45433385 | C95: BERNAOLA CHUQUILLANQUI, ROBERTO JOSE | D95: robertojosebernaola@gmail.com | E95: INGENIERO DE COSTOS | F95: COSTOS | H95: AV. PANAMERICANA N° 894 | I95: HUANCAN | J95: HUANCAYO | K95: JUNIN | L95: CONFIANZA | M95: 45216 | N95: 45322 | O95: 45504 | P95: 45596 | Q95: 45688 | R95: 45323 | S95: 45412 | T95: 45716 | U95: 45777 | AD95: =+MAX(M95:AC95) -> 45777 | AE95: BAJA
B96: 41686216 | C96: BRAVO FIGUEROA MAURO JESUS | D96: mbf3170@gmail.com | E96: ASISTENTE SANITARIO | F96: ESPECIALIDADES | H96: SECTRO 3 GRUPO 10 MZ I LT 16 | I96: VILLA EL SALVADOR | J96: LIMA | K96: LIMA | L96: FISCALIZABLE | M96: 45383 | N96: 45473 | O96: 45565 | P96: 45657 | Q96: 45747 | AD96: =+MAX(M96:AC96) -> 45747 | AE96: BAJA
B97: 40896431 | C97: CALANCHE CARDENAS ROBERTO CARDENAS | D97: rcarlos.calanche.cardenas@gmail.com | E97: ASISTENTE DE SEGURIDAD | F97: SSOMA | G97: SSOMA | H97: JR JERUSALEN 101 SANTA ANA | I97: CUSCO | J97: CUSCO | K97: CUSCO | L97: FISCALIZABLE | M97: 45593 | N97: 45688 | AD97: =+MAX(M97:AC97) -> 45688 | AE97: BAJA
B98: 70348093 | C98: CALDERON TASSARA JOSE ANTONIO | D98: jact080799@outlook.com | E98: MODELADOR BIM | F98: BIM | H98: JR. ROSENDO VIDAURRE 641 DPTO 1783 | I98: BARRANCO | J98: LIMA | K98: LIMA | L98: FISCALIZABLE | M98: 45583 | N98: 45657 | O98: 45688 | AD98: =+MAX(M98:AC98) -> 45688 | AE98: BAJA
B99: 73759376 | C99: CALLO CCANA, DIEGO ALEXIS | D99: diego.alexis.callo.c@gmail.com | E99: INGENIERO DE CALIDAD | F99: CALIDAD | H99: APV LOS MAJEÑOS D-27 | I99: SAYLLA | J99: CUSCO | K99: CUSCO | L99: CONFIANZA | M99: 45261 | N99: 45351 | O99: 45443 | P99: 45535 | Q99: 45626 | T99: 45688 | AD99: =+MAX(M99:AC99) -> 45688 | AE99: BAJA
B100: 70815854 | C100: CAMARGO GONZALES LIZETH MARGARITA | D100: camargo_gonzales@hotmail.com | E100: ENFERMERA | F100: SSOMA | H100: CALLE CAHUIDE S/N SAN JUAN | I100: SAN JUAN | J100: LUCANA | K100: AYACUCHO | L100: CONFIANZA | M100: 45236 | N100: 45322 | O100: 45504 | P100: 45596 | Q100: 45688 | R100: 45323 | S100: 45412 | T100: 45716 | U100: 45777 | AD100: =+MAX(M100:AC100) -> 45777 | AE100: BAJA
B101: 70759003 | C101: CANO MAC DOWALL ANDREA PATRICIA | D101: andrea.canomd@gmail.com | E101: RESPONSABLE 4D | F101: PLANEAMIENTO | H101: URB QUINTA DEL SOL MZ B LT 30 | I101: CERRO COLORADO | J101: AREQUIPA | K101: AREQUIPA | L101: CONFIANZA | M101: 45572 | N101: 45657 | O101: 45747 | AD101: =+MAX(M101:AC101) -> 45747 | AE101: BAJA
...
